Workbook

Sheet サマリー
A1: アニメーション 呪術廻戦展「懐玉・玉折」「渋谷事変」
A2: LEGS／イベント記念商品 42SKU 全会場 販売分析・札幌予測確定・石川会場以降予測・追加発注判定
A3: 基準日：2026年7月28日 ／ 実績データ：東京(25日)・名古屋(19日)・博多(26日)・大阪(20日)＝全会期、札幌＝7/27(会期6日目)まで ＋ 2026/7/28 SPJ様 欠品報告メール
A5: ■ 結論サマリー
A6: ① 札幌 会期20日予測（確定値） | B6: LEGS42SKU 販売数 8,740個／販売金額 6,680,400円 ※東京を除く名古屋・博多・大阪の実績倍率から算出
A7: 札幌 全物販予測 | B7: 数量 37,254個／金額 36,375,678円 → 東京(初回)対比 10.2% ※コナン実績の北海道13.3%を下回る水準
A8: 札幌 入場者予測 | B8: 7,784人（委員会予測18,000人の43%／LEGS予測14,000人の56%）＝計画を大幅に下回る
A9: ② LEGS物販構成比の推移 | B9: 金額：東京28.5%→名古屋29.9%→博多29.4%→大阪21.1%→札幌18.4%(予測) 数量：38.7%→34.5%→40.0%→26.7%→札幌23.5%(予測)
A10: 構成比低下の主因 | B10: 大阪会場からの新商品106SKU投入（大阪の会期20日 金額シェア19.8%）。札幌は新規SKU 0で品揃えは大阪と同一
A11: ③ 石川以降5会場 LEGS必要数 | B11: 81,760個（シナリオ①ユーザー指定：石川11%・仙台13%・神戸12%(仮)・鳥取9%・東京凱旋50%）
A12: シナリオ②企画概要書ベース | B12: 石川12.48%・仙台15.60%（企画概要書グッズ売上÷東京）→ 必要数 85,272個
A13: シナリオ③札幌実績連動(保守) | B13: ②に札幌の計画比達成率46.5%を乗算 → 石川5.83%・仙台7.29%・神戸5.61%・鳥取4.21%（凱旋50%据置）→ 必要数 62,673個
A14: ★残在庫想定の反映 | B14: 在庫フロー台帳の「梅田まで(SET)」列 274,688個を採用（梅田会場後の検品結果まで反映済み）。
A15: ★札幌への追納（実施済） | B15: 2026/7/31・8/1 札幌会場追納リスト（レッグス商品分のみ抜粋）：呪術廻戦 渋谷事変 クリアファイル（脹相） 50個／前髪ヘアバンド 100個／脱兎！ポーチ入りクリップセット 60個／宿儺の指風お菓子 100個 計310個。倉庫在庫からの出荷なので全社在庫は不変
A16: 追納後になお必要な追納 | B16: 2個（会期20日予測が販売可能数を上回る残差）
A17: 石川以降 供給可能在庫 | B17: 265,948個 ＝ 残在庫274,688個 − 札幌 会期20日予測販売8,740個（札幌への追納と会期末返送を相殺した正味）
... A29: 札幌 会期中の追加発注 | B29: 1品目が会期内に在庫切れ見込：呪術廻戦 渋谷事変 クリアファイル（宿儺）(不足2)
A31: ■ 運営（SPJ様）欠品報告との突合 ※2026/7/28受領メール
A32: 報告された欠品／近々欠品 | B32: 8品目：呪術廻戦 渋谷事変 クリアファイル（虎杖 悠仁） 呪術廻戦 渋谷事変 クリアファイル（七海 建人） 呪術廻戦 渋谷事変 クリアファイル（脹相） 呪術廻戦 渋谷事変 クリアファイル（宿儺） 前髪ヘアバンド 宿儺の指風お菓子 脱兎！ポーチ入りクリップセット 気分リフレッシュオルゴール
A33: ◎ モデルも会期中欠品を検知 | B33: 1品目：呪術廻戦 渋谷事変 クリアファイル（宿儺）
A34: ○ モデルは高消化率で整合 | B34: 6品目：呪術廻戦 渋谷事変 クリアファイル（虎杖 悠仁） 呪術廻戦 渋谷事変 クリアファイル（七海 建人） 呪術廻戦 渋谷事変 クリアファイル（脹相） 前髪ヘアバンド 宿儺の指風お菓子 気分リフレッシュオルゴール（予測消化率70%超。会期末までに枯渇する水準）
A35: △ モデル未検知（現場優先） | B35: 1品目：脱兎！ポーチ入りクリップセット(予測消化率67%)
A36: ▲ モデルのみ検知（現場未報告） | B36: 0品目：なし → 現場に実在庫の確認を推奨
A37: ★追納不可と回答された品目 | B37: 気分リフレッシュオルゴール ＝ 前会場時点で「追納困難」と回答済。ただし7/8実在庫では倉庫残23個が確認できるため、下記の要確認事項を参照
A38: 突合の結論 | B38: 現場報告8品目のうち7品目がモデル側でも欠品または高消化率として検知されており、見落とし0・空振り0で完全に整合。
B39: 7/27（6日目）実績を織り込んだことで検知精度が上がり、予測モデルは現場実感と一致する水準にある。
B40: ④シートのU列（運営 欠品報告）・V列（モデル×現場 突合）で商品別に明示している。
A41: ★倉庫在庫による解決可否 | B41: 報告8品目すべて2026/7/8時点で倉庫に在庫が残っており、追加生産ではなく倉庫からの追加納品で対応可能。
A42: 倉庫残（札幌納品を除く） | B42: 呪術廻戦 渋谷事変 クリアファイル（虎杖 悠仁）:1,740個 呪術廻戦 渋谷事変 クリアファイル（七海 建人）:2,423個 呪術廻戦 渋谷事変 クリアファイル（脹相）:208個 呪術廻戦 渋谷事変 クリアファイル（宿儺）:1,281個 前髪ヘアバンド:297個 宿儺の指風お菓子:160個 脱兎！ポーチ入りクリップセット:260個 気分リフレッシュオルゴール:23個
A43: ※要確認 | B43: 「気分リフレッシュオルゴール」は倉庫残28個が存在する。前会場時の「追納困難」回答と実在庫が食い違うため、
B44: 28個が出荷可能かSPJ様・倉庫に再確認のうえ、可能なら札幌へ充当することを推奨。
A46: ■ 最重要リスクと打ち手
A47: 札幌の動員が計画比43% | B47: 初6日入場者3,880人（大阪同期間14,703人の26.4%）。物販売上も東京対比10.2%と、
B48: 石川11%・鳥取9%として設定された「格下」会場と同水準。石川以降の会場比率も下方修正を検討すべき。
A49: 東京凱旋が必要数の53% | B49: 石川以降必要数81,760個のうち43,032個(53%)が東京凱旋。凱旋の50%前提が外れると発注量が大きくブレる。
B50: 発注は「石川〜鳥取(4会場・38,729個)」を先行確定し、凱旋分は会期確定後に第2弾発注とするのが安全。
A51: ★過剰在庫のほうが深刻 | B51: 残在庫274,688個に対し石川以降の必要数は81,760個。差引184,188個（残在庫の67%）が余剰となる見込み。
B52: 特に渋谷事変ポストカードセット(供給可能27,282個 vs 必要1,911個)、懐玉・玉折ポストカードセット(5,977 vs 1,488)は
B53: 20倍超の在庫を抱えている。追加発注よりも、余剰在庫の消化策（セット販売・ノベルティ転用等）の検討が急務。
A54: 不足はごく一部 | B54: 追加生産が必要なのは8品目・2,552個のみ。うち展示会キービジュアル クリアファイルが928個で全体の36%を占める。
A55: 生産リードタイムの制約 | B55: 生産日数は1か月（クリアファイル・ポストカード・缶バッジ・ステッカー系）、2.5か月（ミニ色紙2種・前髪ヘアバンド）、
B56: 3か月（絆創膏・お菓子・クリップ・エコバッグ・オルゴール・リング/フラグメント系）。バスボールは「－」＝再生産不可のため現有在庫で会場配分を組む必要がある。
A57: 賞味期限の制約 | B57: 宿儺の指風お菓子は賞味期限4か月以内の在庫が販売不可。仙台以降向けは2026/5/15手配済だが、
B58: 鳥取(27年3月)・東京凱旋(27年4月)向けは賞味期限の逆算で再手配の要否を要確認。
A60: ■ 算出モデル（①札幌予測）
A61: 基本式 | B61: 札幌 会期20日予測販売数 ＝ 札幌 初6日(7/22-7/27)販売数 × 会期倍率 g
A62: 会期倍率 g | B62: g ＝ 各会場の「20日累計販売数 ÷ 初6日販売数」を商品別に算出し加重平均
A63: 採用会場と加重 | B63: 大阪×2（20日会期・水曜開始・新商品投入後で札幌と同条件）、博多×1、名古屋×1。東京は除外
A64: 名古屋の換算 | B64: 名古屋は19日会期の全日実績あり。札幌20日会期と揃えるため20日目分 +4.83%（大阪・博多の実績比率）のみ補完
A65: 42品計の実効倍率 | B65: 大阪1.659倍・博多2.108倍・名古屋1.581倍(20日換算後) → 加重平均 1.752倍
A67: ■ 算出モデル（③石川以降）
A68: 会場物販売上 | B68: 東京(初回)全物販売上 358,193,925円 × 東京対比比率
A69: LEGS売上 | B69: 会場物販売上 × LEGS金額構成比 18.4%（札幌予測値＝大阪以降の推移の到達点を採用）
A70: LEGS数量 | B70: LEGS売上 ÷ LEGS平均単価 764円（札幌予測ミックスベース）
A71: 商品別按分 | B71: 大阪20日実績の数量構成比50%＋札幌20日予測の数量構成比50%のブレンド
A72: 比率はすべて入力値 | B72: 「前提・入力」シートの青字セルを変更すると全シートが再計算されます
A74: ■ 追加商品によるLEGS売上低下（⑦）
A75: 市場は縮んでいない | B75: 物販客単価（全商品）は名古屋7,012円/人→大阪6,882円/人と▲1.8%でほぼ横ばい。
B76: 同期間にLEGSは2,099円/人→1,455円/人と▲30.7%（▲643円/人）。純粋なカニバリゼーション。
A77: 新商品の約47%が食い合い | B77: 大阪の新商品106SKUは1,360円/人を稼いだが、LEGS減少643円/人はその47%に相当。
A78: LEGSが削られ始めたのは博多 | B78: 博多で「おすわりぬいぐるみ全8種」(230円/人)＋アクリルカードスタンド(233円/人)を投入し、
B79: LEGSは2,099→1,634円/人（▲465）。大阪のうちわ14種・アクリル系39種でさらに▲179円/人。
A80: 被害はブラインド系に集中 | B80: ブラインド缶バッジ▲272円/人・ブラインドミニ色紙▲284円/人の2タイプでLEGS減少の87%。
B81: クリアファイル・ポストカード類は横ばい〜微増で影響なし。追加生産はブラインド系を抑制すべき。
A82: ★石川以降の最大リスク | B82: 同規模の新商品を石川以降に追加投入すると③の必要数86,000個は最大30%過大になる。
B83: 追加生産を確定する前に、石川以降の新商品投入計画（有無・規模）を必ず確認すること。
A85: ■ シート構成
A86: 前提・入力 | B86: 会場比率・構成比・加重など全パラメータの入力（青字＝編集可）
A87: ①札幌予測確定 | B87: 商品別 会期20日予測（会場別g・予測数量/金額・消化率・会期末残在庫）
A88: ②会場別構成比 | B88: 全会場のLEGS物販構成比（数量・金額）、供給元別構成比、東京対比 会場比率
A89: ③石川以降予測 | B89: 残5会場のLEGS売上/数量予測と商品別必要数
A90: ④追加発注判定 | B90: 札幌会期中／石川以降 の商品別 発注要否・推奨数量
A91: ⑤全データ統合リスト | B91: 5会場×42商品の全実績・構成比・消化率・予測を1行に集約
A92: ⑥商品別 会場推移 | B92: 商品別の会場ごと販売数・構成比の推移（トレンド確認用）
A93: ⑦新商品影響分析 | B93: 梅田以降の追加商品（ぬいぐるみ・うちわ等）によるLEGS売上低下の要因分析
A94: ⑧実在庫(7-8)明細 | B94: 2026/7/8時点の実在庫（CX催事＋DBS倉庫＋梅田返送良品）と商品別の欠品算出
A95: ⑨過去4会場 予測vs実績 | B95: 池袋・名古屋・博多・梅田の商品別 販売予測／実績／予測時構成比／実績後の構成比修正
A96: ⑩会場比率シナリオ比較 | B96: 石川以降の東京対比比率 4シナリオ（ユーザー指定／企画概要書／札幌実績連動／手動）の比較
A97: ⑪会場別引当・発注期限 | B97: 会場順の在庫引当、欠品発生会場の特定、生産日数から逆算した最終発注期限
A98: 運営欠品報告の反映先 | B98: ④追加発注判定シートのU列・V列、および⑧シートのT列・備考欄
A100: ■ 前提と留意事項
A101: データ再読込 | B101: 全5会場のレジ通過単品売上を全件再読込・再集計。名古屋は後半4/1-4/5の追加提供データを反映し、
B102: 会期19日間（3/18-4/5）の完全実績となった。これに伴い名古屋の会期倍率gは推計2.438倍→実績2.215倍に修正。
A103: LEGS＝42SKU | B103: 各会場の商品分類「記念商品/レッグス」「レッグス/イベント記念」は全会場で本42SKUと完全一致
A104: 物販売上の定義 | B104: レジ袋代・音声ガイド・当日券を除いた商品売上（税込）。会場報告の総売上とは一致しない場合がある
A105: 残在庫の出所 | B105: 在庫フロー台帳（会場ごとの追加発注→販売→レッグス検品を積み上げた表）の最終実在庫列。
B106: 実際の発注前に倉庫在庫と過去会場の返品在庫を相殺すること（前提・入力シートで控除可能）。
A107: 神戸阪急の会場比率 | B107: 東京対比の指定が無いため12%を仮置き。要確認事項。
A108: 仙台の会場比率 | B108: ユーザー指定13%を採用。コナンカフェ2026実績（東京対比10.5%）とは2.5pt乖離あり。
A109: 鳥取会場 | B109: 会期3/15-4/4を21日間として計上。
A110: 価格改定 | B110: イメージリング8種は東京¥22,000→名古屋以降¥27,500に改定。⑤では会場別の実売単価で金額を算出。
A111: 元データの小数値 | B111: 名古屋の販売可能数に小数を含む商品が3件あるため整数に丸めて処理している（合計への影響は1個未満）。
A112: 東京の内覧会 | B112: 東京の12/4内覧会分（全商品計142個）は会期実績から除外して会場間比較している。

Sheet 前提・入力
A1: 前提・入力パラメータ
A2: 青字・黄色セルが入力値です。変更すると①③④⑤シートの予測が自動再計算されます。
A4: ■ ①札幌予測 モデルパラメータ
A5: 会期倍率g 加重：大阪 | B5: 2 | C5: 20日会期・水曜開始・新商品投入後で札幌と同条件のため2倍加重
A6: 会期倍率g 加重：博多 | B6: 1 | C6: 26日会期のうち初20日で算出
A7: 会期倍率g 加重：名古屋 | B7: 1 | C7: 19日会期・全日実績あり。20日目分のみ補完して札幌20日と揃える
A8: 会期倍率g 加重：東京 | B8: 0 | C8: ユーザー指示により東京は算出根拠から除外（0固定）
A9: 名古屋 20日目 補完率 | B9: 0.048292031 | C9: 大阪・博多の「20日目÷1-19日累計」平均。名古屋19日会期を20日相当に換算
A10: 全体倍率g（実績ゼロ品のフォールバック） | B10: 1.7519247 | C10: 42品計の加重平均倍率
A11: ■ ②③会場比率 前提
A12: 東京(初回) 全物販売上（税込） | B12: 358193925 | C12: 池袋サンシャイン25日間・レジ袋/音声ガイド/当日券を除く
A13: 東京(初回) 全物販 販売数量 | B13: 383342 | C13: 同上
A14: ★シナリオ選択（1〜4） | B14: 1 | C14: 1=ユーザー指定／2=企画概要書ベース／3=札幌実績連動(保守)／4=手動入力（下の手動値を使用）
A15: シナリオ別 東京対比比率 | C15: ①ユーザー指定 | D15: ②企画概要書ベース | E15: ③札幌実績連動(保守) | F15: ④手動入力
A16: 石川 香林坊大和 | B16: 26/8/14(金)-8/31(月)（18日間） | C16: 0.11 | D16: 0.1248 | E16: 0.058030303 | F16: 0.11
A17: 仙台 Ebeans | B17: 26/9/5(土)-10/4(日)（30日間） | C17: 0.13 | D17: 0.156 | E17: 0.072537878 | F17: 0.13
A18: 神戸阪急 | B18: 26/12/16(水)-27/1/7(木)（21日間） | C18: 0.12 | D18: 0.12 | E18: 0.055798368 | F18: 0.12
A19: 鳥取島根 夢みなとタワー | B19: 27/3/15-4/4（21日間） | C19: 0.09 | D19: 0.09 | E19: 0.041848776 | F19: 0.09
A20: 東京凱旋 東京建物ぴあホール | B20: 27年4-5月（25日間） | C20: 0.5 | D20: 0.5 | E20: 0.5 | F20: 0.5
A21: ※③は企画概要書の計画値に札幌の計画比達成率 46.5% を乗じたもの（凱旋は据置）
A23: 東京対比：石川 香林坊大和 | B23: =INDEX(C16:F16,前提・入力!$B$14) -> 0.11 | C23: 緑字＝シナリオ選択で自動決定 ／ ユーザー指定
A24: 東京対比：仙台 Ebeans | B24: =INDEX(C17:F17,前提・入力!$B$14) -> 0.13 | C24: 緑字＝シナリオ選択で自動決定 ／ ユーザー指定（コナン実績は10.5%）
A25: 東京対比：神戸阪急 | B25: =INDEX(C18:F18,前提・入力!$B$14) -> 0.12 | C25: 緑字＝シナリオ選択で自動決定 ／ ★要確認：指定なきため仮置き
A26: 東京対比：鳥取島根 夢みなとタワー | B26: =INDEX(C19:F19,前提・入力!$B$14) -> 0.09 | C26: 緑字＝シナリオ選択で自動決定 ／ ユーザー指定
A27: 東京対比：東京凱旋 東京建物ぴあホール | B27: =INDEX(C20:F20,前提・入力!$B$14) -> 0.5 | C27: 緑字＝シナリオ選択で自動決定 ／ ユーザー指定（初回東京の50%）
A28: ［参考］コナンカフェ2026 東京対比 | C28: 大阪53.6% 名古屋26.8% 神奈川19.1% 北海道13.3% 仙台10.5%
A29: ■ ③石川以降 LEGS構成比 前提
A30: LEGS 金額構成比（石川以降） | B30: 0.18365018 | C30: 札幌の会期20日予測値。大阪21.1%→札幌19.6%の到達点を採用
A31: LEGS 平均単価（税込） | B31: 764 | C31: 札幌20日予測ミックスの加重平均単価
A32: 商品別按分：大阪20日実績の構成比ウェイト | B32: 0.5
A33: 商品別按分：札幌20日予測の構成比ウェイト | B33: 0.5 | C33: 大阪ウェイトとの合計が100%になるよう設定
A34: ■ ④追加発注 前提
A35: 安全率（不足数に対する上乗せ） | B35: 0.1 | C35: 推奨発注数＝不足数×(1+安全率)を切り上げ
A36: ［参考］残在庫想定 全品計（梅田まで(SET)） | B36: 274688 | C36: 在庫フロー台帳の最終実在庫列。商品別の実数を③⑧⑩⑪シートで直接使用
A37: 札幌 会期末残在庫のスライド率 | B37: 1 | C37: 札幌終了在庫を石川以降へ回せる割合
A38: 発注〜納品バッファ日数（輸送・検品） | B38: 14 | C38: 発注期限＝会場初日 − 生産日数 − 本バッファ。⑪シートで使用
A39: 基準日 | B39: 46233 | C39: 生産日数の提示日＝2026/7/28。残日数の起点

Sheet ①札幌予測確定
A1: ① 札幌会場 会期20日間（7/22-8/10）商品別 販売予測【確定値】
A2: 算出根拠：東京を除く名古屋①・博多②・大阪④の「20日累計 ÷ 初6日」倍率を商品別に加重平均し、札幌の初6日(7/22-7/27)実績に乗算
A3: 加重：大阪2・博多1・名古屋1（「前提・入力」シートで変更可）／名古屋は19日全会期実績を20日相当に換算（+4.83%）
A6: No. | B6: JAN | C6: 商品名 | D6: 税込 単価 | E6: 札幌 初6日 7/22-27 | F6: 名古屋① 初6日 | G6: 名古屋① 19日累計 (全会期) | H6: 名古屋 倍率g | I6: 博多② 初6日 | J6: 博多② 20日累計 | K6: 博多 倍率g | L6: 大阪④ 初6日 | M6: 大阪④ 20日累計 | N6: 大阪 倍率g | O6: 採用 倍率g | P6: 札幌 会期20日 予測販売数 | Q6: 札幌 予測販売金額 | R6: 札幌 数量構成比 | S6: 札幌 販売可能数 (追納込) | T6: 予測 消化率 | U6: 会期末 残在庫 | V6: 会期中 過不足 | W6: 会期中 在庫判定
A7: 1 | B7: 4515142545082 | C7: 呪術廻戦 メタリックポストカード 展示会キービジュアル | D7: 500 | E7: 261 | F7: 790 | G7: 1316 | H7: =IF(F7=0,"",G7*(1+前提・入力!$B$9)/F7) -> 1.7462688 | I7: 559 | J7: 987 | K7: =IF(I7=0,"",J7/I7) -> 1.765653 | L7: 1277 | M7: 2325 | N7: =IF(L7=0,"",M7/L7) -> 1.8206735 | O7: =IFERROR((IF(N7="",0,N7*前提・入力!$B$5)+IF(K7="",0,K7*前提・入力!$B$6)+IF(H7="",0,H7*前提・入力!$B$7))/(IF(N7="",0,前提・入力!$B$5)+IF(K7="",0,前提・入力!$B$6)+IF(H7="",0,前提・入力!$B$7)),前提・入力!$B$10) -> 1.7883172 | P7: =ROUND(E7*O7,0) -> 467 | Q7: =P7*D7 -> 233500 | R7: =IFERROR(P7/P$49,0) -> 0.053432494 | S7: 1000 | T7: =IFERROR(P7/S7,0) -> 0.467 | U7: =MAX(0,S7-P7) -> 533 | V7: =P7-S7 -> -533 | W7: =IF(V7>0,"会期中に在庫切れ",IF(T7>=0.9,"要注意(90%超)",IF(T7>=0.5,"適正","在庫余剰"))) -> 在庫余剰
A8: 2 | B8: 4515142545099 | C8: 呪術廻戦 クリアファイル 展示会キービジュアル | D8: 600 | E8: 283 | F8: 812 | G8: 1466 | H8: =IF(F8=0,"",G8*(1+前提・入力!$B$9)/F8) -> 1.8926061 | I8: 486 | J8: 898 | K8: =IF(I8=0,"",J8/I8) -> 1.8477366 | L8: 1137 | M8: 1965 | N8: =IF(L8=0,"",M8/L8) -> 1.7282322 | O8: =IFERROR((IF(N8="",0,N8*前提・入力!$B$5)+IF(K8="",0,K8*前提・入力!$B$6)+IF(H8="",0,H8*前提・入力!$B$7))/(IF(N8="",0,前提・入力!$B$5)+IF(K8="",0,前提・入力!$B$6)+IF(H8="",0,前提・入力!$B$7)),前提・入力!$B$10) -> 1.7992018 | P8: =ROUND(E8*O8,0) -> 509 | Q8: =P8*D8 -> 305400 | R8: =IFERROR(P8/P$49,0) -> 0.058237986 | S8: 1000 | T8: =IFERROR(P8/S8,0) -> 0.509 | U8: =MAX(0,S8-P8) -> 491 | V8: =P8-S8 -> -491 | W8: =IF(V8>0,"会期中に在庫切れ",IF(T8>=0.9,"要注意(90%超)",IF(T8>=0.5,"適正","在庫余剰"))) -> 適正
A9: 3 | B9: 4515142545105 | C9: 呪術廻戦 懐玉・玉折 ポストカードセット（5枚入） | D9: 1000 | E9: 102 | F9: 430 | G9: 601 | H9: =IF(F9=0,"",G9*(1+前提・入力!$B$9)/F9) -> 1.465171 | I9: 217 | J9: 384 | K9: =IF(I9=0,"",J9/I9) -> 1.7695853 | L9: 715 | M9: 1132 | N9: =IF(L9=0,"",M9/L9) -> 1.5832168 | O9: =IFERROR((IF(N9="",0,N9*前提・入力!$B$5)+IF(K9="",0,K9*前提・入力!$B$6)+IF(H9="",0,H9*前提・入力!$B$7))/(IF(N9="",0,前提・入力!$B$5)+IF(K9="",0,前提・入力!$B$6)+IF(H9="",0,前提・入力!$B$7)),前提・入力!$B$10) -> 1.6002974 | P9: =ROUND(E9*O9,0) -> 163 | Q9: =P9*D9 -> 163000 | R9: =IFERROR(P9/P$49,0) -> 0.018649886 | S9: 450 | T9: =IFERROR(P9/S9,0) -> 0.36222222 | U9: =MAX(0,S9-P9) -> 287 | V9: =P9-S9 -> -287 | W9: =IF(V9>0,"会期中に在庫切れ",IF(T9>=0.9,"要注意(90%超)",IF(T9>=0.5,"適正","在庫余剰"))) -> 在庫余剰
A10: 4 | B10: 4515142545112 | C10: 呪術廻戦 渋谷事変 ポストカードセット（9枚入） | D10: 1800 | E10: 144 | F10: 666 | G10: 922 | H10: =IF(F10=0,"",G10*(1+前提・入力!$B$9)/F10) -> 1.4512391 | I10: 280 | J10: 442 | K10: =IF(I10=0,"",J10/I10) -> 1.5785714 | L10: 784 | M10: 1310 | N10: =IF(L10=0,"",M10/L10) -> 1.6709184 | O10: =IFERROR((IF(N10="",0,N10*前提・入力!$B$5)+IF(K10="",0,K10*前提・入力!$B$6)+IF(H10="",0,H10*前提・入力!$B$7))/(IF(N10="",0,前提・入力!$B$5)+IF(K10="",0,前提・入力!$B$6)+IF(H10="",0,前提・入力!$B$7)),前提・入力!$B$10) -> 1.5929118 | P10: =ROUND(E10*O10,0) -> 229 | Q10: =P10*D10 -> 412200 | R10: =IFERROR(P10/P$49,0) -> 0.026201373 | S10: 800 | T10: =IFERROR(P10/S10,0) -> 0.28625 | U10: =MAX(0,S10-P10) -> 571 | V10: =P10-S10 -> -571 | W10: =IF(V10>0,"会期中に在庫切れ",IF(T10>=0.9,"要注意(90%超)",IF(T10>=0.5,"適正","在庫余剰"))) -> 在庫余剰
A11: 5 | B11: 4515142545129 | C11: 呪術廻戦 懐玉・玉折 ブラインド缶バッジ（全5種） | D11: 600 | E11: 268 | F11: 7505 | G11: 10777 | H11: =IF(F11=0,"",G11*(1+前提・入力!$B$9)/F11) -> 1.5053222 | I11: 2716 | J11: 6948 | K11: =IF(I11=0,"",J11/I11) -> 2.5581738 | L11: 6209 | M11: 8936 | N11: =IF(L11=0,"",M11/L11) -> 1.4392012 | O11: =IFERROR((IF(N11="",0,N11*前提・入力!$B$5)+IF(K11="",0,K11*前提・入力!$B$6)+IF(H11="",0,H11*前提・入力!$B$7))/(IF(N11="",0,前提・入力!$B$5)+IF(K11="",0,前提・入力!$B$6)+IF(H11="",0,前提・入力!$B$7)),前提・入力!$B$10) -> 1.7354746 | P11: =ROUND(E11*O11,0) -> 465 | Q11: =P11*D11 -> 279000 | R11: =IFERROR(P11/P$49,0) -> 0.053203661 | S11: 9000 | T11: =IFERROR(P11/S11,0) -> 0.051666667 | U11: =MAX(0,S11-P11) -> 8535 | V11: =P11-S11 -> -8535 | W11: =IF(V11>0,"会期中に在庫切れ",IF(T11>=0.9,"要注意(90%超)",IF(T11>=0.5,"適正","在庫余剰"))) -> 在庫余剰
A12: 6 | B12: 4515142545136 | C12: 呪術廻戦 渋谷事変 ブラインド缶バッジ（全9種） | D12: 600 | E12: 704 | F12: 10406 | G12: 15602 | H12: =IF(F12=0,"",G12*(1+前提・入力!$B$9)/F12) -> 1.5717329 | I12: 3521 | J12: 8314 | K12: =IF(I12=0,"",J12/I12) -> 2.361261 | L12: 10485 | M12: 18611 | N12: =IF(L12=0,"",M12/L12) -> 1.7750119 | O12: =IFERROR((IF(N12="",0,N12*前提・入力!$B$5)+IF(K12="",0,K12*前提・入力!$B$6)+IF(H12="",0,H12*前提・入力!$B$7))/(IF(N12="",0,前提・入力!$B$5)+IF(K12="",0,前提・入力!$B$6)+IF(H12="",0,前提・入力!$B$7)),前提・入力!$B$10) -> 1.8707544 | P12: =ROUND(E12*O12,0) -> 1317 | Q12: =P12*D12 -> 790200 | R12: =IFERROR(P12/P$49,0) -> 0.1506865 | S12: 13991 | T12: =IFERROR(P12/S12,0) -> 0.094131942 | U12: =MAX(0,S12-P12) -> 12674 | V12: =P12-S12 -> -12674 | W12: =IF(V12>0,"会期中に在庫切れ",IF(T12>=0.9,"要注意(90%超)",IF(T12>=0.5,"適正","在庫余剰"))) -> 在庫余剰
A13: 7 | B13: 4515142545143 | C13: 呪術廻戦 懐玉・玉折 ブラインドダイカットステッカー（全5種） | D13: 600 | E13: 108 | F13: 282 | G13: 520 | H13: =IF(F13=0,"",G13*(1+前提・入力!$B$9)/F13) -> 1.9330208 | I13: 190 | J13: 349 | K13: =IF(I13=0,"",J13/I13) -> 1.8368421 | L13: 551 | M13: 940 | N13: =IF(L13=0,"",M13/L13) -> 1.7059891 | O13: =IFERROR((IF(N13="",0,N13*前提・入力!$B$5)+IF(K13="",0,K13*前提・入力!$B$6)+IF(H13="",0,H13*前提・入力!$B$7))/(IF(N13="",0,前提・入力!$B$5)+IF(K13="",0,前提・入力!$B$6)+IF(H13="",0,前提・入力!$B$7)),前提・入力!$B$10) -> 1.7954603 | P13: =ROUND(E13*O13,0) -> 194 | Q13: =P13*D13 -> 116400 | R13: =IFERROR(P13/P$49,0) -> 0.022196796 | S13: 350 | T13: =IFERROR(P13/S13,0) -> 0.55428571 | U13: =MAX(0,S13-P13) -> 156 | V13: =P13-S13 -> -156 | W13: =IF(V13>0,"会期中に在庫切れ",IF(T13>=0.9,"要注意(90%超)",IF(T13>=0.5,"適正","在庫余剰"))) -> 適正
A14: 8 | B14: 4515142545150 | C14: 呪術廻戦 渋谷事変 ブラインドダイカットステッカー（全9種） | D14: 600 | E14: 173 | F14: 588 | G14: 1107 | H14: =IF(F14=0,"",G14*(1+前提・入力!$B$9)/F14) -> 1.9735702 | I14: 330 | J14: 608 | K14: =IF(I14=0,"",J14/I14) -> 1.8424242 | L14: 972 | M14: 1758 | N14: =IF(L14=0,"",M14/L14) -> 1.808642 | O14: =IFERROR((IF(N14="",0,N14*前提・入力!$B$5)+IF(K14="",0,K14*前提・入力!$B$6)+IF(H14="",0,H14*前提・入力!$B$7))/(IF(N14="",0,前提・入力!$B$5)+IF(K14="",0,前提・入力!$B$6)+IF(H14="",0,前提・入力!$B$7)),前提・入力!$B$10) -> 1.8583196 | P14: =ROUND(E14*O14,0) -> 321 | Q14: =P14*D14 -> 192600 | R14: =IFERROR(P14/P$49,0) -> 0.036727689 | S14: 900 | T14: =IFERROR(P14/S14,0) -> 0.35666667 | U14: =MAX(0,S14-P14) -> 579 | V14: =P14-S14 -> -579 | W14: =IF(V14>0,"会期中に在庫切れ",IF(T14>=0.9,"要注意(90%超)",IF(T14>=0.5,"適正","在庫余剰"))) -> 在庫余剰
A15: 9 | B15: 4515142545372 | C15: 呪術廻戦 懐玉・玉折 クリアファイル（五条 悟） | D15: 600 | E15: 87 | F15: 225 | G15: 313 | H15: =IF(F15=0,"",G15*(1+前提・入力!$B$9)/F15) -> 1.4582907 | I15: 185 | J15: 265 | K15: =IF(I15=0,"",J15/I15) -> 1.4324324 | L15: 494 | M15: 743 | N15: =IF(L15=0,"",M15/L15) -> 1.5040486 | O15: =IFERROR((IF(N15="",0,N15*前提・入力!$B$5)+IF(K15="",0,K15*前提・入力!$B$6)+IF(H15="",0,H15*前提・入力!$B$7))/(IF(N15="",0,前提・入力!$B$5)+IF(K15="",0,前提・入力!$B$6)+IF(H15="",0,前提・入力!$B$7)),前提・入力!$B$10) -> 1.4747051 | P15: =ROUND(E15*O15,0) -> 128 | Q15: =P15*D15 -> 76800 | R15: =IFERROR(P15/P$49,0) -> 0.014645309 | S15: 300 | T15: =IFERROR(P15/S15,0) -> 0.42666667 | U15: =MAX(0,S15-P15) -> 172 | V15: =P15-S15 -> -172 | W15: =IF(V15>0,"会期中に在庫切れ",IF(T15>=0.9,"要注意(90%超)",IF(T15>=0.5,"適正","在庫余剰"))) -> 在庫余剰
A16: 10 | B16: 4515142545389 | C16: 呪術廻戦 懐玉・玉折 クリアファイル（夏油 傑） | D16: 600 | E16: 33 | F16: 96 | G16: 141 | H16: =IF(F16=0,"",G16*(1+前提・入力!$B$9)/F16) -> 1.5396789 | I16: 80 | J16: 108 | K16: =IF(I16=0,"",J16/I16) -> 1.35 | L16: 187 | M16: 277 | N16: =IF(L16=0,"",M16/L16) -> 1.4812834 | O16: =IFERROR((IF(N16="",0,N16*前提・入力!$B$5)+IF(K16="",0,K16*前提・入力!$B$6)+IF(H16="",0,H16*前提・入力!$B$7))/(IF(N16="",0,前提・入力!$B$5)+IF(K16="",0,前提・入力!$B$6)+IF(H16="",0,前提・入力!$B$7)),前提・入力!$B$10) -> 1.4630614 | P16: =ROUND(E16*O16,0) -> 48 | Q16: =P16*D16 -> 28800 | R16: =IFERROR(P16/P$49,0) -> 0.0054919908 | S16: 100 | T16: =IFERROR(P16/S16,0) -> 0.48 | U16: =MAX(0,S16-P16) -> 52 | V16: =P16-S16 -> -52 | W16: =IF(V16>0,"会期中に在庫切れ",IF(T16>=0.9,"要注意(90%超)",IF(T16>=0.5,"適正","在庫余剰"))) -> 在庫余剰
A17: 11 | B17: 4515142545396 | C17: 呪術廻戦 懐玉・玉折 クリアファイル（家入 硝子） | D17: 600 | E17: 10 | F17: 11 | G17: 37 | H17: =IF(F17=0,"",G17*(1+前提・入力!$B$9)/F17) -> 3.5260732 | I17: 17 | J17: 30 | K17: =IF(I17=0,"",J17/I17) -> 1.7647059 | L17: 36 | M17: 78 | N17: =IF(L17=0,"",M17/L17) -> 2.1666667 | O17: =IFERROR((IF(N17="",0,N17*前提・入力!$B$5)+IF(K17="",0,K17*前提・入力!$B$6)+IF(H17="",0,H17*前提・入力!$B$7))/(IF(N17="",0,前提・入力!$B$5)+IF(K17="",0,前提・入力!$B$6)+IF(H17="",0,前提・入力!$B$7)),前提・入力!$B$10) -> 2.4060281 | P17: =ROUND(E17*O17,0) -> 24 | Q17: =P17*D17 -> 14400 | R17: =IFERROR(P17/P$49,0) -> 0.0027459954 | S17: 50 | T17: =IFERROR(P17/S17,0) -> 0.48 | U17: =MAX(0,S17-P17) -> 26 | V17: =P17-S17 -> -26 | W17: =IF(V17>0,"会期中に在庫切れ",IF(T17>=0.9,"要注意(90%超)",IF(T17>=0.5,"適正","在庫余剰"))) -> 在庫余剰
A18: 12 | B18: 4515142545402 | C18: 呪術廻戦 懐玉・玉折 クリアファイル（七海 建人） | D18: 600 | E18: 19 | F18: 41 | G18: 58 | H18: =IF(F18=0,"",G18*(1+前提・入力!$B$9)/F18) -> 1.4829497 | I18: 20 | J18: 43 | K18: =IF(I18=0,"",J18/I18) -> 2.15 | L18: 83 | M18: 142 | N18: =IF(L18=0,"",M18/L18) -> 1.7108434 | O18: =IFERROR((IF(N18="",0,N18*前提・入力!$B$5)+IF(K18="",0,K18*前提・入力!$B$6)+IF(H18="",0,H18*前提・入力!$B$7))/(IF(N18="",0,前提・入力!$B$5)+IF(K18="",0,前提・入力!$B$6)+IF(H18="",0,前提・入力!$B$7)),前提・入力!$B$10) -> 1.7636591 | P18: =ROUND(E18*O18,0) -> 34 | Q18: =P18*D18 -> 20400 | R18: =IFERROR(P18/P$49,0) -> 0.0038901602 | S18: 50 | T18: =IFERROR(P18/S18,0) -> 0.68 | U18: =MAX(0,S18-P18) -> 16 | V18: =P18-S18 -> -16 | W18: =IF(V18>0,"会期中に在庫切れ",IF(T18>=0.9,"要注意(90%超)",IF(T18>=0.5,"適正","在庫余剰"))) -> 適正
... A48: 42 | B48: 4515142545365 | C48: 伏黒 恵 イメージフラグメントケース | D48: 25000 | E48: 1 | F48: 4 | G48: 8 | H48: =IF(F48=0,"",G48*(1+前提・入力!$B$9)/F48) -> 2.0965841 | I48: 1 | J48: 2 | K48: =IF(I48=0,"",J48/I48) -> 2 | L48: 4 | M48: 8 | N48: =IF(L48=0,"",M48/L48) -> 2 | O48: =IFERROR((IF(N48="",0,N48*前提・入力!$B$5)+IF(K48="",0,K48*前提・入力!$B$6)+IF(H48="",0,H48*前提・入力!$B$7))/(IF(N48="",0,前提・入力!$B$5)+IF(K48="",0,前提・入力!$B$6)+IF(H48="",0,前提・入力!$B$7)),前提・入力!$B$10) -> 2.024146 | P48: =ROUND(E48*O48,0) -> 2 | Q48: =P48*D48 -> 50000 | R48: =IFERROR(P48/P$49,0) -> 0.00022883295 | S48: 6 | T48: =IFERROR(P48/S48,0) -> 0.33333333 | U48: =MAX(0,S48-P48) -> 4 | V48: =P48-S48 -> -4 | W48: =IF(V48>0,"会期中に在庫切れ",IF(T48>=0.9,"要注意(90%超)",IF(T48>=0.5,"適正","在庫余剰"))) -> 在庫余剰
C49: 合計（LEGS 42SKU） | E49: =SUM(E7:E48) -> 5077 | F49: =SUM(F7:F48) -> 38843 | G49: =SUM(G7:G48) -> 58600 | I49: =SUM(I7:I48) -> 15767 | J49: =SUM(J7:J48) -> 33235 | L49: =SUM(L7:L48) -> 38417 | M49: =SUM(M7:M48) -> 63740 | O49: =IFERROR(P49/E49,0) -> 1.7214891 | P49: =SUM(P7:P48) -> 8740 | Q49: =SUM(Q7:Q48) -> 6680400 | R49: 1 | S49: =SUM(S7:S48) -> 50506 | T49: =IFERROR(P49/S49,0) -> 0.17304875 | U49: =SUM(U7:U48) -> 41768 | V49: =SUM(V7:V48) -> -41766 | W49: =COUNTIF(W7:W48,"会期中に在庫切れ")&"品目" -> 1品目

Sheet ②会場別構成比
A1: ② 会場別 物販実績とLEGS構成比／東京対比 会場比率
A2: 物販売上＝レジ袋代・音声ガイド・当日券を除く商品売上（税込）。LEGS＝本42SKU（各会場の商品分類「レッグス」と完全一致）
A4: ■ 会場別 実績・予測サマリー
A5: 項目 | B5: 東京対比 算出根拠 | C5: 東京 | D5: 名古屋 | E5: 博多 | F5: 大阪 | G5: 札幌 | H5: 札幌(予測) | I5: 石川 香林坊大和 | J5: 仙台 Ebeans | K5: 神戸阪急 | L5: 鳥取島根 夢みなとタワー | M5: 東京凱旋 東京建物ぴあホール
A6: 会期 | C6: 25/12/5(金)-12/29(月) 池袋サンシャインシティ | D6: 26/3/18(水)-4/5(日) 松坂屋 | E6: 26/4/23(木)-5/18(月) 博多阪急 | F6: 26/6/10(水)-6/29(月) 阪急梅田 | G6: 26/7/22(水)-8/10(月) 札幌大丸 | H6: 26/7/22(水)-8/10(月) 会期20日 予測 | I6: 26/8/14(金)-8/31(月) 石川 香林坊大和 | J6: 26/9/5(土)-10/4(日) 仙台 Ebeans | K6: 26/12/16(水)-27/1/7(木) 神戸阪急 | L6: 27/3/15-4/4 鳥取島根 夢みなとタワー | M6: 27年4-5月 東京凱旋 東京建物ぴあホール
A7: 会期日数 | C7: 25 | D7: 19 | E7: 26 | F7: 20 | G7: 20 | H7: 20 | I7: 18 | J7: 30 | K7: 21 | L7: 21 | M7: 25
A8: データ実績日数 | C8: 25 | D8: 19 | E8: 26 | F8: 20 | G8: 8 | H8: 予測 | I8: 予測 | J8: 予測 | K8: 予測 | L8: 予測 | M8: 予測
A9: 入場者数 | C9: 47339 | D9: 19764 | E9: 18993 | F9: 31267 | G9: 3880 | H9: 7784
A10: 全物販 販売数量 | C10: 383342 | D10: 169802 | E10: 112198 | F10: 238658 | G10: 22685 | H10: =G10*1.642236 -> 37254.124 | I10: =前提・入力!$B$13*前提・入力!$B$23 -> 42167.62 | J10: =前提・入力!$B$13*前提・入力!$B$24 -> 49834.46 | K10: =前提・入力!$B$13*前提・入力!$B$25 -> 46001.04 | L10: =前提・入力!$B$13*前提・入力!$B$26 -> 34500.78 | M10: =前提・入力!$B$13*前提・入力!$B$27 -> 191671
A11: 全物販 販売金額(税込) | C11: 358193925 | D11: 138575410 | E11: 105540655 | F11: 215184570 | G11: 22859680 | H11: =G11*1.591259 -> 36375672 | I11: =前提・入力!$B$12*前提・入力!$B$23 -> 39401332 | J11: =前提・入力!$B$12*前提・入力!$B$24 -> 46565210 | K11: =前提・入力!$B$12*前提・入力!$B$25 -> 42983271 | L11: =前提・入力!$B$12*前提・入力!$B$26 -> 32237453 | M11: =前提・入力!$B$12*前提・入力!$B$27 -> 1.7909696e+08
A12: LEGS 販売数量 | C12: 148185 | D12: 58600 | E12: 44871 | F12: 63740 | G12: 5077 | H12: =①札幌予測確定!P49 -> 8740 | I12: =ROUND(I13/前提・入力!$B$31,0) -> 9471 | J12: =ROUND(J13/前提・入力!$B$31,0) -> 11193 | K12: =ROUND(K13/前提・入力!$B$31,0) -> 10332 | L12: =ROUND(L13/前提・入力!$B$31,0) -> 7749 | M12: =ROUND(M13/前提・入力!$B$31,0) -> 43051
A13: LEGS 販売金額(税込) | C13: 102186200 | D13: 41479600 | E13: 31026800 | F13: 45507600 | G13: 4058700 | H13: =①札幌予測確定!Q49 -> 6680400 | I13: =I11*前提・入力!$B$30 -> 7236061.8 | J13: =J11*前提・入力!$B$30 -> 8551709.4 | K13: =K11*前提・入力!$B$30 -> 7893885.6 | L13: =L11*前提・入力!$B$30 -> 5920414.2 | M13: =M11*前提・入力!$B$30 -> 32891190
A14: LEGS 数量構成比 | C14: =C12/C10 -> 0.38656083 | D14: =D12/D10 -> 0.34510783 | E14: =E12/E10 -> 0.39992691 | F14: =F12/F10 -> 0.26707674 | G14: =G12/G10 -> 0.22380428 | H14: =H12/H10 -> 0.2346049 | I14: =I12/I10 -> 0.22460362 | J14: =J12/J10 -> 0.22460362 | ... M14: =M12/M10 -> 0.22460883
A15: LEGS 金額構成比 | C15: =C13/C11 -> 0.28528178 | D15: =D13/D11 -> 0.29932872 | E15: =E13/E11 -> 0.2939796 | F15: =F13/F11 -> 0.21148171 | G15: =G13/G11 -> 0.17754842 | H15: =H13/H11 -> 0.18365022 | I15: =I13/I11 -> 0.18365018 | J15: =J13/J11 -> 0.18365018 | ... M15: =M13/M11 -> 0.18365018
A16: 東京対比（数量） | C16: =C10/$C$10 -> 1 | D16: =D10/$C$10 -> 0.44295172 | E16: =E10/$C$10 -> 0.29268382 | F16: =F10/$C$10 -> 0.62257201 | G16: =G10/$C$10 -> 0.059176923 | H16: =H10/$C$10 -> 0.097182473 | I16: =I10/$C$10 -> 0.11 | J16: =J10/$C$10 -> 0.13 | ... M16: =M10/$C$10 -> 0.5
A17: 東京対比（金額） | B17: ユーザー指定／入力値 | C17: =C11/$C$11 -> 1 | D17: =D11/$C$11 -> 0.38687259 | E17: =E11/$C$11 -> 0.29464669 | F17: =F11/$C$11 -> 0.6007488 | G17: =G11/$C$11 -> 0.063819284 | H17: =H11/$C$11 -> 0.10155301 | I17: =前提・入力!$B$23 -> 0.11 | J17: =前提・入力!$B$24 -> 0.13 | K17: =前提・入力!$B$25 -> 0.12 | L17: =前提・入力!$B$26 -> 0.09 | M17: =前提・入力!$B$27 -> 0.5
A18: LEGS平均単価 | C18: =IFERROR(C13/C12,0) -> 689.58532 | D18: =IFERROR(D13/D12,0) -> 707.843 | E18: =IFERROR(E13/E12,0) -> 691.46665 | F18: =IFERROR(F13/F12,0) -> 713.9567 | G18: =IFERROR(G13/G12,0) -> 799.4288 | H18: =H13/H12 -> 764.34783 | I18: =I13/I12 -> 764.023 | J18: =J13/J12 -> 764.023 | K18: =K13/K12 -> 764.023 | L18: =L13/L12 -> 764.023 | M18: =M13/M12 -> 764.00525
A21: ■ 供給元別 金額構成比（各会場 会期全体。札幌は初6日実績）
A22: 供給元 | C22: 東京 | D22: 名古屋 | E22: 博多 | F22: 大阪 | G22: 札幌
A23: LEGS(42SKU) | C23: 0.28528178 | D23: 0.29932872 | E23: 0.2939796 | F23: 0.21148171 | G23: 0.17754842
A24: ムービック | C24: 0.53383923 | D24: 0.35138442 | E24: 0.32105543 | F24: 0.41894519 | G24: 0.41005955
A25: 東宝 | C25: 0.092163721 | D25: 0.078365491 | E25: 0.078289309 | F25: 0.15216207 | G25: 0.16130191
A26: MAPPA | C26: 0 | D26: 0.23618072 | E26: 0.23252348 | F26: 0.14301109 | G26: 0.18314255
A27: MBS | C27: 0.033272116 | D27: 0.034740651 | E27: 0.074152183 | F27: 0.074399944 | G27: 0.067947583
A28: 書籍 | C28: 0.055443151 | D28: 0 | E28: 0 | F28: 0 | G28: 0
A29: その他 | C29: 0 | D29: 0 | E29: 0 | F29: 0 | G29: 0
A30: 合計 | C30: =SUM(C23:C29) -> 1 | D30: =SUM(D23:D29) -> 1 | E30: =SUM(E23:E29) -> 1 | F30: =SUM(F23:F29) -> 1 | G30: =SUM(G23:G29) -> 1
A32: ■ 新規SKU投入状況（前会場までに存在しなかったJAN）
A33: 会場 | C33: 総SKU数 | D33: 新規SKU数 | E33: 新規の金額シェア(初6日) | F33: LEGS金額構成比(初6日) | G33: 備考
A34: 東京 | C34: 332 | D34: 332 | E34: 1 | F34: 0.29443142 | G34: 初回会場
A35: 名古屋 | C35: 416 | D35: 85 | E35: 0.21558758 | F35: 0.31478048 | G35: MAPPA記念商品26SKU等を追加投入
A36: 博多 | C36: 435 | D36: 19 | E36: 0.15170241 | F36: 0.2439191 | G36: 小幅追加
A37: 大阪 | C37: 515 | D37: 106 | E37: 0.19121268 | F37: 0.206477 | G37: ★新商品106SKU投入（東宝一般66・ムービック23・MAPPA16）
A38: 札幌 | C38: 382 | D38: 0 | E38: 0 | F38: 0.17754842 | G38: 新規なし。品揃えは大阪と同一

Sheet ③石川以降予測
A1: ③ 石川会場以降 5会場 LEGS商品 需要予測
A2: 会場物販売上＝東京(初回)実績 × 東京対比比率 ／ LEGS売上＝会場物販売上 × LEGS金額構成比 ／ LEGS数量＝LEGS売上 ÷ LEGS平均単価
A3: 商品別按分＝大阪20日実績の数量構成比 × ウェイト ＋ 札幌20日予測の数量構成比 × ウェイト（「前提・入力」で調整可）
A4: ※商品別表の必要数合計は、会場×商品ごとに整数丸めを行うため会場別表の合計と数個の差が生じる（発注判断に影響しない範囲）
A5: ■ 会場別 需要予測
A6: 会場 | B6: 会期 | C6: 日数 | D6: 東京対比 | E6: 会場 全物販売上 | F6: LEGS 売上 | G6: LEGS 数量 | H6: 構成比根拠
A7: 石川 香林坊大和 | B7: 26/8/14(金)-8/31(月) | C7: 18 | D7: =前提・入力!$B$23 -> 0.11 | E7: =前提・入力!$B$12*D7 -> 39401332 | F7: =E7*前提・入力!$B$30 -> 7236061.8 | G7: =ROUND(F7/前提・入力!$B$31,0) -> 9471 | H7: ユーザー指定
A8: 仙台 Ebeans | B8: 26/9/5(土)-10/4(日) | C8: 30 | D8: =前提・入力!$B$24 -> 0.13 | E8: =前提・入力!$B$12*D8 -> 46565210 | F8: =E8*前提・入力!$B$30 -> 8551709.4 | G8: =ROUND(F8/前提・入力!$B$31,0) -> 11193 | H8: ユーザー指定（コナン実績は10.5%）
A9: 神戸阪急 | B9: 26/12/16(水)-27/1/7(木) | C9: 21 | D9: =前提・入力!$B$25 -> 0.12 | E9: =前提・入力!$B$12*D9 -> 42983271 | F9: =E9*前提・入力!$B$30 -> 7893885.6 | G9: =ROUND(F9/前提・入力!$B$31,0) -> 10332 | H9: ★要確認：指定なきため仮置き
A10: 鳥取島根 夢みなとタワー | B10: 27/3/15-4/4 | C10: 21 | D10: =前提・入力!$B$26 -> 0.09 | E10: =前提・入力!$B$12*D10 -> 32237453 | F10: =E10*前提・入力!$B$30 -> 5920414.2 | G10: =ROUND(F10/前提・入力!$B$31,0) -> 7749 | H10: ユーザー指定
A11: 東京凱旋 東京建物ぴあホール | B11: 27年4-5月 | C11: 25 | D11: =前提・入力!$B$27 -> 0.5 | E11: =前提・入力!$B$12*D11 -> 1.7909696e+08 | F11: =E11*前提・入力!$B$30 -> 32891190 | G11: =ROUND(F11/前提・入力!$B$31,0) -> 43051 | H11: ユーザー指定（初回東京の50%）
A12: 石川以降 5会場 合計 | D12: =SUM(D7:D11) -> 0.95 | E12: =SUM(E7:E11) -> 3.4028423e+08 | F12: =SUM(F7:F11) -> 62493261 | G12: =SUM(G7:G11) -> 81796
A14: ■ 在庫収支（LEGS 42SKU 合計）
A15: 残在庫想定（梅田まで(SET)／総計） | B15: 274688 | C15: 在庫フロー台帳の最終「実在庫」列。会場ごとの追加発注→販売→検品を積み上げた値
A16: うち札幌会場へ納品（初回＋追納） | B16: =①札幌予測確定!S49 -> 50506 | C16: 札幌の販売可能数。2026/7/31・8/1 札幌会場追納リスト（レッグス商品分のみ抜粋）（LEGS計310個）を含む
A17: 差引 倉庫残（石川以降へ即出荷可） | B17: =B15-B16 -> 224182 | C17: 札幌へ引き当てた分を除いた手元在庫
A18: 札幌 会期20日 予測販売数 | B18: =①札幌予測確定!P49 -> 8740
A19: うち札幌へ追納が必要 | B19: =R72 -> 2 | C19: 札幌の会期20日予測が納品済数を上回る分。倉庫残から充当する（運営欠品報告への対応分）
A20: 札幌 会期末 残在庫（返送見込） | B20: =①札幌予測確定!U49 -> 41768 | C20: 品目別に下限0で集計（在庫切れ品はマイナスにしない）
A21: うち石川以降へスライド可能 | B21: =B20*前提・入力!$B$37 -> 41768 | C21: スライド率は「前提・入力」で調整
A22: 石川以降 供給可能在庫 合計 | B22: =B17-B19+B21 -> 265948 | C22: ＝倉庫残 − 札幌への追納 ＋ 札幌からの返送スライド
A23: 確定済み追加発注（入荷予定） | B23: 1200 | C23: 発注判断済みの分。宿儺の指風お菓子 1,200SET（仙台 Ebeans入荷）
A24: 石川以降 5会場 必要数 | B24: =G12 -> 81796
A25: 全体過不足（供給可能＋確定発注−必要） | B25: =B22+B23-B24 -> 185352 | C25: プラス＝全体では在庫充足。ただし商品別には過不足が生じる
A26: 追加生産 必要数（商品別不足の合計） | B26: =W72 -> 2554 | C26: 下表の商品別「追加生産必要数」の合計。全体余剰でも品目別には不足が出る
A28: ■ 商品別 石川以降 必要数と在庫過不足
A29: No. | B29: JAN | C29: 商品名 | D29: 大阪④ 20日実績 | E29: 大阪 構成比 | F29: 札幌⑤ 20日予測 | G29: 札幌 構成比 | H29: 採用 按分構成比 | I29: 石川 必要数 | J29: 仙台 必要数 | K29: 神戸阪急 必要数 | L29: 鳥取島根 必要数 | M29: 東京凱旋 必要数 | N29: 石川以降 必要数 計 | O29: ★残在庫想定 (梅田会場後) | P29: うち札幌 納品済 | Q29: 差引 倉庫残 | R29: 札幌へ 追納必要数 | S29: 札幌会期末 返送(スライド) | T29: 石川以降 供給可能計 | U29: 確定発注 (入荷予定) | V29: 過不足 (必要−供給可能−確定) | W29: 追加生産 必要数 | X29: 推奨発注数 (安全率込)
A30: 1 | B30: 4515142545082 | C30: 呪術廻戦 メタリックポストカード 展示会キービジュアル | D30: 2325 | E30: =IFERROR(D30/D$72,0) -> 0.03647631 | F30: =①札幌予測確定!P7 -> 467 | G30: =IFERROR(F30/F$72,0) -> 0.053432494 | H30: =E30*前提・入力!$B$32+G30*前提・入力!$B$33 -> 0.044954402 | I30: =ROUND($H30*③石川以降予測!$G$7,0) -> 426 | J30: =ROUND($H30*③石川以降予測!$G$8,0) -> 503 | K30: =ROUND($H30*③石川以降予測!$G$9,0) -> 464 | L30: =ROUND($H30*③石川以降予測!$G$10,0) -> 348 | M30: =ROUND($H30*③石川以降予測!$G$11,0) -> 1935 | N30: =SUM(I30:M30) -> 3676 | O30: 3264 | P30: =①札幌予測確定!S7 -> 1000 | Q30: =O30-P30 -> 2264 | R30: =MAX(0,①札幌予測確定!P7-①札幌予測確定!S7) -> 0 | S30: =ROUND(①札幌予測確定!U7*前提・入力!$B$37,0) -> 533 | T30: =Q30-R30+S30 -> 2797 | U30: 0 | V30: =N30-T30-U30 -> 879 | W30: =MAX(0,V30) -> 879 | X30: =IF(W30>0,ROUNDUP(W30*(1+前提・入力!$B$35),0),0) -> 967
A31: 2 | B31: 4515142545099 | C31: 呪術廻戦 クリアファイル 展示会キービジュアル | D31: 1965 | E31: =IFERROR(D31/D$72,0) -> 0.030828365 | F31: =①札幌予測確定!P8 -> 509 | G31: =IFERROR(F31/F$72,0) -> 0.058237986 | H31: =E31*前提・入力!$B$32+G31*前提・入力!$B$33 -> 0.044533176 | I31: =ROUND($H31*③石川以降予測!$G$7,0) -> 422 | J31: =ROUND($H31*③石川以降予測!$G$8,0) -> 498 | K31: =ROUND($H31*③石川以降予測!$G$9,0) -> 460 | L31: =ROUND($H31*③石川以降予測!$G$10,0) -> 345 | M31: =ROUND($H31*③石川以降予測!$G$11,0) -> 1917 | N31: =SUM(I31:M31) -> 3642 | O31: 5037 | P31: =①札幌予測確定!S8 -> 1000 | Q31: =O31-P31 -> 4037 | R31: =MAX(0,①札幌予測確定!P8-①札幌予測確定!S8) -> 0 | S31: =ROUND(①札幌予測確定!U8*前提・入力!$B$37,0) -> 491 | T31: =Q31-R31+S31 -> 4528 | U31: 0 | V31: =N31-T31-U31 -> -886 | W31: =MAX(0,V31) -> 0 | X31: =IF(W31>0,ROUNDUP(W31*(1+前提・入力!$B$35),0),0) -> 0
A32: 3 | B32: 4515142545105 | C32: 呪術廻戦 懐玉・玉折 ポストカードセット（5枚入） | D32: 1132 | E32: =IFERROR(D32/D$72,0) -> 0.017759649 | F32: =①札幌予測確定!P9 -> 163 | G32: =IFERROR(F32/F$72,0) -> 0.018649886 | H32: =E32*前提・入力!$B$32+G32*前提・入力!$B$33 -> 0.018204767 | I32: =ROUND($H32*③石川以降予測!$G$7,0) -> 172 | J32: =ROUND($H32*③石川以降予測!$G$8,0) -> 204 | K32: =ROUND($H32*③石川以降予測!$G$9,0) -> 188 | L32: =ROUND($H32*③石川以降予測!$G$10,0) -> 141 | M32: =ROUND($H32*③石川以降予測!$G$11,0) -> 784 | N32: =SUM(I32:M32) -> 1489 | O32: 6140 | P32: =①札幌予測確定!S9 -> 450 | Q32: =O32-P32 -> 5690 | R32: =MAX(0,①札幌予測確定!P9-①札幌予測確定!S9) -> 0 | S32: =ROUND(①札幌予測確定!U9*前提・入力!$B$37,0) -> 287 | T32: =Q32-R32+S32 -> 5977 | U32: 0 | V32: =N32-T32-U32 -> -4488 | W32: =MAX(0,V32) -> 0 | X32: =IF(W32>0,ROUNDUP(W32*(1+前提・入力!$B$35),0),0) -> 0
A33: 4 | B33: 4515142545112 | C33: 呪術廻戦 渋谷事変 ポストカードセット（9枚入） | D33: 1310 | E33: =IFERROR(D33/D$72,0) -> 0.020552243 | F33: =①札幌予測確定!P10 -> 229 | G33: =IFERROR(F33/F$72,0) -> 0.026201373 | H33: =E33*前提・入力!$B$32+G33*前提・入力!$B$33 -> 0.023376808 | I33: =ROUND($H33*③石川以降予測!$G$7,0) -> 221 | J33: =ROUND($H33*③石川以降予測!$G$8,0) -> 262 | K33: =ROUND($H33*③石川以降予測!$G$9,0) -> 242 | L33: =ROUND($H33*③石川以降予測!$G$10,0) -> 181 | M33: =ROUND($H33*③石川以降予測!$G$11,0) -> 1006 | N33: =SUM(I33:M33) -> 1912 | O33: 27511 | P33: =①札幌予測確定!S10 -> 800 | Q33: =O33-P33 -> 26711 | R33: =MAX(0,①札幌予測確定!P10-①札幌予測確定!S10) -> 0 | S33: =ROUND(①札幌予測確定!U10*前提・入力!$B$37,0) -> 571 | T33: =Q33-R33+S33 -> 27282 | U33: 0 | V33: =N33-T33-U33 -> -25370 | W33: =MAX(0,V33) -> 0 | X33: =IF(W33>0,ROUNDUP(W33*(1+前提・入力!$B$35),0),0) -> 0
A34: 5 | B34: 4515142545129 | C34: 呪術廻戦 懐玉・玉折 ブラインド缶バッジ（全5種） | D34: 8936 | E34: =IFERROR(D34/D$72,0) -> 0.14019454 | F34: =①札幌予測確定!P11 -> 465 | G34: =IFERROR(F34/F$72,0) -> 0.053203661 | H34: =E34*前提・入力!$B$32+G34*前提・入力!$B$33 -> 0.096699101 | I34: =ROUND($H34*③石川以降予測!$G$7,0) -> 916 | J34: =ROUND($H34*③石川以降予測!$G$8,0) -> 1082 | K34: =ROUND($H34*③石川以降予測!$G$9,0) -> 999 | L34: =ROUND($H34*③石川以降予測!$G$10,0) -> 749 | M34: =ROUND($H34*③石川以降予測!$G$11,0) -> 4163 | N34: =SUM(I34:M34) -> 7909 | O34: 39825 | P34: =①札幌予測確定!S11 -> 9000 | Q34: =O34-P34 -> 30825 | R34: =MAX(0,①札幌予測確定!P11-①札幌予測確定!S11) -> 0 | S34: =ROUND(①札幌予測確定!U11*前提・入力!$B$37,0) -> 8535 | T34: =Q34-R34+S34 -> 39360 | U34: 0 | V34: =N34-T34-U34 -> -31451 | W34: =MAX(0,V34) -> 0 | X34: =IF(W34>0,ROUNDUP(W34*(1+前提・入力!$B$35),0),0) -> 0
A35: 6 | B35: 4515142545136 | C35: 呪術廻戦 渋谷事変 ブラインド缶バッジ（全9種） | D35: 18611 | E35: =IFERROR(D35/D$72,0) -> 0.29198306 | F35: =①札幌予測確定!P12 -> 1317 | G35: =IFERROR(F35/F$72,0) -> 0.1506865 | H35: =E35*前提・入力!$B$32+G35*前提・入力!$B$33 -> 0.22133478 | I35: =ROUND($H35*③石川以降予測!$G$7,0) -> 2096 | J35: =ROUND($H35*③石川以降予測!$G$8,0) -> 2477 | K35: =ROUND($H35*③石川以降予測!$G$9,0) -> 2287 | L35: =ROUND($H35*③石川以降予測!$G$10,0) -> 1715 | M35: =ROUND($H35*③石川以降予測!$G$11,0) -> 9529 | N35: =SUM(I35:M35) -> 18104 | O35: 50834 | P35: =①札幌予測確定!S12 -> 13991 | Q35: =O35-P35 -> 36843 | R35: =MAX(0,①札幌予測確定!P12-①札幌予測確定!S12) -> 0 | S35: =ROUND(①札幌予測確定!U12*前提・入力!$B$37,0) -> 12674 | T35: =Q35-R35+S35 -> 49517 | U35: 0 | V35: =N35-T35-U35 -> -31413 | W35: =MAX(0,V35) -> 0 | X35: =IF(W35>0,ROUNDUP(W35*(1+前提・入力!$B$35),0),0) -> 0
A36: 7 | B36: 4515142545143 | C36: 呪術廻戦 懐玉・玉折 ブラインドダイカットステッカー（全5種） | D36: 940 | E36: =IFERROR(D36/D$72,0) -> 0.014747411 | F36: =①札幌予測確定!P13 -> 194 | G36: =IFERROR(F36/F$72,0) -> 0.022196796 | H36: =E36*前提・入力!$B$32+G36*前提・入力!$B$33 -> 0.018472104 | I36: =ROUND($H36*③石川以降予測!$G$7,0) -> 175 | J36: =ROUND($H36*③石川以降予測!$G$8,0) -> 207 | K36: =ROUND($H36*③石川以降予測!$G$9,0) -> 191 | L36: =ROUND($H36*③石川以降予測!$G$10,0) -> 143 | M36: =ROUND($H36*③石川以降予測!$G$11,0) -> 795 | N36: =SUM(I36:M36) -> 1511 | O36: 4542 | P36: =①札幌予測確定!S13 -> 350 | Q36: =O36-P36 -> 4192 | R36: =MAX(0,①札幌予測確定!P13-①札幌予測確定!S13) -> 0 | S36: =ROUND(①札幌予測確定!U13*前提・入力!$B$37,0) -> 156 | T36: =Q36-R36+S36 -> 4348 | U36: 0 | V36: =N36-T36-U36 -> -2837 | W36: =MAX(0,V36) -> 0 | X36: =IF(W36>0,ROUNDUP(W36*(1+前提・入力!$B$35),0),0) -> 0
A37: 8 | B37: 4515142545150 | C37: 呪術廻戦 渋谷事変 ブラインドダイカットステッカー（全9種） | D37: 1758 | E37: =IFERROR(D37/D$72,0) -> 0.027580797 | F37: =①札幌予測確定!P14 -> 321 | G37: =IFERROR(F37/F$72,0) -> 0.036727689 | H37: =E37*前提・入力!$B$32+G37*前提・入力!$B$33 -> 0.032154243 | I37: =ROUND($H37*③石川以降予測!$G$7,0) -> 305 | J37: =ROUND($H37*③石川以降予測!$G$8,0) -> 360 | K37: =ROUND($H37*③石川以降予測!$G$9,0) -> 332 | L37: =ROUND($H37*③石川以降予測!$G$10,0) -> 249 | M37: =ROUND($H37*③石川以降予測!$G$11,0) -> 1384 | N37: =SUM(I37:M37) -> 2630 | O37: 8551 | P37: =①札幌予測確定!S14 -> 900 | Q37: =O37-P37 -> 7651 | R37: =MAX(0,①札幌予測確定!P14-①札幌予測確定!S14) -> 0 | S37: =ROUND(①札幌予測確定!U14*前提・入力!$B$37,0) -> 579 | T37: =Q37-R37+S37 -> 8230 | U37: 0 | V37: =N37-T37-U37 -> -5600 | W37: =MAX(0,V37) -> 0 | X37: =IF(W37>0,ROUNDUP(W37*(1+前提・入力!$B$35),0),0) -> 0
A38: 9 | B38: 4515142545372 | C38: 呪術廻戦 懐玉・玉折 クリアファイル（五条 悟） | D38: 743 | E38: =IFERROR(D38/D$72,0) -> 0.01165673 | F38: =①札幌予測確定!P15 -> 128 | G38: =IFERROR(F38/F$72,0) -> 0.014645309 | H38: =E38*前提・入力!$B$32+G38*前提・入力!$B$33 -> 0.01315102 | I38: =ROUND($H38*③石川以降予測!$G$7,0) -> 125 | J38: =ROUND($H38*③石川以降予測!$G$8,0) -> 147 | K38: =ROUND($H38*③石川以降予測!$G$9,0) -> 136 | L38: =ROUND($H38*③石川以降予測!$G$10,0) -> 102 | M38: =ROUND($H38*③石川以降予測!$G$11,0) -> 566 | N38: =SUM(I38:M38) -> 1076 | O38: 8759 | P38: =①札幌予測確定!S15 -> 300 | Q38: =O38-P38 -> 8459 | R38: =MAX(0,①札幌予測確定!P15-①札幌予測確定!S15) -> 0 | S38: =ROUND(①札幌予測確定!U15*前提・入力!$B$37,0) -> 172 | T38: =Q38-R38+S38 -> 8631 | U38: 0 | V38: =N38-T38-U38 -> -7555 | W38: =MAX(0,V38) -> 0 | X38: =IF(W38>0,ROUNDUP(W38*(1+前提・入力!$B$35),0),0) -> 0
A39: 10 | B39: 4515142545389 | C39: 呪術廻戦 懐玉・玉折 クリアファイル（夏油 傑） | D39: 277 | E39: =IFERROR(D39/D$72,0) -> 0.0043457797 | F39: =①札幌予測確定!P16 -> 48 | G39: =IFERROR(F39/F$72,0) -> 0.0054919908 | H39: =E39*前提・入力!$B$32+G39*前提・入力!$B$33 -> 0.0049188853 | I39: =ROUND($H39*③石川以降予測!$G$7,0) -> 47 | J39: =ROUND($H39*③石川以降予測!$G$8,0) -> 55 | K39: =ROUND($H39*③石川以降予測!$G$9,0) -> 51 | L39: =ROUND($H39*③石川以降予測!$G$10,0) -> 38 | M39: =ROUND($H39*③石川以降予測!$G$11,0) -> 212 | N39: =SUM(I39:M39) -> 403 | O39: 4935 | P39: =①札幌予測確定!S16 -> 100 | Q39: =O39-P39 -> 4835 | R39: =MAX(0,①札幌予測確定!P16-①札幌予測確定!S16) -> 0 | S39: =ROUND(①札幌予測確定!U16*前提・入力!$B$37,0) -> 52 | T39: =Q39-R39+S39 -> 4887 | U39: 0 | V39: =N39-T39-U39 -> -4484 | W39: =MAX(0,V39) -> 0 | X39: =IF(W39>0,ROUNDUP(W39*(1+前提・入力!$B$35),0),0) -> 0
A40: 11 | B40: 4515142545396 | C40: 呪術廻戦 懐玉・玉折 クリアファイル（家入 硝子） | D40: 78 | E40: =IFERROR(D40/D$72,0) -> 0.0012237214 | F40: =①札幌予測確定!P17 -> 24 | G40: =IFERROR(F40/F$72,0) -> 0.0027459954 | H40: =E40*前提・入力!$B$32+G40*前提・入力!$B$33 -> 0.0019848584 | I40: =ROUND($H40*③石川以降予測!$G$7,0) -> 19 | J40: =ROUND($H40*③石川以降予測!$G$8,0) -> 22 | K40: =ROUND($H40*③石川以降予測!$G$9,0) -> 21 | L40: =ROUND($H40*③石川以降予測!$G$10,0) -> 15 | M40: =ROUND($H40*③石川以降予測!$G$11,0) -> 85 | N40: =SUM(I40:M40) -> 162 | O40: 640 | P40: =①札幌予測確定!S17 -> 50 | Q40: =O40-P40 -> 590 | R40: =MAX(0,①札幌予測確定!P17-①札幌予測確定!S17) -> 0 | S40: =ROUND(①札幌予測確定!U17*前提・入力!$B$37,0) -> 26 | T40: =Q40-R40+S40 -> 616 | U40: 0 | V40: =N40-T40-U40 -> -454 | W40: =MAX(0,V40) -> 0 | X40: =IF(W40>0,ROUNDUP(W40*(1+前提・入力!$B$35),0),0) -> 0
A41: 12 | B41: 4515142545402 | C41: 呪術廻戦 懐玉・玉折 クリアファイル（七海 建人） | D41: 142 | E41: =IFERROR(D41/D$72,0) -> 0.0022278004 | F41: =①札幌予測確定!P18 -> 34 | G41: =IFERROR(F41/F$72,0) -> 0.0038901602 | H41: =E41*前提・入力!$B$32+G41*前提・入力!$B$33 -> 0.0030589803 | I41: =ROUND($H41*③石川以降予測!$G$7,0) -> 29 | J41: =ROUND($H41*③石川以降予測!$G$8,0) -> 34 | K41: =ROUND($H41*③石川以降予測!$G$9,0) -> 32 | L41: =ROUND($H41*③石川以降予測!$G$10,0) -> 24 | M41: =ROUND($H41*③石川以降予測!$G$11,0) -> 132 | N41: =SUM(I41:M41) -> 251 | O41: 953 | P41: =①札幌予測確定!S18 -> 50 | Q41: =O41-P41 -> 903 | R41: =MAX(0,①札幌予測確定!P18-①札幌予測確定!S18) -> 0 | S41: =ROUND(①札幌予測確定!U18*前提・入力!$B$37,0) -> 16 | T41: =Q41-R41+S41 -> 919 | U41: 0 | V41: =N41-T41-U41 -> -668 | W41: =MAX(0,V41) -> 0 | X41: =IF(W41>0,ROUNDUP(W41*(1+前提・入力!$B$35),0),0) -> 0
... A71: 42 | B71: 4515142545365 | C71: 伏黒 恵 イメージフラグメントケース | D71: 8 | E71: =IFERROR(D71/D$72,0) -> 0.00012550988 | F71: =①札幌予測確定!P48 -> 2 | G71: =IFERROR(F71/F$72,0) -> 0.00022883295 | H71: =E71*前提・入力!$B$32+G71*前提・入力!$B$33 -> 0.00017717142 | I71: =ROUND($H71*③石川以降予測!$G$7,0) -> 2 | J71: =ROUND($H71*③石川以降予測!$G$8,0) -> 2 | K71: =ROUND($H71*③石川以降予測!$G$9,0) -> 2 | L71: =ROUND($H71*③石川以降予測!$G$10,0) -> 1 | M71: =ROUND($H71*③石川以降予測!$G$11,0) -> 8 | N71: =SUM(I71:M71) -> 15 | O71: 49 | P71: =①札幌予測確定!S48 -> 6 | Q71: =O71-P71 -> 43 | R71: =MAX(0,①札幌予測確定!P48-①札幌予測確定!S48) -> 0 | S71: =ROUND(①札幌予測確定!U48*前提・入力!$B$37,0) -> 4 | T71: =Q71-R71+S71 -> 47 | U71: 0 | V71: =N71-T71-U71 -> -32 | W71: =MAX(0,V71) -> 0 | X71: =IF(W71>0,ROUNDUP(W71*(1+前提・入力!$B$35),0),0) -> 0
C72: 合計（LEGS 42SKU） | D72: =SUM(D30:D71) -> 63740 | E72: =SUM(E30:E71) -> 1 | F72: =SUM(F30:F71) -> 8740 | G72: =SUM(G30:G71) -> 1 | H72: =SUM(H30:H71) -> 1 | I72: =SUM(I30:I71) -> 9472 | J72: =SUM(J30:J71) -> 11189 | K72: =SUM(K30:K71) -> 10332 | ... X72: =SUM(X30:X71) -> 2812

Sheet ④追加発注判定
A1: ④ 追加発注 必要有無の判定（札幌会期中 ＋ 石川以降5会場）
A2: 【札幌会期中】会期20日予測 vs 札幌への納品済 販売可能数 ／ 【石川以降】5会場必要数 vs 札幌会期末残在庫＋倉庫在庫 ※2026/7/28 SPJ様欠品報告を突合
A3: 推奨発注数＝不足数×(1+安全率10%)を切り上げ。T〜W列に欠品発生会場・最終発注期限（会期初日−生産日数−バッファ）・残日数・緊急度を記載
A6: No. | B6: JAN | C6: 商品名 | D6: 税込単価 | E6: 札幌 初6日実績 | F6: 札幌 会期20日予測 | G6: 札幌 販売可能数 (追納込) | H6: 札幌 予測消化率 | I6: 札幌会期中 過不足 | J6: 札幌会期中 判定 | K6: 札幌会期中 推奨発注数 | L6: 石川以降 必要数 | M6: 札幌からの スライド | N6: 7/8実在庫の 倉庫残 | O6: 石川以降 過不足 | P6: 石川以降 判定 | Q6: 石川以降 推奨発注数 | R6: 発注合計 (札幌+石川以降) | S6: 発注金額 (税込小売換算) | T6: 欠品発生 会場 | U6: 最終発注期限 | V6: 基準日からの 残日数 | W6: 発注の緊急度 | X6: 優先度 | Y6: 運営 欠品報告 (7/28 SPJ様) | Z6: モデル×現場 突合 | AA6: 備考
A7: 1 | B7: 4515142545082 | C7: 呪術廻戦 メタリックポストカード 展示会キービジュアル | D7: 500 | E7: =①札幌予測確定!E7 -> 261 | F7: =①札幌予測確定!P7 -> 467 | G7: =①札幌予測確定!S7 -> 1000 | H7: =IFERROR(F7/G7,0) -> 0.467 | I7: =F7-G7 -> -533 | J7: =IF(I7>0,"要 追加発注",IF(H7>=0.9,"要注意(90%超)",IF(H7>=0.5,"適正","在庫余剰"))) -> 在庫余剰 | K7: =IF(I7>0,ROUNDUP(I7*(1+前提・入力!$B$35),0),0) -> 0 | L7: =③石川以降予測!N30 -> 3676 | M7: =③石川以降予測!S30 -> 533 | N7: =③石川以降予測!Q30 -> 2264 | O7: =L7-M7-N7 -> 879 | P7: =IF(O7>0,"要 追加生産",IF(L7=0,"—","在庫で充足")) -> 要 追加生産 | Q7: =③石川以降予測!X30 -> 967 | R7: =K7+Q7 -> 967 | S7: =R7*D7 -> 483500 | T7: 東京凱旋 東京建物ぴあホール | U7: =DATE(2027,4,1)-30-前提・入力!$B$38 -> 46434 | V7: =IF(OR(U7="",U7="再生産不可"),"",U7-前提・入力!$B$39) -> 201 | W7: =IF(T7="—","—",IF(U7="再生産不可","×再生産不可",_xlfn.IFS(V7<0,"★期限超過",V7<=30,"★至急(30日以内)",V7<=90,"要着手(90日以内)",TRUE(),"余裕あり"))) -> 余裕あり | X7: =IF(Y7<>"",IF(FALSE(),"S:現場欠品(追納不可)","S:現場欠品"),IF(I7>0,"A:会期中欠品",IF(O7>1000,"B:大口",IF(O7>0,"C:通常","D:不要")))) -> C:通常 | Z7: =IF(Y7<>"",IF(I7>0,"◎ 一致（モデルも会期中欠品を検知）",IF(H7>=0.7,"○ 整合（予測消化率70%超）","△ モデル未検知：現場報告を優先")),IF(I7>0,"▲ モデルのみ検知：現場に在庫状況を確認","—")) -> — | AA7: 博多会場で完売（実績が在庫上限で頭打ち＝予測は控えめ）
A8: 2 | B8: 4515142545099 | C8: 呪術廻戦 クリアファイル 展示会キービジュアル | D8: 600 | E8: =①札幌予測確定!E8 -> 283 | F8: =①札幌予測確定!P8 -> 509 | G8: =①札幌予測確定!S8 -> 1000 | H8: =IFERROR(F8/G8,0) -> 0.509 | I8: =F8-G8 -> -491 | J8: =IF(I8>0,"要 追加発注",IF(H8>=0.9,"要注意(90%超)",IF(H8>=0.5,"適正","在庫余剰"))) -> 適正 | K8: =IF(I8>0,ROUNDUP(I8*(1+前提・入力!$B$35),0),0) -> 0 | L8: =③石川以降予測!N31 -> 3642 | M8: =③石川以降予測!S31 -> 491 | N8: =③石川以降予測!Q31 -> 4037 | O8: =L8-M8-N8 -> -886 | P8: =IF(O8>0,"要 追加生産",IF(L8=0,"—","在庫で充足")) -> 在庫で充足 | Q8: =③石川以降予測!X31 -> 0 | R8: =K8+Q8 -> 0 | S8: =R8*D8 -> 0 | T8: — | V8: =IF(OR(U8="",U8="再生産不可"),"",U8-前提・入力!$B$39) | W8: =IF(T8="—","—",IF(U8="再生産不可","×再生産不可",_xlfn.IFS(V8<0,"★期限超過",V8<=30,"★至急(30日以内)",V8<=90,"要着手(90日以内)",TRUE(),"余裕あり"))) -> — | X8: =IF(Y8<>"",IF(FALSE(),"S:現場欠品(追納不可)","S:現場欠品"),IF(I8>0,"A:会期中欠品",IF(O8>1000,"B:大口",IF(O8>0,"C:通常","D:不要")))) -> D:不要 | Z8: =IF(Y8<>"",IF(I8>0,"◎ 一致（モデルも会期中欠品を検知）",IF(H8>=0.7,"○ 整合（予測消化率70%超）","△ モデル未検知：現場報告を優先")),IF(I8>0,"▲ モデルのみ検知：現場に在庫状況を確認","—")) -> —
A9: 3 | B9: 4515142545105 | C9: 呪術廻戦 懐玉・玉折 ポストカードセット（5枚入） | D9: 1000 | E9: =①札幌予測確定!E9 -> 102 | F9: =①札幌予測確定!P9 -> 163 | G9: =①札幌予測確定!S9 -> 450 | H9: =IFERROR(F9/G9,0) -> 0.36222222 | I9: =F9-G9 -> -287 | J9: =IF(I9>0,"要 追加発注",IF(H9>=0.9,"要注意(90%超)",IF(H9>=0.5,"適正","在庫余剰"))) -> 在庫余剰 | K9: =IF(I9>0,ROUNDUP(I9*(1+前提・入力!$B$35),0),0) -> 0 | L9: =③石川以降予測!N32 -> 1489 | M9: =③石川以降予測!S32 -> 287 | N9: =③石川以降予測!Q32 -> 5690 | O9: =L9-M9-N9 -> -4488 | P9: =IF(O9>0,"要 追加生産",IF(L9=0,"—","在庫で充足")) -> 在庫で充足 | Q9: =③石川以降予測!X32 -> 0 | R9: =K9+Q9 -> 0 | S9: =R9*D9 -> 0 | T9: — | V9: =IF(OR(U9="",U9="再生産不可"),"",U9-前提・入力!$B$39) | W9: =IF(T9="—","—",IF(U9="再生産不可","×再生産不可",_xlfn.IFS(V9<0,"★期限超過",V9<=30,"★至急(30日以内)",V9<=90,"要着手(90日以内)",TRUE(),"余裕あり"))) -> — | X9: =IF(Y9<>"",IF(FALSE(),"S:現場欠品(追納不可)","S:現場欠品"),IF(I9>0,"A:会期中欠品",IF(O9>1000,"B:大口",IF(O9>0,"C:通常","D:不要")))) -> D:不要 | Z9: =IF(Y9<>"",IF(I9>0,"◎ 一致（モデルも会期中欠品を検知）",IF(H9>=0.7,"○ 整合（予測消化率70%超）","△ モデル未検知：現場報告を優先")),IF(I9>0,"▲ モデルのみ検知：現場に在庫状況を確認","—")) -> —
A10: 4 | B10: 4515142545112 | C10: 呪術廻戦 渋谷事変 ポストカードセット（9枚入） | D10: 1800 | E10: =①札幌予測確定!E10 -> 144 | F10: =①札幌予測確定!P10 -> 229 | G10: =①札幌予測確定!S10 -> 800 | H10: =IFERROR(F10/G10,0) -> 0.28625 | I10: =F10-G10 -> -571 | J10: =IF(I10>0,"要 追加発注",IF(H10>=0.9,"要注意(90%超)",IF(H10>=0.5,"適正","在庫余剰"))) -> 在庫余剰 | K10: =IF(I10>0,ROUNDUP(I10*(1+前提・入力!$B$35),0),0) -> 0 | L10: =③石川以降予測!N33 -> 1912 | M10: =③石川以降予測!S33 -> 571 | N10: =③石川以降予測!Q33 -> 26711 | O10: =L10-M10-N10 -> -25370 | P10: =IF(O10>0,"要 追加生産",IF(L10=0,"—","在庫で充足")) -> 在庫で充足 | Q10: =③石川以降予測!X33 -> 0 | R10: =K10+Q10 -> 0 | S10: =R10*D10 -> 0 | T10: — | V10: =IF(OR(U10="",U10="再生産不可"),"",U10-前提・入力!$B$39) | W10: =IF(T10="—","—",IF(U10="再生産不可","×再生産不可",_xlfn.IFS(V10<0,"★期限超過",V10<=30,"★至急(30日以内)",V10<=90,"要着手(90日以内)",TRUE(),"余裕あり"))) -> — | X10: =IF(Y10<>"",IF(FALSE(),"S:現場欠品(追納不可)","S:現場欠品"),IF(I10>0,"A:会期中欠品",IF(O10>1000,"B:大口",IF(O10>0,"C:通常","D:不要")))) -> D:不要 | Z10: =IF(Y10<>"",IF(I10>0,"◎ 一致（モデルも会期中欠品を検知）",IF(H10>=0.7,"○ 整合（予測消化率70%超）","△ モデル未検知：現場報告を優先")),IF(I10>0,"▲ モデルのみ検知：現場に在庫状況を確認","—")) -> —
A11: 5 | B11: 4515142545129 | C11: 呪術廻戦 懐玉・玉折 ブラインド缶バッジ（全5種） | D11: 600 | E11: =①札幌予測確定!E11 -> 268 | F11: =①札幌予測確定!P11 -> 465 | G11: =①札幌予測確定!S11 -> 9000 | H11: =IFERROR(F11/G11,0) -> 0.051666667 | I11: =F11-G11 -> -8535 | J11: =IF(I11>0,"要 追加発注",IF(H11>=0.9,"要注意(90%超)",IF(H11>=0.5,"適正","在庫余剰"))) -> 在庫余剰 | K11: =IF(I11>0,ROUNDUP(I11*(1+前提・入力!$B$35),0),0) -> 0 | L11: =③石川以降予測!N34 -> 7909 | M11: =③石川以降予測!S34 -> 8535 | N11: =③石川以降予測!Q34 -> 30825 | O11: =L11-M11-N11 -> -31451 | P11: =IF(O11>0,"要 追加生産",IF(L11=0,"—","在庫で充足")) -> 在庫で充足 | Q11: =③石川以降予測!X34 -> 0 | R11: =K11+Q11 -> 0 | S11: =R11*D11 -> 0 | T11: — | V11: =IF(OR(U11="",U11="再生産不可"),"",U11-前提・入力!$B$39) | W11: =IF(T11="—","—",IF(U11="再生産不可","×再生産不可",_xlfn.IFS(V11<0,"★期限超過",V11<=30,"★至急(30日以内)",V11<=90,"要着手(90日以内)",TRUE(),"余裕あり"))) -> — | X11: =IF(Y11<>"",IF(FALSE(),"S:現場欠品(追納不可)","S:現場欠品"),IF(I11>0,"A:会期中欠品",IF(O11>1000,"B:大口",IF(O11>0,"C:通常","D:不要")))) -> D:不要 | Z11: =IF(Y11<>"",IF(I11>0,"◎ 一致（モデルも会期中欠品を検知）",IF(H11>=0.7,"○ 整合（予測消化率70%超）","△ モデル未検知：現場報告を優先")),IF(I11>0,"▲ モデルのみ検知：現場に在庫状況を確認","—")) -> — | AA11: 博多会場で完売（実績が在庫上限で頭打ち＝予測は控えめ）
A12: 6 | B12: 4515142545136 | C12: 呪術廻戦 渋谷事変 ブラインド缶バッジ（全9種） | D12: 600 | E12: =①札幌予測確定!E12 -> 704 | F12: =①札幌予測確定!P12 -> 1317 | G12: =①札幌予測確定!S12 -> 13991 | H12: =IFERROR(F12/G12,0) -> 0.094131942 | I12: =F12-G12 -> -12674 | J12: =IF(I12>0,"要 追加発注",IF(H12>=0.9,"要注意(90%超)",IF(H12>=0.5,"適正","在庫余剰"))) -> 在庫余剰 | K12: =IF(I12>0,ROUNDUP(I12*(1+前提・入力!$B$35),0),0) -> 0 | L12: =③石川以降予測!N35 -> 18104 | M12: =③石川以降予測!S35 -> 12674 | N12: =③石川以降予測!Q35 -> 36843 | O12: =L12-M12-N12 -> -31413 | P12: =IF(O12>0,"要 追加生産",IF(L12=0,"—","在庫で充足")) -> 在庫で充足 | Q12: =③石川以降予測!X35 -> 0 | R12: =K12+Q12 -> 0 | S12: =R12*D12 -> 0 | T12: — | V12: =IF(OR(U12="",U12="再生産不可"),"",U12-前提・入力!$B$39) | W12: =IF(T12="—","—",IF(U12="再生産不可","×再生産不可",_xlfn.IFS(V12<0,"★期限超過",V12<=30,"★至急(30日以内)",V12<=90,"要着手(90日以内)",TRUE(),"余裕あり"))) -> — | X12: =IF(Y12<>"",IF(FALSE(),"S:現場欠品(追納不可)","S:現場欠品"),IF(I12>0,"A:会期中欠品",IF(O12>1000,"B:大口",IF(O12>0,"C:通常","D:不要")))) -> D:不要 | Z12: =IF(Y12<>"",IF(I12>0,"◎ 一致（モデルも会期中欠品を検知）",IF(H12>=0.7,"○ 整合（予測消化率70%超）","△ モデル未検知：現場報告を優先")),IF(I12>0,"▲ モデルのみ検知：現場に在庫状況を確認","—")) -> — | AA12: 博多会場で完売（実績が在庫上限で頭打ち＝予測は控えめ）
A13: 7 | B13: 4515142545143 | C13: 呪術廻戦 懐玉・玉折 ブラインドダイカットステッカー（全5種） | D13: 600 | E13: =①札幌予測確定!E13 -> 108 | F13: =①札幌予測確定!P13 -> 194 | G13: =①札幌予測確定!S13 -> 350 | H13: =IFERROR(F13/G13,0) -> 0.55428571 | I13: =F13-G13 -> -156 | J13: =IF(I13>0,"要 追加発注",IF(H13>=0.9,"要注意(90%超)",IF(H13>=0.5,"適正","在庫余剰"))) -> 適正 | K13: =IF(I13>0,ROUNDUP(I13*(1+前提・入力!$B$35),0),0) -> 0 | L13: =③石川以降予測!N36 -> 1511 | M13: =③石川以降予測!S36 -> 156 | N13: =③石川以降予測!Q36 -> 4192 | O13: =L13-M13-N13 -> -2837 | P13: =IF(O13>0,"要 追加生産",IF(L13=0,"—","在庫で充足")) -> 在庫で充足 | Q13: =③石川以降予測!X36 -> 0 | R13: =K13+Q13 -> 0 | S13: =R13*D13 -> 0 | T13: — | V13: =IF(OR(U13="",U13="再生産不可"),"",U13-前提・入力!$B$39) | W13: =IF(T13="—","—",IF(U13="再生産不可","×再生産不可",_xlfn.IFS(V13<0,"★期限超過",V13<=30,"★至急(30日以内)",V13<=90,"要着手(90日以内)",TRUE(),"余裕あり"))) -> — | X13: =IF(Y13<>"",IF(FALSE(),"S:現場欠品(追納不可)","S:現場欠品"),IF(I13>0,"A:会期中欠品",IF(O13>1000,"B:大口",IF(O13>0,"C:通常","D:不要")))) -> D:不要 | Z13: =IF(Y13<>"",IF(I13>0,"◎ 一致（モデルも会期中欠品を検知）",IF(H13>=0.7,"○ 整合（予測消化率70%超）","△ モデル未検知：現場報告を優先")),IF(I13>0,"▲ モデルのみ検知：現場に在庫状況を確認","—")) -> — | AA13: 博多会場で完売（実績が在庫上限で頭打ち＝予測は控えめ）
A14: 8 | B14: 4515142545150 | C14: 呪術廻戦 渋谷事変 ブラインドダイカットステッカー（全9種） | D14: 600 | E14: =①札幌予測確定!E14 -> 173 | F14: =①札幌予測確定!P14 -> 321 | G14: =①札幌予測確定!S14 -> 900 | H14: =IFERROR(F14/G14,0) -> 0.35666667 | I14: =F14-G14 -> -579 | J14: =IF(I14>0,"要 追加発注",IF(H14>=0.9,"要注意(90%超)",IF(H14>=0.5,"適正","在庫余剰"))) -> 在庫余剰 | K14: =IF(I14>0,ROUNDUP(I14*(1+前提・入力!$B$35),0),0) -> 0 | L14: =③石川以降予測!N37 -> 2630 | M14: =③石川以降予測!S37 -> 579 | N14: =③石川以降予測!Q37 -> 7651 | O14: =L14-M14-N14 -> -5600 | P14: =IF(O14>0,"要 追加生産",IF(L14=0,"—","在庫で充足")) -> 在庫で充足 | Q14: =③石川以降予測!X37 -> 0 | R14: =K14+Q14 -> 0 | S14: =R14*D14 -> 0 | T14: — | V14: =IF(OR(U14="",U14="再生産不可"),"",U14-前提・入力!$B$39) | W14: =IF(T14="—","—",IF(U14="再生産不可","×再生産不可",_xlfn.IFS(V14<0,"★期限超過",V14<=30,"★至急(30日以内)",V14<=90,"要着手(90日以内)",TRUE(),"余裕あり"))) -> — | X14: =IF(Y14<>"",IF(FALSE(),"S:現場欠品(追納不可)","S:現場欠品"),IF(I14>0,"A:会期中欠品",IF(O14>1000,"B:大口",IF(O14>0,"C:通常","D:不要")))) -> D:不要 | Z14: =IF(Y14<>"",IF(I14>0,"◎ 一致（モデルも会期中欠品を検知）",IF(H14>=0.7,"○ 整合（予測消化率70%超）","△ モデル未検知：現場報告を優先")),IF(I14>0,"▲ モデルのみ検知：現場に在庫状況を確認","—")) -> — | AA14: 博多会場で完売（実績が在庫上限で頭打ち＝予測は控えめ）
A15: 9 | B15: 4515142545372 | C15: 呪術廻戦 懐玉・玉折 クリアファイル（五条 悟） | D15: 600 | E15: =①札幌予測確定!E15 -> 87 | F15: =①札幌予測確定!P15 -> 128 | G15: =①札幌予測確定!S15 -> 300 | H15: =IFERROR(F15/G15,0) -> 0.42666667 | I15: =F15-G15 -> -172 | J15: =IF(I15>0,"要 追加発注",IF(H15>=0.9,"要注意(90%超)",IF(H15>=0.5,"適正","在庫余剰"))) -> 在庫余剰 | K15: =IF(I15>0,ROUNDUP(I15*(1+前提・入力!$B$35),0),0) -> 0 | L15: =③石川以降予測!N38 -> 1076 | M15: =③石川以降予測!S38 -> 172 | N15: =③石川以降予測!Q38 -> 8459 | O15: =L15-M15-N15 -> -7555 | P15: =IF(O15>0,"要 追加生産",IF(L15=0,"—","在庫で充足")) -> 在庫で充足 | Q15: =③石川以降予測!X38 -> 0 | R15: =K15+Q15 -> 0 | S15: =R15*D15 -> 0 | T15: — | V15: =IF(OR(U15="",U15="再生産不可"),"",U15-前提・入力!$B$39) | W15: =IF(T15="—","—",IF(U15="再生産不可","×再生産不可",_xlfn.IFS(V15<0,"★期限超過",V15<=30,"★至急(30日以内)",V15<=90,"要着手(90日以内)",TRUE(),"余裕あり"))) -> — | X15: =IF(Y15<>"",IF(FALSE(),"S:現場欠品(追納不可)","S:現場欠品"),IF(I15>0,"A:会期中欠品",IF(O15>1000,"B:大口",IF(O15>0,"C:通常","D:不要")))) -> D:不要 | Z15: =IF(Y15<>"",IF(I15>0,"◎ 一致（モデルも会期中欠品を検知）",IF(H15>=0.7,"○ 整合（予測消化率70%超）","△ モデル未検知：現場報告を優先")),IF(I15>0,"▲ モデルのみ検知：現場に在庫状況を確認","—")) -> — | AA15: 博多会場で完売（実績が在庫上限で頭打ち＝予測は控えめ）
A16: 10 | B16: 4515142545389 | C16: 呪術廻戦 懐玉・玉折 クリアファイル（夏油 傑） | D16: 600 | E16: =①札幌予測確定!E16 -> 33 | F16: =①札幌予測確定!P16 -> 48 | G16: =①札幌予測確定!S16 -> 100 | H16: =IFERROR(F16/G16,0) -> 0.48 | I16: =F16-G16 -> -52 | J16: =IF(I16>0,"要 追加発注",IF(H16>=0.9,"要注意(90%超)",IF(H16>=0.5,"適正","在庫余剰"))) -> 在庫余剰 | K16: =IF(I16>0,ROUNDUP(I16*(1+前提・入力!$B$35),0),0) -> 0 | L16: =③石川以降予測!N39 -> 403 | M16: =③石川以降予測!S39 -> 52 | N16: =③石川以降予測!Q39 -> 4835 | O16: =L16-M16-N16 -> -4484 | P16: =IF(O16>0,"要 追加生産",IF(L16=0,"—","在庫で充足")) -> 在庫で充足 | Q16: =③石川以降予測!X39 -> 0 | R16: =K16+Q16 -> 0 | S16: =R16*D16 -> 0 | T16: — | V16: =IF(OR(U16="",U16="再生産不可"),"",U16-前提・入力!$B$39) | W16: =IF(T16="—","—",IF(U16="再生産不可","×再生産不可",_xlfn.IFS(V16<0,"★期限超過",V16<=30,"★至急(30日以内)",V16<=90,"要着手(90日以内)",TRUE(),"余裕あり"))) -> — | X16: =IF(Y16<>"",IF(FALSE(),"S:現場欠品(追納不可)","S:現場欠品"),IF(I16>0,"A:会期中欠品",IF(O16>1000,"B:大口",IF(O16>0,"C:通常","D:不要")))) -> D:不要 | Z16: =IF(Y16<>"",IF(I16>0,"◎ 一致（モデルも会期中欠品を検知）",IF(H16>=0.7,"○ 整合（予測消化率70%超）","△ モデル未検知：現場報告を優先")),IF(I16>0,"▲ モデルのみ検知：現場に在庫状況を確認","—")) -> —
A17: 11 | B17: 4515142545396 | C17: 呪術廻戦 懐玉・玉折 クリアファイル（家入 硝子） | D17: 600 | E17: =①札幌予測確定!E17 -> 10 | F17: =①札幌予測確定!P17 -> 24 | G17: =①札幌予測確定!S17 -> 50 | H17: =IFERROR(F17/G17,0) -> 0.48 | I17: =F17-G17 -> -26 | J17: =IF(I17>0,"要 追加発注",IF(H17>=0.9,"要注意(90%超)",IF(H17>=0.5,"適正","在庫余剰"))) -> 在庫余剰 | K17: =IF(I17>0,ROUNDUP(I17*(1+前提・入力!$B$35),0),0) -> 0 | L17: =③石川以降予測!N40 -> 162 | M17: =③石川以降予測!S40 -> 26 | N17: =③石川以降予測!Q40 -> 590 | O17: =L17-M17-N17 -> -454 | P17: =IF(O17>0,"要 追加生産",IF(L17=0,"—","在庫で充足")) -> 在庫で充足 | Q17: =③石川以降予測!X40 -> 0 | R17: =K17+Q17 -> 0 | S17: =R17*D17 -> 0 | T17: — | V17: =IF(OR(U17="",U17="再生産不可"),"",U17-前提・入力!$B$39) | W17: =IF(T17="—","—",IF(U17="再生産不可","×再生産不可",_xlfn.IFS(V17<0,"★期限超過",V17<=30,"★至急(30日以内)",V17<=90,"要着手(90日以内)",TRUE(),"余裕あり"))) -> — | X17: =IF(Y17<>"",IF(FALSE(),"S:現場欠品(追納不可)","S:現場欠品"),IF(I17>0,"A:会期中欠品",IF(O17>1000,"B:大口",IF(O17>0,"C:通常","D:不要")))) -> D:不要 | Z17: =IF(Y17<>"",IF(I17>0,"◎ 一致（モデルも会期中欠品を検知）",IF(H17>=0.7,"○ 整合（予測消化率70%超）","△ モデル未検知：現場報告を優先")),IF(I17>0,"▲ モデルのみ検知：現場に在庫状況を確認","—")) -> — | AA17: 博多会場で完売（実績が在庫上限で頭打ち＝予測は控えめ）
A18: 12 | B18: 4515142545402 | C18: 呪術廻戦 懐玉・玉折 クリアファイル（七海 建人） | D18: 600 | E18: =①札幌予測確定!E18 -> 19 | F18: =①札幌予測確定!P18 -> 34 | G18: =①札幌予測確定!S18 -> 50 | H18: =IFERROR(F18/G18,0) -> 0.68 | I18: =F18-G18 -> -16 | J18: =IF(I18>0,"要 追加発注",IF(H18>=0.9,"要注意(90%超)",IF(H18>=0.5,"適正","在庫余剰"))) -> 適正 | K18: =IF(I18>0,ROUNDUP(I18*(1+前提・入力!$B$35),0),0) -> 0 | L18: =③石川以降予測!N41 -> 251 | M18: =③石川以降予測!S41 -> 16 | N18: =③石川以降予測!Q41 -> 903 | O18: =L18-M18-N18 -> -668 | P18: =IF(O18>0,"要 追加生産",IF(L18=0,"—","在庫で充足")) -> 在庫で充足 | Q18: =③石川以降予測!X41 -> 0 | R18: =K18+Q18 -> 0 | S18: =R18*D18 -> 0 | T18: — | V18: =IF(OR(U18="",U18="再生産不可"),"",U18-前提・入力!$B$39) | W18: =IF(T18="—","—",IF(U18="再生産不可","×再生産不可",_xlfn.IFS(V18<0,"★期限超過",V18<=30,"★至急(30日以内)",V18<=90,"要着手(90日以内)",TRUE(),"余裕あり"))) -> — | X18: =IF(Y18<>"",IF(FALSE(),"S:現場欠品(追納不可)","S:現場欠品"),IF(I18>0,"A:会期中欠品",IF(O18>1000,"B:大口",IF(O18>0,"C:通常","D:不要")))) -> D:不要 | Z18: =IF(Y18<>"",IF(I18>0,"◎ 一致（モデルも会期中欠品を検知）",IF(H18>=0.7,"○ 整合（予測消化率70%超）","△ モデル未検知：現場報告を優先")),IF(I18>0,"▲ モデルのみ検知：現場に在庫状況を確認","—")) -> —
A19: 13 | B19: 4515142545419 | C19: 呪術廻戦 懐玉・玉折 クリアファイル（灰原 雄） | D19: 600 | E19: =①札幌予測確定!E19 -> 3 | F19: =①札幌予測確定!P19 -> 5 | G19: =①札幌予測確定!S19 -> 50 | H19: =IFERROR(F19/G19,0) -> 0.1 | I19: =F19-G19 -> -45 | J19: =IF(I19>0,"要 追加発注",IF(H19>=0.9,"要注意(90%超)",IF(H19>=0.5,"適正","在庫余剰"))) -> 在庫余剰 | K19: =IF(I19>0,ROUNDUP(I19*(1+前提・入力!$B$35),0),0) -> 0 | L19: =③石川以降予測!N42 -> 51 | M19: =③石川以降予測!S42 -> 45 | N19: =③石川以降予測!Q42 -> 270 | O19: =L19-M19-N19 -> -264 | P19: =IF(O19>0,"要 追加生産",IF(L19=0,"—","在庫で充足")) -> 在庫で充足 | Q19: =③石川以降予測!X42 -> 0 | R19: =K19+Q19 -> 0 | S19: =R19*D19 -> 0 | T19: — | V19: =IF(OR(U19="",U19="再生産不可"),"",U19-前提・入力!$B$39) | W19: =IF(T19="—","—",IF(U19="再生産不可","×再生産不可",_xlfn.IFS(V19<0,"★期限超過",V19<=30,"★至急(30日以内)",V19<=90,"要着手(90日以内)",TRUE(),"余裕あり"))) -> — | X19: =IF(Y19<>"",IF(FALSE(),"S:現場欠品(追納不可)","S:現場欠品"),IF(I19>0,"A:会期中欠品",IF(O19>1000,"B:大口",IF(O19>0,"C:通常","D:不要")))) -> D:不要 | Z19: =IF(Y19<>"",IF(I19>0,"◎ 一致（モデルも会期中欠品を検知）",IF(H19>=0.7,"○ 整合（予測消化率70%超）","△ モデル未検知：現場報告を優先")),IF(I19>0,"▲ モデルのみ検知：現場に在庫状況を確認","—")) -> —
A20: 14 | B20: 4515142545426 | C20: 呪術廻戦 渋谷事変 クリアファイル（虎杖 悠仁） | D20: 600 | E20: =①札幌予測確定!E20 -> 21 | F20: =①札幌予測確定!P20 -> 38 | G20: =①札幌予測確定!S20 -> 50 | H20: =IFERROR(F20/G20,0) -> 0.76 | I20: =F20-G20 -> -12 | J20: =IF(I20>0,"要 追加発注",IF(H20>=0.9,"要注意(90%超)",IF(H20>=0.5,"適正","在庫余剰"))) -> 適正 | K20: =IF(I20>0,ROUNDUP(I20*(1+前提・入力!$B$35),0),0) -> 0 | L20: =③石川以降予測!N43 -> 271 | M20: =③石川以降予測!S43 -> 12 | N20: =③石川以降予測!Q43 -> 1740 | O20: =L20-M20-N20 -> -1481 | P20: =IF(O20>0,"要 追加生産",IF(L20=0,"—","在庫で充足")) -> 在庫で充足 | Q20: =③石川以降予測!X43 -> 0 | R20: =K20+Q20 -> 0 | S20: =R20*D20 -> 0 | T20: — | V20: =IF(OR(U20="",U20="再生産不可"),"",U20-前提・入力!$B$39) | W20: =IF(T20="—","—",IF(U20="再生産不可","×再生産不可",_xlfn.IFS(V20<0,"★期限超過",V20<=30,"★至急(30日以内)",V20<=90,"要着手(90日以内)",TRUE(),"余裕あり"))) -> — | X20: =IF(Y20<>"",IF(FALSE(),"S:現場欠品(追納不可)","S:現場欠品"),IF(I20>0,"A:会期中欠品",IF(O20>1000,"B:大口",IF(O20>0,"C:通常","D:不要")))) -> S:現場欠品 | Y20: 欠品／近々欠品 | Z20: =IF(Y20<>"",IF(I20>0,"◎ 一致（モデルも会期中欠品を検知）",IF(H20>=0.7,"○ 整合（予測消化率70%超）","△ モデル未検知：現場報告を優先")),IF(I20>0,"▲ モデルのみ検知：現場に在庫状況を確認","—")) -> ○ 整合（予測消化率70%超） | AA20: 【7/28 運営報告】欠品／近々欠品 ／ 倉庫残1,740個 → ◎倉庫からの追加納品で対応可能（追加生産は不要） ／ 博多会場で完売（実績が在庫上限で頭打ち＝予測は控えめ）
A21: 15 | B21: 4515142545433 | C21: 呪術廻戦 渋谷事変 クリアファイル（伏黒 恵） | D21: 600 | E21: =①札幌予測確定!E21 -> 32 | F21: =①札幌予測確定!P21 -> 59 | G21: =①札幌予測確定!S21 -> 100 | H21: =IFERROR(F21/G21,0) -> 0.59 | I21: =F21-G21 -> -41 | J21: =IF(I21>0,"要 追加発注",IF(H21>=0.9,"要注意(90%超)",IF(H21>=0.5,"適正","在庫余剰"))) -> 適正 | K21: =IF(I21>0,ROUNDUP(I21*(1+前提・入力!$B$35),0),0) -> 0 | L21: =③石川以降予測!N44 -> 403 | M21: =③石川以降予測!S44 -> 41 | N21: =③石川以降予測!Q44 -> 2031 | O21: =L21-M21-N21 -> -1669 | P21: =IF(O21>0,"要 追加生産",IF(L21=0,"—","在庫で充足")) -> 在庫で充足 | Q21: =③石川以降予測!X44 -> 0 | R21: =K21+Q21 -> 0 | S21: =R21*D21 -> 0 | T21: — | V21: =IF(OR(U21="",U21="再生産不可"),"",U21-前提・入力!$B$39) | W21: =IF(T21="—","—",IF(U21="再生産不可","×再生産不可",_xlfn.IFS(V21<0,"★期限超過",V21<=30,"★至急(30日以内)",V21<=90,"要着手(90日以内)",TRUE(),"余裕あり"))) -> — | X21: =IF(Y21<>"",IF(FALSE(),"S:現場欠品(追納不可)","S:現場欠品"),IF(I21>0,"A:会期中欠品",IF(O21>1000,"B:大口",IF(O21>0,"C:通常","D:不要")))) -> D:不要 | Z21: =IF(Y21<>"",IF(I21>0,"◎ 一致（モデルも会期中欠品を検知）",IF(H21>=0.7,"○ 整合（予測消化率70%超）","△ モデル未検知：現場報告を優先")),IF(I21>0,"▲ モデルのみ検知：現場に在庫状況を確認","—")) -> — | AA21: 博多会場で完売（実績が在庫上限で頭打ち＝予測は控えめ）
A22: 16 | B22: 4515142545440 | C22: 呪術廻戦 渋谷事変 クリアファイル（釘崎 野薔薇） | D22: 600 | E22: =①札幌予測確定!E22 -> 7 | F22: =①札幌予測確定!P22 -> 15 | G22: =①札幌予測確定!S22 -> 50 | H22: =IFERROR(F22/G22,0) -> 0.3 | I22: =F22-G22 -> -35 | J22: =IF(I22>0,"要 追加発注",IF(H22>=0.9,"要注意(90%超)",IF(H22>=0.5,"適正","在庫余剰"))) -> 在庫余剰 | K22: =IF(I22>0,ROUNDUP(I22*(1+前提・入力!$B$35),0),0) -> 0 | L22: =③石川以降予測!N45 -> 112 | M22: =③石川以降予測!S45 -> 35 | N22: =③石川以降予測!Q45 -> 722 | O22: =L22-M22-N22 -> -645 | P22: =IF(O22>0,"要 追加生産",IF(L22=0,"—","在庫で充足")) -> 在庫で充足 | Q22: =③石川以降予測!X45 -> 0 | R22: =K22+Q22 -> 0 | S22: =R22*D22 -> 0 | T22: — | V22: =IF(OR(U22="",U22="再生産不可"),"",U22-前提・入力!$B$39) | W22: =IF(T22="—","—",IF(U22="再生産不可","×再生産不可",_xlfn.IFS(V22<0,"★期限超過",V22<=30,"★至急(30日以内)",V22<=90,"要着手(90日以内)",TRUE(),"余裕あり"))) -> — | X22: =IF(Y22<>"",IF(FALSE(),"S:現場欠品(追納不可)","S:現場欠品"),IF(I22>0,"A:会期中欠品",IF(O22>1000,"B:大口",IF(O22>0,"C:通常","D:不要")))) -> D:不要 | Z22: =IF(Y22<>"",IF(I22>0,"◎ 一致（モデルも会期中欠品を検知）",IF(H22>=0.7,"○ 整合（予測消化率70%超）","△ モデル未検知：現場報告を優先")),IF(I22>0,"▲ モデルのみ検知：現場に在庫状況を確認","—")) -> — | AA22: 名古屋会場で完売（実績が在庫上限で頭打ち＝予測は控えめ） ／ 博多会場で完売（実績が在庫上限で頭打ち＝予測は控えめ）
A23: 17 | B23: 4515142545457 | C23: 呪術廻戦 渋谷事変 クリアファイル（七海 建人） | D23: 600 | E23: =①札幌予測確定!E23 -> 53 | F23: =①札幌予測確定!P23 -> 93 | G23: =①札幌予測確定!S23 -> 100 | H23: =IFERROR(F23/G23,0) -> 0.93 | I23: =F23-G23 -> -7 | J23: =IF(I23>0,"要 追加発注",IF(H23>=0.9,"要注意(90%超)",IF(H23>=0.5,"適正","在庫余剰"))) -> 要注意(90%超) | K23: =IF(I23>0,ROUNDUP(I23*(1+前提・入力!$B$35),0),0) -> 0 | L23: =③石川以降予測!N46 -> 602 | M23: =③石川以降予測!S46 -> 7 | N23: =③石川以降予測!Q46 -> 2423 | O23: =L23-M23-N23 -> -1828 | P23: =IF(O23>0,"要 追加生産",IF(L23=0,"—","在庫で充足")) -> 在庫で充足 | Q23: =③石川以降予測!X46 -> 0 | R23: =K23+Q23 -> 0 | S23: =R23*D23 -> 0 | T23: — | V23: =IF(OR(U23="",U23="再生産不可"),"",U23-前提・入力!$B$39) | W23: =IF(T23="—","—",IF(U23="再生産不可","×再生産不可",_xlfn.IFS(V23<0,"★期限超過",V23<=30,"★至急(30日以内)",V23<=90,"要着手(90日以内)",TRUE(),"余裕あり"))) -> — | X23: =IF(Y23<>"",IF(FALSE(),"S:現場欠品(追納不可)","S:現場欠品"),IF(I23>0,"A:会期中欠品",IF(O23>1000,"B:大口",IF(O23>0,"C:通常","D:不要")))) -> S:現場欠品 | Y23: 欠品／近々欠品 | Z23: =IF(Y23<>"",IF(I23>0,"◎ 一致（モデルも会期中欠品を検知）",IF(H23>=0.7,"○ 整合（予測消化率70%超）","△ モデル未検知：現場報告を優先")),IF(I23>0,"▲ モデルのみ検知：現場に在庫状況を確認","—")) -> ○ 整合（予測消化率70%超） | AA23: 【7/28 運営報告】欠品／近々欠品 ／ 倉庫残2,423個 → ◎倉庫からの追加納品で対応可能（追加生産は不要） ／ 博多会場で完売（実績が在庫上限で頭打ち＝予測は控えめ）
A24: 18 | B24: 4515142545464 | C24: 呪術廻戦 渋谷事変 クリアファイル（五条 悟） | D24: 600 | E24: =①札幌予測確定!E24 -> 259 | F24: =①札幌予測確定!P24 -> 407 | G24: =①札幌予測確定!S24 -> 1500 | H24: =IFERROR(F24/G24,0) -> 0.27133333 | I24: =F24-G24 -> -1093 | J24: =IF(I24>0,"要 追加発注",IF(H24>=0.9,"要注意(90%超)",IF(H24>=0.5,"適正","在庫余剰"))) -> 在庫余剰 | K24: =IF(I24>0,ROUNDUP(I24*(1+前提・入力!$B$35),0),0) -> 0 | L24: =③石川以降予測!N47 -> 3201 | M24: =③石川以降予測!S47 -> 1093 | N24: =③石川以降予測!Q47 -> 8225 | O24: =L24-M24-N24 -> -6117 | P24: =IF(O24>0,"要 追加生産",IF(L24=0,"—","在庫で充足")) -> 在庫で充足 | Q24: =③石川以降予測!X47 -> 0 | R24: =K24+Q24 -> 0 | S24: =R24*D24 -> 0 | T24: — | V24: =IF(OR(U24="",U24="再生産不可"),"",U24-前提・入力!$B$39) | W24: =IF(T24="—","—",IF(U24="再生産不可","×再生産不可",_xlfn.IFS(V24<0,"★期限超過",V24<=30,"★至急(30日以内)",V24<=90,"要着手(90日以内)",TRUE(),"余裕あり"))) -> — | X24: =IF(Y24<>"",IF(FALSE(),"S:現場欠品(追納不可)","S:現場欠品"),IF(I24>0,"A:会期中欠品",IF(O24>1000,"B:大口",IF(O24>0,"C:通常","D:不要")))) -> D:不要 | Z24: =IF(Y24<>"",IF(I24>0,"◎ 一致（モデルも会期中欠品を検知）",IF(H24>=0.7,"○ 整合（予測消化率70%超）","△ モデル未検知：現場報告を優先")),IF(I24>0,"▲ モデルのみ検知：現場に在庫状況を確認","—")) -> — | AA24: 博多会場で完売（実績が在庫上限で頭打ち＝予測は控えめ）
A25: 19 | B25: 4515142545471 | C25: 呪術廻戦 渋谷事変 クリアファイル（夏油 傑） | D25: 600 | E25: =①札幌予測確定!E25 -> 10 | F25: =①札幌予測確定!P25 -> 16 | G25: =①札幌予測確定!S25 -> 50 | H25: =IFERROR(F25/G25,0) -> 0.32 | I25: =F25-G25 -> -34 | J25: =IF(I25>0,"要 追加発注",IF(H25>=0.9,"要注意(90%超)",IF(H25>=0.5,"適正","在庫余剰"))) -> 在庫余剰 | K25: =IF(I25>0,ROUNDUP(I25*(1+前提・入力!$B$35),0),0) -> 0 | L25: =③石川以降予測!N48 -> 104 | M25: =③石川以降予測!S48 -> 34 | N25: =③石川以降予測!Q48 -> 2190 | O25: =L25-M25-N25 -> -2120 | P25: =IF(O25>0,"要 追加生産",IF(L25=0,"—","在庫で充足")) -> 在庫で充足 | Q25: =③石川以降予測!X48 -> 0 | R25: =K25+Q25 -> 0 | S25: =R25*D25 -> 0 | T25: — | V25: =IF(OR(U25="",U25="再生産不可"),"",U25-前提・入力!$B$39) | W25: =IF(T25="—","—",IF(U25="再生産不可","×再生産不可",_xlfn.IFS(V25<0,"★期限超過",V25<=30,"★至急(30日以内)",V25<=90,"要着手(90日以内)",TRUE(),"余裕あり"))) -> — | X25: =IF(Y25<>"",IF(FALSE(),"S:現場欠品(追納不可)","S:現場欠品"),IF(I25>0,"A:会期中欠品",IF(O25>1000,"B:大口",IF(O25>0,"C:通常","D:不要")))) -> D:不要 | Z25: =IF(Y25<>"",IF(I25>0,"◎ 一致（モデルも会期中欠品を検知）",IF(H25>=0.7,"○ 整合（予測消化率70%超）","△ モデル未検知：現場報告を優先")),IF(I25>0,"▲ モデルのみ検知：現場に在庫状況を確認","—")) -> — | AA25: 博多会場で完売（実績が在庫上限で頭打ち＝予測は控えめ）
A26: 20 | B26: 4515142545488 | C26: 呪術廻戦 渋谷事変 クリアファイル（真人） | D26: 600 | E26: =①札幌予測確定!E26 -> 8 | F26: =①札幌予測確定!P26 -> 14 | G26: =①札幌予測確定!S26 -> 30 | H26: =IFERROR(F26/G26,0) -> 0.46666667 | I26: =F26-G26 -> -16 | J26: =IF(I26>0,"要 追加発注",IF(H26>=0.9,"要注意(90%超)",IF(H26>=0.5,"適正","在庫余剰"))) -> 在庫余剰 | K26: =IF(I26>0,ROUNDUP(I26*(1+前提・入力!$B$35),0),0) -> 0 | L26: =③石川以降予測!N49 -> 94 | M26: =③石川以降予測!S49 -> 16 | N26: =③石川以降予測!Q49 -> 271 | O26: =L26-M26-N26 -> -193 | P26: =IF(O26>0,"要 追加生産",IF(L26=0,"—","在庫で充足")) -> 在庫で充足 | Q26: =③石川以降予測!X49 -> 0 | R26: =K26+Q26 -> 0 | S26: =R26*D26 -> 0 | T26: — | V26: =IF(OR(U26="",U26="再生産不可"),"",U26-前提・入力!$B$39) | W26: =IF(T26="—","—",IF(U26="再生産不可","×再生産不可",_xlfn.IFS(V26<0,"★期限超過",V26<=30,"★至急(30日以内)",V26<=90,"要着手(90日以内)",TRUE(),"余裕あり"))) -> — | X26: =IF(Y26<>"",IF(FALSE(),"S:現場欠品(追納不可)","S:現場欠品"),IF(I26>0,"A:会期中欠品",IF(O26>1000,"B:大口",IF(O26>0,"C:通常","D:不要")))) -> D:不要 | Z26: =IF(Y26<>"",IF(I26>0,"◎ 一致（モデルも会期中欠品を検知）",IF(H26>=0.7,"○ 整合（予測消化率70%超）","△ モデル未検知：現場報告を優先")),IF(I26>0,"▲ モデルのみ検知：現場に在庫状況を確認","—")) -> — | AA26: 博多会場で完売（実績が在庫上限で頭打ち＝予測は控えめ）
A27: 21 | B27: 4515142545495 | C27: 呪術廻戦 渋谷事変 クリアファイル（脹相） | D27: 600 | E27: =①札幌予測確定!E27 -> 50 | F27: =①札幌予測確定!P27 -> 90 | G27: =①札幌予測確定!S27 -> 100 | H27: =IFERROR(F27/G27,0) -> 0.9 | I27: =F27-G27 -> -10 | J27: =IF(I27>0,"要 追加発注",IF(H27>=0.9,"要注意(90%超)",IF(H27>=0.5,"適正","在庫余剰"))) -> 要注意(90%超) | K27: =IF(I27>0,ROUNDUP(I27*(1+前提・入力!$B$35),0),0) -> 0 | L27: =③石川以降予測!N50 -> 583 | M27: =③石川以降予測!S50 -> 10 | N27: =③石川以降予測!Q50 -> 208 | O27: =L27-M27-N27 -> 365 | P27: =IF(O27>0,"要 追加生産",IF(L27=0,"—","在庫で充足")) -> 要 追加生産 | Q27: =③石川以降予測!X50 -> 402 | R27: =K27+Q27 -> 402 | S27: =R27*D27 -> 241200 | T27: 神戸阪急 | U27: =DATE(2026,12,16)-30-前提・入力!$B$38 -> 46328 | V27: =IF(OR(U27="",U27="再生産不可"),"",U27-前提・入力!$B$39) -> 95 | W27: =IF(T27="—","—",IF(U27="再生産不可","×再生産不可",_xlfn.IFS(V27<0,"★期限超過",V27<=30,"★至急(30日以内)",V27<=90,"要着手(90日以内)",TRUE(),"余裕あり"))) -> 余裕あり | X27: =IF(Y27<>"",IF(FALSE(),"S:現場欠品(追納不可)","S:現場欠品"),IF(I27>0,"A:会期中欠品",IF(O27>1000,"B:大口",IF(O27>0,"C:通常","D:不要")))) -> S:現場欠品 | Y27: 欠品／近々欠品 | Z27: =IF(Y27<>"",IF(I27>0,"◎ 一致（モデルも会期中欠品を検知）",IF(H27>=0.7,"○ 整合（予測消化率70%超）","△ モデル未検知：現場報告を優先")),IF(I27>0,"▲ モデルのみ検知：現場に在庫状況を確認","—")) -> ○ 整合（予測消化率70%超） | AA27: 【7/28 運営報告】欠品／近々欠品 ／ 倉庫残208個 → ◎倉庫からの追加納品で対応可能（追加生産は不要） ／ 名古屋会場で完売（実績が在庫上限で頭打ち＝予測は控えめ） ／ 博多会場で完売（実績が在庫上限で頭打ち＝予測は控えめ）
A28: 22 | B28: 4515142545501 | C28: 呪術廻戦 渋谷事変 クリアファイル（宿儺） | D28: 600 | E28: =①札幌予測確定!E28 -> 23 | F28: =①札幌予測確定!P28 -> 52 | G28: =①札幌予測確定!S28 -> 50 | H28: =IFERROR(F28/G28,0) -> 1.04 | I28: =F28-G28 -> 2 | J28: =IF(I28>0,"要 追加発注",IF(H28>=0.9,"要注意(90%超)",IF(H28>=0.5,"適正","在庫余剰"))) -> 要 追加発注 | K28: =IF(I28>0,ROUNDUP(I28*(1+前提・入力!$B$35),0),0) -> 3 | L28: =③石川以降予測!N51 -> 353 | M28: =③石川以降予測!S51 -> 0 | N28: =③石川以降予測!Q51 -> 1281 | O28: =L28-M28-N28 -> -928 | P28: =IF(O28>0,"要 追加生産",IF(L28=0,"—","在庫で充足")) -> 在庫で充足 | Q28: =③石川以降予測!X51 -> 0 | R28: =K28+Q28 -> 3 | S28: =R28*D28 -> 1800 | T28: — | V28: =IF(OR(U28="",U28="再生産不可"),"",U28-前提・入力!$B$39) | W28: =IF(T28="—","—",IF(U28="再生産不可","×再生産不可",_xlfn.IFS(V28<0,"★期限超過",V28<=30,"★至急(30日以内)",V28<=90,"要着手(90日以内)",TRUE(),"余裕あり"))) -> — | X28: =IF(Y28<>"",IF(FALSE(),"S:現場欠品(追納不可)","S:現場欠品"),IF(I28>0,"A:会期中欠品",IF(O28>1000,"B:大口",IF(O28>0,"C:通常","D:不要")))) -> S:現場欠品 | Y28: 欠品／近々欠品 | Z28: =IF(Y28<>"",IF(I28>0,"◎ 一致（モデルも会期中欠品を検知）",IF(H28>=0.7,"○ 整合（予測消化率70%超）","△ モデル未検知：現場報告を優先")),IF(I28>0,"▲ モデルのみ検知：現場に在庫状況を確認","—")) -> ◎ 一致（モデルも会期中欠品を検知） | AA28: 【7/28 運営報告】欠品／近々欠品 ／ 倉庫残1,281個 → ◎倉庫からの追加納品で対応可能（追加生産は不要） ／ 札幌会期中に欠品見込。至急スライド納品または追加発注 ／ 博多会場で完売（実績が在庫上限で頭打ち＝予測は控えめ）
A29: 23 | B29: 4515142545174 | C29: 呪術廻戦 懐玉・玉折 ブラインドミニ色紙（全5種） | D29: 600 | E29: =①札幌予測確定!E29 -> 1220 | F29: =①札幌予測確定!P29 -> 2100 | G29: =①札幌予測確定!S29 -> 11000 | H29: =IFERROR(F29/G29,0) -> 0.19090909 | I29: =F29-G29 -> -8900 | J29: =IF(I29>0,"要 追加発注",IF(H29>=0.9,"要注意(90%超)",IF(H29>=0.5,"適正","在庫余剰"))) -> 在庫余剰 | K29: =IF(I29>0,ROUNDUP(I29*(1+前提・入力!$B$35),0),0) -> 0 | L29: =③石川以降予測!N52 -> 17991 | M29: =③石川以降予測!S52 -> 8900 | N29: =③石川以降予測!Q52 -> 40818 | O29: =L29-M29-N29 -> -31727 | P29: =IF(O29>0,"要 追加生産",IF(L29=0,"—","在庫で充足")) -> 在庫で充足 | Q29: =③石川以降予測!X52 -> 0 | R29: =K29+Q29 -> 0 | S29: =R29*D29 -> 0 | T29: — | V29: =IF(OR(U29="",U29="再生産不可"),"",U29-前提・入力!$B$39) | W29: =IF(T29="—","—",IF(U29="再生産不可","×再生産不可",_xlfn.IFS(V29<0,"★期限超過",V29<=30,"★至急(30日以内)",V29<=90,"要着手(90日以内)",TRUE(),"余裕あり"))) -> — | X29: =IF(Y29<>"",IF(FALSE(),"S:現場欠品(追納不可)","S:現場欠品"),IF(I29>0,"A:会期中欠品",IF(O29>1000,"B:大口",IF(O29>0,"C:通常","D:不要")))) -> D:不要 | Z29: =IF(Y29<>"",IF(I29>0,"◎ 一致（モデルも会期中欠品を検知）",IF(H29>=0.7,"○ 整合（予測消化率70%超）","△ モデル未検知：現場報告を優先")),IF(I29>0,"▲ モデルのみ検知：現場に在庫状況を確認","—")) -> —
A30: 24 | B30: 4515142545181 | C30: 呪術廻戦 渋谷事変 ブラインドミニ色紙（全5種） | D30: 600 | E30: =①札幌予測確定!E30 -> 682 | F30: =①札幌予測確定!P30 -> 1213 | G30: =①札幌予測確定!S30 -> 8000 | H30: =IFERROR(F30/G30,0) -> 0.151625 | I30: =F30-G30 -> -6787 | J30: =IF(I30>0,"要 追加発注",IF(H30>=0.9,"要注意(90%超)",IF(H30>=0.5,"適正","在庫余剰"))) -> 在庫余剰 | K30: =IF(I30>0,ROUNDUP(I30*(1+前提・入力!$B$35),0),0) -> 0 | L30: =③石川以降予測!N53 -> 10154 | M30: =③石川以降予測!S53 -> 6787 | N30: =③石川以降予測!Q53 -> 24204 | O30: =L30-M30-N30 -> -20837 | P30: =IF(O30>0,"要 追加生産",IF(L30=0,"—","在庫で充足")) -> 在庫で充足 | Q30: =③石川以降予測!X53 -> 0 | R30: =K30+Q30 -> 0 | S30: =R30*D30 -> 0 | T30: — | V30: =IF(OR(U30="",U30="再生産不可"),"",U30-前提・入力!$B$39) | W30: =IF(T30="—","—",IF(U30="再生産不可","×再生産不可",_xlfn.IFS(V30<0,"★期限超過",V30<=30,"★至急(30日以内)",V30<=90,"要着手(90日以内)",TRUE(),"余裕あり"))) -> — | X30: =IF(Y30<>"",IF(FALSE(),"S:現場欠品(追納不可)","S:現場欠品"),IF(I30>0,"A:会期中欠品",IF(O30>1000,"B:大口",IF(O30>0,"C:通常","D:不要")))) -> D:不要 | Z30: =IF(Y30<>"",IF(I30>0,"◎ 一致（モデルも会期中欠品を検知）",IF(H30>=0.7,"○ 整合（予測消化率70%超）","△ モデル未検知：現場報告を優先")),IF(I30>0,"▲ モデルのみ検知：現場に在庫状況を確認","—")) -> —
A31: 25 | B31: 4515142545198 | C31: 虚式『茈』バスボール | D31: 1500 | E31: =①札幌予測確定!E31 -> 29 | F31: =①札幌予測確定!P31 -> 54 | G31: =①札幌予測確定!S31 -> 200 | H31: =IFERROR(F31/G31,0) -> 0.27 | I31: =F31-G31 -> -146 | J31: =IF(I31>0,"要 追加発注",IF(H31>=0.9,"要注意(90%超)",IF(H31>=0.5,"適正","在庫余剰"))) -> 在庫余剰 | K31: =IF(I31>0,ROUNDUP(I31*(1+前提・入力!$B$35),0),0) -> 0 | L31: =③石川以降予測!N54 -> 409 | M31: =③石川以降予測!S54 -> 146 | N31: =③石川以降予測!Q54 -> 3305 | O31: =L31-M31-N31 -> -3042 | P31: =IF(O31>0,"要 追加生産",IF(L31=0,"—","在庫で充足")) -> 在庫で充足 | Q31: =③石川以降予測!X54 -> 0 | R31: =K31+Q31 -> 0 | S31: =R31*D31 -> 0 | T31: — | V31: =IF(OR(U31="",U31="再生産不可"),"",U31-前提・入力!$B$39) | W31: =IF(T31="—","—",IF(U31="再生産不可","×再生産不可",_xlfn.IFS(V31<0,"★期限超過",V31<=30,"★至急(30日以内)",V31<=90,"要着手(90日以内)",TRUE(),"余裕あり"))) -> — | X31: =IF(Y31<>"",IF(FALSE(),"S:現場欠品(追納不可)","S:現場欠品"),IF(I31>0,"A:会期中欠品",IF(O31>1000,"B:大口",IF(O31>0,"C:通常","D:不要")))) -> D:不要 | Z31: =IF(Y31<>"",IF(I31>0,"◎ 一致（モデルも会期中欠品を検知）",IF(H31>=0.7,"○ 整合（予測消化率70%超）","△ モデル未検知：現場報告を優先")),IF(I31>0,"▲ モデルのみ検知：現場に在庫状況を確認","—")) -> — | AA31: 博多会場で完売（実績が在庫上限で頭打ち＝予測は控えめ）
A32: 26 | B32: 4515142545204 | C32: 前髪ヘアバンド | D32: 2200 | E32: =①札幌予測確定!E32 -> 100 | F32: =①札幌予測確定!P32 -> 156 | G32: =①札幌予測確定!S32 -> 200 | H32: =IFERROR(F32/G32,0) -> 0.78 | I32: =F32-G32 -> -44 | J32: =IF(I32>0,"要 追加発注",IF(H32>=0.9,"要注意(90%超)",IF(H32>=0.5,"適正","在庫余剰"))) -> 適正 | K32: =IF(I32>0,ROUNDUP(I32*(1+前提・入力!$B$35),0),0) -> 0 | L32: =③石川以降予測!N55 -> 1270 | M32: =③石川以降予測!S55 -> 44 | N32: =③石川以降予測!Q55 -> 297 | O32: =L32-M32-N32 -> 929 | P32: =IF(O32>0,"要 追加生産",IF(L32=0,"—","在庫で充足")) -> 要 追加生産 | Q32: =③石川以降予測!X55 -> 1022 | R32: =K32+Q32 -> 1022 | S32: =R32*D32 -> 2248400 | T32: 神戸阪急 | U32: =DATE(2026,12,16)-75-前提・入力!$B$38 -> 46283 | V32: =IF(OR(U32="",U32="再生産不可"),"",U32-前提・入力!$B$39) -> 50 | W32: =IF(T32="—","—",IF(U32="再生産不可","×再生産不可",_xlfn.IFS(V32<0,"★期限超過",V32<=30,"★至急(30日以内)",V32<=90,"要着手(90日以内)",TRUE(),"余裕あり"))) -> 要着手(90日以内) | X32: =IF(Y32<>"",IF(FALSE(),"S:現場欠品(追納不可)","S:現場欠品"),IF(I32>0,"A:会期中欠品",IF(O32>1000,"B:大口",IF(O32>0,"C:通常","D:不要")))) -> S:現場欠品 | Y32: 欠品／近々欠品 | Z32: =IF(Y32<>"",IF(I32>0,"◎ 一致（モデルも会期中欠品を検知）",IF(H32>=0.7,"○ 整合（予測消化率70%超）","△ モデル未検知：現場報告を優先")),IF(I32>0,"▲ モデルのみ検知：現場に在庫状況を確認","—")) -> ○ 整合（予測消化率70%超） | AA32: 【7/28 運営報告】欠品／近々欠品 ／ 倉庫残297個 → ◎倉庫からの追加納品で対応可能（追加生産は不要） ／ 名古屋会場で完売（実績が在庫上限で頭打ち＝予測は控えめ）
A33: 27 | B33: 4515142545211 | C33: 反転術式絆創膏 | D33: 1100 | E33: =①札幌予測確定!E33 -> 20 | F33: =①札幌予測確定!P33 -> 40 | G33: =①札幌予測確定!S33 -> 70 | H33: =IFERROR(F33/G33,0) -> 0.57142857 | I33: =F33-G33 -> -30 | J33: =IF(I33>0,"要 追加発注",IF(H33>=0.9,"要注意(90%超)",IF(H33>=0.5,"適正","在庫余剰"))) -> 適正 | K33: =IF(I33>0,ROUNDUP(I33*(1+前提・入力!$B$35),0),0) -> 0 | L33: =③石川以降予測!N56 -> 279 | M33: =③石川以降予測!S56 -> 30 | N33: =③石川以降予測!Q56 -> 1128 | O33: =L33-M33-N33 -> -879 | P33: =IF(O33>0,"要 追加生産",IF(L33=0,"—","在庫で充足")) -> 在庫で充足 | Q33: =③石川以降予測!X56 -> 0 | R33: =K33+Q33 -> 0 | S33: =R33*D33 -> 0 | T33: — | V33: =IF(OR(U33="",U33="再生産不可"),"",U33-前提・入力!$B$39) | W33: =IF(T33="—","—",IF(U33="再生産不可","×再生産不可",_xlfn.IFS(V33<0,"★期限超過",V33<=30,"★至急(30日以内)",V33<=90,"要着手(90日以内)",TRUE(),"余裕あり"))) -> — | X33: =IF(Y33<>"",IF(FALSE(),"S:現場欠品(追納不可)","S:現場欠品"),IF(I33>0,"A:会期中欠品",IF(O33>1000,"B:大口",IF(O33>0,"C:通常","D:不要")))) -> D:不要 | Z33: =IF(Y33<>"",IF(I33>0,"◎ 一致（モデルも会期中欠品を検知）",IF(H33>=0.7,"○ 整合（予測消化率70%超）","△ モデル未検知：現場報告を優先")),IF(I33>0,"▲ モデルのみ検知：現場に在庫状況を確認","—")) -> — | AA33: 博多会場で完売（実績が在庫上限で頭打ち＝予測は控えめ）
A34: 28 | B34: 4515142545228 | C34: 宿儺の指風お菓子 | D34: 1800 | E34: =①札幌予測確定!E34 -> 184 | F34: =①札幌予測確定!P34 -> 216 | G34: =①札幌予測確定!S34 -> 300 | H34: =IFERROR(F34/G34,0) -> 0.72 | I34: =F34-G34 -> -84 | J34: =IF(I34>0,"要 追加発注",IF(H34>=0.9,"要注意(90%超)",IF(H34>=0.5,"適正","在庫余剰"))) -> 適正 | K34: =IF(I34>0,ROUNDUP(I34*(1+前提・入力!$B$35),0),0) -> 0 | L34: =③石川以降予測!N57 -> 1267 | M34: =③石川以降予測!S57 -> 84 | N34: =③石川以降予測!Q57 -> 160 | O34: =L34-M34-N34 -> 1023 | P34: =IF(O34>0,"要 追加生産",IF(L34=0,"—","在庫で充足")) -> 要 追加生産 | Q34: =③石川以降予測!X57 -> 0 | R34: =K34+Q34 -> 0 | S34: =R34*D34 -> 0 | T34: — | V34: =IF(OR(U34="",U34="再生産不可"),"",U34-前提・入力!$B$39) | W34: ◎発注確定済 | X34: =IF(Y34<>"",IF(FALSE(),"S:現場欠品(追納不可)","S:現場欠品"),IF(I34>0,"A:会期中欠品",IF(O34>1000,"B:大口",IF(O34>0,"C:通常","D:不要")))) -> S:現場欠品 | Y34: 欠品／近々欠品 | Z34: =IF(Y34<>"",IF(I34>0,"◎ 一致（モデルも会期中欠品を検知）",IF(H34>=0.7,"○ 整合（予測消化率70%超）","△ モデル未検知：現場報告を優先")),IF(I34>0,"▲ モデルのみ検知：現場に在庫状況を確認","—")) -> ○ 整合（予測消化率70%超） | AA34: 【7/28 運営報告】欠品／近々欠品 ／ 倉庫残160個 → ◎倉庫からの追加納品で対応可能（追加生産は不要） ／ 名古屋会場で完売（実績が在庫上限で頭打ち＝予測は控えめ） ／ 博多会場で完売（実績が在庫上限で頭打ち＝予測は控えめ） ／ 大阪会場で完売（実績が在庫上限で頭打ち＝予測は控えめ）
A35: 29 | B35: 4515142545235 | C35: 脱兎！ポーチ入りクリップセット | D35: 1500 | E35: =①札幌予測確定!E35 -> 89 | F35: =①札幌予測確定!P35 -> 107 | G35: =①札幌予測確定!S35 -> 160 | H35: =IFERROR(F35/G35,0) -> 0.66875 | I35: =F35-G35 -> -53 | J35: =IF(I35>0,"要 追加発注",IF(H35>=0.9,"要注意(90%超)",IF(H35>=0.5,"適正","在庫余剰"))) -> 適正 | K35: =IF(I35>0,ROUNDUP(I35*(1+前提・入力!$B$35),0),0) -> 0 | L35: =③石川以降予測!N58 -> 629 | M35: =③石川以降予測!S58 -> 53 | N35: =③石川以降予測!Q58 -> 260 | O35: =L35-M35-N35 -> 316 | P35: =IF(O35>0,"要 追加生産",IF(L35=0,"—","在庫で充足")) -> 要 追加生産 | Q35: =③石川以降予測!X58 -> 348 | R35: =K35+Q35 -> 348 | S35: =R35*D35 -> 522000 | T35: 東京凱旋 東京建物ぴあホール | U35: =DATE(2027,4,1)-90-前提・入力!$B$38 -> 46374 | V35: =IF(OR(U35="",U35="再生産不可"),"",U35-前提・入力!$B$39) -> 141 | W35: =IF(T35="—","—",IF(U35="再生産不可","×再生産不可",_xlfn.IFS(V35<0,"★期限超過",V35<=30,"★至急(30日以内)",V35<=90,"要着手(90日以内)",TRUE(),"余裕あり"))) -> 余裕あり | X35: =IF(Y35<>"",IF(FALSE(),"S:現場欠品(追納不可)","S:現場欠品"),IF(I35>0,"A:会期中欠品",IF(O35>1000,"B:大口",IF(O35>0,"C:通常","D:不要")))) -> S:現場欠品 | Y35: 欠品／近々欠品 | Z35: =IF(Y35<>"",IF(I35>0,"◎ 一致（モデルも会期中欠品を検知）",IF(H35>=0.7,"○ 整合（予測消化率70%超）","△ モデル未検知：現場報告を優先")),IF(I35>0,"▲ モデルのみ検知：現場に在庫状況を確認","—")) -> △ モデル未検知：現場報告を優先 | AA35: 【7/28 運営報告】欠品／近々欠品 ／ 倉庫残260個 → ◎倉庫からの追加納品で対応可能（追加生産は不要） ／ 名古屋会場で完売（実績が在庫上限で頭打ち＝予測は控えめ） ／ 博多会場で完売（実績が在庫上限で頭打ち＝予測は控えめ） ／ 大阪会場で完売（実績が在庫上限で頭打ち＝予測は控えめ）
A36: 30 | B36: 4515142545242 | C36: 釘崎のポーチ風エコバッグ | D36: 3300 | E36: =①札幌予測確定!E36 -> 29 | F36: =①札幌予測確定!P36 -> 63 | G36: =①札幌予測確定!S36 -> 250 | H36: =IFERROR(F36/G36,0) -> 0.252 | I36: =F36-G36 -> -187 | J36: =IF(I36>0,"要 追加発注",IF(H36>=0.9,"要注意(90%超)",IF(H36>=0.5,"適正","在庫余剰"))) -> 在庫余剰 | K36: =IF(I36>0,ROUNDUP(I36*(1+前提・入力!$B$35),0),0) -> 0 | L36: =③石川以降予測!N59 -> 425 | M36: =③石川以降予測!S59 -> 187 | N36: =③石川以降予測!Q59 -> 648 | O36: =L36-M36-N36 -> -410 | P36: =IF(O36>0,"要 追加生産",IF(L36=0,"—","在庫で充足")) -> 在庫で充足 | Q36: =③石川以降予測!X59 -> 0 | R36: =K36+Q36 -> 0 | S36: =R36*D36 -> 0 | T36: — | V36: =IF(OR(U36="",U36="再生産不可"),"",U36-前提・入力!$B$39) | W36: =IF(T36="—","—",IF(U36="再生産不可","×再生産不可",_xlfn.IFS(V36<0,"★期限超過",V36<=30,"★至急(30日以内)",V36<=90,"要着手(90日以内)",TRUE(),"余裕あり"))) -> — | X36: =IF(Y36<>"",IF(FALSE(),"S:現場欠品(追納不可)","S:現場欠品"),IF(I36>0,"A:会期中欠品",IF(O36>1000,"B:大口",IF(O36>0,"C:通常","D:不要")))) -> D:不要 | Z36: =IF(Y36<>"",IF(I36>0,"◎ 一致（モデルも会期中欠品を検知）",IF(H36>=0.7,"○ 整合（予測消化率70%超）","△ モデル未検知：現場報告を優先")),IF(I36>0,"▲ モデルのみ検知：現場に在庫状況を確認","—")) -> — | AA36: 博多会場で完売（実績が在庫上限で頭打ち＝予測は控えめ）
A37: 31 | B37: 4515142545259 | C37: 半年分の情報が書き込める手帳 | D37: 1300 | E37: =①札幌予測確定!E37 -> 51 | F37: =①札幌予測確定!P37 -> 87 | G37: =①札幌予測確定!S37 -> 200 | H37: =IFERROR(F37/G37,0) -> 0.435 | I37: =F37-G37 -> -113 | J37: =IF(I37>0,"要 追加発注",IF(H37>=0.9,"要注意(90%超)",IF(H37>=0.5,"適正","在庫余剰"))) -> 在庫余剰 | K37: =IF(I37>0,ROUNDUP(I37*(1+前提・入力!$B$35),0),0) -> 0 | L37: =③石川以降予測!N60 -> 681 | M37: =③石川以降予測!S60 -> 113 | N37: =③石川以降予測!Q60 -> 726 | O37: =L37-M37-N37 -> -158 | P37: =IF(O37>0,"要 追加生産",IF(L37=0,"—","在庫で充足")) -> 在庫で充足 | Q37: =③石川以降予測!X60 -> 0 | R37: =K37+Q37 -> 0 | S37: =R37*D37 -> 0 | T37: — | V37: =IF(OR(U37="",U37="再生産不可"),"",U37-前提・入力!$B$39) | W37: =IF(T37="—","—",IF(U37="再生産不可","×再生産不可",_xlfn.IFS(V37<0,"★期限超過",V37<=30,"★至急(30日以内)",V37<=90,"要着手(90日以内)",TRUE(),"余裕あり"))) -> — | X37: =IF(Y37<>"",IF(FALSE(),"S:現場欠品(追納不可)","S:現場欠品"),IF(I37>0,"A:会期中欠品",IF(O37>1000,"B:大口",IF(O37>0,"C:通常","D:不要")))) -> D:不要 | Z37: =IF(Y37<>"",IF(I37>0,"◎ 一致（モデルも会期中欠品を検知）",IF(H37>=0.7,"○ 整合（予測消化率70%超）","△ モデル未検知：現場報告を優先")),IF(I37>0,"▲ モデルのみ検知：現場に在庫状況を確認","—")) -> — | AA37: 博多会場で完売（実績が在庫上限で頭打ち＝予測は控えめ）
A38: 32 | B38: 4515142545266 | C38: 気分リフレッシュオルゴール | D38: 8800 | E38: =①札幌予測確定!E38 -> 10 | F38: =①札幌予測確定!P38 -> 10 | G38: =①札幌予測確定!S38 -> 10 | H38: =IFERROR(F38/G38,0) -> 1 | I38: =F38-G38 -> 0 | J38: =IF(I38>0,"要 追加発注",IF(H38>=0.9,"要注意(90%超)",IF(H38>=0.5,"適正","在庫余剰"))) -> 要注意(90%超) | K38: =IF(I38>0,ROUNDUP(I38*(1+前提・入力!$B$35),0),0) -> 0 | L38: =③石川以降予測!N61 -> 72 | M38: =③石川以降予測!S61 -> 0 | N38: =③石川以降予測!Q61 -> 23 | O38: =L38-M38-N38 -> 49 | P38: =IF(O38>0,"要 追加生産",IF(L38=0,"—","在庫で充足")) -> 要 追加生産 | Q38: =③石川以降予測!X61 -> 54 | R38: =K38+Q38 -> 54 | S38: =R38*D38 -> 475200 | T38: 神戸阪急 | U38: =DATE(2026,12,16)-90-前提・入力!$B$38 -> 46268 | V38: =IF(OR(U38="",U38="再生産不可"),"",U38-前提・入力!$B$39) -> 35 | W38: =IF(T38="—","—",IF(U38="再生産不可","×再生産不可",_xlfn.IFS(V38<0,"★期限超過",V38<=30,"★至急(30日以内)",V38<=90,"要着手(90日以内)",TRUE(),"余裕あり"))) -> 要着手(90日以内) | X38: =IF(Y38<>"",IF(TRUE(),"S:現場欠品(追納不可)","S:現場欠品"),IF(I38>0,"A:会期中欠品",IF(O38>1000,"B:大口",IF(O38>0,"C:通常","D:不要")))) -> S:現場欠品(追納不可) | Y38: 欠品（※前会場時に追納困難と回答済） | Z38: =IF(Y38<>"",IF(I38>0,"◎ 一致（モデルも会期中欠品を検知）",IF(H38>=0.7,"○ 整合（予測消化率70%超）","△ モデル未検知：現場報告を優先")),IF(I38>0,"▲ モデルのみ検知：現場に在庫状況を確認","—")) -> ○ 整合（予測消化率70%超） | AA38: 【7/28 運営報告】欠品（※前会場時に追納困難と回答済） ／ 倉庫残23個 → ◎倉庫からの追加納品で対応可能（追加生産は不要） ／ ★追納不可のため発注推奨は0。石川以降は欠品前提で販売計画を組むか代替商品を手配 ／ 札幌納品数が極小(10個) ／ 名古屋会場で完売（実績が在庫上限で頭打ち＝予測は控えめ） ／ 博多会場で完売（実績が在庫上限で頭打ち＝予測は控えめ） ／ 大阪会場で完売（実績が在庫上限で頭打ち＝予測は控えめ）
A39: 33 | B39: 4515142545273 | C39: 五条 悟 イメージリング（#11） | D39: 27500 | E39: =①札幌予測確定!E39 -> 0 | F39: =①札幌予測確定!P39 -> 0 | G39: =①札幌予測確定!S39 -> 15 | H39: =IFERROR(F39/G39,0) -> 0 | I39: =F39-G39 -> -15 | J39: =IF(I39>0,"要 追加発注",IF(H39>=0.9,"要注意(90%超)",IF(H39>=0.5,"適正","在庫余剰"))) -> 在庫余剰 | K39: =IF(I39>0,ROUNDUP(I39*(1+前提・入力!$B$35),0),0) -> 0 | L39: =③石川以降予測!N62 -> 14 | M39: =③石川以降予測!S62 -> 15 | N39: =③石川以降予測!Q62 -> 91 | O39: =L39-M39-N39 -> -92 | P39: =IF(O39>0,"要 追加生産",IF(L39=0,"—","在庫で充足")) -> 在庫で充足 | Q39: =③石川以降予測!X62 -> 0 | R39: =K39+Q39 -> 0 | S39: =R39*D39 -> 0 | T39: — | V39: =IF(OR(U39="",U39="再生産不可"),"",U39-前提・入力!$B$39) | W39: =IF(T39="—","—",IF(U39="再生産不可","×再生産不可",_xlfn.IFS(V39<0,"★期限超過",V39<=30,"★至急(30日以内)",V39<=90,"要着手(90日以内)",TRUE(),"余裕あり"))) -> — | X39: =IF(Y39<>"",IF(FALSE(),"S:現場欠品(追納不可)","S:現場欠品"),IF(I39>0,"A:会期中欠品",IF(O39>1000,"B:大口",IF(O39>0,"C:通常","D:不要")))) -> D:不要 | Z39: =IF(Y39<>"",IF(I39>0,"◎ 一致（モデルも会期中欠品を検知）",IF(H39>=0.7,"○ 整合（予測消化率70%超）","△ モデル未検知：現場報告を優先")),IF(I39>0,"▲ モデルのみ検知：現場に在庫状況を確認","—")) -> — | AA39: 札幌初6日の販売実績ゼロ（予測は大阪・博多構成比で按分）
A40: 34 | B40: 4515142545280 | C40: 五条 悟 イメージリング（#13） | D40: 27500 | E40: =①札幌予測確定!E40 -> 1 | F40: =①札幌予測確定!P40 -> 1 | G40: =①札幌予測確定!S40 -> 2 | H40: =IFERROR(F40/G40,0) -> 0.5 | I40: =F40-G40 -> -1 | J40: =IF(I40>0,"要 追加発注",IF(H40>=0.9,"要注意(90%超)",IF(H40>=0.5,"適正","在庫余剰"))) -> 適正 | K40: =IF(I40>0,ROUNDUP(I40*(1+前提・入力!$B$35),0),0) -> 0 | L40: =③石川以降予測!N63 -> 7 | M40: =③石川以降予測!S63 -> 1 | N40: =③石川以降予測!Q63 -> 2 | O40: =L40-M40-N40 -> 4 | P40: =IF(O40>0,"要 追加生産",IF(L40=0,"—","在庫で充足")) -> 要 追加生産 | Q40: =③石川以降予測!X63 -> 5 | R40: =K40+Q40 -> 5 | S40: =R40*D40 -> 137500 | T40: 鳥取島根 夢みなとタワー | U40: =DATE(2027,3,15)-90-前提・入力!$B$38 -> 46357 | V40: =IF(OR(U40="",U40="再生産不可"),"",U40-前提・入力!$B$39) -> 124 | W40: =IF(T40="—","—",IF(U40="再生産不可","×再生産不可",_xlfn.IFS(V40<0,"★期限超過",V40<=30,"★至急(30日以内)",V40<=90,"要着手(90日以内)",TRUE(),"余裕あり"))) -> 余裕あり | X40: =IF(Y40<>"",IF(FALSE(),"S:現場欠品(追納不可)","S:現場欠品"),IF(I40>0,"A:会期中欠品",IF(O40>1000,"B:大口",IF(O40>0,"C:通常","D:不要")))) -> C:通常 | Z40: =IF(Y40<>"",IF(I40>0,"◎ 一致（モデルも会期中欠品を検知）",IF(H40>=0.7,"○ 整合（予測消化率70%超）","△ モデル未検知：現場報告を優先")),IF(I40>0,"▲ モデルのみ検知：現場に在庫状況を確認","—")) -> — | AA40: 札幌納品数が極小(2個) ／ 名古屋会場で完売（実績が在庫上限で頭打ち＝予測は控えめ） ／ 博多会場で完売（実績が在庫上限で頭打ち＝予測は控えめ） ／ 大阪会場で完売（実績が在庫上限で頭打ち＝予測は控えめ）
A41: 35 | B41: 4515142545297 | C41: 五条 悟 イメージリング（#15） | D41: 27500 | E41: =①札幌予測確定!E41 -> 0 | F41: =①札幌予測確定!P41 -> 0 | G41: =①札幌予測確定!S41 -> 2 | H41: =IFERROR(F41/G41,0) -> 0 | I41: =F41-G41 -> -2 | J41: =IF(I41>0,"要 追加発注",IF(H41>=0.9,"要注意(90%超)",IF(H41>=0.5,"適正","在庫余剰"))) -> 在庫余剰 | K41: =IF(I41>0,ROUNDUP(I41*(1+前提・入力!$B$35),0),0) -> 0 | L41: =③石川以降予測!N64 -> 1 | M41: =③石川以降予測!S64 -> 2 | N41: =③石川以降予測!Q64 -> 2 | O41: =L41-M41-N41 -> -3 | P41: =IF(O41>0,"要 追加生産",IF(L41=0,"—","在庫で充足")) -> 在庫で充足 | Q41: =③石川以降予測!X64 -> 0 | R41: =K41+Q41 -> 0 | S41: =R41*D41 -> 0 | T41: — | V41: =IF(OR(U41="",U41="再生産不可"),"",U41-前提・入力!$B$39) | W41: =IF(T41="—","—",IF(U41="再生産不可","×再生産不可",_xlfn.IFS(V41<0,"★期限超過",V41<=30,"★至急(30日以内)",V41<=90,"要着手(90日以内)",TRUE(),"余裕あり"))) -> — | X41: =IF(Y41<>"",IF(FALSE(),"S:現場欠品(追納不可)","S:現場欠品"),IF(I41>0,"A:会期中欠品",IF(O41>1000,"B:大口",IF(O41>0,"C:通常","D:不要")))) -> D:不要 | Z41: =IF(Y41<>"",IF(I41>0,"◎ 一致（モデルも会期中欠品を検知）",IF(H41>=0.7,"○ 整合（予測消化率70%超）","△ モデル未検知：現場報告を優先")),IF(I41>0,"▲ モデルのみ検知：現場に在庫状況を確認","—")) -> — | AA41: 札幌納品数が極小(2個) ／ 札幌初6日の販売実績ゼロ（予測は大阪・博多構成比で按分） ／ 名古屋会場で完売（実績が在庫上限で頭打ち＝予測は控えめ） ／ 博多会場で完売（実績が在庫上限で頭打ち＝予測は控えめ） ／ 大阪会場で完売（実績が在庫上限で頭打ち＝予測は控えめ）
A42: 36 | B42: 4515142545303 | C42: 五条 悟 イメージリング（#17） | D42: 27500 | E42: =①札幌予測確定!E42 -> 0 | F42: =①札幌予測確定!P42 -> 0 | G42: =①札幌予測確定!S42 -> 2 | H42: =IFERROR(F42/G42,0) -> 0 | I42: =F42-G42 -> -2 | J42: =IF(I42>0,"要 追加発注",IF(H42>=0.9,"要注意(90%超)",IF(H42>=0.5,"適正","在庫余剰"))) -> 在庫余剰 | K42: =IF(I42>0,ROUNDUP(I42*(1+前提・入力!$B$35),0),0) -> 0 | L42: =③石川以降予測!N65 -> 1 | M42: =③石川以降予測!S65 -> 2 | N42: =③石川以降予測!Q65 -> 2 | O42: =L42-M42-N42 -> -3 | P42: =IF(O42>0,"要 追加生産",IF(L42=0,"—","在庫で充足")) -> 在庫で充足 | Q42: =③石川以降予測!X65 -> 0 | R42: =K42+Q42 -> 0 | S42: =R42*D42 -> 0 | T42: — | V42: =IF(OR(U42="",U42="再生産不可"),"",U42-前提・入力!$B$39) | W42: =IF(T42="—","—",IF(U42="再生産不可","×再生産不可",_xlfn.IFS(V42<0,"★期限超過",V42<=30,"★至急(30日以内)",V42<=90,"要着手(90日以内)",TRUE(),"余裕あり"))) -> — | X42: =IF(Y42<>"",IF(FALSE(),"S:現場欠品(追納不可)","S:現場欠品"),IF(I42>0,"A:会期中欠品",IF(O42>1000,"B:大口",IF(O42>0,"C:通常","D:不要")))) -> D:不要 | Z42: =IF(Y42<>"",IF(I42>0,"◎ 一致（モデルも会期中欠品を検知）",IF(H42>=0.7,"○ 整合（予測消化率70%超）","△ モデル未検知：現場報告を優先")),IF(I42>0,"▲ モデルのみ検知：現場に在庫状況を確認","—")) -> — | AA42: 札幌納品数が極小(2個) ／ 札幌初6日の販売実績ゼロ（予測は大阪・博多構成比で按分） ／ 名古屋会場で完売（実績が在庫上限で頭打ち＝予測は控えめ） ／ 博多会場で完売（実績が在庫上限で頭打ち＝予測は控えめ） ／ 大阪会場で完売（実績が在庫上限で頭打ち＝予測は控えめ）
A43: 37 | B43: 4515142545310 | C43: 夏油 傑 イメージリング（#11） | D43: 27500 | E43: =①札幌予測確定!E43 -> 0 | F43: =①札幌予測確定!P43 -> 0 | G43: =①札幌予測確定!S43 -> 8 | H43: =IFERROR(F43/G43,0) -> 0 | I43: =F43-G43 -> -8 | J43: =IF(I43>0,"要 追加発注",IF(H43>=0.9,"要注意(90%超)",IF(H43>=0.5,"適正","在庫余剰"))) -> 在庫余剰 | K43: =IF(I43>0,ROUNDUP(I43*(1+前提・入力!$B$35),0),0) -> 0 | L43: =③石川以降予測!N66 -> 17 | M43: =③石川以降予測!S66 -> 8 | N43: =③石川以降予測!Q66 -> 35 | O43: =L43-M43-N43 -> -26 | P43: =IF(O43>0,"要 追加生産",IF(L43=0,"—","在庫で充足")) -> 在庫で充足 | Q43: =③石川以降予測!X66 -> 0 | R43: =K43+Q43 -> 0 | S43: =R43*D43 -> 0 | T43: — | V43: =IF(OR(U43="",U43="再生産不可"),"",U43-前提・入力!$B$39) | W43: =IF(T43="—","—",IF(U43="再生産不可","×再生産不可",_xlfn.IFS(V43<0,"★期限超過",V43<=30,"★至急(30日以内)",V43<=90,"要着手(90日以内)",TRUE(),"余裕あり"))) -> — | X43: =IF(Y43<>"",IF(FALSE(),"S:現場欠品(追納不可)","S:現場欠品"),IF(I43>0,"A:会期中欠品",IF(O43>1000,"B:大口",IF(O43>0,"C:通常","D:不要")))) -> D:不要 | Z43: =IF(Y43<>"",IF(I43>0,"◎ 一致（モデルも会期中欠品を検知）",IF(H43>=0.7,"○ 整合（予測消化率70%超）","△ モデル未検知：現場報告を優先")),IF(I43>0,"▲ モデルのみ検知：現場に在庫状況を確認","—")) -> — | AA43: 札幌納品数が極小(8個) ／ 札幌初6日の販売実績ゼロ（予測は大阪・博多構成比で按分） ／ 名古屋会場で完売（実績が在庫上限で頭打ち＝予測は控えめ）
A44: 38 | B44: 4515142545327 | C44: 夏油 傑 イメージリング（#13） | D44: 27500 | E44: =①札幌予測確定!E44 -> 2 | F44: =①札幌予測確定!P44 -> 2 | G44: =①札幌予測確定!S44 -> 2 | H44: =IFERROR(F44/G44,0) -> 1 | I44: =F44-G44 -> 0 | J44: =IF(I44>0,"要 追加発注",IF(H44>=0.9,"要注意(90%超)",IF(H44>=0.5,"適正","在庫余剰"))) -> 要注意(90%超) | K44: =IF(I44>0,ROUNDUP(I44*(1+前提・入力!$B$35),0),0) -> 0 | L44: =③石川以降予測!N67 -> 11 | M44: =③石川以降予測!S67 -> 0 | N44: =③石川以降予測!Q67 -> 2 | O44: =L44-M44-N44 -> 9 | P44: =IF(O44>0,"要 追加生産",IF(L44=0,"—","在庫で充足")) -> 要 追加生産 | Q44: =③石川以降予測!X67 -> 10 | R44: =K44+Q44 -> 10 | S44: =R44*D44 -> 275000 | T44: 仙台 Ebeans | U44: =DATE(2026,9,5)-90-前提・入力!$B$38 -> 46166 | V44: =IF(OR(U44="",U44="再生産不可"),"",U44-前提・入力!$B$39) -> -67 | W44: =IF(T44="—","—",IF(U44="再生産不可","×再生産不可",_xlfn.IFS(V44<0,"★期限超過",V44<=30,"★至急(30日以内)",V44<=90,"要着手(90日以内)",TRUE(),"余裕あり"))) -> ★期限超過 | X44: =IF(Y44<>"",IF(FALSE(),"S:現場欠品(追納不可)","S:現場欠品"),IF(I44>0,"A:会期中欠品",IF(O44>1000,"B:大口",IF(O44>0,"C:通常","D:不要")))) -> C:通常 | Z44: =IF(Y44<>"",IF(I44>0,"◎ 一致（モデルも会期中欠品を検知）",IF(H44>=0.7,"○ 整合（予測消化率70%超）","△ モデル未検知：現場報告を優先")),IF(I44>0,"▲ モデルのみ検知：現場に在庫状況を確認","—")) -> — | AA44: 札幌納品数が極小(2個) ／ 名古屋会場で完売（実績が在庫上限で頭打ち＝予測は控えめ） ／ 博多会場で完売（実績が在庫上限で頭打ち＝予測は控えめ） ／ 大阪会場で完売（実績が在庫上限で頭打ち＝予測は控えめ）
A45: 39 | B45: 4515142545334 | C45: 夏油 傑 イメージリング（#15） | D45: 27500 | E45: =①札幌予測確定!E45 -> 1 | F45: =①札幌予測確定!P45 -> 1 | G45: =①札幌予測確定!S45 -> 2 | H45: =IFERROR(F45/G45,0) -> 0.5 | I45: =F45-G45 -> -1 | J45: =IF(I45>0,"要 追加発注",IF(H45>=0.9,"要注意(90%超)",IF(H45>=0.5,"適正","在庫余剰"))) -> 適正 | K45: =IF(I45>0,ROUNDUP(I45*(1+前提・入力!$B$35),0),0) -> 0 | L45: =③石川以降予測!N68 -> 7 | M45: =③石川以降予測!S68 -> 1 | N45: =③石川以降予測!Q68 -> 3 | O45: =L45-M45-N45 -> 3 | P45: =IF(O45>0,"要 追加生産",IF(L45=0,"—","在庫で充足")) -> 要 追加生産 | Q45: =③石川以降予測!X68 -> 4 | R45: =K45+Q45 -> 4 | S45: =R45*D45 -> 110000 | T45: 東京凱旋 東京建物ぴあホール | U45: =DATE(2027,4,1)-90-前提・入力!$B$38 -> 46374 | V45: =IF(OR(U45="",U45="再生産不可"),"",U45-前提・入力!$B$39) -> 141 | W45: =IF(T45="—","—",IF(U45="再生産不可","×再生産不可",_xlfn.IFS(V45<0,"★期限超過",V45<=30,"★至急(30日以内)",V45<=90,"要着手(90日以内)",TRUE(),"余裕あり"))) -> 余裕あり | X45: =IF(Y45<>"",IF(FALSE(),"S:現場欠品(追納不可)","S:現場欠品"),IF(I45>0,"A:会期中欠品",IF(O45>1000,"B:大口",IF(O45>0,"C:通常","D:不要")))) -> C:通常 | Z45: =IF(Y45<>"",IF(I45>0,"◎ 一致（モデルも会期中欠品を検知）",IF(H45>=0.7,"○ 整合（予測消化率70%超）","△ モデル未検知：現場報告を優先")),IF(I45>0,"▲ モデルのみ検知：現場に在庫状況を確認","—")) -> — | AA45: 札幌納品数が極小(2個) ／ 名古屋会場で完売（実績が在庫上限で頭打ち＝予測は控えめ） ／ 博多会場で完売（実績が在庫上限で頭打ち＝予測は控えめ） ／ 大阪会場で完売（実績が在庫上限で頭打ち＝予測は控えめ）
A46: 40 | B46: 4515142545341 | C46: 夏油 傑 イメージリング（#17） | D46: 27500 | E46: =①札幌予測確定!E46 -> 0 | F46: =①札幌予測確定!P46 -> 0 | G46: =①札幌予測確定!S46 -> 2 | H46: =IFERROR(F46/G46,0) -> 0 | I46: =F46-G46 -> -2 | J46: =IF(I46>0,"要 追加発注",IF(H46>=0.9,"要注意(90%超)",IF(H46>=0.5,"適正","在庫余剰"))) -> 在庫余剰 | K46: =IF(I46>0,ROUNDUP(I46*(1+前提・入力!$B$35),0),0) -> 0 | L46: =③石川以降予測!N69 -> 1 | M46: =③石川以降予測!S69 -> 2 | N46: =③石川以降予測!Q69 -> 2 | O46: =L46-M46-N46 -> -3 | P46: =IF(O46>0,"要 追加生産",IF(L46=0,"—","在庫で充足")) -> 在庫で充足 | Q46: =③石川以降予測!X69 -> 0 | R46: =K46+Q46 -> 0 | S46: =R46*D46 -> 0 | T46: — | V46: =IF(OR(U46="",U46="再生産不可"),"",U46-前提・入力!$B$39) | W46: =IF(T46="—","—",IF(U46="再生産不可","×再生産不可",_xlfn.IFS(V46<0,"★期限超過",V46<=30,"★至急(30日以内)",V46<=90,"要着手(90日以内)",TRUE(),"余裕あり"))) -> — | X46: =IF(Y46<>"",IF(FALSE(),"S:現場欠品(追納不可)","S:現場欠品"),IF(I46>0,"A:会期中欠品",IF(O46>1000,"B:大口",IF(O46>0,"C:通常","D:不要")))) -> D:不要 | Z46: =IF(Y46<>"",IF(I46>0,"◎ 一致（モデルも会期中欠品を検知）",IF(H46>=0.7,"○ 整合（予測消化率70%超）","△ モデル未検知：現場報告を優先")),IF(I46>0,"▲ モデルのみ検知：現場に在庫状況を確認","—")) -> — | AA46: 札幌納品数が極小(2個) ／ 札幌初6日の販売実績ゼロ（予測は大阪・博多構成比で按分） ／ 名古屋会場で完売（実績が在庫上限で頭打ち＝予測は控えめ） ／ 博多会場で完売（実績が在庫上限で頭打ち＝予測は控えめ） ／ 大阪会場で完売（実績が在庫上限で頭打ち＝予測は控えめ）
A47: 41 | B47: 4515142545358 | C47: 虎杖 悠仁 イメージフラグメントケース | D47: 25000 | E47: =①札幌予測確定!E47 -> 0 | F47: =①札幌予測確定!P47 -> 0 | G47: =①札幌予測確定!S47 -> 4 | H47: =IFERROR(F47/G47,0) -> 0 | I47: =F47-G47 -> -4 | J47: =IF(I47>0,"要 追加発注",IF(H47>=0.9,"要注意(90%超)",IF(H47>=0.5,"適正","在庫余剰"))) -> 在庫余剰 | K47: =IF(I47>0,ROUNDUP(I47*(1+前提・入力!$B$35),0),0) -> 0 | L47: =③石川以降予測!N70 -> 1 | M47: =③石川以降予測!S70 -> 4 | N47: =③石川以降予測!Q70 -> 70 | O47: =L47-M47-N47 -> -73 | P47: =IF(O47>0,"要 追加生産",IF(L47=0,"—","在庫で充足")) -> 在庫で充足 | Q47: =③石川以降予測!X70 -> 0 | R47: =K47+Q47 -> 0 | S47: =R47*D47 -> 0 | T47: — | V47: =IF(OR(U47="",U47="再生産不可"),"",U47-前提・入力!$B$39) | W47: =IF(T47="—","—",IF(U47="再生産不可","×再生産不可",_xlfn.IFS(V47<0,"★期限超過",V47<=30,"★至急(30日以内)",V47<=90,"要着手(90日以内)",TRUE(),"余裕あり"))) -> — | X47: =IF(Y47<>"",IF(FALSE(),"S:現場欠品(追納不可)","S:現場欠品"),IF(I47>0,"A:会期中欠品",IF(O47>1000,"B:大口",IF(O47>0,"C:通常","D:不要")))) -> D:不要 | Z47: =IF(Y47<>"",IF(I47>0,"◎ 一致（モデルも会期中欠品を検知）",IF(H47>=0.7,"○ 整合（予測消化率70%超）","△ モデル未検知：現場報告を優先")),IF(I47>0,"▲ モデルのみ検知：現場に在庫状況を確認","—")) -> — | AA47: 札幌納品数が極小(4個) ／ 札幌初6日の販売実績ゼロ（予測は大阪・博多構成比で按分）
A48: 42 | B48: 4515142545365 | C48: 伏黒 恵 イメージフラグメントケース | D48: 25000 | E48: =①札幌予測確定!E48 -> 1 | F48: =①札幌予測確定!P48 -> 2 | G48: =①札幌予測確定!S48 -> 6 | H48: =IFERROR(F48/G48,0) -> 0.33333333 | I48: =F48-G48 -> -4 | J48: =IF(I48>0,"要 追加発注",IF(H48>=0.9,"要注意(90%超)",IF(H48>=0.5,"適正","在庫余剰"))) -> 在庫余剰 | K48: =IF(I48>0,ROUNDUP(I48*(1+前提・入力!$B$35),0),0) -> 0 | L48: =③石川以降予測!N71 -> 15 | M48: =③石川以降予測!S71 -> 4 | N48: =③石川以降予測!Q71 -> 43 | O48: =L48-M48-N48 -> -32 | P48: =IF(O48>0,"要 追加生産",IF(L48=0,"—","在庫で充足")) -> 在庫で充足 | Q48: =③石川以降予測!X71 -> 0 | R48: =K48+Q48 -> 0 | S48: =R48*D48 -> 0 | T48: — | V48: =IF(OR(U48="",U48="再生産不可"),"",U48-前提・入力!$B$39) | W48: =IF(T48="—","—",IF(U48="再生産不可","×再生産不可",_xlfn.IFS(V48<0,"★期限超過",V48<=30,"★至急(30日以内)",V48<=90,"要着手(90日以内)",TRUE(),"余裕あり"))) -> — | X48: =IF(Y48<>"",IF(FALSE(),"S:現場欠品(追納不可)","S:現場欠品"),IF(I48>0,"A:会期中欠品",IF(O48>1000,"B:大口",IF(O48>0,"C:通常","D:不要")))) -> D:不要 | Z48: =IF(Y48<>"",IF(I48>0,"◎ 一致（モデルも会期中欠品を検知）",IF(H48>=0.7,"○ 整合（予測消化率70%超）","△ モデル未検知：現場報告を優先")),IF(I48>0,"▲ モデルのみ検知：現場に在庫状況を確認","—")) -> — | AA48: 札幌納品数が極小(6個)
C49: 合計（LEGS 42SKU） | E49: =SUM(E7:E48) -> 5077 | F49: =SUM(F7:F48) -> 8740 | G49: =SUM(G7:G48) -> 50506 | H49: =IFERROR(F49/G49,0) -> 0.17304875 | I49: =SUM(I7:I48) -> -41766 | J49: =COUNTIF(J7:J48,"要 追加発注")&"品目" -> 1品目 | K49: =SUM(K7:K48) -> 3 | L49: =SUM(L7:L48) -> 81791 | M49: =SUM(M7:M48) -> 41768 | N49: =SUM(N7:N48) -> 224182 | O49: =SUM(O7:O48) -> -184159 | P49: =COUNTIF(P7:P48,"要 追加生産")&"品目" -> 9品目 | Q49: =SUM(Q7:Q48) -> 2812 | R49: =SUM(R7:R48) -> 2815 | S49: =SUM(S7:S48) -> 4494600 | U49: =IF(COUNT(U7:U48)=0,"",TEXT(MIN(U7:U48),"yyyy/m/d")&" が最短期限") -> 2026/5/24 が最短期限 | W49: =COUNTIF(W7:W48,"★期限超過")&"品目が期限超過／"&COUNTIF(W7:W48,"★至急(30日以内)")&"品目が至急" -> 1品目が期限超過／0品目が至急 | Y49: =COUNTIF(Y7:Y48,"<>")&"品目 報告あり" -> 8品目 報告あり

Sheet ⑤全データ統合リスト
A1: ⑤ 商品別 全データ統合リスト（5会場実績 ＋ 札幌予測 ＋ 石川以降予測）
A2: 構成比＝LEGS 42SKU内シェア（数量・金額）。消化率＝販売数÷販売可能数。札幌のみ7/27(6日目)時点の実績
A3: ※イメージリング8種は東京¥22,000→名古屋以降¥27,500に改定。販売金額は各会場の実売単価で算出している
A5: 基本情報 | E5: 東京（25/12/5(金)・25日） | L5: 名古屋（26/3/18(水)・19日） | S5: 博多（26/4/23(木)・26日） | Z5: 大阪（26/6/10(水)・20日） | AG5: 札幌（7/22-7/27 実績6日） | AN5: 札幌 会期20日予測 | AS5: 石川以降 5会場 | AW5: 発注判定
A6: No. | B6: JAN | C6: 商品名 | D6: 現行 税込単価 | E6: 税込 単価 | F6: 販売数 | G6: 数量 構成比 | H6: 販売金額 | I6: 金額 構成比 | J6: 販売 可能数 | K6: 消化率 | L6: 税込 単価 | M6: 販売数 | N6: 数量 構成比 | O6: 販売金額 | P6: 金額 構成比 | Q6: 販売 可能数 | R6: 消化率 | S6: 税込 単価 | T6: 販売数 | U6: 数量 構成比 | V6: 販売金額 | W6: 金額 構成比 | X6: 販売 可能数 | Y6: 消化率 | Z6: 税込 単価 | AA6: 販売数 | AB6: 数量 構成比 | AC6: 販売金額 | AD6: 金額 構成比 | AE6: 販売 可能数 | AF6: 消化率 | AG6: 税込 単価 | AH6: 販売数 | AI6: 数量 構成比 | AJ6: 販売金額 | AK6: 金額 構成比 | AL6: 販売 可能数 | AM6: 消化率 | AN6: 採用 倍率g | AO6: 予測 販売数 | AP6: 予測 販売金額 | AQ6: 予測 消化率 | AR6: 会期末 残在庫 | AS6: 必要数 | AT6: 供給可能 在庫 | AU6: 過不足 | AV6: 追加生産 必要数 | AW6: 札幌会期中 判定 | AX6: 石川以降 判定 | AY6: 発注合計 | AZ6: 優先度
A7: 1 | B7: 4515142545082 | C7: 呪術廻戦 メタリックポストカード 展示会キービジュアル | D7: 500 | E7: 500 | F7: 4965 | G7: =IFERROR(F7/F$49,0) -> 0.033505416 | H7: =F7*E7 -> 2482500 | I7: =IFERROR(H7/H$49,0) -> 0.024293887 | J7: 6000 | K7: =IFERROR(F7/J7,0) -> 0.8275 | L7: 500 | M7: 1316 | N7: =IFERROR(M7/M$49,0) -> 0.022457338 | O7: =M7*L7 -> 658000 | P7: =IFERROR(O7/O$49,0) -> 0.01586322 | Q7: 1998 | R7: =IFERROR(M7/Q7,0) -> 0.65865866 | S7: 500 | T7: 1092 | U7: =IFERROR(T7/T$49,0) -> 0.024336431 | V7: =T7*S7 -> 546000 | W7: =IFERROR(V7/V$49,0) -> 0.01759769 | X7: 1099 | Y7: =IFERROR(T7/X7,0) -> 0.99363057 | Z7: 500 | AA7: 2325 | AB7: =IFERROR(AA7/AA$49,0) -> 0.03647631 | AC7: =AA7*Z7 -> 1162500 | AD7: =IFERROR(AC7/AC$49,0) -> 0.025545184 | AE7: 3000 | AF7: =IFERROR(AA7/AE7,0) -> 0.775 | AG7: 500 | AH7: 261 | AI7: =IFERROR(AH7/AH$49,0) -> 0.051408312 | AJ7: =AH7*AG7 -> 130500 | AK7: =IFERROR(AJ7/AJ$49,0) -> 0.032153152 | AL7: 1000 | AM7: =IFERROR(AH7/AL7,0) -> 0.261 | AN7: =①札幌予測確定!O7 -> 1.7883172 | AO7: =①札幌予測確定!P7 -> 467 | AP7: =①札幌予測確定!Q7 -> 233500 | AQ7: =①札幌予測確定!T7 -> 0.467 | AR7: =①札幌予測確定!U7 -> 533 | AS7: =③石川以降予測!N30 -> 3676 | AT7: =③石川以降予測!T30 -> 2797 | AU7: =③石川以降予測!V30 -> 879 | AV7: =③石川以降予測!W30 -> 879 | AW7: =④追加発注判定!J7 -> 在庫余剰 | AX7: =④追加発注判定!P7 -> 要 追加生産 | AY7: =④追加発注判定!R7 -> 967 | AZ7: =④追加発注判定!X7 -> C:通常
A8: 2 | B8: 4515142545099 | C8: 呪術廻戦 クリアファイル 展示会キービジュアル | D8: 600 | E8: 600 | F8: 4902 | G8: =IFERROR(F8/F$49,0) -> 0.033080271 | H8: =F8*E8 -> 2941200 | I8: =IFERROR(H8/H$49,0) -> 0.028782751 | J8: 5699 | K8: =IFERROR(F8/J8,0) -> 0.8601509 | L8: 600 | M8: 1466 | N8: =IFERROR(M8/M$49,0) -> 0.025017065 | O8: =M8*L8 -> 879600 | P8: =IFERROR(O8/O$49,0) -> 0.021205605 | Q8: 1999 | R8: =IFERROR(M8/Q8,0) -> 0.73336668 | S8: 600 | T8: 1132 | U8: =IFERROR(T8/T$49,0) -> 0.025227875 | V8: =T8*S8 -> 679200 | W8: =IFERROR(V8/V$49,0) -> 0.021890753 | X8: 1200 | Y8: =IFERROR(T8/X8,0) -> 0.94333333 | Z8: 600 | AA8: 1965 | AB8: =IFERROR(AA8/AA$49,0) -> 0.030828365 | AC8: =AA8*Z8 -> 1179000 | AD8: =IFERROR(AC8/AC$49,0) -> 0.02590776 | AE8: 3000 | AF8: =IFERROR(AA8/AE8,0) -> 0.655 | AG8: 600 | AH8: 283 | AI8: =IFERROR(AH8/AH$49,0) -> 0.05574158 | AJ8: =AH8*AG8 -> 169800 | AK8: =IFERROR(AJ8/AJ$49,0) -> 0.041836056 | AL8: 1000 | AM8: =IFERROR(AH8/AL8,0) -> 0.283 | AN8: =①札幌予測確定!O8 -> 1.7992018 | AO8: =①札幌予測確定!P8 -> 509 | AP8: =①札幌予測確定!Q8 -> 305400 | AQ8: =①札幌予測確定!T8 -> 0.509 | AR8: =①札幌予測確定!U8 -> 491 | AS8: =③石川以降予測!N31 -> 3642 | AT8: =③石川以降予測!T31 -> 4528 | AU8: =③石川以降予測!V31 -> -886 | AV8: =③石川以降予測!W31 -> 0 | AW8: =④追加発注判定!J8 -> 適正 | AX8: =④追加発注判定!P8 -> 在庫で充足 | AY8: =④追加発注判定!R8 -> 0 | AZ8: =④追加発注判定!X8 -> D:不要
A9: 3 | B9: 4515142545105 | C9: 呪術廻戦 懐玉・玉折 ポストカードセット（5枚入） | D9: 1000 | E9: 1000 | F9: 2956 | G9: =IFERROR(F9/F$49,0) -> 0.019948038 | H9: =F9*E9 -> 2956000 | I9: =IFERROR(H9/H$49,0) -> 0.028927585 | J9: 3700 | K9: =IFERROR(F9/J9,0) -> 0.79891892 | L9: 1000 | M9: 601 | N9: =IFERROR(M9/M$49,0) -> 0.010255973 | O9: =M9*L9 -> 601000 | P9: =IFERROR(O9/O$49,0) -> 0.01448905 | Q9: 1200 | R9: =IFERROR(M9/Q9,0) -> 0.50083333 | S9: 1000 | T9: 454 | U9: =IFERROR(T9/T$49,0) -> 0.010117894 | V9: =T9*S9 -> 454000 | W9: =IFERROR(V9/V$49,0) -> 0.014632511 | X9: 500 | Y9: =IFERROR(T9/X9,0) -> 0.908 | Z9: 1000 | AA9: 1132 | AB9: =IFERROR(AA9/AA$49,0) -> 0.017759649 | AC9: =AA9*Z9 -> 1132000 | AD9: =IFERROR(AC9/AC$49,0) -> 0.024874966 | AE9: 2000 | AF9: =IFERROR(AA9/AE9,0) -> 0.566 | AG9: 1000 | AH9: 102 | AI9: =IFERROR(AH9/AH$49,0) -> 0.020090605 | AJ9: =AH9*AG9 -> 102000 | AK9: =IFERROR(AJ9/AJ$49,0) -> 0.0251312 | AL9: 450 | AM9: =IFERROR(AH9/AL9,0) -> 0.22666667 | AN9: =①札幌予測確定!O9 -> 1.6002974 | AO9: =①札幌予測確定!P9 -> 163 | AP9: =①札幌予測確定!Q9 -> 163000 | AQ9: =①札幌予測確定!T9 -> 0.36222222 | AR9: =①札幌予測確定!U9 -> 287 | AS9: =③石川以降予測!N32 -> 1489 | AT9: =③石川以降予測!T32 -> 5977 | AU9: =③石川以降予測!V32 -> -4488 | AV9: =③石川以降予測!W32 -> 0 | AW9: =④追加発注判定!J9 -> 在庫余剰 | AX9: =④追加発注判定!P9 -> 在庫で充足 | AY9: =④追加発注判定!R9 -> 0 | AZ9: =④追加発注判定!X9 -> D:不要
A10: 4 | B10: 4515142545112 | C10: 呪術廻戦 渋谷事変 ポストカードセット（9枚入） | D10: 1800 | E10: 1800 | F10: 1819 | G10: =IFERROR(F10/F$49,0) -> 0.012275197 | H10: =F10*E10 -> 3274200 | I10: =IFERROR(H10/H$49,0) -> 0.032041509 | J10: 2620 | K10: =IFERROR(F10/J10,0) -> 0.69427481 | L10: 1800 | M10: 922 | N10: =IFERROR(M10/M$49,0) -> 0.015733788 | O10: =M10*L10 -> 1659600 | P10: =IFERROR(O10/O$49,0) -> 0.040010029 | Q10: 1330 | R10: =IFERROR(M10/Q10,0) -> 0.69323308 | S10: 1800 | T10: 539 | U10: =IFERROR(T10/T$49,0) -> 0.012012213 | V10: =T10*S10 -> 970200 | W10: =IFERROR(V10/V$49,0) -> 0.031269741 | X10: 800 | Y10: =IFERROR(T10/X10,0) -> 0.67375 | Z10: 1800 | AA10: 1310 | AB10: =IFERROR(AA10/AA$49,0) -> 0.020552243 | AC10: =AA10*Z10 -> 2358000 | AD10: =IFERROR(AC10/AC$49,0) -> 0.051815521 | AE10: 2000 | AF10: =IFERROR(AA10/AE10,0) -> 0.655 | AG10: 1800 | AH10: 144 | AI10: =IFERROR(AH10/AH$49,0) -> 0.028363207 | AJ10: =AH10*AG10 -> 259200 | AK10: =IFERROR(AJ10/AJ$49,0) -> 0.063862813 | AL10: 800 | AM10: =IFERROR(AH10/AL10,0) -> 0.18 | AN10: =①札幌予測確定!O10 -> 1.5929118 | AO10: =①札幌予測確定!P10 -> 229 | AP10: =①札幌予測確定!Q10 -> 412200 | AQ10: =①札幌予測確定!T10 -> 0.28625 | AR10: =①札幌予測確定!U10 -> 571 | AS10: =③石川以降予測!N33 -> 1912 | AT10: =③石川以降予測!T33 -> 27282 | AU10: =③石川以降予測!V33 -> -25370 | AV10: =③石川以降予測!W33 -> 0 | AW10: =④追加発注判定!J10 -> 在庫余剰 | AX10: =④追加発注判定!P10 -> 在庫で充足 | AY10: =④追加発注判定!R10 -> 0 | AZ10: =④追加発注判定!X10 -> D:不要
A11: 5 | B11: 4515142545129 | C11: 呪術廻戦 懐玉・玉折 ブラインド缶バッジ（全5種） | D11: 600 | E11: 600 | F11: 18759 | G11: =IFERROR(F11/F$49,0) -> 0.12659176 | H11: =F11*E11 -> 11255400 | I11: =IFERROR(H11/H$49,0) -> 0.11014599 | J11: 24996 | K11: =IFERROR(F11/J11,0) -> 0.75048008 | L11: 600 | M11: 10777 | N11: =IFERROR(M11/M$49,0) -> 0.18390785 | O11: =M11*L11 -> 6466200 | P11: =IFERROR(O11/O$49,0) -> 0.15588868 | Q11: 16500 | R11: =IFERROR(M11/Q11,0) -> 0.65315152 | S11: 600 | T11: 8991 | U11: =IFERROR(T11/T$49,0) -> 0.20037441 | V11: =T11*S11 -> 5394600 | W11: =IFERROR(V11/V$49,0) -> 0.17386904 | X11: 9000 | Y11: =IFERROR(T11/X11,0) -> 0.999 | Z11: 600 | AA11: 8936 | AB11: =IFERROR(AA11/AA$49,0) -> 0.14019454 | AC11: =AA11*Z11 -> 5361600 | AD11: =IFERROR(AC11/AC$49,0) -> 0.11781768 | AE11: 24996 | AF11: =IFERROR(AA11/AE11,0) -> 0.3574972 | AG11: 600 | AH11: 268 | AI11: =IFERROR(AH11/AH$49,0) -> 0.052787079 | AJ11: =AH11*AG11 -> 160800 | AK11: =IFERROR(AJ11/AJ$49,0) -> 0.039618597 | AL11: 9000 | AM11: =IFERROR(AH11/AL11,0) -> 0.029777778 | AN11: =①札幌予測確定!O11 -> 1.7354746 | AO11: =①札幌予測確定!P11 -> 465 | AP11: =①札幌予測確定!Q11 -> 279000 | AQ11: =①札幌予測確定!T11 -> 0.051666667 | AR11: =①札幌予測確定!U11 -> 8535 | AS11: =③石川以降予測!N34 -> 7909 | AT11: =③石川以降予測!T34 -> 39360 | AU11: =③石川以降予測!V34 -> -31451 | AV11: =③石川以降予測!W34 -> 0 | AW11: =④追加発注判定!J11 -> 在庫余剰 | AX11: =④追加発注判定!P11 -> 在庫で充足 | AY11: =④追加発注判定!R11 -> 0 | AZ11: =④追加発注判定!X11 -> D:不要
A12: 6 | B12: 4515142545136 | C12: 呪術廻戦 渋谷事変 ブラインド缶バッジ（全9種） | D12: 600 | E12: 600 | F12: 31070 | G12: =IFERROR(F12/F$49,0) -> 0.20967034 | H12: =F12*E12 -> 18642000 | I12: =IFERROR(H12/H$49,0) -> 0.18243168 | J12: 44999 | K12: =IFERROR(F12/J12,0) -> 0.69045979 | L12: 600 | M12: 15602 | N12: =IFERROR(M12/M$49,0) -> 0.26624573 | O12: =M12*L12 -> 9361200 | P12: =IFERROR(O12/O$49,0) -> 0.22568202 | Q12: 21439 | R12: =IFERROR(M12/Q12,0) -> 0.72773917 | S12: 600 | T12: 13877 | U12: =IFERROR(T12/T$49,0) -> 0.30926434 | V12: =T12*S12 -> 8326200 | W12: =IFERROR(V12/V$49,0) -> 0.2683551 | X12: 13986 | Y12: =IFERROR(T12/X12,0) -> 0.99220649 | Z12: 600 | AA12: 18611 | AB12: =IFERROR(AA12/AA$49,0) -> 0.29198306 | AC12: =AA12*Z12 -> 11166600 | AD12: =IFERROR(AC12/AC$49,0) -> 0.24537879 | AE12: 35999 | AF12: =IFERROR(AA12/AE12,0) -> 0.51698658 | AG12: 600 | AH12: 704 | AI12: =IFERROR(AH12/AH$49,0) -> 0.13866457 | AJ12: =AH12*AG12 -> 422400 | AK12: =IFERROR(AJ12/AJ$49,0) -> 0.10407273 | AL12: 13991 | AM12: =IFERROR(AH12/AL12,0) -> 0.050318062 | AN12: =①札幌予測確定!O12 -> 1.8707544 | AO12: =①札幌予測確定!P12 -> 1317 | AP12: =①札幌予測確定!Q12 -> 790200 | AQ12: =①札幌予測確定!T12 -> 0.094131942 | AR12: =①札幌予測確定!U12 -> 12674 | AS12: =③石川以降予測!N35 -> 18104 | AT12: =③石川以降予測!T35 -> 49517 | AU12: =③石川以降予測!V35 -> -31413 | AV12: =③石川以降予測!W35 -> 0 | AW12: =④追加発注判定!J12 -> 在庫余剰 | AX12: =④追加発注判定!P12 -> 在庫で充足 | AY12: =④追加発注判定!R12 -> 0 | AZ12: =④追加発注判定!X12 -> D:不要
A13: 7 | B13: 4515142545143 | C13: 呪術廻戦 懐玉・玉折 ブラインドダイカットステッカー（全5種） | D13: 600 | E13: 600 | F13: 3471 | G13: =IFERROR(F13/F$49,0) -> 0.023423423 | H13: =F13*E13 -> 2082600 | I13: =IFERROR(H13/H$49,0) -> 0.020380443 | J13: 7000 | K13: =IFERROR(F13/J13,0) -> 0.49585714 | L13: 600 | M13: 520 | N13: =IFERROR(M13/M$49,0) -> 0.0088737201 | O13: =M13*L13 -> 312000 | P13: =IFERROR(O13/O$49,0) -> 0.0075217697 | Q13: 1390 | R13: =IFERROR(M13/Q13,0) -> 0.37410072 | S13: 600 | T13: 384 | U13: =IFERROR(T13/T$49,0) -> 0.0085578659 | V13: =T13*S13 -> 230400 | W13: =IFERROR(V13/V$49,0) -> 0.0074258383 | X13: 400 | Y13: =IFERROR(T13/X13,0) -> 0.96 | Z13: 600 | AA13: 940 | AB13: =IFERROR(AA13/AA$49,0) -> 0.014747411 | AC13: =AA13*Z13 -> 564000 | AD13: =IFERROR(AC13/AC$49,0) -> 0.012393534 | AE13: 2000 | AF13: =IFERROR(AA13/AE13,0) -> 0.47 | AG13: 600 | AH13: 108 | AI13: =IFERROR(AH13/AH$49,0) -> 0.021272405 | AJ13: =AH13*AG13 -> 64800 | AK13: =IFERROR(AJ13/AJ$49,0) -> 0.015965703 | AL13: 350 | AM13: =IFERROR(AH13/AL13,0) -> 0.30857143 | AN13: =①札幌予測確定!O13 -> 1.7954603 | AO13: =①札幌予測確定!P13 -> 194 | AP13: =①札幌予測確定!Q13 -> 116400 | AQ13: =①札幌予測確定!T13 -> 0.55428571 | AR13: =①札幌予測確定!U13 -> 156 | AS13: =③石川以降予測!N36 -> 1511 | AT13: =③石川以降予測!T36 -> 4348 | AU13: =③石川以降予測!V36 -> -2837 | AV13: =③石川以降予測!W36 -> 0 | AW13: =④追加発注判定!J13 -> 適正 | AX13: =④追加発注判定!P13 -> 在庫で充足 | AY13: =④追加発注判定!R13 -> 0 | AZ13: =④追加発注判定!X13 -> D:不要
A14: 8 | B14: 4515142545150 | C14: 呪術廻戦 渋谷事変 ブラインドダイカットステッカー（全9種） | D14: 600 | E14: 600 | F14: 5596 | G14: =IFERROR(F14/F$49,0) -> 0.037763606 | H14: =F14*E14 -> 3357600 | I14: =IFERROR(H14/H$49,0) -> 0.032857666 | J14: 12600 | K14: =IFERROR(F14/J14,0) -> 0.44412698 | L14: 600 | M14: 1107 | N14: =IFERROR(M14/M$49,0) -> 0.018890785 | O14: =M14*L14 -> 664200 | P14: =IFERROR(O14/O$49,0) -> 0.016012691 | Q14: 2240 | R14: =IFERROR(M14/Q14,0) -> 0.49419643 | S14: 600 | T14: 799 | U14: =IFERROR(T14/T$49,0) -> 0.017806601 | V14: =T14*S14 -> 479400 | W14: =IFERROR(V14/V$49,0) -> 0.015451158 | X14: 840 | Y14: =IFERROR(T14/X14,0) -> 0.95119048 | Z14: 600 | AA14: 1758 | AB14: =IFERROR(AA14/AA$49,0) -> 0.027580797 | AC14: =AA14*Z14 -> 1054800 | AD14: =IFERROR(AC14/AC$49,0) -> 0.023178546 | AE14: 3000 | AF14: =IFERROR(AA14/AE14,0) -> 0.586 | AG14: 600 | AH14: 173 | AI14: =IFERROR(AH14/AH$49,0) -> 0.034075241 | AJ14: =AH14*AG14 -> 103800 | AK14: =IFERROR(AJ14/AJ$49,0) -> 0.025574691 | AL14: 900 | AM14: =IFERROR(AH14/AL14,0) -> 0.19222222 | AN14: =①札幌予測確定!O14 -> 1.8583196 | AO14: =①札幌予測確定!P14 -> 321 | AP14: =①札幌予測確定!Q14 -> 192600 | AQ14: =①札幌予測確定!T14 -> 0.35666667 | AR14: =①札幌予測確定!U14 -> 579 | AS14: =③石川以降予測!N37 -> 2630 | AT14: =③石川以降予測!T37 -> 8230 | AU14: =③石川以降予測!V37 -> -5600 | AV14: =③石川以降予測!W37 -> 0 | AW14: =④追加発注判定!J14 -> 在庫余剰 | AX14: =④追加発注判定!P14 -> 在庫で充足 | AY14: =④追加発注判定!R14 -> 0 | AZ14: =④追加発注判定!X14 -> D:不要
A15: 9 | B15: 4515142545372 | C15: 呪術廻戦 懐玉・玉折 クリアファイル（五条 悟） | D15: 600 | E15: 600 | F15: 2381 | G15: =IFERROR(F15/F$49,0) -> 0.016067753 | H15: =F15*E15 -> 1428600 | I15: =IFERROR(H15/H$49,0) -> 0.013980361 | J15: 8749 | K15: =IFERROR(F15/J15,0) -> 0.27214539 | L15: 600 | M15: 313 | N15: =IFERROR(M15/M$49,0) -> 0.0053412969 | O15: =M15*L15 -> 187800 | P15: =IFERROR(O15/O$49,0) -> 0.0045275268 | Q15: 950 | R15: =IFERROR(M15/Q15,0) -> 0.32947368 | S15: 600 | T15: 301 | U15: =IFERROR(T15/T$49,0) -> 0.0067081188 | V15: =T15*S15 -> 180600 | W15: =IFERROR(V15/V$49,0) -> 0.0058207743 | X15: 300 | Y15: =IFERROR(T15/X15,0) -> 1.0033333 | Z15: 600 | AA15: 743 | AB15: =IFERROR(AA15/AA$49,0) -> 0.01165673 | AC15: =AA15*Z15 -> 445800 | AD15: =IFERROR(AC15/AC$49,0) -> 0.0097961659 | AE15: 1500 | AF15: =IFERROR(AA15/AE15,0) -> 0.49533333 | AG15: 600 | AH15: 87 | AI15: =IFERROR(AH15/AH$49,0) -> 0.017136104 | AJ15: =AH15*AG15 -> 52200 | AK15: =IFERROR(AJ15/AJ$49,0) -> 0.012861261 | AL15: 300 | AM15: =IFERROR(AH15/AL15,0) -> 0.29 | AN15: =①札幌予測確定!O15 -> 1.4747051 | AO15: =①札幌予測確定!P15 -> 128 | AP15: =①札幌予測確定!Q15 -> 76800 | AQ15: =①札幌予測確定!T15 -> 0.42666667 | AR15: =①札幌予測確定!U15 -> 172 | AS15: =③石川以降予測!N38 -> 1076 | AT15: =③石川以降予測!T38 -> 8631 | AU15: =③石川以降予測!V38 -> -7555 | AV15: =③石川以降予測!W38 -> 0 | AW15: =④追加発注判定!J15 -> 在庫余剰 | AX15: =④追加発注判定!P15 -> 在庫で充足 | AY15: =④追加発注判定!R15 -> 0 | AZ15: =④追加発注判定!X15 -> D:不要
A16: 10 | B16: 4515142545389 | C16: 呪術廻戦 懐玉・玉折 クリアファイル（夏油 傑） | D16: 600 | E16: 600 | F16: 1025 | G16: =IFERROR(F16/F$49,0) -> 0.0069170294 | H16: =F16*E16 -> 615000 | I16: =IFERROR(H16/H$49,0) -> 0.0060184252 | J16: 4549 | K16: =IFERROR(F16/J16,0) -> 0.22532425 | L16: 600 | M16: 141 | N16: =IFERROR(M16/M$49,0) -> 0.0024061433 | O16: =M16*L16 -> 84600 | P16: =IFERROR(O16/O$49,0) -> 0.0020395568 | Q16: 410 | R16: =IFERROR(M16/Q16,0) -> 0.34390244 | S16: 600 | T16: 123 | U16: =IFERROR(T16/T$49,0) -> 0.0027411914 | V16: =T16*S16 -> 73800 | W16: =IFERROR(V16/V$49,0) -> 0.0023785888 | X16: 180 | Y16: =IFERROR(T16/X16,0) -> 0.68333333 | Z16: 600 | AA16: 277 | AB16: =IFERROR(AA16/AA$49,0) -> 0.0043457797 | AC16: =AA16*Z16 -> 166200 | AD16: =IFERROR(AC16/AC$49,0) -> 0.0036521372 | AE16: 500 | AF16: =IFERROR(AA16/AE16,0) -> 0.554 | AG16: 600 | AH16: 33 | AI16: =IFERROR(AH16/AH$49,0) -> 0.0064999015 | AJ16: =AH16*AG16 -> 19800 | AK16: =IFERROR(AJ16/AJ$49,0) -> 0.0048784093 | AL16: 100 | AM16: =IFERROR(AH16/AL16,0) -> 0.33 | AN16: =①札幌予測確定!O16 -> 1.4630614 | AO16: =①札幌予測確定!P16 -> 48 | AP16: =①札幌予測確定!Q16 -> 28800 | AQ16: =①札幌予測確定!T16 -> 0.48 | AR16: =①札幌予測確定!U16 -> 52 | AS16: =③石川以降予測!N39 -> 403 | AT16: =③石川以降予測!T39 -> 4887 | AU16: =③石川以降予測!V39 -> -4484 | AV16: =③石川以降予測!W39 -> 0 | AW16: =④追加発注判定!J16 -> 在庫余剰 | AX16: =④追加発注判定!P16 -> 在庫で充足 | AY16: =④追加発注判定!R16 -> 0 | AZ16: =④追加発注判定!X16 -> D:不要
A17: 11 | B17: 4515142545396 | C17: 呪術廻戦 懐玉・玉折 クリアファイル（家入 硝子） | D17: 600 | E17: 600 | F17: 215 | G17: =IFERROR(F17/F$49,0) -> 0.0014508891 | H17: =F17*E17 -> 129000 | I17: =IFERROR(H17/H$49,0) -> 0.0012624014 | J17: 699 | K17: =IFERROR(F17/J17,0) -> 0.30758226 | L17: 600 | M17: 37 | N17: =IFERROR(M17/M$49,0) -> 0.00063139932 | O17: =M17*L17 -> 22200 | P17: =IFERROR(O17/O$49,0) -> 0.00053520285 | Q17: 90 | R17: =IFERROR(M17/Q17,0) -> 0.41111111 | S17: 600 | T17: 30 | U17: =IFERROR(T17/T$49,0) -> 0.00066858327 | V17: =T17*S17 -> 18000 | W17: =IFERROR(V17/V$49,0) -> 0.00058014362 | X17: 30 | Y17: =IFERROR(T17/X17,0) -> 1 | Z17: 600 | AA17: 78 | AB17: =IFERROR(AA17/AA$49,0) -> 0.0012237214 | AC17: =AA17*Z17 -> 46800 | AD17: =IFERROR(AC17/AC$49,0) -> 0.0010283997 | AE17: 100 | AF17: =IFERROR(AA17/AE17,0) -> 0.78 | AG17: 600 | AH17: 10 | AI17: =IFERROR(AH17/AH$49,0) -> 0.0019696671 | AJ17: =AH17*AG17 -> 6000 | AK17: =IFERROR(AJ17/AJ$49,0) -> 0.0014783059 | AL17: 50 | AM17: =IFERROR(AH17/AL17,0) -> 0.2 | AN17: =①札幌予測確定!O17 -> 2.4060281 | AO17: =①札幌予測確定!P17 -> 24 | AP17: =①札幌予測確定!Q17 -> 14400 | AQ17: =①札幌予測確定!T17 -> 0.48 | AR17: =①札幌予測確定!U17 -> 26 | AS17: =③石川以降予測!N40 -> 162 | AT17: =③石川以降予測!T40 -> 616 | AU17: =③石川以降予測!V40 -> -454 | AV17: =③石川以降予測!W40 -> 0 | AW17: =④追加発注判定!J17 -> 在庫余剰 | AX17: =④追加発注判定!P17 -> 在庫で充足 | AY17: =④追加発注判定!R17 -> 0 | AZ17: =④追加発注判定!X17 -> D:不要
A18: 12 | B18: 4515142545402 | C18: 呪術廻戦 懐玉・玉折 クリアファイル（七海 建人） | D18: 600 | E18: 600 | F18: 291 | G18: =IFERROR(F18/F$49,0) -> 0.0019637615 | H18: =F18*E18 -> 174600 | I18: =IFERROR(H18/H$49,0) -> 0.0017086456 | J18: 1049 | K18: =IFERROR(F18/J18,0) -> 0.27740705 | L18: 600 | M18: 58 | N18: =IFERROR(M18/M$49,0) -> 0.00098976109 | O18: =M18*L18 -> 34800 | P18: =IFERROR(O18/O$49,0) -> 0.00083896662 | Q18: 119 | R18: =IFERROR(M18/Q18,0) -> 0.48739496 | S18: 600 | T18: 54 | U18: =IFERROR(T18/T$49,0) -> 0.0012034499 | V18: =T18*S18 -> 32400 | W18: =IFERROR(V18/V$49,0) -> 0.0010442585 | X18: 80 | Y18: =IFERROR(T18/X18,0) -> 0.675 | Z18: 600 | AA18: 142 | AB18: =IFERROR(AA18/AA$49,0) -> 0.0022278004 | AC18: =AA18*Z18 -> 85200 | AD18: =IFERROR(AC18/AC$49,0) -> 0.0018722148 | AE18: 150 | AF18: =IFERROR(AA18/AE18,0) -> 0.94666667 | AG18: 600 | AH18: 19 | AI18: =IFERROR(AH18/AH$49,0) -> 0.0037423675 | AJ18: =AH18*AG18 -> 11400 | AK18: =IFERROR(AJ18/AJ$49,0) -> 0.0028087811 | AL18: 50 | AM18: =IFERROR(AH18/AL18,0) -> 0.38 | AN18: =①札幌予測確定!O18 -> 1.7636591 | AO18: =①札幌予測確定!P18 -> 34 | AP18: =①札幌予測確定!Q18 -> 20400 | AQ18: =①札幌予測確定!T18 -> 0.68 | AR18: =①札幌予測確定!U18 -> 16 | AS18: =③石川以降予測!N41 -> 251 | AT18: =③石川以降予測!T41 -> 919 | AU18: =③石川以降予測!V41 -> -668 | AV18: =③石川以降予測!W41 -> 0 | AW18: =④追加発注判定!J18 -> 適正 | AX18: =④追加発注判定!P18 -> 在庫で充足 | AY18: =④追加発注判定!R18 -> 0 | AZ18: =④追加発注判定!X18 -> D:不要
... A48: 42 | B48: 4515142545365 | C48: 伏黒 恵 イメージフラグメントケース | D48: 25000 | E48: 25000 | F48: 24 | G48: =IFERROR(F48/F$49,0) -> 0.00016195971 | H48: =F48*E48 -> 600000 | I48: =IFERROR(H48/H$49,0) -> 0.0058716343 | J48: 38 | K48: =IFERROR(F48/J48,0) -> 0.63157895 | L48: 25000 | M48: 8 | N48: =IFERROR(M48/M$49,0) -> 0.00013651877 | O48: =M48*L48 -> 200000 | P48: =IFERROR(O48/O$49,0) -> 0.0048216473 | Q48: 10 | R48: =IFERROR(M48/Q48,0) -> 0.8 | S48: 25000 | T48: 3 | U48: =IFERROR(T48/T$49,0) -> 6.6858327e-05 | V48: =T48*S48 -> 75000 | W48: =IFERROR(V48/V$49,0) -> 0.0024172651 | X48: 5 | Y48: =IFERROR(T48/X48,0) -> 0.6 | Z48: 25000 | AA48: 8 | AB48: =IFERROR(AA48/AA$49,0) -> 0.00012550988 | AC48: =AA48*Z48 -> 200000 | AD48: =IFERROR(AC48/AC$49,0) -> 0.0043948703 | AE48: 20 | AF48: =IFERROR(AA48/AE48,0) -> 0.4 | AG48: 25000 | AH48: 1 | AI48: =IFERROR(AH48/AH$49,0) -> 0.00019696671 | AJ48: =AH48*AG48 -> 25000 | AK48: =IFERROR(AJ48/AJ$49,0) -> 0.0061596078 | AL48: 6 | AM48: =IFERROR(AH48/AL48,0) -> 0.16666667 | AN48: =①札幌予測確定!O48 -> 2.024146 | AO48: =①札幌予測確定!P48 -> 2 | AP48: =①札幌予測確定!Q48 -> 50000 | AQ48: =①札幌予測確定!T48 -> 0.33333333 | AR48: =①札幌予測確定!U48 -> 4 | AS48: =③石川以降予測!N71 -> 15 | AT48: =③石川以降予測!T71 -> 47 | AU48: =③石川以降予測!V71 -> -32 | AV48: =③石川以降予測!W71 -> 0 | AW48: =④追加発注判定!J48 -> 在庫余剰 | AX48: =④追加発注判定!P48 -> 在庫で充足 | AY48: =④追加発注判定!R48 -> 0 | AZ48: =④追加発注判定!X48 -> D:不要
C49: 合計（LEGS 42SKU） | F49: =SUM(F7:F48) -> 148185 | H49: =SUM(H7:H48) -> 102186200 | J49: =SUM(J7:J48) -> 211152 | M49: =SUM(M7:M48) -> 58600 | O49: =SUM(O7:O48) -> 41479600 | Q49: =SUM(Q7:Q48) -> 83271 | T49: =SUM(T7:T48) -> 44871 | V49: =SUM(V7:V48) -> 31026800 | X49: =SUM(X7:X48) -> 49598 | AA49: =SUM(AA7:AA48) -> 63740 | AC49: =SUM(AC7:AC48) -> 45507600 | AE49: =SUM(AE7:AE48) -> 137560 | AH49: =SUM(AH7:AH48) -> 5077 | AJ49: =SUM(AJ7:AJ48) -> 4058700 | AL49: =SUM(AL7:AL48) -> 50506 | AO49: =SUM(AO7:AO48) -> 8740 | AP49: =SUM(AP7:AP48) -> 6680400 | AR49: =SUM(AR7:AR48) -> 41768 | AS49: =SUM(AS7:AS48) -> 81791 | AT49: =SUM(AT7:AT48) -> 265948 | AU49: =SUM(AU7:AU48) -> -185357 | AV49: =SUM(AV7:AV48) -> 2554 | AY49: =SUM(AY7:AY48) -> 2815

Sheet ⑥商品別 会場推移
A1: ⑥ 商品別 会場推移（LEGS 42SKU内 数量構成比の会場間トレンド）
A2: 各会場の会期全体（札幌は初6日実績と20日予測）。構成比の伸び／減退から石川以降の重点商品を判断
A5: No. | B5: JAN | C5: 商品名 | D5: 東京 販売数 | E5: 名古屋 販売数 | F5: 博多 販売数 | G5: 大阪 販売数 | H5: 札幌 販売数 | I5: 東京 構成比 | J5: 名古屋 構成比 | K5: 博多 構成比 | L5: 大阪 構成比 | M5: 札幌 構成比 | N5: 札幌20日 予測構成比 | O5: 大阪→札幌 構成比変化 | P5: 東京→大阪 構成比変化 | Q5: トレンド
A6: 1 | B6: 4515142545082 | C6: 呪術廻戦 メタリックポストカード 展示会キービジュアル | D6: 4965 | E6: 1316 | F6: 1092 | G6: 2325 | H6: 261 | I6: =IFERROR(D6/D$48,0) -> 0.033505416 | J6: =IFERROR(E6/E$48,0) -> 0.022457338 | K6: =IFERROR(F6/F$48,0) -> 0.024336431 | L6: =IFERROR(G6/G$48,0) -> 0.03647631 | M6: =IFERROR(H6/H$48,0) -> 0.051408312 | N6: =①札幌予測確定!R7 -> 0.053432494 | O6: =N6-L6 -> 0.016956184 | P6: =L6-I6 -> 0.0029708945 | Q6: =IF(O6>=0.005,"↑ 伸長",IF(O6<=-0.005,"↓ 減退","→ 横ばい")) -> ↑ 伸長
A7: 2 | B7: 4515142545099 | C7: 呪術廻戦 クリアファイル 展示会キービジュアル | D7: 4902 | E7: 1466 | F7: 1132 | G7: 1965 | H7: 283 | I7: =IFERROR(D7/D$48,0) -> 0.033080271 | J7: =IFERROR(E7/E$48,0) -> 0.025017065 | K7: =IFERROR(F7/F$48,0) -> 0.025227875 | L7: =IFERROR(G7/G$48,0) -> 0.030828365 | M7: =IFERROR(H7/H$48,0) -> 0.05574158 | N7: =①札幌予測確定!R8 -> 0.058237986 | O7: =N7-L7 -> 0.027409621 | P7: =L7-I7 -> -0.002251906 | Q7: =IF(O7>=0.005,"↑ 伸長",IF(O7<=-0.005,"↓ 減退","→ 横ばい")) -> ↑ 伸長
A8: 3 | B8: 4515142545105 | C8: 呪術廻戦 懐玉・玉折 ポストカードセット（5枚入） | D8: 2956 | E8: 601 | F8: 454 | G8: 1132 | H8: 102 | I8: =IFERROR(D8/D$48,0) -> 0.019948038 | J8: =IFERROR(E8/E$48,0) -> 0.010255973 | K8: =IFERROR(F8/F$48,0) -> 0.010117894 | L8: =IFERROR(G8/G$48,0) -> 0.017759649 | M8: =IFERROR(H8/H$48,0) -> 0.020090605 | N8: =①札幌予測確定!R9 -> 0.018649886 | O8: =N8-L8 -> 0.00089023701 | P8: =L8-I8 -> -0.0021883894 | Q8: =IF(O8>=0.005,"↑ 伸長",IF(O8<=-0.005,"↓ 減退","→ 横ばい")) -> → 横ばい
A9: 4 | B9: 4515142545112 | C9: 呪術廻戦 渋谷事変 ポストカードセット（9枚入） | D9: 1819 | E9: 922 | F9: 539 | G9: 1310 | H9: 144 | I9: =IFERROR(D9/D$48,0) -> 0.012275197 | J9: =IFERROR(E9/E$48,0) -> 0.015733788 | K9: =IFERROR(F9/F$48,0) -> 0.012012213 | L9: =IFERROR(G9/G$48,0) -> 0.020552243 | M9: =IFERROR(H9/H$48,0) -> 0.028363207 | N9: =①札幌予測確定!R10 -> 0.026201373 | O9: =N9-L9 -> 0.0056491295 | P9: =L9-I9 -> 0.0082770469 | Q9: =IF(O9>=0.005,"↑ 伸長",IF(O9<=-0.005,"↓ 減退","→ 横ばい")) -> ↑ 伸長
A10: 5 | B10: 4515142545129 | C10: 呪術廻戦 懐玉・玉折 ブラインド缶バッジ（全5種） | D10: 18759 | E10: 10777 | F10: 8991 | G10: 8936 | H10: 268 | I10: =IFERROR(D10/D$48,0) -> 0.12659176 | J10: =IFERROR(E10/E$48,0) -> 0.18390785 | K10: =IFERROR(F10/F$48,0) -> 0.20037441 | L10: =IFERROR(G10/G$48,0) -> 0.14019454 | M10: =IFERROR(H10/H$48,0) -> 0.052787079 | N10: =①札幌予測確定!R11 -> 0.053203661 | O10: =N10-L10 -> -0.086990879 | P10: =L10-I10 -> 0.01360278 | Q10: =IF(O10>=0.005,"↑ 伸長",IF(O10<=-0.005,"↓ 減退","→ 横ばい")) -> ↓ 減退
A11: 6 | B11: 4515142545136 | C11: 呪術廻戦 渋谷事変 ブラインド缶バッジ（全9種） | D11: 31070 | E11: 15602 | F11: 13877 | G11: 18611 | H11: 704 | I11: =IFERROR(D11/D$48,0) -> 0.20967034 | J11: =IFERROR(E11/E$48,0) -> 0.26624573 | K11: =IFERROR(F11/F$48,0) -> 0.30926434 | L11: =IFERROR(G11/G$48,0) -> 0.29198306 | M11: =IFERROR(H11/H$48,0) -> 0.13866457 | N11: =①札幌予測確定!R12 -> 0.1506865 | O11: =N11-L11 -> -0.14129656 | P11: =L11-I11 -> 0.082312712 | Q11: =IF(O11>=0.005,"↑ 伸長",IF(O11<=-0.005,"↓ 減退","→ 横ばい")) -> ↓ 減退
A12: 7 | B12: 4515142545143 | C12: 呪術廻戦 懐玉・玉折 ブラインドダイカットステッカー（全5種） | D12: 3471 | E12: 520 | F12: 384 | G12: 940 | H12: 108 | I12: =IFERROR(D12/D$48,0) -> 0.023423423 | J12: =IFERROR(E12/E$48,0) -> 0.0088737201 | K12: =IFERROR(F12/F$48,0) -> 0.0085578659 | L12: =IFERROR(G12/G$48,0) -> 0.014747411 | M12: =IFERROR(H12/H$48,0) -> 0.021272405 | N12: =①札幌予測確定!R13 -> 0.022196796 | O12: =N12-L12 -> 0.007449385 | P12: =L12-I12 -> -0.0086760121 | Q12: =IF(O12>=0.005,"↑ 伸長",IF(O12<=-0.005,"↓ 減退","→ 横ばい")) -> ↑ 伸長
A13: 8 | B13: 4515142545150 | C13: 呪術廻戦 渋谷事変 ブラインドダイカットステッカー（全9種） | D13: 5596 | E13: 1107 | F13: 799 | G13: 1758 | H13: 173 | I13: =IFERROR(D13/D$48,0) -> 0.037763606 | J13: =IFERROR(E13/E$48,0) -> 0.018890785 | K13: =IFERROR(F13/F$48,0) -> 0.017806601 | L13: =IFERROR(G13/G$48,0) -> 0.027580797 | M13: =IFERROR(H13/H$48,0) -> 0.034075241 | N13: =①札幌予測確定!R14 -> 0.036727689 | O13: =N13-L13 -> 0.0091468918 | P13: =L13-I13 -> -0.010182809 | Q13: =IF(O13>=0.005,"↑ 伸長",IF(O13<=-0.005,"↓ 減退","→ 横ばい")) -> ↑ 伸長
A14: 9 | B14: 4515142545372 | C14: 呪術廻戦 懐玉・玉折 クリアファイル（五条 悟） | D14: 2381 | E14: 313 | F14: 301 | G14: 743 | H14: 87 | I14: =IFERROR(D14/D$48,0) -> 0.016067753 | J14: =IFERROR(E14/E$48,0) -> 0.0053412969 | K14: =IFERROR(F14/F$48,0) -> 0.0067081188 | L14: =IFERROR(G14/G$48,0) -> 0.01165673 | M14: =IFERROR(H14/H$48,0) -> 0.017136104 | N14: =①札幌予測確定!R15 -> 0.014645309 | O14: =N14-L14 -> 0.0029885785 | P14: =L14-I14 -> -0.0044110227 | Q14: =IF(O14>=0.005,"↑ 伸長",IF(O14<=-0.005,"↓ 減退","→ 横ばい")) -> → 横ばい
A15: 10 | B15: 4515142545389 | C15: 呪術廻戦 懐玉・玉折 クリアファイル（夏油 傑） | D15: 1025 | E15: 141 | F15: 123 | G15: 277 | H15: 33 | I15: =IFERROR(D15/D$48,0) -> 0.0069170294 | J15: =IFERROR(E15/E$48,0) -> 0.0024061433 | K15: =IFERROR(F15/F$48,0) -> 0.0027411914 | L15: =IFERROR(G15/G$48,0) -> 0.0043457797 | M15: =IFERROR(H15/H$48,0) -> 0.0064999015 | N15: =①札幌予測確定!R16 -> 0.0054919908 | O15: =N15-L15 -> 0.0011462111 | P15: =L15-I15 -> -0.0025712497 | Q15: =IF(O15>=0.005,"↑ 伸長",IF(O15<=-0.005,"↓ 減退","→ 横ばい")) -> → 横ばい
A16: 11 | B16: 4515142545396 | C16: 呪術廻戦 懐玉・玉折 クリアファイル（家入 硝子） | D16: 215 | E16: 37 | F16: 30 | G16: 78 | H16: 10 | I16: =IFERROR(D16/D$48,0) -> 0.0014508891 | J16: =IFERROR(E16/E$48,0) -> 0.00063139932 | K16: =IFERROR(F16/F$48,0) -> 0.00066858327 | L16: =IFERROR(G16/G$48,0) -> 0.0012237214 | M16: =IFERROR(H16/H$48,0) -> 0.0019696671 | N16: =①札幌予測確定!R17 -> 0.0027459954 | O16: =N16-L16 -> 0.0015222741 | P16: =L16-I16 -> -0.00022716772 | Q16: =IF(O16>=0.005,"↑ 伸長",IF(O16<=-0.005,"↓ 減退","→ 横ばい")) -> → 横ばい
A17: 12 | B17: 4515142545402 | C17: 呪術廻戦 懐玉・玉折 クリアファイル（七海 建人） | D17: 291 | E17: 58 | F17: 54 | G17: 142 | H17: 19 | I17: =IFERROR(D17/D$48,0) -> 0.0019637615 | J17: =IFERROR(E17/E$48,0) -> 0.00098976109 | K17: =IFERROR(F17/F$48,0) -> 0.0012034499 | L17: =IFERROR(G17/G$48,0) -> 0.0022278004 | M17: =IFERROR(H17/H$48,0) -> 0.0037423675 | N17: =①札幌予測確定!R18 -> 0.0038901602 | O17: =N17-L17 -> 0.0016623597 | P17: =L17-I17 -> 0.00026403892 | Q17: =IF(O17>=0.005,"↑ 伸長",IF(O17<=-0.005,"↓ 減退","→ 横ばい")) -> → 横ばい
... A47: 42 | B47: 4515142545365 | C47: 伏黒 恵 イメージフラグメントケース | D47: 24 | E47: 8 | F47: 3 | G47: 8 | H47: 1 | I47: =IFERROR(D47/D$48,0) -> 0.00016195971 | J47: =IFERROR(E47/E$48,0) -> 0.00013651877 | K47: =IFERROR(F47/F$48,0) -> 6.6858327e-05 | L47: =IFERROR(G47/G$48,0) -> 0.00012550988 | M47: =IFERROR(H47/H$48,0) -> 0.00019696671 | N47: =①札幌予測確定!R48 -> 0.00022883295 | O47: =N47-L47 -> 0.00010332307 | P47: =L47-I47 -> -3.6449829e-05 | Q47: =IF(O47>=0.005,"↑ 伸長",IF(O47<=-0.005,"↓ 減退","→ 横ばい")) -> → 横ばい
C48: 合計（LEGS 42SKU） | D48: =SUM(D6:D47) -> 148185 | E48: =SUM(E6:E47) -> 58600 | F48: =SUM(F6:F47) -> 44871 | G48: =SUM(G6:G47) -> 63740 | H48: =SUM(H6:H47) -> 5077 | I48: 1 | J48: 1 | K48: 1 | L48: 1 | M48: 1 | N48: 1

Sheet ⑦新商品影響分析
A1: ⑦ 梅田(大阪)会場以降の追加商品による LEGS売上低下の要因分析
A2: 会場ごとに規模が違うため、すべて「入場者1人あたり売上（円/人）」に正規化して比較する（札幌は7/27までの6日実績）
A4: ■ 結論：市場は縮んでいない。LEGSの財布が新商品に奪われた（カニバリゼーション）
A5: ・物販客単価（全商品）は名古屋7,012円/人 → 大阪6,882円/人 と ▲1.8% でほぼ横ばい。
A6: ・同期間にLEGSは2,099円/人 → 1,455円/人 と ▲30.7%（▲643円/人）。会場全体の購買力は落ちていない。
A7: ・大阪の新商品106SKUは1,360円/人を稼いでおり、LEGSの減少分643円/人はその約47%に相当する。
A8: ・つまり新商品売上のおよそ半分は「純増」ではなく既存商品（特にLEGSとMAPPA）からの移動である。
A10: ■ ① 入場者1人あたり売上（円/人）の会場推移 供給元別
A11: 供給元 | B11: 東京 | C11: 名古屋 | D11: 博多 | E11: 大阪 | F11: 札幌 | G11: 名古屋→大阪 増減 | H11: 増減率 | I11: 評価
A12: LEGS(42SKU) | B12: 2159 | C12: 2099 | D12: 1634 | E12: 1455 | F12: 1046 | G12: =E12-C12 -> -644 | H12: =IFERROR(G12/C12,"") -> -0.30681277 | I12: ★最大の被害。新商品に置き換わった
A13: ムービック | B13: 4039 | C13: 2464 | D13: 1784 | E13: 2883 | F13: 2416 | G13: =E13-C13 -> 419 | H13: =IFERROR(G13/C13,"") -> 0.1700487 | I13: 新商品投入側。大きく増加
A14: 東宝 | B14: 697 | C14: 549 | D14: 435 | E14: 1047 | F14: 950 | G14: =E14-C14 -> 498 | H14: =IFERROR(G14/C14,"") -> 0.90710383 | I14: 新商品投入側。ほぼ倍増
A15: MAPPA | B15: 0 | C15: 1656 | D15: 1292 | E15: 984 | F15: 1079 | G15: =E15-C15 -> -672 | H15: =IFERROR(G15/C15,"") -> -0.4057971 | I15: LEGSと並ぶ被害。自社新商品にも食われた
A16: MBS | B16: 252 | C16: 244 | D16: 412 | E16: 512 | F16: 400 | G16: =E16-C16 -> 268 | H16: =IFERROR(G16/C16,"") -> 1.0983607 | I16: 新商品投入側。増加
A17: 書籍 | B17: 420 | C17: 0 | D17: 0 | E17: 0 | F17: 0 | G17: =E17-C17 -> 0 | H17: =IFERROR(G17/C17,"") | I17: 大阪では取扱なし
A18: 物販客単価（全商品計） | B18: 7567 | C18: 7012 | D18: 5557 | E18: 6882 | F18: 5892 | G18: =E18-C18 -> -130 | H18: =IFERROR(G18/C18,"") -> -0.018539646 | I18: 会場全体では ほぼ横ばい ＝ 市場は縮んでいない
A20: ■ ② 会場ごとの新商品投入と1人あたり売上（LEGSがいつ削られ始めたか）
A21: 会場 | B21: 新規SKU数 | C21: 新商品 売上(円/人) | D21: LEGS 売上(円/人) | E21: LEGS 前会場差 | F21: 物販客単価 (全商品) | G21: 主な新商品
A22: 東京 | B22: 332 | C22: 7567 | D22: 2159 | F22: 7567 | G22: （初回：全商品が新規）
A23: 名古屋 | B23: 85 | C23: 1480 | D23: 2099 | E23: =D23-D22 -> -60 | F23: 7012 | G23: MAPPAブラインドカード4種（フォト風カード・原画クリアカード）＝1,014円/人
A24: 博多 | B24: 19 | C24: 712 | D24: 1634 | E24: =D24-D23 -> -465 | F24: 5557 | G24: ★おすわりぬいぐるみ全8種（230円/人）、アクリルカードスタンド（233円/人）、原画ポストカードセット（178円/人）
A25: 大阪 | B25: 106 | C25: 1360 | D25: 1455 | E25: =D25-D24 -> -179 | F25: 6882 | G25: ★うちわ14種（195円/人）、アクリル系39種（450円/人）、劇場版ED系カード/ファイル（500円/人）、ぐみっとシール（101円/人）
A26: 札幌 | B26: 0 | C26: 0 | D26: 1046 | E26: =D26-D25 -> -409 | F26: 5892 | G26: 新規なし（品揃えは大阪と同一）
A29: ■ ③ LEGS 商品タイプ別 1人あたり売上（円/人）— どのタイプが削られたか
A30: LEGS 商品タイプ | B30: 東京 | C30: 名古屋 | D30: 博多 | E30: 大阪 | F30: 札幌 | G30: 名古屋→大阪 増減 | H30: LEGS減少への 寄与度 | I30: 競合した新商品
A31: ブラインド缶バッジ | B31: 632 | C31: 801 | D31: 722 | E31: 529 | F31: 150 | G31: =E31-C31 -> -272 | H31: =IFERROR(G31/G$38,"") -> 0.42301711 | I31: ★アクリル系39SKU（450円/人）・ぬいぐるみ全8種。同じ「引く／集める」コレクション需要が直撃
A32: ブラインドミニ色紙 | B32: 712 | C32: 662 | D32: 442 | E32: 378 | F32: 294 | G32: =E32-C32 -> -284 | H32: =IFERROR(G32/G$38,"") -> 0.44167963 | I32: ★アクリル系・劇場版EDカード類（293円/人）。ブラインド飽和＋新規コレクション商材へ移行
A33: クリアファイル | B33: 215 | C33: 117 | D33: 99 | E33: 124 | F33: 139 | G33: =E33-C33 -> 7 | H33: =IFERROR(G33/G$38,"") -> -0.01088647 | I33: 劇場版EDクリアファイル10SKU（207円/人）と競合するが、LEGS側は横ばいを維持
A34: ポストカード類 | B34: 184 | C34: 148 | D34: 104 | E34: 149 | F34: 127 | G34: =E34-C34 -> 1 | H34: =IFERROR(G34/G$38,"") -> -0.00155521 | I34: 劇場版EDポストカード/Pictas（199円/人）と競合。LEGS側は横ばい
A35: ブラインドステッカー | B35: 115 | C35: 49 | D35: 37 | E35: 52 | F35: 43 | G35: =E35-C35 -> 3 | H35: =IFERROR(G35/G$38,"") -> -0.0046656299 | I35: ぐみっとシール等9SKU（121円/人）。影響軽微
A36: 雑貨・その他 | B36: 247 | C36: 203 | D36: 161 | E36: 159 | F36: 258 | G36: =E36-C36 -> -44 | H36: =IFERROR(G36/G$38,"") -> 0.068429238 | I36: うちわ14SKU（195円/人）が近い衝動買い枠。バスボール・お菓子等が微減
A37: アクセサリー(リング等) | B37: 54 | C37: 119 | D37: 68 | E37: 65 | F37: 35 | G37: =E37-C37 -> -54 | H37: =IFERROR(G37/G$38,"") -> 0.083981337 | I37: 高単価アクセ。ぬいぐるみコンプリート(¥19,840)等の高単価枠と競合
A38: LEGS 合計 | B38: =SUM(B31:B37) -> 2159 | C38: =SUM(C31:C37) -> 2099 | D38: =SUM(D31:D37) -> 1633 | E38: =SUM(E31:E37) -> 1456 | F38: =SUM(F31:F37) -> 1046 | G38: =E38-C38 -> -643 | H38: 1
A40: ■ ④ 大阪 新商品106SKU の内訳（タイプ別）
A41: 新商品タイプ | B41: SKU数 | C41: 販売数量 | D41: 販売金額(税込) | E41: 会場売上 構成比 | F41: 1人あたり 売上 | G41: 競合するLEGS商品
A42: アクリル系（コレクション） | B42: 39 | C42: 11147 | D42: 14080770 | E42: =D42/215184570 -> 0.065435779 | F42: =ROUND(D42/31267,0) -> 450 | G42: ★ブラインド缶バッジ・ブラインドミニ色紙（直接競合）
A43: カード・ポストカード類 | B43: 7 | C43: 17060 | D43: 9360615 | E43: =D43/215184570 -> 0.043500401 | F43: =ROUND(D43/31267,0) -> 299 | G43: ポストカードセット2種・メタリックポストカード
A44: クリアファイル | B44: 10 | C44: 11836 | D44: 6460410 | E44: =D44/215184570 -> 0.030022645 | F44: =ROUND(D44/31267,0) -> 207 | G44: クリアファイル14種（展示会KV・キャラ別）
A45: うちわ（新カテゴリ） | B45: 14 | C45: 5531 | D45: 6084100 | E45: =D45/215184570 -> 0.028273867 | F45: =ROUND(D45/31267,0) -> 195 | G45: 直接競合なし。ただし1,100円の衝動買い枠を奪う
A46: シール・ステッカー | B46: 9 | C46: 5528 | D46: 3778060 | E46: =D46/215184570 -> 0.0175573 | F46: =ROUND(D46/31267,0) -> 121 | G46: ブラインドダイカットステッカー2種
A47: その他新商品 | B47: 16 | C47: 1561 | D47: 1814100 | E47: =D47/215184570 -> 0.0084304372 | F47: =ROUND(D47/31267,0) -> 58 | G47: 雑貨・その他
A48: 缶バッジ | B48: 11 | C48: 1719 | D48: 945450 | E48: =D48/215184570 -> 0.00439367 | F48: =ROUND(D48/31267,0) -> 30 | G48: ★ブラインド缶バッジ2種（直接競合）
A49: 新商品 合計 | B49: =SUM(B42:B48) -> 106 | C49: =SUM(C42:C48) -> 54382 | D49: =SUM(D42:D48) -> 42523505 | E49: =D49/215184570 -> 0.1976141 | F49: =ROUND(D49/31267,0) -> 1360 | G49: うち約47%がLEGSからの移動と推定
A51: ■ ⑤ 石川会場以降への示唆
A52: LEGS構成比は底打ちの見込み | B52: 札幌は新規SKU 0で品揃えが大阪と同一。LEGS金額構成比 大阪21.1%→札幌19.6%(予測)で減少幅は縮小しており、石川以降も新商品の追加が無ければ19〜20%で安定すると想定。③の予測はこの水準を採用している。
A53: ★最大のリスクは「石川以降の新商品追加」 | B53: 大阪の実績では新商品1,360円/人の投入に対しLEGSが643円/人失われた。同規模の新商品を石川以降に投入すると、LEGS構成比はさらに5〜7pt下がり、③の必要数86,000個は最大で30%程度過大になる。
A54: → 発注前の必須確認事項 | B54: 石川以降に新商品（ぬいぐるみ第2弾・うちわ第2弾等）の投入計画があるか、あるなら規模はどの程度か。これを確認せずに追加生産46,000個を確定するのは危険。
A55: ブラインド系は減産、定番系は維持 | B55: ブラインド缶バッジ▲272円/人・ミニ色紙▲284円/人でLEGS減少の87%を占める一方、クリアファイル・ポストカード類はほぼ横ばい。追加生産はブラインド系を抑え、クリアファイル系を優先すべき。
A56: 高単価コレクション商材が主戦場 | B56: おすわりぬいぐるみコンプリート(¥19,840)が大阪で203個、アクリル系39SKUで450円/人。「引く」から「選んで揃える」へ需要が移行している。LEGS側もブラインド偏重の見直しが必要。

Sheet ⑧実在庫(7-8)明細
A1: ⑧ 残在庫想定（梅田まで(SET)）の明細と欠品算出
A2: 残在庫想定 ＝ 在庫フロー台帳（【清算(卸値67％)】…_検品差異）の「梅田まで(SET)」列。会場ごとの 追加発注→販売→レッグス検品 を積み上げた最終値で、梅田会場後の検品結果まで反映済み
A3: この残在庫から札幌会場へ7/21に出荷（＝札幌の販売可能数）。石川以降に使えるのは「倉庫残 − 札幌への追納 ＋ 札幌会期末の返送見込」＝ 残在庫 − 札幌会期予測販売数
A4: ※同ファイルの「元データ」「在庫合算」「在庫元データ(12月清算後)」シートは池袋終了時点の古いスナップショット（合計183,696個）であり、残在庫として使ってはいけない。ポストカードセット2種・宿儺の指風お菓子はSET商品で、台帳の発注数はバラ単位・実在庫はSET単位
A5: ※P列の過不足には確定済み追加発注（宿儺の指風お菓子 1,200SET）を加算している
A6: No. | B6: JAN | C6: 商品名 | D6: 税込単価 | E6: 実在庫 池袋まで | F6: 実在庫 名古屋まで | G6: 実在庫 福岡まで | H6: ★残在庫想定 梅田まで | I6: 残在庫 金額(税込) | J6: 札幌へ納品 (7/21) | K6: 札幌 会期20日 予測販売 | L6: 札幌 会期末 返送見込 | M6: 差引 倉庫残 (即出荷可) | N6: 石川以降 供給可能計 | O6: 石川以降 必要数 | P6: 過不足 (供給−必要) | Q6: 欠品 (追加生産必要数) | R6: 推奨発注数 (安全率込) | S6: 欠品発生 会場 | T6: 最終発注期限 | U6: 発注の緊急度 | V6: 判定 | W6: 運営欠品報告 (7/28) | X6: 備考
A7: 1 | B7: 4515142545082 | C7: 呪術廻戦 メタリックポストカード 展示会キービジュアル | D7: 500 | E7: 4024 | F7: 2689 | G7: 5590 | H7: 3264 | I7: =H7*D7 -> 1632000 | J7: =①札幌予測確定!S7 -> 1000 | K7: =①札幌予測確定!P7 -> 467 | L7: =①札幌予測確定!U7 -> 533 | M7: =H7-J7 -> 2264 | N7: =M7+ROUND(L7*前提・入力!$B$37,0) -> 2797 | O7: =③石川以降予測!N30 -> 3676 | P7: =N7-O7 -> -879 | Q7: =MAX(0,-P7) -> 879 | R7: =IF(Q7>0,ROUNDUP(Q7*(1+前提・入力!$B$35),0),0) -> 967 | S7: 東京凱旋 東京建物ぴあホール | T7: =DATE(2027,4,1)-30-前提・入力!$B$38 -> 46434 | U7: =IF(S7="—","—",IF(T7="再生産不可","×再生産不可",_xlfn.IFS(T7-前提・入力!$B$39<0,"★期限超過",T7-前提・入力!$B$39<=30,"★至急(30日以内)",T7-前提・入力!$B$39<=90,"要着手(90日以内)",TRUE(),"余裕あり"))) -> 余裕あり | V7: =IF(Q7>0,"★欠品：追加生産が必要",IF(P7>=O7*2,"大幅余剰","在庫で充足")) -> ★欠品：追加生産が必要
A8: 2 | B8: 4515142545099 | C8: 呪術廻戦 クリアファイル 展示会キービジュアル | D8: 600 | E8: 1096 | F8: 5135 | G8: 7002 | H8: 5037 | I8: =H8*D8 -> 3022200 | J8: =①札幌予測確定!S8 -> 1000 | K8: =①札幌予測確定!P8 -> 509 | L8: =①札幌予測確定!U8 -> 491 | M8: =H8-J8 -> 4037 | N8: =M8+ROUND(L8*前提・入力!$B$37,0) -> 4528 | O8: =③石川以降予測!N31 -> 3642 | P8: =N8-O8 -> 886 | Q8: =MAX(0,-P8) -> 0 | R8: =IF(Q8>0,ROUNDUP(Q8*(1+前提・入力!$B$35),0),0) -> 0 | S8: — | U8: =IF(S8="—","—",IF(T8="再生産不可","×再生産不可",_xlfn.IFS(T8-前提・入力!$B$39<0,"★期限超過",T8-前提・入力!$B$39<=30,"★至急(30日以内)",T8-前提・入力!$B$39<=90,"要着手(90日以内)",TRUE(),"余裕あり"))) -> — | V8: =IF(Q8>0,"★欠品：追加生産が必要",IF(P8>=O8*2,"大幅余剰","在庫で充足")) -> 在庫で充足
A9: 3 | B9: 4515142545105 | C9: 呪術廻戦 懐玉・玉折 ポストカードセット（5枚入） | D9: 1000 | E9: 3340 | F9: 2735 | G9: 7280 | H9: 6140 | I9: =H9*D9 -> 6140000 | J9: =①札幌予測確定!S9 -> 450 | K9: =①札幌予測確定!P9 -> 163 | L9: =①札幌予測確定!U9 -> 287 | M9: =H9-J9 -> 5690 | N9: =M9+ROUND(L9*前提・入力!$B$37,0) -> 5977 | O9: =③石川以降予測!N32 -> 1489 | P9: =N9-O9 -> 4488 | Q9: =MAX(0,-P9) -> 0 | R9: =IF(Q9>0,ROUNDUP(Q9*(1+前提・入力!$B$35),0),0) -> 0 | S9: — | U9: =IF(S9="—","—",IF(T9="再生産不可","×再生産不可",_xlfn.IFS(T9-前提・入力!$B$39<0,"★期限超過",T9-前提・入力!$B$39<=30,"★至急(30日以内)",T9-前提・入力!$B$39<=90,"要着手(90日以内)",TRUE(),"余裕あり"))) -> — | V9: =IF(Q9>0,"★欠品：追加生産が必要",IF(P9>=O9*2,"大幅余剰","在庫で充足")) -> 大幅余剰 | X9: SET商品（1販売単位＝5個）。台帳の発注数はバラ単位
A10: 4 | B10: 4515142545112 | C10: 呪術廻戦 渋谷事変 ポストカードセット（9枚入） | D10: 1800 | E10: 3297 | F10: 2368 | G10: 28823 | H10: 27511 | I10: =H10*D10 -> 49519800 | J10: =①札幌予測確定!S10 -> 800 | K10: =①札幌予測確定!P10 -> 229 | L10: =①札幌予測確定!U10 -> 571 | M10: =H10-J10 -> 26711 | N10: =M10+ROUND(L10*前提・入力!$B$37,0) -> 27282 | O10: =③石川以降予測!N33 -> 1912 | P10: =N10-O10 -> 25370 | Q10: =MAX(0,-P10) -> 0 | R10: =IF(Q10>0,ROUNDUP(Q10*(1+前提・入力!$B$35),0),0) -> 0 | S10: — | U10: =IF(S10="—","—",IF(T10="再生産不可","×再生産不可",_xlfn.IFS(T10-前提・入力!$B$39<0,"★期限超過",T10-前提・入力!$B$39<=30,"★至急(30日以内)",T10-前提・入力!$B$39<=90,"要着手(90日以内)",TRUE(),"余裕あり"))) -> — | V10: =IF(Q10>0,"★欠品：追加生産が必要",IF(P10>=O10*2,"大幅余剰","在庫で充足")) -> 大幅余剰 | X10: SET商品（1販売単位＝9個）。台帳の発注数はバラ単位
A11: 5 | B11: 4515142545129 | C11: 呪術廻戦 懐玉・玉折 ブラインド缶バッジ（全5種） | D11: 600 | E11: 5958 | F11: 10871 | G11: 48871 | H11: 39825 | I11: =H11*D11 -> 23895000 | J11: =①札幌予測確定!S11 -> 9000 | K11: =①札幌予測確定!P11 -> 465 | L11: =①札幌予測確定!U11 -> 8535 | M11: =H11-J11 -> 30825 | N11: =M11+ROUND(L11*前提・入力!$B$37,0) -> 39360 | O11: =③石川以降予測!N34 -> 7909 | P11: =N11-O11 -> 31451 | Q11: =MAX(0,-P11) -> 0 | R11: =IF(Q11>0,ROUNDUP(Q11*(1+前提・入力!$B$35),0),0) -> 0 | S11: — | U11: =IF(S11="—","—",IF(T11="再生産不可","×再生産不可",_xlfn.IFS(T11-前提・入力!$B$39<0,"★期限超過",T11-前提・入力!$B$39<=30,"★至急(30日以内)",T11-前提・入力!$B$39<=90,"要着手(90日以内)",TRUE(),"余裕あり"))) -> — | V11: =IF(Q11>0,"★欠品：追加生産が必要",IF(P11>=O11*2,"大幅余剰","在庫で充足")) -> 大幅余剰
A12: 6 | B12: 4515142545136 | C12: 呪術廻戦 渋谷事変 ブラインド缶バッジ（全9種） | D12: 600 | E12: 12914 | F12: 18595 | G12: 69589 | H12: 50834 | I12: =H12*D12 -> 30500400 | J12: =①札幌予測確定!S12 -> 13991 | K12: =①札幌予測確定!P12 -> 1317 | L12: =①札幌予測確定!U12 -> 12674 | M12: =H12-J12 -> 36843 | N12: =M12+ROUND(L12*前提・入力!$B$37,0) -> 49517 | O12: =③石川以降予測!N35 -> 18104 | P12: =N12-O12 -> 31413 | Q12: =MAX(0,-P12) -> 0 | R12: =IF(Q12>0,ROUNDUP(Q12*(1+前提・入力!$B$35),0),0) -> 0 | S12: — | U12: =IF(S12="—","—",IF(T12="再生産不可","×再生産不可",_xlfn.IFS(T12-前提・入力!$B$39<0,"★期限超過",T12-前提・入力!$B$39<=30,"★至急(30日以内)",T12-前提・入力!$B$39<=90,"要着手(90日以内)",TRUE(),"余裕あり"))) -> — | V12: =IF(Q12>0,"★欠品：追加生産が必要",IF(P12>=O12*2,"大幅余剰","在庫で充足")) -> 在庫で充足
A13: 7 | B13: 4515142545143 | C13: 呪術廻戦 懐玉・玉折 ブラインドダイカットステッカー（全5種） | D13: 600 | E13: 6467 | F13: 5884 | G13: 5484 | H13: 4542 | I13: =H13*D13 -> 2725200 | J13: =①札幌予測確定!S13 -> 350 | K13: =①札幌予測確定!P13 -> 194 | L13: =①札幌予測確定!U13 -> 156 | M13: =H13-J13 -> 4192 | N13: =M13+ROUND(L13*前提・入力!$B$37,0) -> 4348 | O13: =③石川以降予測!N36 -> 1511 | P13: =N13-O13 -> 2837 | Q13: =MAX(0,-P13) -> 0 | R13: =IF(Q13>0,ROUNDUP(Q13*(1+前提・入力!$B$35),0),0) -> 0 | S13: — | U13: =IF(S13="—","—",IF(T13="再生産不可","×再生産不可",_xlfn.IFS(T13-前提・入力!$B$39<0,"★期限超過",T13-前提・入力!$B$39<=30,"★至急(30日以内)",T13-前提・入力!$B$39<=90,"要着手(90日以内)",TRUE(),"余裕あり"))) -> — | V13: =IF(Q13>0,"★欠品：追加生産が必要",IF(P13>=O13*2,"大幅余剰","在庫で充足")) -> 在庫で充足
A14: 8 | B14: 4515142545150 | C14: 呪術廻戦 渋谷事変 ブラインドダイカットステッカー（全9種） | D14: 600 | E14: 12329 | F14: 11145 | G14: 10317 | H14: 8551 | I14: =H14*D14 -> 5130600 | J14: =①札幌予測確定!S14 -> 900 | K14: =①札幌予測確定!P14 -> 321 | L14: =①札幌予測確定!U14 -> 579 | M14: =H14-J14 -> 7651 | N14: =M14+ROUND(L14*前提・入力!$B$37,0) -> 8230 | O14: =③石川以降予測!N37 -> 2630 | P14: =N14-O14 -> 5600 | Q14: =MAX(0,-P14) -> 0 | R14: =IF(Q14>0,ROUNDUP(Q14*(1+前提・入力!$B$35),0),0) -> 0 | S14: — | U14: =IF(S14="—","—",IF(T14="再生産不可","×再生産不可",_xlfn.IFS(T14-前提・入力!$B$39<0,"★期限超過",T14-前提・入力!$B$39<=30,"★至急(30日以内)",T14-前提・入力!$B$39<=90,"要着手(90日以内)",TRUE(),"余裕あり"))) -> — | V14: =IF(Q14>0,"★欠品：追加生産が必要",IF(P14>=O14*2,"大幅余剰","在庫で充足")) -> 大幅余剰
A15: 9 | B15: 4515142545372 | C15: 呪術廻戦 懐玉・玉折 クリアファイル（五条 悟） | D15: 600 | E15: 10118 | F15: 9802 | G15: 9502 | H15: 8759 | I15: =H15*D15 -> 5255400 | J15: =①札幌予測確定!S15 -> 300 | K15: =①札幌予測確定!P15 -> 128 | L15: =①札幌予測確定!U15 -> 172 | M15: =H15-J15 -> 8459 | N15: =M15+ROUND(L15*前提・入力!$B$37,0) -> 8631 | O15: =③石川以降予測!N38 -> 1076 | P15: =N15-O15 -> 7555 | Q15: =MAX(0,-P15) -> 0 | R15: =IF(Q15>0,ROUNDUP(Q15*(1+前提・入力!$B$35),0),0) -> 0 | S15: — | U15: =IF(S15="—","—",IF(T15="再生産不可","×再生産不可",_xlfn.IFS(T15-前提・入力!$B$39<0,"★期限超過",T15-前提・入力!$B$39<=30,"★至急(30日以内)",T15-前提・入力!$B$39<=90,"要着手(90日以内)",TRUE(),"余裕あり"))) -> — | V15: =IF(Q15>0,"★欠品：追加生産が必要",IF(P15>=O15*2,"大幅余剰","在庫で充足")) -> 大幅余剰
A16: 10 | B16: 4515142545389 | C16: 呪術廻戦 懐玉・玉折 クリアファイル（夏油 傑） | D16: 600 | E16: 5476 | F16: 5335 | G16: 5213 | H16: 4935 | I16: =H16*D16 -> 2961000 | J16: =①札幌予測確定!S16 -> 100 | K16: =①札幌予測確定!P16 -> 48 | L16: =①札幌予測確定!U16 -> 52 | M16: =H16-J16 -> 4835 | N16: =M16+ROUND(L16*前提・入力!$B$37,0) -> 4887 | O16: =③石川以降予測!N39 -> 403 | P16: =N16-O16 -> 4484 | Q16: =MAX(0,-P16) -> 0 | R16: =IF(Q16>0,ROUNDUP(Q16*(1+前提・入力!$B$35),0),0) -> 0 | S16: — | U16: =IF(S16="—","—",IF(T16="再生産不可","×再生産不可",_xlfn.IFS(T16-前提・入力!$B$39<0,"★期限超過",T16-前提・入力!$B$39<=30,"★至急(30日以内)",T16-前提・入力!$B$39<=90,"要着手(90日以内)",TRUE(),"余裕あり"))) -> — | V16: =IF(Q16>0,"★欠品：追加生産が必要",IF(P16>=O16*2,"大幅余剰","在庫で充足")) -> 大幅余剰
A17: 11 | B17: 4515142545396 | C17: 呪術廻戦 懐玉・玉折 クリアファイル（家入 硝子） | D17: 600 | E17: 785 | F17: 748 | G17: 718 | H17: 640 | I17: =H17*D17 -> 384000 | J17: =①札幌予測確定!S17 -> 50 | K17: =①札幌予測確定!P17 -> 24 | L17: =①札幌予測確定!U17 -> 26 | M17: =H17-J17 -> 590 | N17: =M17+ROUND(L17*前提・入力!$B$37,0) -> 616 | O17: =③石川以降予測!N40 -> 162 | P17: =N17-O17 -> 454 | Q17: =MAX(0,-P17) -> 0 | R17: =IF(Q17>0,ROUNDUP(Q17*(1+前提・入力!$B$35),0),0) -> 0 | S17: — | U17: =IF(S17="—","—",IF(T17="再生産不可","×再生産不可",_xlfn.IFS(T17-前提・入力!$B$39<0,"★期限超過",T17-前提・入力!$B$39<=30,"★至急(30日以内)",T17-前提・入力!$B$39<=90,"要着手(90日以内)",TRUE(),"余裕あり"))) -> — | V17: =IF(Q17>0,"★欠品：追加生産が必要",IF(P17>=O17*2,"大幅余剰","在庫で充足")) -> 大幅余剰
A18: 12 | B18: 4515142545402 | C18: 呪術廻戦 懐玉・玉折 クリアファイル（七海 建人） | D18: 600 | E18: 1209 | F18: 1149 | G18: 1095 | H18: 953 | I18: =H18*D18 -> 571800 | J18: =①札幌予測確定!S18 -> 50 | K18: =①札幌予測確定!P18 -> 34 | L18: =①札幌予測確定!U18 -> 16 | M18: =H18-J18 -> 903 | N18: =M18+ROUND(L18*前提・入力!$B$37,0) -> 919 | O18: =③石川以降予測!N41 -> 251 | P18: =N18-O18 -> 668 | Q18: =MAX(0,-P18) -> 0 | R18: =IF(Q18>0,ROUNDUP(Q18*(1+前提・入力!$B$35),0),0) -> 0 | S18: — | U18: =IF(S18="—","—",IF(T18="再生産不可","×再生産不可",_xlfn.IFS(T18-前提・入力!$B$39<0,"★期限超過",T18-前提・入力!$B$39<=30,"★至急(30日以内)",T18-前提・入力!$B$39<=90,"要着手(90日以内)",TRUE(),"余裕あり"))) -> — | V18: =IF(Q18>0,"★欠品：追加生産が必要",IF(P18>=O18*2,"大幅余剰","在庫で充足")) -> 大幅余剰
A19: 13 | B19: 4515142545419 | C19: 呪術廻戦 懐玉・玉折 クリアファイル（灰原 雄） | D19: 600 | E19: 401 | F19: 385 | G19: 363 | H19: 320 | I19: =H19*D19 -> 192000 | J19: =①札幌予測確定!S19 -> 50 | K19: =①札幌予測確定!P19 -> 5 | L19: =①札幌予測確定!U19 -> 45 | M19: =H19-J19 -> 270 | N19: =M19+ROUND(L19*前提・入力!$B$37,0) -> 315 | O19: =③石川以降予測!N42 -> 51 | P19: =N19-O19 -> 264 | Q19: =MAX(0,-P19) -> 0 | R19: =IF(Q19>0,ROUNDUP(Q19*(1+前提・入力!$B$35),0),0) -> 0 | S19: — | U19: =IF(S19="—","—",IF(T19="再生産不可","×再生産不可",_xlfn.IFS(T19-前提・入力!$B$39<0,"★期限超過",T19-前提・入力!$B$39<=30,"★至急(30日以内)",T19-前提・入力!$B$39<=90,"要着手(90日以内)",TRUE(),"余裕あり"))) -> — | V19: =IF(Q19>0,"★欠品：追加生産が必要",IF(P19>=O19*2,"大幅余剰","在庫で充足")) -> 大幅余剰
A20: 14 | B20: 4515142545426 | C20: 呪術廻戦 渋谷事変 クリアファイル（虎杖 悠仁） | D20: 600 | E20: 2089 | F20: 2016 | G20: 1936 | H20: 1790 | I20: =H20*D20 -> 1074000 | J20: =①札幌予測確定!S20 -> 50 | K20: =①札幌予測確定!P20 -> 38 | L20: =①札幌予測確定!U20 -> 12 | M20: =H20-J20 -> 1740 | N20: =M20+ROUND(L20*前提・入力!$B$37,0) -> 1752 | O20: =③石川以降予測!N43 -> 271 | P20: =N20-O20 -> 1481 | Q20: =MAX(0,-P20) -> 0 | R20: =IF(Q20>0,ROUNDUP(Q20*(1+前提・入力!$B$35),0),0) -> 0 | S20: — | U20: =IF(S20="—","—",IF(T20="再生産不可","×再生産不可",_xlfn.IFS(T20-前提・入力!$B$39<0,"★期限超過",T20-前提・入力!$B$39<=30,"★至急(30日以内)",T20-前提・入力!$B$39<=90,"要着手(90日以内)",TRUE(),"余裕あり"))) -> — | V20: =IF(Q20>0,"★欠品：追加生産が必要",IF(P20>=O20*2,"大幅余剰","在庫で充足")) -> 大幅余剰 | W20: 欠品報告あり | X20: 倉庫残1,740個 → ◎倉庫からの追加納品で即対応可能
A21: 15 | B21: 4515142545433 | C21: 呪術廻戦 渋谷事変 クリアファイル（伏黒 恵） | D21: 600 | E21: 2529 | F21: 2429 | G21: 2329 | H21: 2131 | I21: =H21*D21 -> 1278600 | J21: =①札幌予測確定!S21 -> 100 | K21: =①札幌予測確定!P21 -> 59 | L21: =①札幌予測確定!U21 -> 41 | M21: =H21-J21 -> 2031 | N21: =M21+ROUND(L21*前提・入力!$B$37,0) -> 2072 | O21: =③石川以降予測!N44 -> 403 | P21: =N21-O21 -> 1669 | Q21: =MAX(0,-P21) -> 0 | R21: =IF(Q21>0,ROUNDUP(Q21*(1+前提・入力!$B$35),0),0) -> 0 | S21: — | U21: =IF(S21="—","—",IF(T21="再生産不可","×再生産不可",_xlfn.IFS(T21-前提・入力!$B$39<0,"★期限超過",T21-前提・入力!$B$39<=30,"★至急(30日以内)",T21-前提・入力!$B$39<=90,"要着手(90日以内)",TRUE(),"余裕あり"))) -> — | V21: =IF(Q21>0,"★欠品：追加生産が必要",IF(P21>=O21*2,"大幅余剰","在庫で充足")) -> 大幅余剰
A22: 16 | B22: 4515142545440 | C22: 呪術廻戦 渋谷事変 クリアファイル（釘崎 野薔薇） | D22: 600 | E22: 905 | F22: 867 | G22: 837 | H22: 772 | I22: =H22*D22 -> 463200 | J22: =①札幌予測確定!S22 -> 50 | K22: =①札幌予測確定!P22 -> 15 | L22: =①札幌予測確定!U22 -> 35 | M22: =H22-J22 -> 722 | N22: =M22+ROUND(L22*前提・入力!$B$37,0) -> 757 | O22: =③石川以降予測!N45 -> 112 | P22: =N22-O22 -> 645 | Q22: =MAX(0,-P22) -> 0 | R22: =IF(Q22>0,ROUNDUP(Q22*(1+前提・入力!$B$35),0),0) -> 0 | S22: — | U22: =IF(S22="—","—",IF(T22="再生産不可","×再生産不可",_xlfn.IFS(T22-前提・入力!$B$39<0,"★期限超過",T22-前提・入力!$B$39<=30,"★至急(30日以内)",T22-前提・入力!$B$39<=90,"要着手(90日以内)",TRUE(),"余裕あり"))) -> — | V22: =IF(Q22>0,"★欠品：追加生産が必要",IF(P22>=O22*2,"大幅余剰","在庫で充足")) -> 大幅余剰
A23: 17 | B23: 4515142545457 | C23: 呪術廻戦 渋谷事変 クリアファイル（七海 建人） | D23: 600 | E23: 3008 | F23: 2885 | G23: 2785 | H23: 2523 | I23: =H23*D23 -> 1513800 | J23: =①札幌予測確定!S23 -> 100 | K23: =①札幌予測確定!P23 -> 93 | L23: =①札幌予測確定!U23 -> 7 | M23: =H23-J23 -> 2423 | N23: =M23+ROUND(L23*前提・入力!$B$37,0) -> 2430 | O23: =③石川以降予測!N46 -> 602 | P23: =N23-O23 -> 1828 | Q23: =MAX(0,-P23) -> 0 | R23: =IF(Q23>0,ROUNDUP(Q23*(1+前提・入力!$B$35),0),0) -> 0 | S23: — | U23: =IF(S23="—","—",IF(T23="再生産不可","×再生産不可",_xlfn.IFS(T23-前提・入力!$B$39<0,"★期限超過",T23-前提・入力!$B$39<=30,"★至急(30日以内)",T23-前提・入力!$B$39<=90,"要着手(90日以内)",TRUE(),"余裕あり"))) -> — | V23: =IF(Q23>0,"★欠品：追加生産が必要",IF(P23>=O23*2,"大幅余剰","在庫で充足")) -> 大幅余剰 | W23: 欠品報告あり | X23: 倉庫残2,423個 → ◎倉庫からの追加納品で即対応可能
A24: 18 | B24: 4515142545464 | C24: 呪術廻戦 渋谷事変 クリアファイル（五条 悟） | D24: 600 | E24: 6837 | F24: 12650 | G24: 11750 | H24: 9725 | I24: =H24*D24 -> 5835000 | J24: =①札幌予測確定!S24 -> 1500 | K24: =①札幌予測確定!P24 -> 407 | L24: =①札幌予測確定!U24 -> 1093 | M24: =H24-J24 -> 8225 | N24: =M24+ROUND(L24*前提・入力!$B$37,0) -> 9318 | O24: =③石川以降予測!N47 -> 3201 | P24: =N24-O24 -> 6117 | Q24: =MAX(0,-P24) -> 0 | R24: =IF(Q24>0,ROUNDUP(Q24*(1+前提・入力!$B$35),0),0) -> 0 | S24: — | U24: =IF(S24="—","—",IF(T24="再生産不可","×再生産不可",_xlfn.IFS(T24-前提・入力!$B$39<0,"★期限超過",T24-前提・入力!$B$39<=30,"★至急(30日以内)",T24-前提・入力!$B$39<=90,"要着手(90日以内)",TRUE(),"余裕あり"))) -> — | V24: =IF(Q24>0,"★欠品：追加生産が必要",IF(P24>=O24*2,"大幅余剰","在庫で充足")) -> 在庫で充足
A25: 19 | B25: 4515142545471 | C25: 呪術廻戦 渋谷事変 クリアファイル（夏油 傑） | D25: 600 | E25: 2332 | F25: 2305 | G25: 2285 | H25: 2240 | I25: =H25*D25 -> 1344000 | J25: =①札幌予測確定!S25 -> 50 | K25: =①札幌予測確定!P25 -> 16 | L25: =①札幌予測確定!U25 -> 34 | M25: =H25-J25 -> 2190 | N25: =M25+ROUND(L25*前提・入力!$B$37,0) -> 2224 | O25: =③石川以降予測!N48 -> 104 | P25: =N25-O25 -> 2120 | Q25: =MAX(0,-P25) -> 0 | R25: =IF(Q25>0,ROUNDUP(Q25*(1+前提・入力!$B$35),0),0) -> 0 | S25: — | U25: =IF(S25="—","—",IF(T25="再生産不可","×再生産不可",_xlfn.IFS(T25-前提・入力!$B$39<0,"★期限超過",T25-前提・入力!$B$39<=30,"★至急(30日以内)",T25-前提・入力!$B$39<=90,"要着手(90日以内)",TRUE(),"余裕あり"))) -> — | V25: =IF(Q25>0,"★欠品：追加生産が必要",IF(P25>=O25*2,"大幅余剰","在庫で充足")) -> 大幅余剰
A26: 20 | B26: 4515142545488 | C26: 呪術廻戦 渋谷事変 クリアファイル（真人） | D26: 600 | E26: 382 | F26: 358 | G26: 343 | H26: 301 | I26: =H26*D26 -> 180600 | J26: =①札幌予測確定!S26 -> 30 | K26: =①札幌予測確定!P26 -> 14 | L26: =①札幌予測確定!U26 -> 16 | M26: =H26-J26 -> 271 | N26: =M26+ROUND(L26*前提・入力!$B$37,0) -> 287 | O26: =③石川以降予測!N49 -> 94 | P26: =N26-O26 -> 193 | Q26: =MAX(0,-P26) -> 0 | R26: =IF(Q26>0,ROUNDUP(Q26*(1+前提・入力!$B$35),0),0) -> 0 | S26: — | U26: =IF(S26="—","—",IF(T26="再生産不可","×再生産不可",_xlfn.IFS(T26-前提・入力!$B$39<0,"★期限超過",T26-前提・入力!$B$39<=30,"★至急(30日以内)",T26-前提・入力!$B$39<=90,"要着手(90日以内)",TRUE(),"余裕あり"))) -> — | V26: =IF(Q26>0,"★欠品：追加生産が必要",IF(P26>=O26*2,"大幅余剰","在庫で充足")) -> 大幅余剰
A27: 21 | B27: 4515142545495 | C27: 呪術廻戦 渋谷事変 クリアファイル（脹相） | D27: 600 | E27: 150 | F27: 710 | G27: 560 | H27: 308 | I27: =H27*D27 -> 184800 | J27: =①札幌予測確定!S27 -> 100 | K27: =①札幌予測確定!P27 -> 90 | L27: =①札幌予測確定!U27 -> 10 | M27: =H27-J27 -> 208 | N27: =M27+ROUND(L27*前提・入力!$B$37,0) -> 218 | O27: =③石川以降予測!N50 -> 583 | P27: =N27-O27 -> -365 | Q27: =MAX(0,-P27) -> 365 | R27: =IF(Q27>0,ROUNDUP(Q27*(1+前提・入力!$B$35),0),0) -> 402 | S27: 神戸阪急 | T27: =DATE(2026,12,16)-30-前提・入力!$B$38 -> 46328 | U27: =IF(S27="—","—",IF(T27="再生産不可","×再生産不可",_xlfn.IFS(T27-前提・入力!$B$39<0,"★期限超過",T27-前提・入力!$B$39<=30,"★至急(30日以内)",T27-前提・入力!$B$39<=90,"要着手(90日以内)",TRUE(),"余裕あり"))) -> 余裕あり | V27: =IF(Q27>0,"★欠品：追加生産が必要",IF(P27>=O27*2,"大幅余剰","在庫で充足")) -> ★欠品：追加生産が必要 | W27: 欠品報告あり | X27: 倉庫残208個 → ◎倉庫からの追加納品で即対応可能
A28: 22 | B28: 4515142545501 | C28: 呪術廻戦 渋谷事変 クリアファイル（宿儺） | D28: 600 | E28: 1681 | F28: 1582 | G28: 1502 | H28: 1331 | I28: =H28*D28 -> 798600 | J28: =①札幌予測確定!S28 -> 50 | K28: =①札幌予測確定!P28 -> 52 | L28: =①札幌予測確定!U28 -> 0 | M28: =H28-J28 -> 1281 | N28: =M28+ROUND(L28*前提・入力!$B$37,0) -> 1281 | O28: =③石川以降予測!N51 -> 353 | P28: =N28-O28 -> 928 | Q28: =MAX(0,-P28) -> 0 | R28: =IF(Q28>0,ROUNDUP(Q28*(1+前提・入力!$B$35),0),0) -> 0 | S28: — | U28: =IF(S28="—","—",IF(T28="再生産不可","×再生産不可",_xlfn.IFS(T28-前提・入力!$B$39<0,"★期限超過",T28-前提・入力!$B$39<=30,"★至急(30日以内)",T28-前提・入力!$B$39<=90,"要着手(90日以内)",TRUE(),"余裕あり"))) -> — | V28: =IF(Q28>0,"★欠品：追加生産が必要",IF(P28>=O28*2,"大幅余剰","在庫で充足")) -> 大幅余剰 | W28: 欠品報告あり | X28: 倉庫残1,281個 → ◎倉庫からの追加納品で即対応可能
A29: 23 | B29: 4515142545174 | C29: 呪術廻戦 懐玉・玉折 ブラインドミニ色紙（全5種） | D29: 600 | E29: 3581 | F29: 34189 | G29: 64588 | H29: 51818 | I29: =H29*D29 -> 31090800 | J29: =①札幌予測確定!S29 -> 11000 | K29: =①札幌予測確定!P29 -> 2100 | L29: =①札幌予測確定!U29 -> 8900 | M29: =H29-J29 -> 40818 | N29: =M29+ROUND(L29*前提・入力!$B$37,0) -> 49718 | O29: =③石川以降予測!N52 -> 17991 | P29: =N29-O29 -> 31727 | Q29: =MAX(0,-P29) -> 0 | R29: =IF(Q29>0,ROUNDUP(Q29*(1+前提・入力!$B$35),0),0) -> 0 | S29: — | U29: =IF(S29="—","—",IF(T29="再生産不可","×再生産不可",_xlfn.IFS(T29-前提・入力!$B$39<0,"★期限超過",T29-前提・入力!$B$39<=30,"★至急(30日以内)",T29-前提・入力!$B$39<=90,"要着手(90日以内)",TRUE(),"余裕あり"))) -> — | V29: =IF(Q29>0,"★欠品：追加生産が必要",IF(P29>=O29*2,"大幅余剰","在庫で充足")) -> 在庫で充足
A30: 24 | B30: 4515142545181 | C30: 呪術廻戦 渋谷事変 ブラインドミニ色紙（全5種） | D30: 600 | E30: 0 | F30: 9438 | G30: 39210 | H30: 32204 | I30: =H30*D30 -> 19322400 | J30: =①札幌予測確定!S30 -> 8000 | K30: =①札幌予測確定!P30 -> 1213 | L30: =①札幌予測確定!U30 -> 6787 | M30: =H30-J30 -> 24204 | N30: =M30+ROUND(L30*前提・入力!$B$37,0) -> 30991 | O30: =③石川以降予測!N53 -> 10154 | P30: =N30-O30 -> 20837 | Q30: =MAX(0,-P30) -> 0 | R30: =IF(Q30>0,ROUNDUP(Q30*(1+前提・入力!$B$35),0),0) -> 0 | S30: — | U30: =IF(S30="—","—",IF(T30="再生産不可","×再生産不可",_xlfn.IFS(T30-前提・入力!$B$39<0,"★期限超過",T30-前提・入力!$B$39<=30,"★至急(30日以内)",T30-前提・入力!$B$39<=90,"要着手(90日以内)",TRUE(),"余裕あり"))) -> — | V30: =IF(Q30>0,"★欠品：追加生産が必要",IF(P30>=O30*2,"大幅余剰","在庫で充足")) -> 大幅余剰
A31: 25 | B31: 4515142545198 | C31: 虚式『茈』バスボール | D31: 1500 | E31: 4137 | F31: 3916 | G31: 3748 | H31: 3505 | I31: =H31*D31 -> 5257500 | J31: =①札幌予測確定!S31 -> 200 | K31: =①札幌予測確定!P31 -> 54 | L31: =①札幌予測確定!U31 -> 146 | M31: =H31-J31 -> 3305 | N31: =M31+ROUND(L31*前提・入力!$B$37,0) -> 3451 | O31: =③石川以降予測!N54 -> 409 | P31: =N31-O31 -> 3042 | Q31: =MAX(0,-P31) -> 0 | R31: =IF(Q31>0,ROUNDUP(Q31*(1+前提・入力!$B$35),0),0) -> 0 | S31: — | U31: =IF(S31="—","—",IF(T31="再生産不可","×再生産不可",_xlfn.IFS(T31-前提・入力!$B$39<0,"★期限超過",T31-前提・入力!$B$39<=30,"★至急(30日以内)",T31-前提・入力!$B$39<=90,"要着手(90日以内)",TRUE(),"余裕あり"))) -> — | V31: =IF(Q31>0,"★欠品：追加生産が必要",IF(P31>=O31*2,"大幅余剰","在庫で充足")) -> 大幅余剰
A32: 26 | B32: 4515142545204 | C32: 前髪ヘアバンド | D32: 2200 | E32: 692 | F32: 1784 | G32: 1340 | H32: 497 | I32: =H32*D32 -> 1093400 | J32: =①札幌予測確定!S32 -> 200 | K32: =①札幌予測確定!P32 -> 156 | L32: =①札幌予測確定!U32 -> 44 | M32: =H32-J32 -> 297 | N32: =M32+ROUND(L32*前提・入力!$B$37,0) -> 341 | O32: =③石川以降予測!N55 -> 1270 | P32: =N32-O32 -> -929 | Q32: =MAX(0,-P32) -> 929 | R32: =IF(Q32>0,ROUNDUP(Q32*(1+前提・入力!$B$35),0),0) -> 1022 | S32: 神戸阪急 | T32: =DATE(2026,12,16)-75-前提・入力!$B$38 -> 46283 | U32: =IF(S32="—","—",IF(T32="再生産不可","×再生産不可",_xlfn.IFS(T32-前提・入力!$B$39<0,"★期限超過",T32-前提・入力!$B$39<=30,"★至急(30日以内)",T32-前提・入力!$B$39<=90,"要着手(90日以内)",TRUE(),"余裕あり"))) -> 要着手(90日以内) | V32: =IF(Q32>0,"★欠品：追加生産が必要",IF(P32>=O32*2,"大幅余剰","在庫で充足")) -> ★欠品：追加生産が必要 | W32: 欠品報告あり | X32: 倉庫残297個 → ◎倉庫からの追加納品で即対応可能
A33: 27 | B33: 4515142545211 | C33: 反転術式絆創膏 | D33: 1100 | E33: 1518 | F33: 1413 | G33: 1343 | H33: 1198 | I33: =H33*D33 -> 1317800 | J33: =①札幌予測確定!S33 -> 70 | K33: =①札幌予測確定!P33 -> 40 | L33: =①札幌予測確定!U33 -> 30 | M33: =H33-J33 -> 1128 | N33: =M33+ROUND(L33*前提・入力!$B$37,0) -> 1158 | O33: =③石川以降予測!N56 -> 279 | P33: =N33-O33 -> 879 | Q33: =MAX(0,-P33) -> 0 | R33: =IF(Q33>0,ROUNDUP(Q33*(1+前提・入力!$B$35),0),0) -> 0 | S33: — | U33: =IF(S33="—","—",IF(T33="再生産不可","×再生産不可",_xlfn.IFS(T33-前提・入力!$B$39<0,"★期限超過",T33-前提・入力!$B$39<=30,"★至急(30日以内)",T33-前提・入力!$B$39<=90,"要着手(90日以内)",TRUE(),"余裕あり"))) -> — | V33: =IF(Q33>0,"★欠品：追加生産が必要",IF(P33>=O33*2,"大幅余剰","在庫で充足")) -> 大幅余剰
A34: 28 | B34: 4515142545228 | C34: 宿儺の指風お菓子 | D34: 1800 | E34: 440 | F34: 1193 | G34: 860 | H34: 460 | I34: =H34*D34 -> 828000 | J34: =①札幌予測確定!S34 -> 300 | K34: =①札幌予測確定!P34 -> 216 | L34: =①札幌予測確定!U34 -> 84 | M34: =H34-J34 -> 160 | N34: =M34+ROUND(L34*前提・入力!$B$37,0) -> 244 | O34: =③石川以降予測!N57 -> 1267 | P34: =N34-O34+1200 -> 177 | Q34: =MAX(0,-P34) -> 0 | R34: =IF(Q34>0,ROUNDUP(Q34*(1+前提・入力!$B$35),0),0) -> 0 | S34: — | U34: ◎発注確定済 | V34: =IF(Q34>0,"★欠品：追加生産が必要",IF(P34>=O34*2,"大幅余剰","在庫で充足")) -> 在庫で充足 | W34: 欠品報告あり | X34: ◎追加発注 確定済 1,200SET（仙台 Ebeans入荷）を過不足に加算済／ミニマム1,200〜1,500SET（12,000〜15,000本） ／ 【賞味期限】賞味期限4か月以内は販売不可。現在庫は金沢(石川)会場までは賞味期限OK。残すと廃棄になるため石川会期内での売り切りを目標にする ／ 倉庫残160個 → ◎倉庫からの追加納品で即対応可能 ／ SET商品（1販売単位＝10個）。台帳の発注数はバラ単位
A35: 29 | B35: 4515142545235 | C35: 脱兎！ポーチ入りクリップセット | D35: 1500 | E35: 1190 | F35: 870 | G35: 620 | H35: 420 | I35: =H35*D35 -> 630000 | J35: =①札幌予測確定!S35 -> 160 | K35: =①札幌予測確定!P35 -> 107 | L35: =①札幌予測確定!U35 -> 53 | M35: =H35-J35 -> 260 | N35: =M35+ROUND(L35*前提・入力!$B$37,0) -> 313 | O35: =③石川以降予測!N58 -> 629 | P35: =N35-O35 -> -316 | Q35: =MAX(0,-P35) -> 316 | R35: =IF(Q35>0,ROUNDUP(Q35*(1+前提・入力!$B$35),0),0) -> 348 | S35: 東京凱旋 東京建物ぴあホール | T35: =DATE(2027,4,1)-90-前提・入力!$B$38 -> 46374 | U35: =IF(S35="—","—",IF(T35="再生産不可","×再生産不可",_xlfn.IFS(T35-前提・入力!$B$39<0,"★期限超過",T35-前提・入力!$B$39<=30,"★至急(30日以内)",T35-前提・入力!$B$39<=90,"要着手(90日以内)",TRUE(),"余裕あり"))) -> 余裕あり | V35: =IF(Q35>0,"★欠品：追加生産が必要",IF(P35>=O35*2,"大幅余剰","在庫で充足")) -> ★欠品：追加生産が必要 | W35: 欠品報告あり | X35: 倉庫残260個 → ◎倉庫からの追加納品で即対応可能
A36: 30 | B36: 4515142545242 | C36: 釘崎のポーチ風エコバッグ | D36: 3300 | E36: 1364 | F36: 1193 | G36: 1103 | H36: 898 | I36: =H36*D36 -> 2963400 | J36: =①札幌予測確定!S36 -> 250 | K36: =①札幌予測確定!P36 -> 63 | L36: =①札幌予測確定!U36 -> 187 | M36: =H36-J36 -> 648 | N36: =M36+ROUND(L36*前提・入力!$B$37,0) -> 835 | O36: =③石川以降予測!N59 -> 425 | P36: =N36-O36 -> 410 | Q36: =MAX(0,-P36) -> 0 | R36: =IF(Q36>0,ROUNDUP(Q36*(1+前提・入力!$B$35),0),0) -> 0 | S36: — | U36: =IF(S36="—","—",IF(T36="再生産不可","×再生産不可",_xlfn.IFS(T36-前提・入力!$B$39<0,"★期限超過",T36-前提・入力!$B$39<=30,"★至急(30日以内)",T36-前提・入力!$B$39<=90,"要着手(90日以内)",TRUE(),"余裕あり"))) -> — | V36: =IF(Q36>0,"★欠品：追加生産が必要",IF(P36>=O36*2,"大幅余剰","在庫で充足")) -> 在庫で充足
A37: 31 | B37: 4515142545259 | C37: 半年分の情報が書き込める手帳 | D37: 1300 | E37: 1769 | F37: 1533 | G37: 1353 | H37: 926 | I37: =H37*D37 -> 1203800 | J37: =①札幌予測確定!S37 -> 200 | K37: =①札幌予測確定!P37 -> 87 | L37: =①札幌予測確定!U37 -> 113 | M37: =H37-J37 -> 726 | N37: =M37+ROUND(L37*前提・入力!$B$37,0) -> 839 | O37: =③石川以降予測!N60 -> 681 | P37: =N37-O37 -> 158 | Q37: =MAX(0,-P37) -> 0 | R37: =IF(Q37>0,ROUNDUP(Q37*(1+前提・入力!$B$35),0),0) -> 0 | S37: — | U37: =IF(S37="—","—",IF(T37="再生産不可","×再生産不可",_xlfn.IFS(T37-前提・入力!$B$39<0,"★期限超過",T37-前提・入力!$B$39<=30,"★至急(30日以内)",T37-前提・入力!$B$39<=90,"要着手(90日以内)",TRUE(),"余裕あり"))) -> — | V37: =IF(Q37>0,"★欠品：追加生産が必要",IF(P37>=O37*2,"大幅余剰","在庫で充足")) -> 在庫で充足
A38: 32 | B38: 4515142545266 | C38: 気分リフレッシュオルゴール | D38: 8800 | E38: 38 | F38: 102 | G38: 73 | H38: 33 | I38: =H38*D38 -> 290400 | J38: =①札幌予測確定!S38 -> 10 | K38: =①札幌予測確定!P38 -> 10 | L38: =①札幌予測確定!U38 -> 0 | M38: =H38-J38 -> 23 | N38: =M38+ROUND(L38*前提・入力!$B$37,0) -> 23 | O38: =③石川以降予測!N61 -> 72 | P38: =N38-O38 -> -49 | Q38: =MAX(0,-P38) -> 49 | R38: =IF(Q38>0,ROUNDUP(Q38*(1+前提・入力!$B$35),0),0) -> 54 | S38: 神戸阪急 | T38: =DATE(2026,12,16)-90-前提・入力!$B$38 -> 46268 | U38: =IF(S38="—","—",IF(T38="再生産不可","×再生産不可",_xlfn.IFS(T38-前提・入力!$B$39<0,"★期限超過",T38-前提・入力!$B$39<=30,"★至急(30日以内)",T38-前提・入力!$B$39<=90,"要着手(90日以内)",TRUE(),"余裕あり"))) -> 要着手(90日以内) | V38: =IF(Q38>0,"★欠品：追加生産が必要",IF(P38>=O38*2,"大幅余剰","在庫で充足")) -> ★欠品：追加生産が必要 | W38: 欠品報告あり | X38: 倉庫残23個 → ◎倉庫からの追加納品で即対応可能 ／ ★「追納困難」との回答だが実在庫23個あり。出荷可否を要再確認
A39: 33 | B39: 4515142545273 | C39: 五条 悟 イメージリング（#11） | D39: 27500 | E39: 13 | F39: 141 | G39: 127 | H39: 106 | I39: =H39*D39 -> 2915000 | J39: =①札幌予測確定!S39 -> 15 | K39: =①札幌予測確定!P39 -> 0 | L39: =①札幌予測確定!U39 -> 15 | M39: =H39-J39 -> 91 | N39: =M39+ROUND(L39*前提・入力!$B$37,0) -> 106 | O39: =③石川以降予測!N62 -> 14 | P39: =N39-O39 -> 92 | Q39: =MAX(0,-P39) -> 0 | R39: =IF(Q39>0,ROUNDUP(Q39*(1+前提・入力!$B$35),0),0) -> 0 | S39: — | U39: =IF(S39="—","—",IF(T39="再生産不可","×再生産不可",_xlfn.IFS(T39-前提・入力!$B$39<0,"★期限超過",T39-前提・入力!$B$39<=30,"★至急(30日以内)",T39-前提・入力!$B$39<=90,"要着手(90日以内)",TRUE(),"余裕あり"))) -> — | V39: =IF(Q39>0,"★欠品：追加生産が必要",IF(P39>=O39*2,"大幅余剰","在庫で充足")) -> 大幅余剰
A40: 34 | B40: 4515142545280 | C40: 五条 悟 イメージリング（#13） | D40: 27500 | E40: 13 | F40: 10 | G40: 7 | H40: 4 | I40: =H40*D40 -> 110000 | J40: =①札幌予測確定!S40 -> 2 | K40: =①札幌予測確定!P40 -> 1 | L40: =①札幌予測確定!U40 -> 1 | M40: =H40-J40 -> 2 | N40: =M40+ROUND(L40*前提・入力!$B$37,0) -> 3 | O40: =③石川以降予測!N63 -> 7 | P40: =N40-O40 -> -4 | Q40: =MAX(0,-P40) -> 4 | R40: =IF(Q40>0,ROUNDUP(Q40*(1+前提・入力!$B$35),0),0) -> 5 | S40: 鳥取島根 夢みなとタワー | T40: =DATE(2027,3,15)-90-前提・入力!$B$38 -> 46357 | U40: =IF(S40="—","—",IF(T40="再生産不可","×再生産不可",_xlfn.IFS(T40-前提・入力!$B$39<0,"★期限超過",T40-前提・入力!$B$39<=30,"★至急(30日以内)",T40-前提・入力!$B$39<=90,"要着手(90日以内)",TRUE(),"余裕あり"))) -> 余裕あり | V40: =IF(Q40>0,"★欠品：追加生産が必要",IF(P40>=O40*2,"大幅余剰","在庫で充足")) -> ★欠品：追加生産が必要
A41: 35 | B41: 4515142545297 | C41: 五条 悟 イメージリング（#15） | D41: 27500 | E41: 13 | F41: 10 | G41: 7 | H41: 4 | I41: =H41*D41 -> 110000 | J41: =①札幌予測確定!S41 -> 2 | K41: =①札幌予測確定!P41 -> 0 | L41: =①札幌予測確定!U41 -> 2 | M41: =H41-J41 -> 2 | N41: =M41+ROUND(L41*前提・入力!$B$37,0) -> 4 | O41: =③石川以降予測!N64 -> 1 | P41: =N41-O41 -> 3 | Q41: =MAX(0,-P41) -> 0 | R41: =IF(Q41>0,ROUNDUP(Q41*(1+前提・入力!$B$35),0),0) -> 0 | S41: — | U41: =IF(S41="—","—",IF(T41="再生産不可","×再生産不可",_xlfn.IFS(T41-前提・入力!$B$39<0,"★期限超過",T41-前提・入力!$B$39<=30,"★至急(30日以内)",T41-前提・入力!$B$39<=90,"要着手(90日以内)",TRUE(),"余裕あり"))) -> — | V41: =IF(Q41>0,"★欠品：追加生産が必要",IF(P41>=O41*2,"大幅余剰","在庫で充足")) -> 大幅余剰
A42: 36 | B42: 4515142545303 | C42: 五条 悟 イメージリング（#17） | D42: 27500 | E42: 13 | F42: 10 | G42: 7 | H42: 4 | I42: =H42*D42 -> 110000 | J42: =①札幌予測確定!S42 -> 2 | K42: =①札幌予測確定!P42 -> 0 | L42: =①札幌予測確定!U42 -> 2 | M42: =H42-J42 -> 2 | N42: =M42+ROUND(L42*前提・入力!$B$37,0) -> 4 | O42: =③石川以降予測!N65 -> 1 | P42: =N42-O42 -> 3 | Q42: =MAX(0,-P42) -> 0 | R42: =IF(Q42>0,ROUNDUP(Q42*(1+前提・入力!$B$35),0),0) -> 0 | S42: — | U42: =IF(S42="—","—",IF(T42="再生産不可","×再生産不可",_xlfn.IFS(T42-前提・入力!$B$39<0,"★期限超過",T42-前提・入力!$B$39<=30,"★至急(30日以内)",T42-前提・入力!$B$39<=90,"要着手(90日以内)",TRUE(),"余裕あり"))) -> — | V42: =IF(Q42>0,"★欠品：追加生産が必要",IF(P42>=O42*2,"大幅余剰","在庫で充足")) -> 大幅余剰
A43: 37 | B43: 4515142545310 | C43: 夏油 傑 イメージリング（#11） | D43: 27500 | E43: 13 | F43: 81 | G43: 69 | H43: 43 | I43: =H43*D43 -> 1182500 | J43: =①札幌予測確定!S43 -> 8 | K43: =①札幌予測確定!P43 -> 0 | L43: =①札幌予測確定!U43 -> 8 | M43: =H43-J43 -> 35 | N43: =M43+ROUND(L43*前提・入力!$B$37,0) -> 43 | O43: =③石川以降予測!N66 -> 17 | P43: =N43-O43 -> 26 | Q43: =MAX(0,-P43) -> 0 | R43: =IF(Q43>0,ROUNDUP(Q43*(1+前提・入力!$B$35),0),0) -> 0 | S43: — | U43: =IF(S43="—","—",IF(T43="再生産不可","×再生産不可",_xlfn.IFS(T43-前提・入力!$B$39<0,"★期限超過",T43-前提・入力!$B$39<=30,"★至急(30日以内)",T43-前提・入力!$B$39<=90,"要着手(90日以内)",TRUE(),"余裕あり"))) -> — | V43: =IF(Q43>0,"★欠品：追加生産が必要",IF(P43>=O43*2,"大幅余剰","在庫で充足")) -> 在庫で充足
A44: 38 | B44: 4515142545327 | C44: 夏油 傑 イメージリング（#13） | D44: 27500 | E44: 13 | F44: 10 | G44: 7 | H44: 4 | I44: =H44*D44 -> 110000 | J44: =①札幌予測確定!S44 -> 2 | K44: =①札幌予測確定!P44 -> 2 | L44: =①札幌予測確定!U44 -> 0 | M44: =H44-J44 -> 2 | N44: =M44+ROUND(L44*前提・入力!$B$37,0) -> 2 | O44: =③石川以降予測!N67 -> 11 | P44: =N44-O44 -> -9 | Q44: =MAX(0,-P44) -> 9 | R44: =IF(Q44>0,ROUNDUP(Q44*(1+前提・入力!$B$35),0),0) -> 10 | S44: 仙台 Ebeans | T44: =DATE(2026,9,5)-90-前提・入力!$B$38 -> 46166 | U44: =IF(S44="—","—",IF(T44="再生産不可","×再生産不可",_xlfn.IFS(T44-前提・入力!$B$39<0,"★期限超過",T44-前提・入力!$B$39<=30,"★至急(30日以内)",T44-前提・入力!$B$39<=90,"要着手(90日以内)",TRUE(),"余裕あり"))) -> ★期限超過 | V44: =IF(Q44>0,"★欠品：追加生産が必要",IF(P44>=O44*2,"大幅余剰","在庫で充足")) -> ★欠品：追加生産が必要
A45: 39 | B45: 4515142545334 | C45: 夏油 傑 イメージリング（#15） | D45: 27500 | E45: 13 | F45: 10 | G45: 8 | H45: 5 | I45: =H45*D45 -> 137500 | J45: =①札幌予測確定!S45 -> 2 | K45: =①札幌予測確定!P45 -> 1 | L45: =①札幌予測確定!U45 -> 1 | M45: =H45-J45 -> 3 | N45: =M45+ROUND(L45*前提・入力!$B$37,0) -> 4 | O45: =③石川以降予測!N68 -> 7 | P45: =N45-O45 -> -3 | Q45: =MAX(0,-P45) -> 3 | R45: =IF(Q45>0,ROUNDUP(Q45*(1+前提・入力!$B$35),0),0) -> 4 | S45: 東京凱旋 東京建物ぴあホール | T45: =DATE(2027,4,1)-90-前提・入力!$B$38 -> 46374 | U45: =IF(S45="—","—",IF(T45="再生産不可","×再生産不可",_xlfn.IFS(T45-前提・入力!$B$39<0,"★期限超過",T45-前提・入力!$B$39<=30,"★至急(30日以内)",T45-前提・入力!$B$39<=90,"要着手(90日以内)",TRUE(),"余裕あり"))) -> 余裕あり | V45: =IF(Q45>0,"★欠品：追加生産が必要",IF(P45>=O45*2,"大幅余剰","在庫で充足")) -> ★欠品：追加生産が必要
A46: 40 | B46: 4515142545341 | C46: 夏油 傑 イメージリング（#17） | D46: 27500 | E46: 13 | F46: 10 | G46: 7 | H46: 4 | I46: =H46*D46 -> 110000 | J46: =①札幌予測確定!S46 -> 2 | K46: =①札幌予測確定!P46 -> 0 | L46: =①札幌予測確定!U46 -> 2 | M46: =H46-J46 -> 2 | N46: =M46+ROUND(L46*前提・入力!$B$37,0) -> 4 | O46: =③石川以降予測!N69 -> 1 | P46: =N46-O46 -> 3 | Q46: =MAX(0,-P46) -> 0 | R46: =IF(Q46>0,ROUNDUP(Q46*(1+前提・入力!$B$35),0),0) -> 0 | S46: — | U46: =IF(S46="—","—",IF(T46="再生産不可","×再生産不可",_xlfn.IFS(T46-前提・入力!$B$39<0,"★期限超過",T46-前提・入力!$B$39<=30,"★至急(30日以内)",T46-前提・入力!$B$39<=90,"要着手(90日以内)",TRUE(),"余裕あり"))) -> — | V46: =IF(Q46>0,"★欠品：追加生産が必要",IF(P46>=O46*2,"大幅余剰","在庫で充足")) -> 大幅余剰
A47: 41 | B47: 4515142545358 | C47: 虎杖 悠仁 イメージフラグメントケース | D47: 25000 | E47: 81 | F47: 76 | G47: 75 | H47: 74 | I47: =H47*D47 -> 1850000 | J47: =①札幌予測確定!S47 -> 4 | K47: =①札幌予測確定!P47 -> 0 | L47: =①札幌予測確定!U47 -> 4 | M47: =H47-J47 -> 70 | N47: =M47+ROUND(L47*前提・入力!$B$37,0) -> 74 | O47: =③石川以降予測!N70 -> 1 | P47: =N47-O47 -> 73 | Q47: =MAX(0,-P47) -> 0 | R47: =IF(Q47>0,ROUNDUP(Q47*(1+前提・入力!$B$35),0),0) -> 0 | S47: — | U47: =IF(S47="—","—",IF(T47="再生産不可","×再生産不可",_xlfn.IFS(T47-前提・入力!$B$39<0,"★期限超過",T47-前提・入力!$B$39<=30,"★至急(30日以内)",T47-前提・入力!$B$39<=90,"要着手(90日以内)",TRUE(),"余裕あり"))) -> — | V47: =IF(Q47>0,"★欠品：追加生産が必要",IF(P47>=O47*2,"大幅余剰","在庫で充足")) -> 大幅余剰
A48: 42 | B48: 4515142545365 | C48: 伏黒 恵 イメージフラグメントケース | D48: 25000 | E48: 69 | F48: 61 | G48: 58 | H48: 49 | I48: =H48*D48 -> 1225000 | J48: =①札幌予測確定!S48 -> 6 | K48: =①札幌予測確定!P48 -> 2 | L48: =①札幌予測確定!U48 -> 4 | M48: =H48-J48 -> 43 | N48: =M48+ROUND(L48*前提・入力!$B$37,0) -> 47 | O48: =③石川以降予測!N71 -> 15 | P48: =N48-O48 -> 32 | Q48: =MAX(0,-P48) -> 0 | R48: =IF(Q48>0,ROUNDUP(Q48*(1+前提・入力!$B$35),0),0) -> 0 | S48: — | U48: =IF(S48="—","—",IF(T48="再生産不可","×再生産不可",_xlfn.IFS(T48-前提・入力!$B$39<0,"★期限超過",T48-前提・入力!$B$39<=30,"★至急(30日以内)",T48-前提・入力!$B$39<=90,"要着手(90日以内)",TRUE(),"余裕あり"))) -> — | V48: =IF(Q48>0,"★欠品：追加生産が必要",IF(P48>=O48*2,"大幅余剰","在庫で充足")) -> 大幅余剰
C49: 合計（LEGS 42SKU） | E49: =SUM(E7:E48) -> 102310 | F49: =SUM(F7:F48) -> 158693 | G49: =SUM(G7:G48) -> 338784 | H49: =SUM(H7:H48) -> 274688 | I49: =SUM(I7:I48) -> 216459500 | J49: =SUM(J7:J48) -> 50506 | K49: =SUM(K7:K48) -> 8740 | L49: =SUM(L7:L48) -> 41768 | ... R49: =SUM(R7:R48) -> 2812 | U49: =COUNTIF(U7:U48,"★期限超過")&"品目が期限超過" -> 1品目が期限超過 | V49: =COUNTIF(V7:V48,"★欠品：追加生産が必要")&"品目が欠品" -> 8品目が欠品 | W49: =COUNTIF(W7:W48,"<>")&"品目" -> 8品目

Sheet ⑨過去4会場 予測vs実績
A1: ⑨ 過去4会場（①池袋・②名古屋・③博多阪急・④梅田阪急）商品別 販売予測 vs 実績販売・構成比の修正
A2: 販売予測＝各会場の「初6日実績 × 会期倍率g」。gはその時点で判明していた過去会場のみから算出（直近会場を2倍加重）。池袋は初回会場のため予測不能で、投入数（販売可能数）を計画値として表示
A3: 予測時構成比＝予測販売数のLEGS42SKU内シェア（池袋は投入数シェア）／実績構成比＝実績販売数のシェア／構成比修正＝実績構成比 − 予測時構成比（ポイント）
A4: 会期日数が異なるため、過去会場の累計は博多26日間の日次消化カーブで対象会場の会期日数に換算している／名古屋の販売可能数は元データに小数値が含まれるため整数に丸めている（3品目）
A6: ■ 会場別 予測精度サマリー（LEGS 42SKU 合計）
A7: 会場 | B7: 会期日数 | C7: 参照した過去会場（加重） | D7: 会期倍率g | E7: 投入数 (販売可能数) | F7: モデル 予測販売数 | G7: 実績 販売数 | H7: 予測誤差 (実績−予測) | I7: 誤差率 | J7: 商品別 絶対誤差率 | K7: 消化率 (実績/投入) | L7: 評価
A8: 東京 | B8: 25 | C8: —（初回会場） | E8: 211152 | G8: 148185 | K8: =IFERROR(G8/E8,0) -> 0.70179302 | L8: 初回会場。予測モデルの参照元が無いため投入数のみ
A9: 名古屋 | B9: 19 | C9: 東京×2 | D9: 1.5422133 | E9: 83271 | F9: 59078 | G9: 58600 | H9: =G9-F9 -> -478 | I9: =IFERROR(-H9/G9,"") -> 0.0081569966 | J9: 0.062525597 | K9: =IFERROR(G9/E9,0) -> 0.70372639 | L9: 池袋のみを参照。実績が予測を上回り、やや保守的な予測だった
A10: 博多 | B10: 26 | C10: 東京×1・名古屋×2 | D10: 2.0315901 | E10: 49598 | F10: 32081 | G10: 44871 | H10: =G10-F10 -> 12790 | I10: =IFERROR(-H10/G10,"") -> -0.28503933 | J10: 0.31503644 | K10: =IFERROR(G10/E10,0) -> 0.90469374 | L10: 26日間の長期会期で後半にブラインド系が伸び、予測を大きく上回った
A11: 大阪 | B11: 20 | C11: 東京×1・名古屋×1・博多×2 | D11: 1.8448079 | E11: 137560 | F11: 71190 | G11: 63740 | H11: =G11-F11 -> -7450 | I11: =IFERROR(-H11/G11,"") -> 0.11688108 | J11: 0.14028867 | K11: =IFERROR(G11/E11,0) -> 0.46336144 | L11: 博多の高い伸長率を引き継いだため予測が上振れ。新商品106SKU投入でLEGSが想定より抑制された
A12: 4会場 合計 | E12: =SUM(E8:E11) -> 481581 | F12: =SUM(F8:F11) -> 162349 | G12: =SUM(G8:G11) -> 315396 | H12: =G12-F12 -> 153047 | I12: =IFERROR(-H12/G12,"") -> -0.48525346 | K12: =IFERROR(G12/E12,0) -> 0.65491786 | L12: 池袋は予測対象外のため、予測計・誤差は名古屋以降3会場の合計
A14: ■ 商品別 予測 vs 実績・構成比の修正
A15: No. | B15: JAN | C15: 商品名 | D15: 税込単価 | E15: 東京 投入数 | F15: 東京 予測販売数 | G15: 東京 実績販売数 | H15: 東京 予測誤差 | I15: 東京 予測時構成比 | J15: 東京 実績構成比 | K15: 東京 構成比修正 | L15: 名古屋 投入数 | M15: 名古屋 予測販売数 | N15: 名古屋 実績販売数 | O15: 名古屋 予測誤差 | P15: 名古屋 予測時構成比 | Q15: 名古屋 実績構成比 | R15: 名古屋 構成比修正 | S15: 博多 投入数 | T15: 博多 予測販売数 | U15: 博多 実績販売数 | V15: 博多 予測誤差 | W15: 博多 予測時構成比 | X15: 博多 実績構成比 | Y15: 博多 構成比修正 | Z15: 大阪 投入数 | AA15: 大阪 予測販売数 | AB15: 大阪 実績販売数 | AC15: 大阪 予測誤差 | AD15: 大阪 予測時構成比 | AE15: 大阪 実績構成比 | AF15: 大阪 構成比修正 | AG15: 4会場 実績合計 | AH15: 4会場 実績構成比 | AI15: 札幌 予測構成比 | AJ15: 石川以降 適用構成比 | AK15: 構成比トレンド
A16: 1 | B16: 4515142545082 | C16: 呪術廻戦 メタリックポストカード 展示会キービジュアル | D16: 500 | E16: 6000 | F16: — | G16: 4965 | H16: — | I16: =IFERROR(E16/E$58,0) -> 0.028415549 | J16: =IFERROR(G16/G$58,0) -> 0.033505416 | K16: =J16-I16 -> 0.0050898665 | L16: 1998 | M16: 974 | N16: 1316 | O16: =N16-M16 -> 342 | P16: =IFERROR(M16/M$58,0) -> 0.016486679 | Q16: =IFERROR(N16/N$58,0) -> 0.022457338 | R16: =Q16-P16 -> 0.0059706593 | S16: 1099 | T16: 1177 | U16: 1092 | V16: =U16-T16 -> -85 | W16: =IFERROR(T16/T$58,0) -> 0.036688383 | X16: =IFERROR(U16/U$58,0) -> 0.024336431 | Y16: =X16-W16 -> -0.012351951 | Z16: 3000 | AA16: 2097 | AB16: 2325 | AC16: =AB16-AA16 -> 228 | AD16: =IFERROR(AA16/AA$58,0) -> 0.029456384 | AE16: =IFERROR(AB16/AB$58,0) -> 0.03647631 | AF16: =AE16-AD16 -> 0.0070199257 | AG16: =G16+N16+U16+AB16 -> 9698 | AH16: =IFERROR(AG16/AG$58,0) -> 0.030748646 | AI16: =①札幌予測確定!R7 -> 0.053432494 | AJ16: =③石川以降予測!H30 -> 0.044954402 | AK16: =IF(AJ16-AH16>=0.005,"↑ 上方修正",IF(AJ16-AH16<=-0.005,"↓ 下方修正","→ 据置")) -> ↑ 上方修正
A17: 2 | B17: 4515142545099 | C17: 呪術廻戦 クリアファイル 展示会キービジュアル | D17: 600 | E17: 5699 | F17: — | G17: 4902 | H17: — | I17: =IFERROR(E17/E$58,0) -> 0.026990036 | J17: =IFERROR(G17/G$58,0) -> 0.033080271 | K17: =J17-I17 -> 0.0060902357 | L17: 1999 | M17: 1402 | N17: 1466 | O17: =N17-M17 -> 64 | P17: =IFERROR(M17/M$58,0) -> 0.023731338 | Q17: =IFERROR(N17/N$58,0) -> 0.025017065 | R17: =Q17-P17 -> 0.0012857266 | S17: 1200 | T17: 1167 | U17: 1132 | V17: =U17-T17 -> -35 | W17: =IFERROR(T17/T$58,0) -> 0.036376672 | X17: =IFERROR(U17/U$58,0) -> 0.025227875 | Y17: =X17-W17 -> -0.011148796 | Z17: 3000 | AA17: 2085 | AB17: 1965 | AC17: =AB17-AA17 -> -120 | AD17: =IFERROR(AA17/AA$58,0) -> 0.029287821 | AE17: =IFERROR(AB17/AB$58,0) -> 0.030828365 | AF17: =AE17-AD17 -> 0.0015405439 | AG17: =G17+N17+U17+AB17 -> 9465 | AH17: =IFERROR(AG17/AG$58,0) -> 0.030009892 | AI17: =①札幌予測確定!R8 -> 0.058237986 | AJ17: =③石川以降予測!H31 -> 0.044533176 | AK17: =IF(AJ17-AH17>=0.005,"↑ 上方修正",IF(AJ17-AH17<=-0.005,"↓ 下方修正","→ 据置")) -> ↑ 上方修正
A18: 3 | B18: 4515142545105 | C18: 呪術廻戦 懐玉・玉折 ポストカードセット（5枚入） | D18: 1000 | E18: 3700 | F18: — | G18: 2956 | H18: — | I18: =IFERROR(E18/E$58,0) -> 0.017522922 | J18: =IFERROR(G18/G$58,0) -> 0.019948038 | K18: =J18-I18 -> 0.002425116 | L18: 1200 | M18: 636 | N18: 601 | O18: =N18-M18 -> -35 | P18: =IFERROR(M18/M$58,0) -> 0.010765429 | Q18: =IFERROR(N18/N$58,0) -> 0.010255973 | R18: =Q18-P18 -> -0.00050945606 | S18: 500 | T18: 412 | U18: 454 | V18: =U18-T18 -> 42 | W18: =IFERROR(T18/T$58,0) -> 0.012842492 | X18: =IFERROR(U18/U$58,0) -> 0.010117894 | Y18: =X18-W18 -> -0.0027245989 | Z18: 2000 | AA18: 1162 | AB18: 1132 | AC18: =AB18-AA18 -> -30 | AD18: =IFERROR(AA18/AA$58,0) -> 0.016322517 | AE18: =IFERROR(AB18/AB$58,0) -> 0.017759649 | AF18: =AE18-AD18 -> 0.0014371314 | AG18: =G18+N18+U18+AB18 -> 5143 | AH18: =IFERROR(AG18/AG$58,0) -> 0.016306485 | AI18: =①札幌予測確定!R9 -> 0.018649886 | AJ18: =③石川以降予測!H32 -> 0.018204767 | AK18: =IF(AJ18-AH18>=0.005,"↑ 上方修正",IF(AJ18-AH18<=-0.005,"↓ 下方修正","→ 据置")) -> → 据置
A19: 4 | B19: 4515142545112 | C19: 呪術廻戦 渋谷事変 ポストカードセット（9枚入） | D19: 1800 | E19: 2620 | F19: — | G19: 1819 | H19: — | I19: =IFERROR(E19/E$58,0) -> 0.012408123 | J19: =IFERROR(G19/G$58,0) -> 0.012275197 | K19: =J19-I19 -> -0.00013292651 | L19: 1330 | M19: 666 | N19: 922 | O19: =N19-M19 -> 256 | P19: =IFERROR(M19/M$58,0) -> 0.011273232 | Q19: =IFERROR(N19/N$58,0) -> 0.015733788 | R19: =Q19-P19 -> 0.0044605564 | S19: 800 | T19: 523 | U19: 539 | V19: =U19-T19 -> 16 | W19: =IFERROR(T19/T$58,0) -> 0.016302484 | X19: =IFERROR(U19/U$58,0) -> 0.012012213 | Y19: =X19-W19 -> -0.0042902715 | Z19: 2000 | AA19: 1102 | AB19: 1310 | AC19: =AB19-AA19 -> 208 | AD19: =IFERROR(AA19/AA$58,0) -> 0.015479702 | AE19: =IFERROR(AB19/AB$58,0) -> 0.020552243 | AF19: =AE19-AD19 -> 0.0050725413 | AG19: =G19+N19+U19+AB19 -> 4590 | AH19: =IFERROR(AG19/AG$58,0) -> 0.014553133 | AI19: =①札幌予測確定!R10 -> 0.026201373 | AJ19: =③石川以降予測!H33 -> 0.023376808 | AK19: =IF(AJ19-AH19>=0.005,"↑ 上方修正",IF(AJ19-AH19<=-0.005,"↓ 下方修正","→ 据置")) -> ↑ 上方修正
A20: 5 | B20: 4515142545129 | C20: 呪術廻戦 懐玉・玉折 ブラインド缶バッジ（全5種） | D20: 600 | E20: 24996 | F20: — | G20: 18759 | H20: — | I20: =IFERROR(E20/E$58,0) -> 0.11837918 | J20: =IFERROR(G20/G$58,0) -> 0.12659176 | K20: =J20-I20 -> 0.0082125832 | L20: 16500 | M20: 10892 | N20: 10777 | O20: =N20-M20 -> -115 | P20: =IFERROR(M20/M$58,0) -> 0.18436643 | Q20: =IFERROR(N20/N$58,0) -> 0.18390785 | R20: =Q20-P20 -> -0.00045858099 | S20: 9000 | T20: 5230 | U20: 8991 | V20: =U20-T20 -> 3761 | W20: =IFERROR(T20/T$58,0) -> 0.16302484 | X20: =IFERROR(U20/U$58,0) -> 0.20037441 | Y20: =X20-W20 -> 0.037349563 | Z20: 24996 | AA20: 12602 | AB20: 8936 | AC20: =AB20-AA20 -> -3666 | AD20: =IFERROR(AA20/AA$58,0) -> 0.17701924 | AE20: =IFERROR(AB20/AB$58,0) -> 0.14019454 | AF20: =AE20-AD20 -> -0.036824704 | AG20: =G20+N20+U20+AB20 -> 47463 | AH20: =IFERROR(AG20/AG$58,0) -> 0.15048701 | AI20: =①札幌予測確定!R11 -> 0.053203661 | AJ20: =③石川以降予測!H34 -> 0.096699101 | AK20: =IF(AJ20-AH20>=0.005,"↑ 上方修正",IF(AJ20-AH20<=-0.005,"↓ 下方修正","→ 据置")) -> ↓ 下方修正
A21: 6 | B21: 4515142545136 | C21: 呪術廻戦 渋谷事変 ブラインド缶バッジ（全9種） | D21: 600 | E21: 44999 | F21: — | G21: 31070 | H21: — | I21: =IFERROR(E21/E$58,0) -> 0.21311188 | J21: =IFERROR(G21/G$58,0) -> 0.20967034 | K21: =J21-I21 -> -0.003441537 | L21: 21439 | M21: 15582 | N21: 15602 | O21: =N21-M21 -> 20 | P21: =IFERROR(M21/M$58,0) -> 0.263753 | Q21: =IFERROR(N21/N$58,0) -> 0.26624573 | R21: =Q21-P21 -> 0.0024927293 | S21: 13986 | T21: 7088 | U21: 13877 | V21: =U21-T21 -> 6789 | W21: =IFERROR(T21/T$58,0) -> 0.22094074 | X21: =IFERROR(U21/U$58,0) -> 0.30926434 | Y21: =X21-W21 -> 0.088323592 | Z21: 35999 | AA21: 20543 | AB21: 18611 | AC21: =AB21-AA21 -> -1932 | AD21: =IFERROR(AA21/AA$58,0) -> 0.28856581 | AE21: =IFERROR(AB21/AB$58,0) -> 0.29198306 | AF21: =AE21-AD21 -> 0.0034172464 | AG21: =G21+N21+U21+AB21 -> 79160 | AH21: =IFERROR(AG21/AG$58,0) -> 0.25098606 | AI21: =①札幌予測確定!R12 -> 0.1506865 | AJ21: =③石川以降予測!H35 -> 0.22133478 | AK21: =IF(AJ21-AH21>=0.005,"↑ 上方修正",IF(AJ21-AH21<=-0.005,"↓ 下方修正","→ 据置")) -> ↓ 下方修正
A22: 7 | B22: 4515142545143 | C22: 呪術廻戦 懐玉・玉折 ブラインドダイカットステッカー（全5種） | D22: 600 | E22: 7000 | F22: — | G22: 3471 | H22: — | I22: =IFERROR(E22/E$58,0) -> 0.033151474 | J22: =IFERROR(G22/G$58,0) -> 0.023423423 | K22: =J22-I22 -> -0.0097280504 | L22: 1390 | M22: 526 | N22: 520 | O22: =N22-M22 -> -6 | P22: =IFERROR(M22/M$58,0) -> 0.0089034835 | Q22: =IFERROR(N22/N$58,0) -> 0.0088737201 | R22: =Q22-P22 -> -2.9763394e-05 | S22: 400 | T22: 474 | U22: 384 | V22: =U22-T22 -> -90 | W22: =IFERROR(T22/T$58,0) -> 0.014775101 | X22: =IFERROR(U22/U$58,0) -> 0.0085578659 | Y22: =X22-W22 -> -0.0062172346 | Z22: 2000 | AA22: 1037 | AB22: 940 | AC22: =AB22-AA22 -> -97 | AD22: =IFERROR(AA22/AA$58,0) -> 0.014566653 | AE22: =IFERROR(AB22/AB$58,0) -> 0.014747411 | AF22: =AE22-AD22 -> 0.00018075874 | AG22: =G22+N22+U22+AB22 -> 5315 | AH22: =IFERROR(AG22/AG$58,0) -> 0.016851831 | AI22: =①札幌予測確定!R13 -> 0.022196796 | AJ22: =③石川以降予測!H36 -> 0.018472104 | AK22: =IF(AJ22-AH22>=0.005,"↑ 上方修正",IF(AJ22-AH22<=-0.005,"↓ 下方修正","→ 据置")) -> → 据置
A23: 8 | B23: 4515142545150 | C23: 呪術廻戦 渋谷事変 ブラインドダイカットステッカー（全9種） | D23: 600 | E23: 12600 | F23: — | G23: 5596 | H23: — | I23: =IFERROR(E23/E$58,0) -> 0.059672653 | J23: =IFERROR(G23/G$58,0) -> 0.037763606 | K23: =J23-I23 -> -0.021909047 | L23: 2240 | M23: 1107 | N23: 1107 | O23: =N23-M23 -> 0 | P23: =IFERROR(M23/M$58,0) -> 0.01873794 | Q23: =IFERROR(N23/N$58,0) -> 0.018890785 | R23: =Q23-P23 -> 0.00015284531 | S23: 840 | T23: 839 | U23: 799 | V23: =U23-T23 -> -40 | W23: =IFERROR(T23/T$58,0) -> 0.026152551 | X23: =IFERROR(U23/U$58,0) -> 0.017806601 | Y23: =X23-W23 -> -0.0083459502 | Z23: 3000 | AA23: 1844 | AB23: 1758 | AC23: =AB23-AA23 -> -86 | AD23: =IFERROR(AA23/AA$58,0) -> 0.025902514 | AE23: =IFERROR(AB23/AB$58,0) -> 0.027580797 | AF23: =AE23-AD23 -> 0.0016782826 | AG23: =G23+N23+U23+AB23 -> 9260 | AH23: =IFERROR(AG23/AG$58,0) -> 0.029359916 | AI23: =①札幌予測確定!R14 -> 0.036727689 | AJ23: =③石川以降予測!H37 -> 0.032154243 | AK23: =IF(AJ23-AH23>=0.005,"↑ 上方修正",IF(AJ23-AH23<=-0.005,"↓ 下方修正","→ 据置")) -> → 据置
A24: 9 | B24: 4515142545372 | C24: 呪術廻戦 懐玉・玉折 クリアファイル（五条 悟） | D24: 600 | E24: 8749 | F24: — | G24: 2381 | H24: — | I24: =IFERROR(E24/E$58,0) -> 0.041434606 | J24: =IFERROR(G24/G$58,0) -> 0.016067753 | K24: =J24-I24 -> -0.025366853 | L24: 950 | M24: 369 | N24: 313 | O24: =N24-M24 -> -56 | P24: =IFERROR(M24/M$58,0) -> 0.0062459799 | Q24: =IFERROR(N24/N$58,0) -> 0.0053412969 | R24: =Q24-P24 -> -0.00090468296 | S24: 300 | T24: 358 | U24: 301 | V24: =U24-T24 -> -57 | W24: =IFERROR(T24/T$58,0) -> 0.011159253 | X24: =IFERROR(U24/U$58,0) -> 0.0067081188 | Y24: =X24-W24 -> -0.0044511343 | Z24: 1500 | AA24: 743 | AB24: 743 | AC24: =AB24-AA24 -> 0 | AD24: =IFERROR(AA24/AA$58,0) -> 0.010436859 | AE24: =IFERROR(AB24/AB$58,0) -> 0.01165673 | AF24: =AE24-AD24 -> 0.0012198714 | AG24: =G24+N24+U24+AB24 -> 3738 | AH24: =IFERROR(AG24/AG$58,0) -> 0.011851767 | AI24: =①札幌予測確定!R15 -> 0.014645309 | AJ24: =③石川以降予測!H38 -> 0.01315102 | AK24: =IF(AJ24-AH24>=0.005,"↑ 上方修正",IF(AJ24-AH24<=-0.005,"↓ 下方修正","→ 据置")) -> → 据置
A25: 10 | B25: 4515142545389 | C25: 呪術廻戦 懐玉・玉折 クリアファイル（夏油 傑） | D25: 600 | E25: 4549 | F25: — | G25: 1025 | H25: — | I25: =IFERROR(E25/E$58,0) -> 0.021543722 | J25: =IFERROR(G25/G$58,0) -> 0.0069170294 | K25: =J25-I25 -> -0.014626693 | L25: 410 | M25: 166 | N25: 141 | O25: =N25-M25 -> -25 | P25: =IFERROR(M25/M$58,0) -> 0.0028098446 | Q25: =IFERROR(N25/N$58,0) -> 0.0024061433 | R25: =Q25-P25 -> -0.00040370127 | S25: 180 | T25: 163 | U25: 123 | V25: =U25-T25 -> -40 | W25: =IFERROR(T25/T$58,0) -> 0.005080889 | X25: =IFERROR(U25/U$58,0) -> 0.0027411914 | Y25: =X25-W25 -> -0.0023396976 | Z25: 500 | AA25: 282 | AB25: 277 | AC25: =AB25-AA25 -> -5 | AD25: =IFERROR(AA25/AA$58,0) -> 0.0039612305 | AE25: =IFERROR(AB25/AB$58,0) -> 0.0043457797 | AF25: =AE25-AD25 -> 0.00038454922 | AG25: =G25+N25+U25+AB25 -> 1566 | AH25: =IFERROR(AG25/AG$58,0) -> 0.0049651866 | AI25: =①札幌予測確定!R16 -> 0.0054919908 | AJ25: =③石川以降予測!H39 -> 0.0049188853 | AK25: =IF(AJ25-AH25>=0.005,"↑ 上方修正",IF(AJ25-AH25<=-0.005,"↓ 下方修正","→ 据置")) -> → 据置
A26: 11 | B26: 4515142545396 | C26: 呪術廻戦 懐玉・玉折 クリアファイル（家入 硝子） | D26: 600 | E26: 699 | F26: — | G26: 215 | H26: — | I26: =IFERROR(E26/E$58,0) -> 0.0033104115 | J26: =IFERROR(G26/G$58,0) -> 0.0014508891 | K26: =J26-I26 -> -0.0018595224 | L26: 90 | M26: 25 | N26: 37 | O26: =N26-M26 -> 12 | P26: =IFERROR(M26/M$58,0) -> 0.00042316937 | Q26: =IFERROR(N26/N$58,0) -> 0.00063139932 | R26: =Q26-P26 -> 0.00020822995 | S26: 30 | T26: 70 | U26: 30 | V26: =U26-T26 -> -40 | W26: =IFERROR(T26/T$58,0) -> 0.0021819769 | X26: =IFERROR(U26/U$58,0) -> 0.00066858327 | Y26: =X26-W26 -> -0.0015133936 | Z26: 100 | AA26: 85 | AB26: 78 | AC26: =AB26-AA26 -> -7 | AD26: =IFERROR(AA26/AA$58,0) -> 0.0011939879 | AE26: =IFERROR(AB26/AB$58,0) -> 0.0012237214 | AF26: =AE26-AD26 -> 2.9733448e-05 | AG26: =G26+N26+U26+AB26 -> 360 | AH26: =IFERROR(AG26/AG$58,0) -> 0.0011414222 | AI26: =①札幌予測確定!R17 -> 0.0027459954 | AJ26: =③石川以降予測!H40 -> 0.0019848584 | AK26: =IF(AJ26-AH26>=0.005,"↑ 上方修正",IF(AJ26-AH26<=-0.005,"↓ 下方修正","→ 据置")) -> → 据置
A27: 12 | B27: 4515142545402 | C27: 呪術廻戦 懐玉・玉折 クリアファイル（七海 建人） | D27: 600 | E27: 1049 | F27: — | G27: 291 | H27: — | I27: =IFERROR(E27/E$58,0) -> 0.0049679851 | J27: =IFERROR(G27/G$58,0) -> 0.0019637615 | K27: =J27-I27 -> -0.0030042236 | L27: 119 | M27: 68 | N27: 58 | O27: =N27-M27 -> -10 | P27: =IFERROR(M27/M$58,0) -> 0.0011510207 | Q27: =IFERROR(N27/N$58,0) -> 0.00098976109 | R27: =Q27-P27 -> -0.00016125959 | S27: 80 | T27: 39 | U27: 54 | V27: =U27-T27 -> 15 | W27: =IFERROR(T27/T$58,0) -> 0.0012156728 | X27: =IFERROR(U27/U$58,0) -> 0.0012034499 | Y27: =X27-W27 -> -1.2222938e-05 | Z27: 150 | AA27: 156 | AB27: 142 | AC27: =AB27-AA27 -> -14 | AD27: =IFERROR(AA27/AA$58,0) -> 0.002191319 | AE27: =IFERROR(AB27/AB$58,0) -> 0.0022278004 | AF27: =AE27-AD27 -> 3.6481434e-05 | AG27: =G27+N27+U27+AB27 -> 545 | AH27: =IFERROR(AG27/AG$58,0) -> 0.0017279864 | AI27: =①札幌予測確定!R18 -> 0.0038901602 | AJ27: =③石川以降予測!H41 -> 0.0030589803 | AK27: =IF(AJ27-AH27>=0.005,"↑ 上方修正",IF(AJ27-AH27<=-0.005,"↓ 下方修正","→ 据置")) -> → 据置
... A57: 42 | B57: 4515142545365 | C57: 伏黒 恵 イメージフラグメントケース | D57: 25000 | E57: 38 | F57: — | G57: 24 | H57: — | I57: =IFERROR(E57/E$58,0) -> 0.00017996514 | J57: =IFERROR(G57/G$58,0) -> 0.00016195971 | K57: =J57-I57 -> -1.8005431e-05 | L57: 10 | M57: 6 | N57: 8 | O57: =N57-M57 -> 2 | P57: =IFERROR(M57/M$58,0) -> 0.00010156065 | Q57: =IFERROR(N57/N$58,0) -> 0.00013651877 | R57: =Q57-P57 -> 3.4958123e-05 | S57: 5 | T57: 3 | U57: 3 | V57: =U57-T57 -> 0 | W57: =IFERROR(T57/T$58,0) -> 9.3513294e-05 | X57: =IFERROR(U57/U$58,0) -> 6.6858327e-05 | Y57: =X57-W57 -> -2.6654967e-05 | Z57: 20 | AA57: 8 | AB57: 8 | AC57: =AB57-AA57 -> 0 | AD57: =IFERROR(AA57/AA$58,0) -> 0.00011237533 | AE57: =IFERROR(AB57/AB$58,0) -> 0.00012550988 | AF57: =AE57-AD57 -> 1.313455e-05 | AG57: =G57+N57+U57+AB57 -> 43 | AH57: =IFERROR(AG57/AG$58,0) -> 0.00013633654 | AI57: =①札幌予測確定!R48 -> 0.00022883295 | AJ57: =③石川以降予測!H71 -> 0.00017717142 | AK57: =IF(AJ57-AH57>=0.005,"↑ 上方修正",IF(AJ57-AH57<=-0.005,"↓ 下方修正","→ 据置")) -> → 据置
C58: 合計（LEGS 42SKU） | E58: =SUM(E16:E57) -> 211152 | G58: =SUM(G16:G57) -> 148185 | I58: 1 | J58: 1 | K58: 0 | L58: =SUM(L16:L57) -> 83271 | M58: =SUM(M16:M57) -> 59078 | N58: =SUM(N16:N57) -> 58600 | O58: =SUM(O16:O57) -> -478 | P58: 1 | Q58: 1 | R58: 0 | S58: =SUM(S16:S57) -> 49598 | T58: =SUM(T16:T57) -> 32081 | U58: =SUM(U16:U57) -> 44871 | V58: =SUM(V16:V57) -> 12790 | W58: 1 | X58: 1 | Y58: 0 | Z58: =SUM(Z16:Z57) -> 137560 | AA58: =SUM(AA16:AA57) -> 71190 | AB58: =SUM(AB16:AB57) -> 63740 | AC58: =SUM(AC16:AC57) -> -7450 | AD58: 1 | AE58: 1 | AF58: 0 | AG58: =SUM(AG16:AG57) -> 315396 | AH58: 1 | AI58: 1 | AJ58: 1
A60: ■ 構成比修正の考え方と次会場への反映
A61: 予測時構成比 | B61: 各会場の会期前〜初6日時点で、過去会場の実績から見込んでいた商品別シェア。池袋のみ実績データが無いため投入数（販売可能数）のシェアを計画値として採用している。
A62: 実績構成比 | B62: 各会場の会期全体の実績販売数に基づく商品別シェア。
A63: 構成比修正 | B63: 実績構成比 − 予測時構成比（ポイント）。プラスは想定より売れた＝次会場で構成比を引き上げるべき商品。
A64: 石川以降 適用構成比 | B64: 大阪20日実績のシェア50% ＋ 札幌20日予測のシェア50%のブレンド（③シートで算出）。直近2会場は品揃えが同一のため、この2会場に絞って重み付けしている。
A65: モデル精度の読み方 | B65: 3会場の絶対誤差率は10〜27%。ブラインド系など会期後半に伸びる商品ほど予測が下振れしやすく、
B66: 定番のクリアファイル・ポストカード系は誤差が小さい。発注量は絶対誤差率を織り込んだ安全率で調整すること。

Sheet ⑩会場比率シナリオ比較
A1: ⑩ 石川会場以降の 東京対比 会場比率 シナリオ比較
A2: 「前提・入力」シートのシナリオ選択セルで①〜④を切り替えると、③④⑤⑧シートの予測がすべて連動して再計算される。本シートは4シナリオを並べて比較するためのもの
A3: ②企画概要書ベースは、企画概要書「グッズ売上(LEGS予測値)」の 各会場÷東京 で算出（石川 31,200千円÷250,000千円＝12.48%、仙台 39,000千円÷250,000千円＝15.60%）
A4: ③札幌実績連動は、②に札幌の計画比達成率 46.5%（予測東京対比10.16% ÷ 企画概要書21.84%）を乗じた保守シナリオ。東京凱旋のみ50%で据置
A6: ■ 企画概要書の計画値と実績の乖離（東京対比・物販売上ベース）
A7: 会場 | B7: 企画概要書 グッズ売上予測 | C7: 企画概要書 東京対比 | D7: 実績／予測 物販売上 | E7: 実績／予測 東京対比 | F7: 計画比 達成率 | G7: 評価
A8: 東京 | B8: 250000000 | C8: =B8/$B$8 -> 1 | D8: 358193925 | E8: =D8/$D$8 -> 1 | F8: =IFERROR(E8/C8,"") -> 1 | G8: 基準会場
A9: 名古屋 | B9: 72000000 | C9: =B9/$B$8 -> 0.288 | D9: 138575410 | E9: =D9/$D$8 -> 0.38687259 | F9: =IFERROR(E9/C9,"") -> 1.3433076 | G9: 計画を大幅超過
A10: 博多 | B10: 56000000 | C10: =B10/$B$8 -> 0.224 | D10: 105540655 | E10: =D10/$D$8 -> 0.29464669 | F10: =IFERROR(E10/C10,"") -> 1.315387 | G10: 計画を大幅超過
A11: 大阪 | B11: 80000000 | C11: =B11/$B$8 -> 0.32 | D11: 215184570 | E11: =D11/$D$8 -> 0.6007488 | F11: =IFERROR(E11/C11,"") -> 1.87734 | G11: 計画の1.9倍。新商品投入で会場全体が伸びた
A12: 札幌（予測） | B12: 54600000 | C12: =B12/$B$8 -> 0.2184 | D12: 36375678 | E12: =D12/$D$8 -> 0.10155303 | F12: =IFERROR(E12/C12,"") -> 0.4649864 | G12: ★計画の47%。動員が大きく下振れ
A13: 石川 | B13: 31200000 | C13: =B13/$B$8 -> 0.1248 | D13: — | E13: — | F13: — | G13: 実績未確定。②はこの計画値を採用
A14: 仙台 | B14: 39000000 | C14: =B14/$B$8 -> 0.156 | D14: — | E14: — | F14: — | G14: 実績未確定。②はこの計画値を採用
A16: ■ シナリオ別 東京対比比率と LEGS必要数
A17: 会場 | B17: 会期日数 | C17: ①ユーザー指定 東京対比 | D17: ①ユーザー指定 LEGS必要数 | E17: ②企画概要書ベース 東京対比 | F17: ②企画概要書ベース LEGS必要数 | G17: ③札幌実績連動(保守) 東京対比 | H17: ③札幌実績連動(保守) LEGS必要数 | I17: ④手動入力 東京対比 | J17: ④手動入力 LEGS必要数
A18: 石川 香林坊大和 | B18: 18 | C18: =前提・入力!C16 -> 0.11 | D18: =ROUND(前提・入力!$B$12*C18*前提・入力!$B$30/前提・入力!$B$31,0) -> 9471 | E18: =前提・入力!D16 -> 0.1248 | F18: =ROUND(前提・入力!$B$12*E18*前提・入力!$B$30/前提・入力!$B$31,0) -> 10746 | G18: =前提・入力!E16 -> 0.058030303 | H18: =ROUND(前提・入力!$B$12*G18*前提・入力!$B$30/前提・入力!$B$31,0) -> 4997 | I18: =前提・入力!F16 -> 0.11 | J18: =ROUND(前提・入力!$B$12*I18*前提・入力!$B$30/前提・入力!$B$31,0) -> 9471
A19: 仙台 Ebeans | B19: 30 | C19: =前提・入力!C17 -> 0.13 | D19: =ROUND(前提・入力!$B$12*C19*前提・入力!$B$30/前提・入力!$B$31,0) -> 11193 | E19: =前提・入力!D17 -> 0.156 | F19: =ROUND(前提・入力!$B$12*E19*前提・入力!$B$30/前提・入力!$B$31,0) -> 13432 | G19: =前提・入力!E17 -> 0.072537878 | H19: =ROUND(前提・入力!$B$12*G19*前提・入力!$B$30/前提・入力!$B$31,0) -> 6246 | I19: =前提・入力!F17 -> 0.13 | J19: =ROUND(前提・入力!$B$12*I19*前提・入力!$B$30/前提・入力!$B$31,0) -> 11193
A20: 神戸阪急 | B20: 21 | C20: =前提・入力!C18 -> 0.12 | D20: =ROUND(前提・入力!$B$12*C20*前提・入力!$B$30/前提・入力!$B$31,0) -> 10332 | E20: =前提・入力!D18 -> 0.12 | F20: =ROUND(前提・入力!$B$12*E20*前提・入力!$B$30/前提・入力!$B$31,0) -> 10332 | G20: =前提・入力!E18 -> 0.055798368 | H20: =ROUND(前提・入力!$B$12*G20*前提・入力!$B$30/前提・入力!$B$31,0) -> 4804 | I20: =前提・入力!F18 -> 0.12 | J20: =ROUND(前提・入力!$B$12*I20*前提・入力!$B$30/前提・入力!$B$31,0) -> 10332
A21: 鳥取島根 夢みなとタワー | B21: 21 | C21: =前提・入力!C19 -> 0.09 | D21: =ROUND(前提・入力!$B$12*C21*前提・入力!$B$30/前提・入力!$B$31,0) -> 7749 | E21: =前提・入力!D19 -> 0.09 | F21: =ROUND(前提・入力!$B$12*E21*前提・入力!$B$30/前提・入力!$B$31,0) -> 7749 | G21: =前提・入力!E19 -> 0.041848776 | H21: =ROUND(前提・入力!$B$12*G21*前提・入力!$B$30/前提・入力!$B$31,0) -> 3603 | I21: =前提・入力!F19 -> 0.09 | J21: =ROUND(前提・入力!$B$12*I21*前提・入力!$B$30/前提・入力!$B$31,0) -> 7749
A22: 東京凱旋 東京建物ぴあホール | B22: 25 | C22: =前提・入力!C20 -> 0.5 | D22: =ROUND(前提・入力!$B$12*C22*前提・入力!$B$30/前提・入力!$B$31,0) -> 43051 | E22: =前提・入力!D20 -> 0.5 | F22: =ROUND(前提・入力!$B$12*E22*前提・入力!$B$30/前提・入力!$B$31,0) -> 43051 | G22: =前提・入力!E20 -> 0.5 | H22: =ROUND(前提・入力!$B$12*G22*前提・入力!$B$30/前提・入力!$B$31,0) -> 43051 | I22: =前提・入力!F20 -> 0.5 | J22: =ROUND(前提・入力!$B$12*I22*前提・入力!$B$30/前提・入力!$B$31,0) -> 43051
A23: 5会場 合計 | C23: =SUM(C18:C22) -> 0.95 | D23: =SUM(D18:D22) -> 81796 | E23: =SUM(E18:E22) -> 0.9908 | F23: =SUM(F18:F22) -> 85310 | G23: =SUM(G18:G22) -> 0.72821532 | H23: =SUM(H18:H22) -> 62701 | I23: =SUM(I18:I22) -> 0.95 | J23: =SUM(J18:J22) -> 81796
A25: ■ 商品別 シナリオ別 必要数と追加生産必要数（供給可能在庫はシナリオ共通）
A26: No. | B26: JAN | C26: 商品名 | D26: 按分 構成比 | E26: 石川以降 供給可能在庫 | F26: ①ユーザー指定 必要数 | G26: ①ユーザー指定 追加生産 | H26: ②企画概要書ベース 必要数 | I26: ②企画概要書ベース 追加生産 | J26: ③札幌実績連動(保守) 必要数 | K26: ③札幌実績連動(保守) 追加生産 | L26: ④手動入力 必要数 | M26: ④手動入力 追加生産
A27: 1 | B27: 4515142545082 | C27: 呪術廻戦 メタリックポストカード 展示会キービジュアル | D27: =③石川以降予測!H30 -> 0.044954402 | E27: =③石川以降予測!T30 -> 2797 | F27: =ROUND($D27*D$23,0) -> 3677 | G27: =MAX(0,F27-$E27) -> 880 | H27: =ROUND($D27*F$23,0) -> 3835 | I27: =MAX(0,H27-$E27) -> 1038 | J27: =ROUND($D27*H$23,0) -> 2819 | K27: =MAX(0,J27-$E27) -> 22 | L27: =ROUND($D27*J$23,0) -> 3677 | M27: =MAX(0,L27-$E27) -> 880
A28: 2 | B28: 4515142545099 | C28: 呪術廻戦 クリアファイル 展示会キービジュアル | D28: =③石川以降予測!H31 -> 0.044533176 | E28: =③石川以降予測!T31 -> 4528 | F28: =ROUND($D28*D$23,0) -> 3643 | G28: =MAX(0,F28-$E28) -> 0 | H28: =ROUND($D28*F$23,0) -> 3799 | I28: =MAX(0,H28-$E28) -> 0 | J28: =ROUND($D28*H$23,0) -> 2792 | K28: =MAX(0,J28-$E28) -> 0 | L28: =ROUND($D28*J$23,0) -> 3643 | M28: =MAX(0,L28-$E28) -> 0
A29: 3 | B29: 4515142545105 | C29: 呪術廻戦 懐玉・玉折 ポストカードセット（5枚入） | D29: =③石川以降予測!H32 -> 0.018204767 | E29: =③石川以降予測!T32 -> 5977 | F29: =ROUND($D29*D$23,0) -> 1489 | G29: =MAX(0,F29-$E29) -> 0 | H29: =ROUND($D29*F$23,0) -> 1553 | I29: =MAX(0,H29-$E29) -> 0 | J29: =ROUND($D29*H$23,0) -> 1141 | K29: =MAX(0,J29-$E29) -> 0 | L29: =ROUND($D29*J$23,0) -> 1489 | M29: =MAX(0,L29-$E29) -> 0
A30: 4 | B30: 4515142545112 | C30: 呪術廻戦 渋谷事変 ポストカードセット（9枚入） | D30: =③石川以降予測!H33 -> 0.023376808 | E30: =③石川以降予測!T33 -> 27282 | F30: =ROUND($D30*D$23,0) -> 1912 | G30: =MAX(0,F30-$E30) -> 0 | H30: =ROUND($D30*F$23,0) -> 1994 | I30: =MAX(0,H30-$E30) -> 0 | J30: =ROUND($D30*H$23,0) -> 1466 | K30: =MAX(0,J30-$E30) -> 0 | L30: =ROUND($D30*J$23,0) -> 1912 | M30: =MAX(0,L30-$E30) -> 0
A31: 5 | B31: 4515142545129 | C31: 呪術廻戦 懐玉・玉折 ブラインド缶バッジ（全5種） | D31: =③石川以降予測!H34 -> 0.096699101 | E31: =③石川以降予測!T34 -> 39360 | F31: =ROUND($D31*D$23,0) -> 7910 | G31: =MAX(0,F31-$E31) -> 0 | H31: =ROUND($D31*F$23,0) -> 8249 | I31: =MAX(0,H31-$E31) -> 0 | J31: =ROUND($D31*H$23,0) -> 6063 | K31: =MAX(0,J31-$E31) -> 0 | L31: =ROUND($D31*J$23,0) -> 7910 | M31: =MAX(0,L31-$E31) -> 0
A32: 6 | B32: 4515142545136 | C32: 呪術廻戦 渋谷事変 ブラインド缶バッジ（全9種） | D32: =③石川以降予測!H35 -> 0.22133478 | E32: =③石川以降予測!T35 -> 49517 | F32: =ROUND($D32*D$23,0) -> 18104 | G32: =MAX(0,F32-$E32) -> 0 | H32: =ROUND($D32*F$23,0) -> 18882 | I32: =MAX(0,H32-$E32) -> 0 | J32: =ROUND($D32*H$23,0) -> 13878 | K32: =MAX(0,J32-$E32) -> 0 | L32: =ROUND($D32*J$23,0) -> 18104 | M32: =MAX(0,L32-$E32) -> 0
A33: 7 | B33: 4515142545143 | C33: 呪術廻戦 懐玉・玉折 ブラインドダイカットステッカー（全5種） | D33: =③石川以降予測!H36 -> 0.018472104 | E33: =③石川以降予測!T36 -> 4348 | F33: =ROUND($D33*D$23,0) -> 1511 | G33: =MAX(0,F33-$E33) -> 0 | H33: =ROUND($D33*F$23,0) -> 1576 | I33: =MAX(0,H33-$E33) -> 0 | J33: =ROUND($D33*H$23,0) -> 1158 | K33: =MAX(0,J33-$E33) -> 0 | L33: =ROUND($D33*J$23,0) -> 1511 | M33: =MAX(0,L33-$E33) -> 0
A34: 8 | B34: 4515142545150 | C34: 呪術廻戦 渋谷事変 ブラインドダイカットステッカー（全9種） | D34: =③石川以降予測!H37 -> 0.032154243 | E34: =③石川以降予測!T37 -> 8230 | F34: =ROUND($D34*D$23,0) -> 2630 | G34: =MAX(0,F34-$E34) -> 0 | H34: =ROUND($D34*F$23,0) -> 2743 | I34: =MAX(0,H34-$E34) -> 0 | J34: =ROUND($D34*H$23,0) -> 2016 | K34: =MAX(0,J34-$E34) -> 0 | L34: =ROUND($D34*J$23,0) -> 2630 | M34: =MAX(0,L34-$E34) -> 0
A35: 9 | B35: 4515142545372 | C35: 呪術廻戦 懐玉・玉折 クリアファイル（五条 悟） | D35: =③石川以降予測!H38 -> 0.01315102 | E35: =③石川以降予測!T38 -> 8631 | F35: =ROUND($D35*D$23,0) -> 1076 | G35: =MAX(0,F35-$E35) -> 0 | H35: =ROUND($D35*F$23,0) -> 1122 | I35: =MAX(0,H35-$E35) -> 0 | J35: =ROUND($D35*H$23,0) -> 825 | K35: =MAX(0,J35-$E35) -> 0 | L35: =ROUND($D35*J$23,0) -> 1076 | M35: =MAX(0,L35-$E35) -> 0
A36: 10 | B36: 4515142545389 | C36: 呪術廻戦 懐玉・玉折 クリアファイル（夏油 傑） | D36: =③石川以降予測!H39 -> 0.0049188853 | E36: =③石川以降予測!T39 -> 4887 | F36: =ROUND($D36*D$23,0) -> 402 | G36: =MAX(0,F36-$E36) -> 0 | H36: =ROUND($D36*F$23,0) -> 420 | I36: =MAX(0,H36-$E36) -> 0 | J36: =ROUND($D36*H$23,0) -> 308 | K36: =MAX(0,J36-$E36) -> 0 | L36: =ROUND($D36*J$23,0) -> 402 | M36: =MAX(0,L36-$E36) -> 0
A37: 11 | B37: 4515142545396 | C37: 呪術廻戦 懐玉・玉折 クリアファイル（家入 硝子） | D37: =③石川以降予測!H40 -> 0.0019848584 | E37: =③石川以降予測!T40 -> 616 | F37: =ROUND($D37*D$23,0) -> 162 | G37: =MAX(0,F37-$E37) -> 0 | H37: =ROUND($D37*F$23,0) -> 169 | I37: =MAX(0,H37-$E37) -> 0 | J37: =ROUND($D37*H$23,0) -> 124 | K37: =MAX(0,J37-$E37) -> 0 | L37: =ROUND($D37*J$23,0) -> 162 | M37: =MAX(0,L37-$E37) -> 0
A38: 12 | B38: 4515142545402 | C38: 呪術廻戦 懐玉・玉折 クリアファイル（七海 建人） | D38: =③石川以降予測!H41 -> 0.0030589803 | E38: =③石川以降予測!T41 -> 919 | F38: =ROUND($D38*D$23,0) -> 250 | G38: =MAX(0,F38-$E38) -> 0 | H38: =ROUND($D38*F$23,0) -> 261 | I38: =MAX(0,H38-$E38) -> 0 | J38: =ROUND($D38*H$23,0) -> 192 | K38: =MAX(0,J38-$E38) -> 0 | L38: =ROUND($D38*J$23,0) -> 250 | M38: =MAX(0,L38-$E38) -> 0
... A68: 42 | B68: 4515142545365 | C68: 伏黒 恵 イメージフラグメントケース | D68: =③石川以降予測!H71 -> 0.00017717142 | E68: =③石川以降予測!T71 -> 47 | F68: =ROUND($D68*D$23,0) -> 14 | G68: =MAX(0,F68-$E68) -> 0 | H68: =ROUND($D68*F$23,0) -> 15 | I68: =MAX(0,H68-$E68) -> 0 | J68: =ROUND($D68*H$23,0) -> 11 | K68: =MAX(0,J68-$E68) -> 0 | L68: =ROUND($D68*J$23,0) -> 14 | M68: =MAX(0,L68-$E68) -> 0
C69: 合計（LEGS 42SKU） | D69: =SUM(D27:D68) -> 1 | E69: =SUM(E27:E68) -> 265948 | F69: =SUM(F27:F68) -> 81793 | G69: =SUM(G27:G68) -> 3578 | H69: =SUM(H27:H68) -> 85309 | I69: =SUM(I27:I68) -> 3903 | J69: =SUM(J27:J68) -> 62701 | K69: =SUM(K27:K68) -> 1824 | ... M69: =SUM(M27:M68) -> 3578
A71: ■ シナリオ別 結論
A72: 項目 | B72: ①ユーザー指定 | C72: ②企画概要書ベース | D72: ③札幌実績連動(保守) | E72: ④手動入力
A73: 石川以降 LEGS必要数 | B73: =F69 -> 81793 | C73: =H69 -> 85309 | D73: =J69 -> 62701 | E73: =L69 -> 81793
A74: 石川以降 供給可能在庫 | B74: =$E$69 -> 265948 | C74: =$E$69 -> 265948 | D74: =$E$69 -> 265948 | E74: =$E$69 -> 265948
A75: 全体過不足 | B75: =B74-B73 -> 184155 | C75: =C74-C73 -> 180639 | D75: =D74-D73 -> 203247 | E75: =E74-E73 -> 184155
A76: 追加生産 必要数 | B76: =G69 -> 3578 | C76: =I69 -> 3903 | D76: =K69 -> 1824 | E76: =M69 -> 3578
A77: 不足品目数 | B77: =COUNTIF(G27:G68,">0")&"品目" -> 9品目 | C77: =COUNTIF(I27:I68,">0")&"品目" -> 9品目 | D77: =COUNTIF(K27:K68,">0")&"品目" -> 9品目 | E77: =COUNTIF(M27:M68,">0")&"品目" -> 9品目
A78: 推奨発注数(安全率込) | B78: =ROUNDUP(G69*(1+前提・入力!$B$35),0) -> 3936 | C78: =ROUNDUP(I69*(1+前提・入力!$B$35),0) -> 4294 | D78: =ROUNDUP(K69*(1+前提・入力!$B$35),0) -> 2007 | E78: =ROUNDUP(M69*(1+前提・入力!$B$35),0) -> 3936
A80: 推奨 | B80: ②企画概要書ベースは石川12.48%・仙台15.60%と①より強気。ただし札幌が計画の47%に留まっている実態を踏まえると、
B81: 発注量の意思決定は③札幌実績連動（保守）を下限、②企画概要書ベースを上限としたレンジで持つのが妥当。
A82: 留意 | B82: 名古屋134%・博多132%・大阪188%と、札幌以前の3会場はいずれも計画を大きく超過している。
B83: 札幌だけが47%と外れ値であり、これが札幌固有の要因（会場規模・立地）か地方会場全体の傾向かで判断が分かれる。
B84: 石川・仙台の前売/予約状況が判明した時点でシナリオを確定させることを推奨する。

Sheet ⑪会場別引当・発注期限
A1: ⑪ 石川以降 会場別 在庫引当シミュレーションと 最終追加発注期限
A2: 札幌の欠品分は倉庫在庫から追納する前提。石川以降の供給可能在庫（＝7/8実在庫 − 札幌会期20日予測販売数）を会場順に引き当て、在庫が尽きる会場＝「欠品発生会場」を特定する
A3: 発注期限 ＝ 欠品発生会場の会期初日 − 生産日数 − 発注〜納品バッファ（既定14日）。生産日数は2026/7/28時点の提示値で、物価高騰・素材/材料の入手困難等により変動の可能性あり
A5: ■ 既に手配済みの追加発注（参考）
A6: 商品 | B6: 発注／納品日 | C6: 充当先 | D6: 備考
A7: 呪術廻戦 渋谷事変／懐玉・玉折 ブラインド缶バッジ | B7: 2026/4/24(金) | C7: 一部 大阪＆北海道(札幌)以降用
A8: 呪術廻戦 渋谷事変 ブラインドミニ色紙（全5種） | B8: 2026/5/8(金) | C8: 北海道(札幌)会場以降用
A9: 宿儺の指風お菓子 | B9: 2026/5/15(金) | C9: 仙台会場以降 | D9: ★賞味期限4か月以内のものは販売不可
A10: ― 開催中会場への追納 ― | D10: 2026/7/31・8/1 札幌会場追納リスト（レッグス商品分のみ抜粋）
A11: 呪術廻戦 渋谷事変 クリアファイル（脹相） | B11: 2026/7/31 | C11: 札幌会場（50個） | D11: 4個口／17時着予定
A12: 前髪ヘアバンド | B12: 2026/7/31 | C12: 札幌会場（100個）
A13: 脱兎！ポーチ入りクリップセット | B13: 2026/7/31 | C13: 札幌会場（60個）
A14: 宿儺の指風お菓子 | B14: 2026/7/31 | C14: 札幌会場（100個） | D14: 路線伝票 確認中
A15: （レッグス商品の追納なし） | B15: 2026/8/1 | C15: 札幌会場（0個） | D15: ムービック商品・MAPPA原画集のみ
A17: ■ 商品別 会場別 在庫引当と発注期限
A18: No. | B18: JAN | C18: 商品名 | D18: 生産日数 (か月) | E18: 生産日数 (日換算) | F18: 石川以降 供給可能在庫 | G18: 石川 必要数 | H18: 石川 引当後残 | I18: 仙台 必要数 | J18: 仙台 引当後残 | K18: 神戸阪急 必要数 | L18: 神戸阪急 引当後残 | M18: 鳥取島根 必要数 | N18: 鳥取島根 引当後残 | O18: 東京凱旋 必要数 | P18: 東京凱旋 引当後残 | Q18: 欠品発生会場 | R18: 欠品会場 会期初日 | S18: 不足数 (会期末まで) | T18: 推奨発注数 (安全率込) | U18: 最終発注期限 | V18: 基準日からの 残日数 | W18: 緊急度 | X18: 備考
A19: 1 | B19: 4515142545082 | C19: 呪術廻戦 メタリックポストカード 展示会キービジュアル | D19: 1 | E19: =IF(ISNUMBER(D19),ROUND(D19*30,0),"－") -> 30 | F19: =③石川以降予測!T30 -> 2797 | G19: =③石川以降予測!I30 -> 426 | H19: =F19-G19 -> 2371 | I19: =③石川以降予測!J30 -> 503 | J19: =H19-I19 -> 1868 | K19: =③石川以降予測!K30 -> 464 | L19: =J19-K19 -> 1404 | M19: =③石川以降予測!L30 -> 348 | N19: =L19-M19 -> 1056 | O19: =③石川以降予測!M30 -> 1935 | P19: =N19-O19 -> -879 | Q19: =_xlfn.IFS(H19<0,"石川 香林坊大和",J19<0,"仙台 Ebeans",L19<0,"神戸阪急",N19<0,"鳥取島根 夢みなとタワー",P19<0,"東京凱旋 東京建物ぴあホール",TRUE(),"—") -> 東京凱旋 東京建物ぴあホール | R19: =IF(Q19="—","",_xlfn.IFS(H19<0,DATE(2026,8,14),J19<0,DATE(2026,9,5),L19<0,DATE(2026,12,16),N19<0,DATE(2027,3,15),P19<0,DATE(2027,4,1))) -> 46478 | S19: =MAX(0,-P19) -> 879 | T19: =IF(S19>0,ROUNDUP(S19*(1+前提・入力!$B$35),0),0) -> 967 | U19: =IF(R19="","",IF(NOT(ISNUMBER(D19)),"再生産不可",R19-E19-前提・入力!$B$38)) -> 46434 | V19: =IF(OR(U19="",U19="再生産不可"),"",U19-前提・入力!$B$39) -> 201 | W19: =IF(Q19="","—",IF(U19="再生産不可","×再生産不可",_xlfn.IFS(V19<0,"★期限超過",V19<=30,"★至急(30日以内)",V19<=90,"要着手(90日以内)",TRUE(),"余裕あり"))) -> 余裕あり
A20: 2 | B20: 4515142545099 | C20: 呪術廻戦 クリアファイル 展示会キービジュアル | D20: 1 | E20: =IF(ISNUMBER(D20),ROUND(D20*30,0),"－") -> 30 | F20: =③石川以降予測!T31 -> 4528 | G20: =③石川以降予測!I31 -> 422 | H20: =F20-G20 -> 4106 | I20: =③石川以降予測!J31 -> 498 | J20: =H20-I20 -> 3608 | K20: =③石川以降予測!K31 -> 460 | L20: =J20-K20 -> 3148 | M20: =③石川以降予測!L31 -> 345 | N20: =L20-M20 -> 2803 | O20: =③石川以降予測!M31 -> 1917 | P20: =N20-O20 -> 886 | Q20: =_xlfn.IFS(H20<0,"石川 香林坊大和",J20<0,"仙台 Ebeans",L20<0,"神戸阪急",N20<0,"鳥取島根 夢みなとタワー",P20<0,"東京凱旋 東京建物ぴあホール",TRUE(),"—") -> — | R20: =IF(Q20="—","",_xlfn.IFS(H20<0,DATE(2026,8,14),J20<0,DATE(2026,9,5),L20<0,DATE(2026,12,16),N20<0,DATE(2027,3,15),P20<0,DATE(2027,4,1))) | S20: =MAX(0,-P20) -> 0 | T20: =IF(S20>0,ROUNDUP(S20*(1+前提・入力!$B$35),0),0) -> 0 | U20: =IF(R20="","",IF(NOT(ISNUMBER(D20)),"再生産不可",R20-E20-前提・入力!$B$38)) | V20: =IF(OR(U20="",U20="再生産不可"),"",U20-前提・入力!$B$39) | W20: =IF(Q20="","—",IF(U20="再生産不可","×再生産不可",_xlfn.IFS(V20<0,"★期限超過",V20<=30,"★至急(30日以内)",V20<=90,"要着手(90日以内)",TRUE(),"余裕あり"))) -> 余裕あり
A21: 3 | B21: 4515142545105 | C21: 呪術廻戦 懐玉・玉折 ポストカードセット（5枚入） | D21: 1 | E21: =IF(ISNUMBER(D21),ROUND(D21*30,0),"－") -> 30 | F21: =③石川以降予測!T32 -> 5977 | G21: =③石川以降予測!I32 -> 172 | H21: =F21-G21 -> 5805 | I21: =③石川以降予測!J32 -> 204 | J21: =H21-I21 -> 5601 | K21: =③石川以降予測!K32 -> 188 | L21: =J21-K21 -> 5413 | M21: =③石川以降予測!L32 -> 141 | N21: =L21-M21 -> 5272 | O21: =③石川以降予測!M32 -> 784 | P21: =N21-O21 -> 4488 | Q21: =_xlfn.IFS(H21<0,"石川 香林坊大和",J21<0,"仙台 Ebeans",L21<0,"神戸阪急",N21<0,"鳥取島根 夢みなとタワー",P21<0,"東京凱旋 東京建物ぴあホール",TRUE(),"—") -> — | R21: =IF(Q21="—","",_xlfn.IFS(H21<0,DATE(2026,8,14),J21<0,DATE(2026,9,5),L21<0,DATE(2026,12,16),N21<0,DATE(2027,3,15),P21<0,DATE(2027,4,1))) | S21: =MAX(0,-P21) -> 0 | T21: =IF(S21>0,ROUNDUP(S21*(1+前提・入力!$B$35),0),0) -> 0 | U21: =IF(R21="","",IF(NOT(ISNUMBER(D21)),"再生産不可",R21-E21-前提・入力!$B$38)) | V21: =IF(OR(U21="",U21="再生産不可"),"",U21-前提・入力!$B$39) | W21: =IF(Q21="","—",IF(U21="再生産不可","×再生産不可",_xlfn.IFS(V21<0,"★期限超過",V21<=30,"★至急(30日以内)",V21<=90,"要着手(90日以内)",TRUE(),"余裕あり"))) -> 余裕あり
A22: 4 | B22: 4515142545112 | C22: 呪術廻戦 渋谷事変 ポストカードセット（9枚入） | D22: 1 | E22: =IF(ISNUMBER(D22),ROUND(D22*30,0),"－") -> 30 | F22: =③石川以降予測!T33 -> 27282 | G22: =③石川以降予測!I33 -> 221 | H22: =F22-G22 -> 27061 | I22: =③石川以降予測!J33 -> 262 | J22: =H22-I22 -> 26799 | K22: =③石川以降予測!K33 -> 242 | L22: =J22-K22 -> 26557 | M22: =③石川以降予測!L33 -> 181 | N22: =L22-M22 -> 26376 | O22: =③石川以降予測!M33 -> 1006 | P22: =N22-O22 -> 25370 | Q22: =_xlfn.IFS(H22<0,"石川 香林坊大和",J22<0,"仙台 Ebeans",L22<0,"神戸阪急",N22<0,"鳥取島根 夢みなとタワー",P22<0,"東京凱旋 東京建物ぴあホール",TRUE(),"—") -> — | R22: =IF(Q22="—","",_xlfn.IFS(H22<0,DATE(2026,8,14),J22<0,DATE(2026,9,5),L22<0,DATE(2026,12,16),N22<0,DATE(2027,3,15),P22<0,DATE(2027,4,1))) | S22: =MAX(0,-P22) -> 0 | T22: =IF(S22>0,ROUNDUP(S22*(1+前提・入力!$B$35),0),0) -> 0 | U22: =IF(R22="","",IF(NOT(ISNUMBER(D22)),"再生産不可",R22-E22-前提・入力!$B$38)) | V22: =IF(OR(U22="",U22="再生産不可"),"",U22-前提・入力!$B$39) | W22: =IF(Q22="","—",IF(U22="再生産不可","×再生産不可",_xlfn.IFS(V22<0,"★期限超過",V22<=30,"★至急(30日以内)",V22<=90,"要着手(90日以内)",TRUE(),"余裕あり"))) -> 余裕あり
A23: 5 | B23: 4515142545129 | C23: 呪術廻戦 懐玉・玉折 ブラインド缶バッジ（全5種） | D23: 1 | E23: =IF(ISNUMBER(D23),ROUND(D23*30,0),"－") -> 30 | F23: =③石川以降予測!T34 -> 39360 | G23: =③石川以降予測!I34 -> 916 | H23: =F23-G23 -> 38444 | I23: =③石川以降予測!J34 -> 1082 | J23: =H23-I23 -> 37362 | K23: =③石川以降予測!K34 -> 999 | L23: =J23-K23 -> 36363 | M23: =③石川以降予測!L34 -> 749 | N23: =L23-M23 -> 35614 | O23: =③石川以降予測!M34 -> 4163 | P23: =N23-O23 -> 31451 | Q23: =_xlfn.IFS(H23<0,"石川 香林坊大和",J23<0,"仙台 Ebeans",L23<0,"神戸阪急",N23<0,"鳥取島根 夢みなとタワー",P23<0,"東京凱旋 東京建物ぴあホール",TRUE(),"—") -> — | R23: =IF(Q23="—","",_xlfn.IFS(H23<0,DATE(2026,8,14),J23<0,DATE(2026,9,5),L23<0,DATE(2026,12,16),N23<0,DATE(2027,3,15),P23<0,DATE(2027,4,1))) | S23: =MAX(0,-P23) -> 0 | T23: =IF(S23>0,ROUNDUP(S23*(1+前提・入力!$B$35),0),0) -> 0 | U23: =IF(R23="","",IF(NOT(ISNUMBER(D23)),"再生産不可",R23-E23-前提・入力!$B$38)) | V23: =IF(OR(U23="",U23="再生産不可"),"",U23-前提・入力!$B$39) | W23: =IF(Q23="","—",IF(U23="再生産不可","×再生産不可",_xlfn.IFS(V23<0,"★期限超過",V23<=30,"★至急(30日以内)",V23<=90,"要着手(90日以内)",TRUE(),"余裕あり"))) -> 余裕あり
A24: 6 | B24: 4515142545136 | C24: 呪術廻戦 渋谷事変 ブラインド缶バッジ（全9種） | D24: 1 | E24: =IF(ISNUMBER(D24),ROUND(D24*30,0),"－") -> 30 | F24: =③石川以降予測!T35 -> 49517 | G24: =③石川以降予測!I35 -> 2096 | H24: =F24-G24 -> 47421 | I24: =③石川以降予測!J35 -> 2477 | J24: =H24-I24 -> 44944 | K24: =③石川以降予測!K35 -> 2287 | L24: =J24-K24 -> 42657 | M24: =③石川以降予測!L35 -> 1715 | N24: =L24-M24 -> 40942 | O24: =③石川以降予測!M35 -> 9529 | P24: =N24-O24 -> 31413 | Q24: =_xlfn.IFS(H24<0,"石川 香林坊大和",J24<0,"仙台 Ebeans",L24<0,"神戸阪急",N24<0,"鳥取島根 夢みなとタワー",P24<0,"東京凱旋 東京建物ぴあホール",TRUE(),"—") -> — | R24: =IF(Q24="—","",_xlfn.IFS(H24<0,DATE(2026,8,14),J24<0,DATE(2026,9,5),L24<0,DATE(2026,12,16),N24<0,DATE(2027,3,15),P24<0,DATE(2027,4,1))) | S24: =MAX(0,-P24) -> 0 | T24: =IF(S24>0,ROUNDUP(S24*(1+前提・入力!$B$35),0),0) -> 0 | U24: =IF(R24="","",IF(NOT(ISNUMBER(D24)),"再生産不可",R24-E24-前提・入力!$B$38)) | V24: =IF(OR(U24="",U24="再生産不可"),"",U24-前提・入力!$B$39) | W24: =IF(Q24="","—",IF(U24="再生産不可","×再生産不可",_xlfn.IFS(V24<0,"★期限超過",V24<=30,"★至急(30日以内)",V24<=90,"要着手(90日以内)",TRUE(),"余裕あり"))) -> 余裕あり
A25: 7 | B25: 4515142545143 | C25: 呪術廻戦 懐玉・玉折 ブラインドダイカットステッカー（全5種） | D25: 1 | E25: =IF(ISNUMBER(D25),ROUND(D25*30,0),"－") -> 30 | F25: =③石川以降予測!T36 -> 4348 | G25: =③石川以降予測!I36 -> 175 | H25: =F25-G25 -> 4173 | I25: =③石川以降予測!J36 -> 207 | J25: =H25-I25 -> 3966 | K25: =③石川以降予測!K36 -> 191 | L25: =J25-K25 -> 3775 | M25: =③石川以降予測!L36 -> 143 | N25: =L25-M25 -> 3632 | O25: =③石川以降予測!M36 -> 795 | P25: =N25-O25 -> 2837 | Q25: =_xlfn.IFS(H25<0,"石川 香林坊大和",J25<0,"仙台 Ebeans",L25<0,"神戸阪急",N25<0,"鳥取島根 夢みなとタワー",P25<0,"東京凱旋 東京建物ぴあホール",TRUE(),"—") -> — | R25: =IF(Q25="—","",_xlfn.IFS(H25<0,DATE(2026,8,14),J25<0,DATE(2026,9,5),L25<0,DATE(2026,12,16),N25<0,DATE(2027,3,15),P25<0,DATE(2027,4,1))) | S25: =MAX(0,-P25) -> 0 | T25: =IF(S25>0,ROUNDUP(S25*(1+前提・入力!$B$35),0),0) -> 0 | U25: =IF(R25="","",IF(NOT(ISNUMBER(D25)),"再生産不可",R25-E25-前提・入力!$B$38)) | V25: =IF(OR(U25="",U25="再生産不可"),"",U25-前提・入力!$B$39) | W25: =IF(Q25="","—",IF(U25="再生産不可","×再生産不可",_xlfn.IFS(V25<0,"★期限超過",V25<=30,"★至急(30日以内)",V25<=90,"要着手(90日以内)",TRUE(),"余裕あり"))) -> 余裕あり
A26: 8 | B26: 4515142545150 | C26: 呪術廻戦 渋谷事変 ブラインドダイカットステッカー（全9種） | D26: 1 | E26: =IF(ISNUMBER(D26),ROUND(D26*30,0),"－") -> 30 | F26: =③石川以降予測!T37 -> 8230 | G26: =③石川以降予測!I37 -> 305 | H26: =F26-G26 -> 7925 | I26: =③石川以降予測!J37 -> 360 | J26: =H26-I26 -> 7565 | K26: =③石川以降予測!K37 -> 332 | L26: =J26-K26 -> 7233 | M26: =③石川以降予測!L37 -> 249 | N26: =L26-M26 -> 6984 | O26: =③石川以降予測!M37 -> 1384 | P26: =N26-O26 -> 5600 | Q26: =_xlfn.IFS(H26<0,"石川 香林坊大和",J26<0,"仙台 Ebeans",L26<0,"神戸阪急",N26<0,"鳥取島根 夢みなとタワー",P26<0,"東京凱旋 東京建物ぴあホール",TRUE(),"—") -> — | R26: =IF(Q26="—","",_xlfn.IFS(H26<0,DATE(2026,8,14),J26<0,DATE(2026,9,5),L26<0,DATE(2026,12,16),N26<0,DATE(2027,3,15),P26<0,DATE(2027,4,1))) | S26: =MAX(0,-P26) -> 0 | T26: =IF(S26>0,ROUNDUP(S26*(1+前提・入力!$B$35),0),0) -> 0 | U26: =IF(R26="","",IF(NOT(ISNUMBER(D26)),"再生産不可",R26-E26-前提・入力!$B$38)) | V26: =IF(OR(U26="",U26="再生産不可"),"",U26-前提・入力!$B$39) | W26: =IF(Q26="","—",IF(U26="再生産不可","×再生産不可",_xlfn.IFS(V26<0,"★期限超過",V26<=30,"★至急(30日以内)",V26<=90,"要着手(90日以内)",TRUE(),"余裕あり"))) -> 余裕あり
A27: 9 | B27: 4515142545372 | C27: 呪術廻戦 懐玉・玉折 クリアファイル（五条 悟） | D27: 1 | E27: =IF(ISNUMBER(D27),ROUND(D27*30,0),"－") -> 30 | F27: =③石川以降予測!T38 -> 8631 | G27: =③石川以降予測!I38 -> 125 | H27: =F27-G27 -> 8506 | I27: =③石川以降予測!J38 -> 147 | J27: =H27-I27 -> 8359 | K27: =③石川以降予測!K38 -> 136 | L27: =J27-K27 -> 8223 | M27: =③石川以降予測!L38 -> 102 | N27: =L27-M27 -> 8121 | O27: =③石川以降予測!M38 -> 566 | P27: =N27-O27 -> 7555 | Q27: =_xlfn.IFS(H27<0,"石川 香林坊大和",J27<0,"仙台 Ebeans",L27<0,"神戸阪急",N27<0,"鳥取島根 夢みなとタワー",P27<0,"東京凱旋 東京建物ぴあホール",TRUE(),"—") -> — | R27: =IF(Q27="—","",_xlfn.IFS(H27<0,DATE(2026,8,14),J27<0,DATE(2026,9,5),L27<0,DATE(2026,12,16),N27<0,DATE(2027,3,15),P27<0,DATE(2027,4,1))) | S27: =MAX(0,-P27) -> 0 | T27: =IF(S27>0,ROUNDUP(S27*(1+前提・入力!$B$35),0),0) -> 0 | U27: =IF(R27="","",IF(NOT(ISNUMBER(D27)),"再生産不可",R27-E27-前提・入力!$B$38)) | V27: =IF(OR(U27="",U27="再生産不可"),"",U27-前提・入力!$B$39) | W27: =IF(Q27="","—",IF(U27="再生産不可","×再生産不可",_xlfn.IFS(V27<0,"★期限超過",V27<=30,"★至急(30日以内)",V27<=90,"要着手(90日以内)",TRUE(),"余裕あり"))) -> 余裕あり
A28: 10 | B28: 4515142545389 | C28: 呪術廻戦 懐玉・玉折 クリアファイル（夏油 傑） | D28: 1 | E28: =IF(ISNUMBER(D28),ROUND(D28*30,0),"－") -> 30 | F28: =③石川以降予測!T39 -> 4887 | G28: =③石川以降予測!I39 -> 47 | H28: =F28-G28 -> 4840 | I28: =③石川以降予測!J39 -> 55 | J28: =H28-I28 -> 4785 | K28: =③石川以降予測!K39 -> 51 | L28: =J28-K28 -> 4734 | M28: =③石川以降予測!L39 -> 38 | N28: =L28-M28 -> 4696 | O28: =③石川以降予測!M39 -> 212 | P28: =N28-O28 -> 4484 | Q28: =_xlfn.IFS(H28<0,"石川 香林坊大和",J28<0,"仙台 Ebeans",L28<0,"神戸阪急",N28<0,"鳥取島根 夢みなとタワー",P28<0,"東京凱旋 東京建物ぴあホール",TRUE(),"—") -> — | R28: =IF(Q28="—","",_xlfn.IFS(H28<0,DATE(2026,8,14),J28<0,DATE(2026,9,5),L28<0,DATE(2026,12,16),N28<0,DATE(2027,3,15),P28<0,DATE(2027,4,1))) | S28: =MAX(0,-P28) -> 0 | T28: =IF(S28>0,ROUNDUP(S28*(1+前提・入力!$B$35),0),0) -> 0 | U28: =IF(R28="","",IF(NOT(ISNUMBER(D28)),"再生産不可",R28-E28-前提・入力!$B$38)) | V28: =IF(OR(U28="",U28="再生産不可"),"",U28-前提・入力!$B$39) | W28: =IF(Q28="","—",IF(U28="再生産不可","×再生産不可",_xlfn.IFS(V28<0,"★期限超過",V28<=30,"★至急(30日以内)",V28<=90,"要着手(90日以内)",TRUE(),"余裕あり"))) -> 余裕あり
A29: 11 | B29: 4515142545396 | C29: 呪術廻戦 懐玉・玉折 クリアファイル（家入 硝子） | D29: 1 | E29: =IF(ISNUMBER(D29),ROUND(D29*30,0),"－") -> 30 | F29: =③石川以降予測!T40 -> 616 | G29: =③石川以降予測!I40 -> 19 | H29: =F29-G29 -> 597 | I29: =③石川以降予測!J40 -> 22 | J29: =H29-I29 -> 575 | K29: =③石川以降予測!K40 -> 21 | L29: =J29-K29 -> 554 | M29: =③石川以降予測!L40 -> 15 | N29: =L29-M29 -> 539 | O29: =③石川以降予測!M40 -> 85 | P29: =N29-O29 -> 454 | Q29: =_xlfn.IFS(H29<0,"石川 香林坊大和",J29<0,"仙台 Ebeans",L29<0,"神戸阪急",N29<0,"鳥取島根 夢みなとタワー",P29<0,"東京凱旋 東京建物ぴあホール",TRUE(),"—") -> — | R29: =IF(Q29="—","",_xlfn.IFS(H29<0,DATE(2026,8,14),J29<0,DATE(2026,9,5),L29<0,DATE(2026,12,16),N29<0,DATE(2027,3,15),P29<0,DATE(2027,4,1))) | S29: =MAX(0,-P29) -> 0 | T29: =IF(S29>0,ROUNDUP(S29*(1+前提・入力!$B$35),0),0) -> 0 | U29: =IF(R29="","",IF(NOT(ISNUMBER(D29)),"再生産不可",R29-E29-前提・入力!$B$38)) | V29: =IF(OR(U29="",U29="再生産不可"),"",U29-前提・入力!$B$39) | W29: =IF(Q29="","—",IF(U29="再生産不可","×再生産不可",_xlfn.IFS(V29<0,"★期限超過",V29<=30,"★至急(30日以内)",V29<=90,"要着手(90日以内)",TRUE(),"余裕あり"))) -> 余裕あり
A30: 12 | B30: 4515142545402 | C30: 呪術廻戦 懐玉・玉折 クリアファイル（七海 建人） | D30: 1 | E30: =IF(ISNUMBER(D30),ROUND(D30*30,0),"－") -> 30 | F30: =③石川以降予測!T41 -> 919 | G30: =③石川以降予測!I41 -> 29 | H30: =F30-G30 -> 890 | I30: =③石川以降予測!J41 -> 34 | J30: =H30-I30 -> 856 | K30: =③石川以降予測!K41 -> 32 | L30: =J30-K30 -> 824 | M30: =③石川以降予測!L41 -> 24 | N30: =L30-M30 -> 800 | O30: =③石川以降予測!M41 -> 132 | P30: =N30-O30 -> 668 | Q30: =_xlfn.IFS(H30<0,"石川 香林坊大和",J30<0,"仙台 Ebeans",L30<0,"神戸阪急",N30<0,"鳥取島根 夢みなとタワー",P30<0,"東京凱旋 東京建物ぴあホール",TRUE(),"—") -> — | R30: =IF(Q30="—","",_xlfn.IFS(H30<0,DATE(2026,8,14),J30<0,DATE(2026,9,5),L30<0,DATE(2026,12,16),N30<0,DATE(2027,3,15),P30<0,DATE(2027,4,1))) | S30: =MAX(0,-P30) -> 0 | T30: =IF(S30>0,ROUNDUP(S30*(1+前提・入力!$B$35),0),0) -> 0 | U30: =IF(R30="","",IF(NOT(ISNUMBER(D30)),"再生産不可",R30-E30-前提・入力!$B$38)) | V30: =IF(OR(U30="",U30="再生産不可"),"",U30-前提・入力!$B$39) | W30: =IF(Q30="","—",IF(U30="再生産不可","×再生産不可",_xlfn.IFS(V30<0,"★期限超過",V30<=30,"★至急(30日以内)",V30<=90,"要着手(90日以内)",TRUE(),"余裕あり"))) -> 余裕あり
A31: 13 | B31: 4515142545419 | C31: 呪術廻戦 懐玉・玉折 クリアファイル（灰原 雄） | D31: 1 | E31: =IF(ISNUMBER(D31),ROUND(D31*30,0),"－") -> 30 | F31: =③石川以降予測!T42 -> 315 | G31: =③石川以降予測!I42 -> 6 | H31: =F31-G31 -> 309 | I31: =③石川以降予測!J42 -> 7 | J31: =H31-I31 -> 302 | K31: =③石川以降予測!K42 -> 6 | L31: =J31-K31 -> 296 | M31: =③石川以降予測!L42 -> 5 | N31: =L31-M31 -> 291 | O31: =③石川以降予測!M42 -> 27 | P31: =N31-O31 -> 264 | Q31: =_xlfn.IFS(H31<0,"石川 香林坊大和",J31<0,"仙台 Ebeans",L31<0,"神戸阪急",N31<0,"鳥取島根 夢みなとタワー",P31<0,"東京凱旋 東京建物ぴあホール",TRUE(),"—") -> — | R31: =IF(Q31="—","",_xlfn.IFS(H31<0,DATE(2026,8,14),J31<0,DATE(2026,9,5),L31<0,DATE(2026,12,16),N31<0,DATE(2027,3,15),P31<0,DATE(2027,4,1))) | S31: =MAX(0,-P31) -> 0 | T31: =IF(S31>0,ROUNDUP(S31*(1+前提・入力!$B$35),0),0) -> 0 | U31: =IF(R31="","",IF(NOT(ISNUMBER(D31)),"再生産不可",R31-E31-前提・入力!$B$38)) | V31: =IF(OR(U31="",U31="再生産不可"),"",U31-前提・入力!$B$39) | W31: =IF(Q31="","—",IF(U31="再生産不可","×再生産不可",_xlfn.IFS(V31<0,"★期限超過",V31<=30,"★至急(30日以内)",V31<=90,"要着手(90日以内)",TRUE(),"余裕あり"))) -> 余裕あり
A32: 14 | B32: 4515142545426 | C32: 呪術廻戦 渋谷事変 クリアファイル（虎杖 悠仁） | D32: 1 | E32: =IF(ISNUMBER(D32),ROUND(D32*30,0),"－") -> 30 | F32: =③石川以降予測!T43 -> 1752 | G32: =③石川以降予測!I43 -> 31 | H32: =F32-G32 -> 1721 | I32: =③石川以降予測!J43 -> 37 | J32: =H32-I32 -> 1684 | K32: =③石川以降予測!K43 -> 34 | L32: =J32-K32 -> 1650 | M32: =③石川以降予測!L43 -> 26 | N32: =L32-M32 -> 1624 | O32: =③石川以降予測!M43 -> 143 | P32: =N32-O32 -> 1481 | Q32: =_xlfn.IFS(H32<0,"石川 香林坊大和",J32<0,"仙台 Ebeans",L32<0,"神戸阪急",N32<0,"鳥取島根 夢みなとタワー",P32<0,"東京凱旋 東京建物ぴあホール",TRUE(),"—") -> — | R32: =IF(Q32="—","",_xlfn.IFS(H32<0,DATE(2026,8,14),J32<0,DATE(2026,9,5),L32<0,DATE(2026,12,16),N32<0,DATE(2027,3,15),P32<0,DATE(2027,4,1))) | S32: =MAX(0,-P32) -> 0 | T32: =IF(S32>0,ROUNDUP(S32*(1+前提・入力!$B$35),0),0) -> 0 | U32: =IF(R32="","",IF(NOT(ISNUMBER(D32)),"再生産不可",R32-E32-前提・入力!$B$38)) | V32: =IF(OR(U32="",U32="再生産不可"),"",U32-前提・入力!$B$39) | W32: =IF(Q32="","—",IF(U32="再生産不可","×再生産不可",_xlfn.IFS(V32<0,"★期限超過",V32<=30,"★至急(30日以内)",V32<=90,"要着手(90日以内)",TRUE(),"余裕あり"))) -> 余裕あり | X32: 7/28 運営欠品報告あり（札幌へ倉庫から追納）
A33: 15 | B33: 4515142545433 | C33: 呪術廻戦 渋谷事変 クリアファイル（伏黒 恵） | D33: 1 | E33: =IF(ISNUMBER(D33),ROUND(D33*30,0),"－") -> 30 | F33: =③石川以降予測!T44 -> 2072 | G33: =③石川以降予測!I44 -> 47 | H33: =F33-G33 -> 2025 | I33: =③石川以降予測!J44 -> 55 | J33: =H33-I33 -> 1970 | K33: =③石川以降予測!K44 -> 51 | L33: =J33-K33 -> 1919 | M33: =③石川以降予測!L44 -> 38 | N33: =L33-M33 -> 1881 | O33: =③石川以降予測!M44 -> 212 | P33: =N33-O33 -> 1669 | Q33: =_xlfn.IFS(H33<0,"石川 香林坊大和",J33<0,"仙台 Ebeans",L33<0,"神戸阪急",N33<0,"鳥取島根 夢みなとタワー",P33<0,"東京凱旋 東京建物ぴあホール",TRUE(),"—") -> — | R33: =IF(Q33="—","",_xlfn.IFS(H33<0,DATE(2026,8,14),J33<0,DATE(2026,9,5),L33<0,DATE(2026,12,16),N33<0,DATE(2027,3,15),P33<0,DATE(2027,4,1))) | S33: =MAX(0,-P33) -> 0 | T33: =IF(S33>0,ROUNDUP(S33*(1+前提・入力!$B$35),0),0) -> 0 | U33: =IF(R33="","",IF(NOT(ISNUMBER(D33)),"再生産不可",R33-E33-前提・入力!$B$38)) | V33: =IF(OR(U33="",U33="再生産不可"),"",U33-前提・入力!$B$39) | W33: =IF(Q33="","—",IF(U33="再生産不可","×再生産不可",_xlfn.IFS(V33<0,"★期限超過",V33<=30,"★至急(30日以内)",V33<=90,"要着手(90日以内)",TRUE(),"余裕あり"))) -> 余裕あり
A34: 16 | B34: 4515142545440 | C34: 呪術廻戦 渋谷事変 クリアファイル（釘崎 野薔薇） | D34: 1 | E34: =IF(ISNUMBER(D34),ROUND(D34*30,0),"－") -> 30 | F34: =③石川以降予測!T45 -> 757 | G34: =③石川以降予測!I45 -> 13 | H34: =F34-G34 -> 744 | I34: =③石川以降予測!J45 -> 15 | J34: =H34-I34 -> 729 | K34: =③石川以降予測!K45 -> 14 | L34: =J34-K34 -> 715 | M34: =③石川以降予測!L45 -> 11 | N34: =L34-M34 -> 704 | O34: =③石川以降予測!M45 -> 59 | P34: =N34-O34 -> 645 | Q34: =_xlfn.IFS(H34<0,"石川 香林坊大和",J34<0,"仙台 Ebeans",L34<0,"神戸阪急",N34<0,"鳥取島根 夢みなとタワー",P34<0,"東京凱旋 東京建物ぴあホール",TRUE(),"—") -> — | R34: =IF(Q34="—","",_xlfn.IFS(H34<0,DATE(2026,8,14),J34<0,DATE(2026,9,5),L34<0,DATE(2026,12,16),N34<0,DATE(2027,3,15),P34<0,DATE(2027,4,1))) | S34: =MAX(0,-P34) -> 0 | T34: =IF(S34>0,ROUNDUP(S34*(1+前提・入力!$B$35),0),0) -> 0 | U34: =IF(R34="","",IF(NOT(ISNUMBER(D34)),"再生産不可",R34-E34-前提・入力!$B$38)) | V34: =IF(OR(U34="",U34="再生産不可"),"",U34-前提・入力!$B$39) | W34: =IF(Q34="","—",IF(U34="再生産不可","×再生産不可",_xlfn.IFS(V34<0,"★期限超過",V34<=30,"★至急(30日以内)",V34<=90,"要着手(90日以内)",TRUE(),"余裕あり"))) -> 余裕あり
A35: 17 | B35: 4515142545457 | C35: 呪術廻戦 渋谷事変 クリアファイル（七海 建人） | D35: 1 | E35: =IF(ISNUMBER(D35),ROUND(D35*30,0),"－") -> 30 | F35: =③石川以降予測!T46 -> 2430 | G35: =③石川以降予測!I46 -> 70 | H35: =F35-G35 -> 2360 | I35: =③石川以降予測!J46 -> 82 | J35: =H35-I35 -> 2278 | K35: =③石川以降予測!K46 -> 76 | L35: =J35-K35 -> 2202 | M35: =③石川以降予測!L46 -> 57 | N35: =L35-M35 -> 2145 | O35: =③石川以降予測!M46 -> 317 | P35: =N35-O35 -> 1828 | Q35: =_xlfn.IFS(H35<0,"石川 香林坊大和",J35<0,"仙台 Ebeans",L35<0,"神戸阪急",N35<0,"鳥取島根 夢みなとタワー",P35<0,"東京凱旋 東京建物ぴあホール",TRUE(),"—") -> — | R35: =IF(Q35="—","",_xlfn.IFS(H35<0,DATE(2026,8,14),J35<0,DATE(2026,9,5),L35<0,DATE(2026,12,16),N35<0,DATE(2027,3,15),P35<0,DATE(2027,4,1))) | S35: =MAX(0,-P35) -> 0 | T35: =IF(S35>0,ROUNDUP(S35*(1+前提・入力!$B$35),0),0) -> 0 | U35: =IF(R35="","",IF(NOT(ISNUMBER(D35)),"再生産不可",R35-E35-前提・入力!$B$38)) | V35: =IF(OR(U35="",U35="再生産不可"),"",U35-前提・入力!$B$39) | W35: =IF(Q35="","—",IF(U35="再生産不可","×再生産不可",_xlfn.IFS(V35<0,"★期限超過",V35<=30,"★至急(30日以内)",V35<=90,"要着手(90日以内)",TRUE(),"余裕あり"))) -> 余裕あり | X35: 7/28 運営欠品報告あり（札幌へ倉庫から追納）
A36: 18 | B36: 4515142545464 | C36: 呪術廻戦 渋谷事変 クリアファイル（五条 悟） | D36: 1 | E36: =IF(ISNUMBER(D36),ROUND(D36*30,0),"－") -> 30 | F36: =③石川以降予測!T47 -> 9318 | G36: =③石川以降予測!I47 -> 371 | H36: =F36-G36 -> 8947 | I36: =③石川以降予測!J47 -> 438 | J36: =H36-I36 -> 8509 | K36: =③石川以降予測!K47 -> 404 | L36: =J36-K36 -> 8105 | M36: =③石川以降予測!L47 -> 303 | N36: =L36-M36 -> 7802 | O36: =③石川以降予測!M47 -> 1685 | P36: =N36-O36 -> 6117 | Q36: =_xlfn.IFS(H36<0,"石川 香林坊大和",J36<0,"仙台 Ebeans",L36<0,"神戸阪急",N36<0,"鳥取島根 夢みなとタワー",P36<0,"東京凱旋 東京建物ぴあホール",TRUE(),"—") -> — | R36: =IF(Q36="—","",_xlfn.IFS(H36<0,DATE(2026,8,14),J36<0,DATE(2026,9,5),L36<0,DATE(2026,12,16),N36<0,DATE(2027,3,15),P36<0,DATE(2027,4,1))) | S36: =MAX(0,-P36) -> 0 | T36: =IF(S36>0,ROUNDUP(S36*(1+前提・入力!$B$35),0),0) -> 0 | U36: =IF(R36="","",IF(NOT(ISNUMBER(D36)),"再生産不可",R36-E36-前提・入力!$B$38)) | V36: =IF(OR(U36="",U36="再生産不可"),"",U36-前提・入力!$B$39) | W36: =IF(Q36="","—",IF(U36="再生産不可","×再生産不可",_xlfn.IFS(V36<0,"★期限超過",V36<=30,"★至急(30日以内)",V36<=90,"要着手(90日以内)",TRUE(),"余裕あり"))) -> 余裕あり
A37: 19 | B37: 4515142545471 | C37: 呪術廻戦 渋谷事変 クリアファイル（夏油 傑） | D37: 1 | E37: =IF(ISNUMBER(D37),ROUND(D37*30,0),"－") -> 30 | F37: =③石川以降予測!T48 -> 2224 | G37: =③石川以降予測!I48 -> 12 | H37: =F37-G37 -> 2212 | I37: =③石川以降予測!J48 -> 14 | J37: =H37-I37 -> 2198 | K37: =③石川以降予測!K48 -> 13 | L37: =J37-K37 -> 2185 | M37: =③石川以降予測!L48 -> 10 | N37: =L37-M37 -> 2175 | O37: =③石川以降予測!M48 -> 55 | P37: =N37-O37 -> 2120 | Q37: =_xlfn.IFS(H37<0,"石川 香林坊大和",J37<0,"仙台 Ebeans",L37<0,"神戸阪急",N37<0,"鳥取島根 夢みなとタワー",P37<0,"東京凱旋 東京建物ぴあホール",TRUE(),"—") -> — | R37: =IF(Q37="—","",_xlfn.IFS(H37<0,DATE(2026,8,14),J37<0,DATE(2026,9,5),L37<0,DATE(2026,12,16),N37<0,DATE(2027,3,15),P37<0,DATE(2027,4,1))) | S37: =MAX(0,-P37) -> 0 | T37: =IF(S37>0,ROUNDUP(S37*(1+前提・入力!$B$35),0),0) -> 0 | U37: =IF(R37="","",IF(NOT(ISNUMBER(D37)),"再生産不可",R37-E37-前提・入力!$B$38)) | V37: =IF(OR(U37="",U37="再生産不可"),"",U37-前提・入力!$B$39) | W37: =IF(Q37="","—",IF(U37="再生産不可","×再生産不可",_xlfn.IFS(V37<0,"★期限超過",V37<=30,"★至急(30日以内)",V37<=90,"要着手(90日以内)",TRUE(),"余裕あり"))) -> 余裕あり
A38: 20 | B38: 4515142545488 | C38: 呪術廻戦 渋谷事変 クリアファイル（真人） | D38: 1 | E38: =IF(ISNUMBER(D38),ROUND(D38*30,0),"－") -> 30 | F38: =③石川以降予測!T49 -> 287 | G38: =③石川以降予測!I49 -> 11 | H38: =F38-G38 -> 276 | I38: =③石川以降予測!J49 -> 13 | J38: =H38-I38 -> 263 | K38: =③石川以降予測!K49 -> 12 | L38: =J38-K38 -> 251 | M38: =③石川以降予測!L49 -> 9 | N38: =L38-M38 -> 242 | O38: =③石川以降予測!M49 -> 49 | P38: =N38-O38 -> 193 | Q38: =_xlfn.IFS(H38<0,"石川 香林坊大和",J38<0,"仙台 Ebeans",L38<0,"神戸阪急",N38<0,"鳥取島根 夢みなとタワー",P38<0,"東京凱旋 東京建物ぴあホール",TRUE(),"—") -> — | R38: =IF(Q38="—","",_xlfn.IFS(H38<0,DATE(2026,8,14),J38<0,DATE(2026,9,5),L38<0,DATE(2026,12,16),N38<0,DATE(2027,3,15),P38<0,DATE(2027,4,1))) | S38: =MAX(0,-P38) -> 0 | T38: =IF(S38>0,ROUNDUP(S38*(1+前提・入力!$B$35),0),0) -> 0 | U38: =IF(R38="","",IF(NOT(ISNUMBER(D38)),"再生産不可",R38-E38-前提・入力!$B$38)) | V38: =IF(OR(U38="",U38="再生産不可"),"",U38-前提・入力!$B$39) | W38: =IF(Q38="","—",IF(U38="再生産不可","×再生産不可",_xlfn.IFS(V38<0,"★期限超過",V38<=30,"★至急(30日以内)",V38<=90,"要着手(90日以内)",TRUE(),"余裕あり"))) -> 余裕あり
