Workbook

Sheet サマリー
A1: アニメーション 呪術廻戦展「懐玉・玉折」「渋谷事変」
A2: LEGS／イベント記念商品 42SKU 全会場 販売分析・石川予測確定・仙台会場以降予測・追加発注判定
A3: 基準日：2026年8月26日 ／ 実績データ：東京(25日)・名古屋(19日)・博多(26日)・大阪(20日)・札幌(20日)＝全会期、石川＝8/25(会期12日目)まで ＋ SPJ様 欠品報告メール
A5: ■ 結論サマリー
A6: ① 石川 会期18日予測（確定値） | B6: LEGS42SKU 販売数 5,151個／販売金額 4,292,200円 ※博多・大阪・札幌 の実績倍率から算出
A7: 石川 全物販予測 | B7: 数量 24,559個／金額 25,161,149円 → 東京(初回)対比 7.0%
A8: 石川 入場者予測 | B8: 8,923人（初12日実績5,304人 × 札幌の初12日→20日 伸び率）
A9: ② LEGS物販構成比の推移 | B9: 金額：東京28.5%→名古屋29.9%→博多29.4%→大阪21.1%→札幌17.6%→石川17.1%(予測) 数量：38.7%→34.5%→40.0%→26.7%→21.8%→石川21.0%(予測)
A10: 構成比低下の主因 | B10: 大阪会場からの新商品106SKU投入（大阪の会期20日 金額シェア19.8%）。札幌・石川 は新規SKU 0で品揃えは大阪と同一
A11: ③ 仙台以降4会場 LEGS必要数 | B11: 61,617個（シナリオ①ユーザー指定：仙台13%・神戸阪急12%・鳥取島根9%・東京凱旋50%）
A12: シナリオ②企画概要書ベース | B12: 仙台15.60%・神戸阪急12.00%・鳥取島根9.00%・東京凱旋50.00%（企画概要書グッズ売上÷東京）→ 必要数 63,524個
A13: シナリオ③石川実績連動(保守) | B13: ②に石川の計画比達成率56.3%を乗算 → 仙台8.78%・神戸阪急6.75%・鳥取島根5.07%・東京凱旋50.00%（凱旋は据置）→ 必要数 51,789個
A14: ★残在庫想定の反映 | B14: 在庫フロー台帳の「梅田まで(SET)」列 276,521個を採用（梅田会場後の検品結果まで反映済み）。
A15: ★石川 への追納（実施済） | B15: 2026/8 石川(金沢)会場への札幌転送分＋8/22追納：札幌会場からの転送（LEGS 42SKU 計） 41,612個／宿儺の指風お菓子 20個 計41,632個（日報の販売可能数に反映済み）。倉庫在庫からの出荷なので全社在庫は不変
A16: 追納後になお必要な追納 | B16: 33個（会期20日予測が販売可能数を上回る残差）
A17: 仙台以降 供給可能在庫 | B17: 234,426個 ＝ 倉庫残197,962個 − 石川会期中の追納33個 ＋ 会期末の返送見込41,810個
... A34: 石川 会期中の追加発注 | B34: 3品目が会期内に在庫切れ見込：前髪ヘアバンド(不足20) 宿儺の指風お菓子(不足12) 夏油 傑 イメージリング（#15）(不足1)
A36: ■ 運営（SPJ様）欠品報告との突合 ※受領メール
A37: 報告された欠品／近々欠品 | B37: 0品目：
A38: ◎ モデルも会期中欠品を検知 | B38: 0品目：なし
A39: ○ モデルは高消化率で整合 | B39: 0品目：なし（予測消化率70%超。会期末までに枯渇する水準）
A40: △ モデル未検知（現場優先） | B40: 0品目：なし
A41: ▲ モデルのみ検知（現場未報告） | B41: 3品目：前髪ヘアバンド 宿儺の指風お菓子 夏油 傑 イメージリング（#15） → 現場に実在庫の確認を推奨
A42: ★追納不可と回答された品目 | B42: なし ＝ 前会場時点で「追納困難」と回答済。ただし7/8実在庫では倉庫残0個が確認できるため、下記の要確認事項を参照
A43: 突合の結論 | B43: 現場報告0品目のうち0品目がモデル側でも欠品または高消化率として検知されており、見落とし0・空振り0で完全に整合。
B44: 8/25（12日目）実績を織り込んだことで検知精度が上がり、予測モデルは現場実感と一致する水準にある。
B45: ④シートの「運営 欠品報告」「モデル×現場 突合」列で商品別に明示している（列位置は⑫シート参照）。
A46: ★倉庫在庫による解決可否 | B46: 報告0品目すべて2026/7/8時点で倉庫に在庫が残っており、追加生産ではなく倉庫からの追加納品で対応可能。
A47: 倉庫残（石川納品を除く）
A48: ※要確認 | B48: 「気分リフレッシュオルゴール」は倉庫残28個が存在する。前会場時の「追納困難」回答と実在庫が食い違うため、
B49: 出荷可否をSPJ様・倉庫に再確認のうえ、可能なら石川会場へ充当することを推奨。
A51: ■ 最重要リスクと打ち手
A52: 石川 の動員が計画比50% | B52: 初12日入場者5,304人（大阪同期間6,105人の86.9%）。物販売上も東京対比7.0%と、
B53: 仙台以降の会場比率も、この水準を踏まえて下方修正を検討すべき。
A54: 東京凱旋が必要数の60% | B54: 仙台以降 必要数61,617個のうち36,677個(60%)が東京凱旋。凱旋の50%前提が外れると発注量が大きくブレる。
B55: 発注は「仙台〜鳥取島根(3会場・24,940個)」を先行確定し、凱旋分は会期確定後に第2弾発注とするのが安全。
A56: ★過剰在庫のほうが深刻 | B56: 供給可能234,426個に対し仙台以降の必要数は61,617個。差引172,809個（供給可能の74%）が余剰となる見込み。
B57: 余剰上位：呪術廻戦 渋谷事変 ブラインド缶バッジ（全9 供給可能50,228個 vs 必要6,990個／呪術廻戦 懐玉・玉折 ブラインド缶バッジ（全 供給可能39,392個 vs 必要3,173個／呪術廻戦 懐玉・玉折 ブラインドミニ色紙（全 供給可能48,729個 vs 必要15,264個
B58: 追加発注よりも、余剰在庫の消化策（セット販売・ノベルティ転用等）の検討が急務。
A59: 不足はごく一部 | B59: 追加生産が必要なのは13品目・3,384個のみ。うち展示会キービジュアル クリアファイルが895個で全体の26%を占める。
A60: 生産リードタイムの制約 | B60: 生産日数は1か月（クリアファイル・ポストカード・缶バッジ・ステッカー系）、2.5か月（ミニ色紙2種・前髪ヘアバンド）、
B61: 3か月（絆創膏・お菓子・クリップ・エコバッグ・オルゴール・リング/フラグメント系）。バスボールは「－」＝再生産不可のため現有在庫で会場配分を組む必要がある。
A62: 賞味期限の制約 | B62: 宿儺の指風お菓子は賞味期限4か月以内の在庫が販売不可。仙台以降向けは2026/5/15手配済だが、
B63: 鳥取(27年3月)・東京凱旋(27年4月)向けは賞味期限の逆算で再手配の要否を要確認。
A65: ■ 算出モデル（①石川予測）
A66: 基本式 | B66: 石川 会期18日予測販売数 ＝ 石川 初12日(8/14-8/25)販売数 × 会期倍率 g
A67: 会期倍率 g | B67: g ＝ 各会場の「18日累計販売数 ÷ 初12日販売数」を商品別に算出し加重平均
A68: 採用会場と加重 | B68: 博多×1、大阪×1、札幌×2（直前会場・品揃え同一で条件が最も近い）。東京・名古屋 は除外
A69: 会期日数の揃え方 | B69: 各参照会場の頭から18日分を切り出して倍率化。18日に満たない会場は+0.00%を補完
A70: 42品計の実効倍率 | B70: 博多1.413倍・大阪1.225倍・札幌1.274倍 → 加重平均 1.296倍
A72: ■ 算出モデル（③仙台以降）
A73: 会場物販売上 | B73: 東京(初回)全物販売上 358,193,925円 × 東京対比比率
A74: LEGS売上 | B74: 会場物販売上 × LEGS金額構成比 17.1%（石川予測値＝大阪以降の推移の到達点を採用）
A75: LEGS数量 | B75: LEGS売上 ÷ LEGS平均単価 833円（石川予測ミックスベース）
A76: 商品別按分 | B76: 札幌20日実績の数量構成比50% ＋ 石川18日予測の数量構成比50% のブレンド
A77: 供給可能在庫 | B77: 倉庫残（札幌出荷後）197,962個 ＋ 札幌会期末残41,615個 − 石川会期18日予測販売5,151個 ＝ 234,426個
A79: ■ 追加商品によるLEGS売上低下（⑦）
A80: 市場は縮んでいない | B80: 物販客単価（全商品）は名古屋7,012円/人→大阪6,882円/人と▲1.8%でほぼ横ばい。
B81: 同期間にLEGSは2,099円/人→1,455円/人と▲30.7%（▲643円/人）。純粋なカニバリゼーション。
A82: 新商品の約47%が食い合い | B82: 大阪の新商品106SKUは1,360円/人を稼いだが、LEGS減少643円/人はその47%に相当。
A83: LEGSが削られ始めたのは博多 | B83: 博多で「おすわりぬいぐるみ全8種」(230円/人)＋アクリルカードスタンド(233円/人)を投入し、
B84: LEGSは2,099→1,634円/人（▲465）。大阪のうちわ14種・アクリル系39種でさらに▲179円/人。
A85: 被害はブラインド系に集中 | B85: ブラインド缶バッジ▲272円/人・ブラインドミニ色紙▲284円/人の2タイプでLEGS減少の87%。
B86: クリアファイル・ポストカード類は横ばい〜微増で影響なし。追加生産はブラインド系を抑制すべき。
A87: ★仙台以降の最大リスク | B87: 同規模の新商品を仙台以降に追加投入すると③の必要数61,617個は最大30%過大になる。
B88: 追加生産を確定する前に、仙台以降の新商品投入計画（有無・規模）を必ず確認すること。
A90: ■ シート構成
A91: 前提・入力 | B91: 会場比率・構成比・加重など全パラメータの入力（青字＝編集可）
A92: ①石川予測確定 | B92: 商品別 会期18日予測（会場別g・予測数量/金額・消化率・会期末残在庫）
A93: ②会場別構成比 | B93: 全会場のLEGS物販構成比（数量・金額）、供給元別構成比、東京対比 会場比率
A94: ③仙台以降予測 | B94: 残4会場のLEGS売上/数量予測と商品別必要数
A95: ④追加発注判定 | B95: 石川会期中／仙台以降 の商品別 発注要否・推奨数量
A96: ⑤全データ統合リスト | B96: 5会場×42商品の全実績・構成比・消化率・予測を1行に集約
A97: ⑥商品別 会場推移 | B97: 商品別の会場ごと販売数・構成比の推移（トレンド確認用）
A98: ⑦新商品影響分析 | B98: 梅田以降の追加商品（ぬいぐるみ・うちわ等）によるLEGS売上低下の要因分析
A99: ⑧実在庫(7-8)明細 | B99: 2026/7/8時点の実在庫（CX催事＋DBS倉庫＋梅田返送良品）と商品別の欠品算出
A100: ⑨過去4会場 予測vs実績 | B100: 池袋・名古屋・博多・梅田の商品別 販売予測／実績／予測時構成比／実績後の構成比修正
A101: ⑩会場比率シナリオ比較 | B101: 仙台以降の東京対比比率 4シナリオ（ユーザー指定／企画概要書／石川実績連動／手動）の比較
A102: ⑪会場別引当・発注期限 | B102: 会場順の在庫引当、欠品発生会場の特定、生産日数から逆算した最終発注期限
... A105: 運営欠品報告の反映先 | B105: ④追加発注判定シートの「運営 欠品報告」「モデル×現場 突合」列、および⑧シートの運営欠品報告列・備考欄
A107: ■ 前提と留意事項
A108: データ再読込 | B108: 全5会場のレジ通過単品売上を全件再読込・再集計。名古屋は後半4/1-4/5の追加提供データを反映し、
B109: 会期19日間（3/18-4/5）の完全実績となった。これに伴い名古屋の会期倍率gは推計2.438倍→実績2.215倍に修正。
A110: LEGS＝42SKU | B110: 各会場の商品分類「記念商品/レッグス」「レッグス/イベント記念」は全会場で本42SKUと完全一致
A111: 物販売上の定義 | B111: レジ袋代・音声ガイド・当日券を除いた商品売上（税込）。会場報告の総売上とは一致しない場合がある
A112: 残在庫の出所 | B112: 在庫フロー台帳（会場ごとの追加発注→販売→レッグス検品を積み上げた表）の最終実在庫列。
B113: 実際の発注前に倉庫在庫と過去会場の返品在庫を相殺すること（前提・入力シートで控除可能）。
A114: 神戸阪急の会場比率 | B114: 東京対比の指定が無いため12%を仮置き。要確認事項。
A115: 仙台の会場比率 | B115: ユーザー指定13%を採用。コナンカフェ2026実績（東京対比10.5%）とは2.5pt乖離あり。
A116: 鳥取会場 | B116: 会期3/15-4/4を21日間として計上。
A117: 価格改定 | B117: イメージリング8種は東京¥22,000→名古屋以降¥27,500に改定。⑤では会場別の実売単価で金額を算出。
A118: 元データの小数値 | B118: 名古屋の販売可能数に小数を含む商品が3件あるため整数に丸めて処理している（合計への影響は1個未満）。
A119: 東京の内覧会 | B119: 東京の12/4内覧会分（全商品計142個）は会期実績から除外して会場間比較している。

Sheet 前提・入力
A1: 前提・入力パラメータ
A2: 青字・黄色セルが入力値です。変更すると①③④⑤シートの予測が自動再計算されます。
A4: ■ ①石川予測 モデルパラメータ
A5: 会期倍率g 加重：東京 | B5: 0 | C5: 【何に効くか】①シートO列「採用倍率g」の加重平均ウェイト。石川18日予測＝初12日(8/14-8/25)実績×採用倍率g。 【なぜ0か】東京は初動カーブが石川と大きく異なるため、ユーザー指示により倍率の算出根拠から除外している（0固定）。0以外にすると①の採用倍率g＝石川予測が全品変動する。
A6: 会期倍率g 加重：名古屋 | B6: 0 | C6: 【何に効くか】①シートO列「採用倍率g」の加重平均ウェイト。石川18日予測＝初12日(8/14-8/25)実績×採用倍率g。 【なぜ0か】名古屋は初動カーブが石川と大きく異なるため、ユーザー指示により倍率の算出根拠から除外している（0固定）。0以外にすると①の採用倍率g＝石川予測が全品変動する。
A7: 会期倍率g 加重：博多 | B7: 1 | C7: 【何に効くか】①シートO列「採用倍率g」の加重平均ウェイト。石川18日予測＝初12日(8/14-8/25)実績×採用倍率g。 【算出】博多③は26日会期のため、頭から18日分だけを切り出して倍率化する（18日累計 ÷ 初12日）。博多の倍率g＝1.413。会期構成が石川と異なるため加重1。
A8: 会期倍率g 加重：大阪 | B8: 1 | C8: 【何に効くか】①シートO列「採用倍率g」の加重平均ウェイト。石川18日予測＝初12日(8/14-8/25)実績×採用倍率g。 【算出】大阪④は20日会期のため、頭から18日分だけを切り出して倍率化する（18日累計 ÷ 初12日）。大阪の倍率g＝1.225。会期構成が石川と異なるため加重1。
A9: 会期倍率g 加重：札幌 | B9: 2 | C9: 【何に効くか】①シートO列「採用倍率g」の加重平均ウェイト。石川18日予測＝初12日(8/14-8/25)実績×採用倍率g。 【なぜ2倍か】札幌⑤は直前に終了した会場で、品揃えが石川と同一・会期20日と条件が最も近い。このため他会場の2倍の重みを置く。札幌の倍率g＝1.274（42品計）。
A10: 会期が18日に満たない参照会場の補完率 | B10: 0 | C10: 【何に効くか】会期が18日より短い参照会場（今回は該当なし）の倍率gの分子補正。 【算出】18日以上ある会場の「18日累計 ÷ その会場の会期日数までの累計」の伸び率の平均。短い会場の累計にこの率を掛けて18日相当に補完し、他会場と粒度を揃える。
A11: 全体倍率g（実績ゼロ品のフォールバック） | B11: 1.2962063 | C11: 【何に効くか】①シートの採用倍率gのIFERROR代替値。 【算出】42品計の初12日→18日 加重平均倍率＝1.296。参照会場（博多／大阪／札幌）のいずれにも初12日実績が無く商品別倍率を計算できない品にだけ適用する。
A12: ■ ②③会場比率 前提
A13: 東京(初回) 全物販売上（税込） | B13: 358193925 | C13: 【出所】東京(初回) 池袋サンシャインシティ 25日間の全物販実績（税込）。レジ袋代・音声ガイド・当日券を除いた商品売上のみ。 【何に効くか】③シートE列の基準額。本値×東京対比で次会場以降 各会場の物販売上を推定する。
A14: 東京(初回) 全物販 販売数量 | B14: 383342 | C14: 【出所】同上（東京25日間の全物販 販売数量）。 【何に効くか】②シートの「全物販 販売数量」の次会場以降 予測（＝本値×東京対比）と、LEGS数量構成比の母数。
A15: ★シナリオ選択（1〜4） | B15: 1 | C15: 1＝ユーザー指定／2＝企画概要書ベース／3＝石川実績連動(保守)／4＝手動入力(F列を使用)。 【何に効くか】下の「東京対比：〇〇」がINDEXで自動切替 → ③D列 → 会場売上 → 必要数 → ④の発注判定まで一気に連動する。4シナリオの結果比較は⑩シート。
A16: シナリオ別 東京対比比率 | C16: ①ユーザー指定 | D16: ②企画概要書ベース | E16: ③石川実績連動(保守) | F16: ④手動入力
A17: 仙台 Ebeans | B17: 26/9/5(土)-10/4(日)（30日間） | C17: 0.13 | D17: 0.156 | E17: 0.087805611 | F17: 0.13
A18: 神戸阪急 | B18: 26/12/16(水)-27/1/7(木)（21日間） | C18: 0.12 | D18: 0.12 | E18: 0.067542777 | F18: 0.12
A19: 鳥取島根 夢みなとタワー | B19: 27/3/15-4/4（21日間） | C19: 0.09 | D19: 0.09 | E19: 0.050657083 | F19: 0.09
A20: 東京凱旋 東京建物ぴあホール | B20: 27年4-5月（25日間） | C20: 0.5 | D20: 0.5 | E20: 0.5 | F20: 0.5
A21: ※③は企画概要書の計画値に石川の計画比達成率 56.3% を乗じたもの（凱旋は据置）
A23: 東京対比：仙台 Ebeans | B23: =INDEX(C17:F17,前提・入力!$B$15) -> 0.13 | C23: 【何に効くか】緑字＝シナリオ選択に応じて上表からINDEXで自動取得。仙台 Ebeansの物販売上を東京(初回)の13.00%＝46,565,210円と置く（③シートE列）。 【根拠】ユーザー指定値。会期が30日間と全会場で最長のため高めに設定している。同規模イベントのコナンカフェ2026では仙台は東京対比10.5%の実績。
A24: 東京対比：神戸阪急 | B24: =INDEX(C18:F18,前提・入力!$B$15) -> 0.12 | C24: 【何に効くか】緑字＝シナリオ選択に応じて上表からINDEXで自動取得。神戸阪急の物販売上を東京(初回)の12.00%＝42,983,271円と置く（③シートE列）。 【根拠】★要確認：指定も類似実績も無いため仮置き。確定したらシナリオ④の手動入力(F列)を書き換え、シナリオ選択＝4で反映させる。
A25: 東京対比：鳥取島根 夢みなとタワー | B25: =INDEX(C19:F19,前提・入力!$B$15) -> 0.09 | C25: 【何に効くか】緑字＝シナリオ選択に応じて上表からINDEXで自動取得。鳥取島根 夢みなとタワーの物販売上を東京(初回)の9.00%＝32,237,453円と置く（③シートE列）。 【根拠】商圏規模が小さく信頼できる類似実績も無いため、他の地方会場より低めに置いたユーザー指定値。
A26: 東京対比：東京凱旋 東京建物ぴあホール | B26: =INDEX(C20:F20,前提・入力!$B$15) -> 0.5 | C26: 【何に効くか】緑字＝シナリオ選択に応じて上表からINDEXで自動取得。東京凱旋 東京建物ぴあホールの物販売上を東京(初回)の50.00%＝179,096,962円と置く（③シートE列）。 【根拠】ユーザー指定「初回東京の50%」。全シナリオ共通で据置のためシナリオを切り替えても動かない。次会場以降の必要数の過半を占める、最も感度の高い前提。
A27: ［参考］コナンカフェ2026 東京対比 | C27: 【参考実績】大阪53.6%・名古屋26.8%・神奈川19.1%・北海道13.3%・仙台10.5%。地方会場は東京の10〜20%に収束する傾向がある。 上の東京対比の水準感が妥当かを検証するための参考値で、計算には使っていない。
A28: ■ ③仙台以降 LEGS構成比 前提
A29: LEGS 金額構成比（仙台以降） | B29: 0.17058839 | C29: 【意味】会場の全物販売上のうち LEGS 42SKU が占める金額シェア。 【推移】東京 28.5% → 名古屋 29.9% → 博多 29.4% → 大阪 21.1% → 札幌 17.6% → 石川18日予測 17.1%。大阪以降の新商品106SKU投入で低下しており、その到達点を次会場以降にも適用する。 【何に効くか】③シートF列＝E列(会場 全物販売上)×本値。
A30: LEGS 平均単価（税込） | B30: 833 | C30: 【算出】石川18日予測の金額 4,292,200円 ÷ 数量 5,151個 ≒ 833円（①シートQ49合計 ÷ P49合計）。新商品投入後の商品ミックスを反映した加重平均単価。 【何に効くか】③シートG列＝ROUND(F列 LEGS売上 ÷ 本単価,0)＝次会場以降の必要数量。
A31: 商品別按分：札幌20日実績の構成比ウェイト | B31: 0.5 | C31: 【何に効くか】③シートH列「採用 按分構成比」＝大阪構成比(E列)×本値 ＋ 石川構成比(G列)×下の値。総必要数をどの商品に何個振るかを決める。 【札幌を使う理由】直前に終了した会場で42品すべての確定実績（20日・8,891個）があり、品揃えも石川と同一。
A32: 商品別按分：石川18日予測の構成比ウェイト | B32: 0.5 | C32: 大阪ウェイトとの合計が100%になるよう設定する。 【石川を使う理由】新商品投入後のミックスで、次会場以降の品揃えに条件が近い（ただし予測値）。 【感度】総必要数は変わらず、品目別の偏りだけが動く。大阪100%に寄せると定番商品へ、石川100%に寄せると直近で伸びている商品へ配分が寄る。
A33: ■ ④追加発注 前提
A34: 安全率（不足数に対する上乗せ） | B34: 0.1 | C34: 【何に効くか】③④⑧⑪シートの推奨発注数＝IF(不足>0, ROUNDUP(不足数×(1+本率),0), 0)。 【根拠】輸送中の破損・検品不良・予測超過の緩衝として10%を上乗せしている。
A35: ［参考］残在庫想定 全品計（梅田まで(SET)） | B35: 276521 | C35: 【出所】在庫フロー台帳「【清算(卸値67％)】…_検品差異」シートの最終「実在庫」列（梅田まで(SET)）の42SKU合計。会場ごとの 追加発注→販売→レッグス検品 を積み上げた確定値で、直近会場の返送検品まで反映済み。石川会場への納品数と石川会場の販売数はまだ差し引かれていない。 【何に効くか】本セルは⑧シートH49合計へのリンク（表示用）。商品別の実数を③⑧⑩⑪シートが直接参照する。
A36: 石川 会期末残在庫のスライド率 | B36: 1 | C36: 【何に効くか】③シートS列「石川会期末 返送(スライド)」＝ROUND(①シートU列×本率,0)。次会場以降の供給可能在庫に加算される。 【100%の意味】石川終了在庫 41,810個を全量 次会場以降へ回せる前提。損傷・返送ロスを見込むなら下げる → 供給が減り追加生産が増える。
A37: 発注〜納品バッファ日数（輸送・検品） | B37: 14 | C37: 【何に効くか】④⑧⑪シートの最終発注期限＝欠品発生会場の会期初日 − 生産日数(か月×30日) − 本バッファ。 【内訳】14日＝工場出荷 → 国内輸送・入荷検品・会場搬入のリードタイム。
A38: 基準日 | B38: 46260 | C38: 【根拠】2026/08/26＝本分析の基準日（生産日数の提示は2026/7/28時点）。 【何に効くか】④⑧⑪シートの「基準日からの残日数」＝最終発注期限 − 本日付。日付を進めると残日数が減り、期限超過の判定が増える。

Sheet ①石川予測確定
A1: ① 石川会場 会期18日間（26/8/14(金)-8/31(月)）商品別 販売予測【確定値】
A2: 算出根拠：東京を除く名古屋①・博多②・大阪④の「18日累計 ÷ 初12日」倍率を商品別に加重平均し、石川の初12日(8/14-8/25)実績に乗算
A3: 加重：博多1・大阪1・札幌2（「前提・入力」シートで変更可）
A6: No. | B6: JAN | C6: 商品名 | D6: 税込 単価 | E6: 石川 初12日 8/14-8/25 | F6: 博多③ 初12日 | G6: 博多③ 18日累計 | H6: 博多 倍率g | I6: 大阪④ 初12日 | J6: 大阪④ 18日累計 | K6: 大阪 倍率g | L6: 札幌⑤ 初12日 | M6: 札幌⑤ 18日累計 | N6: 札幌 倍率g | O6: 採用 倍率g | P6: 石川 会期18日 予測販売数 | Q6: 石川 予測販売金額 | R6: 石川 数量構成比 | S6: 石川 販売可能数 (追納込) | T6: 予測 消化率 | U6: 会期末 残在庫 | V6: 会期中 過不足 | W6: 会期中 在庫判定
A7: 1 | B7: 4515142545082 | C7: 呪術廻戦 メタリックポストカード 展示会キービジュアル | D7: 500 | E7: 210 | F7: 719 | G7: 944 | H7: =IF(F7=0,"",G7/F7) -> 1.3129346 | I7: 1710 | J7: 2158 | K7: =IF(I7=0,"",J7/I7) -> 1.2619883 | L7: 343 | M7: 447 | N7: =IF(L7=0,"",M7/L7) -> 1.303207 | O7: =IFERROR((IF(H7="",0,H7*前提・入力!$B$7)+IF(K7="",0,K7*前提・入力!$B$8)+IF(N7="",0,N7*前提・入力!$B$9))/(IF(H7="",0,前提・入力!$B$7)+IF(K7="",0,前提・入力!$B$8)+IF(N7="",0,前提・入力!$B$9)),前提・入力!$B$11) -> 1.2953342 | P7: =ROUND(E7*O7,0) -> 272 | Q7: =P7*D7 -> 136000 | R7: =IFERROR(P7/P$49,0) -> 0.052805281 | S7: 693 | T7: =IFERROR(P7/S7,0) -> 0.39249639 | U7: =MAX(0,S7-P7) -> 421 | V7: =P7-S7 -> -421 | W7: =IF(V7>0,"会期中に在庫切れ",IF(T7>=0.9,"要注意(90%超)",IF(T7>=0.5,"適正","在庫余剰"))) -> 在庫余剰
A8: 2 | B8: 4515142545099 | C8: 呪術廻戦 クリアファイル 展示会キービジュアル | D8: 600 | E8: 250 | F8: 653 | G8: 850 | H8: =IF(F8=0,"",G8/F8) -> 1.3016845 | I8: 1500 | J8: 1781 | K8: =IF(I8=0,"",J8/I8) -> 1.1873333 | L8: 362 | M8: 492 | N8: =IF(L8=0,"",M8/L8) -> 1.359116 | O8: =IFERROR((IF(H8="",0,H8*前提・入力!$B$7)+IF(K8="",0,K8*前提・入力!$B$8)+IF(N8="",0,N8*前提・入力!$B$9))/(IF(H8="",0,前提・入力!$B$7)+IF(K8="",0,前提・入力!$B$8)+IF(N8="",0,前提・入力!$B$9)),前提・入力!$B$11) -> 1.3018125 | P8: =ROUND(E8*O8,0) -> 325 | Q8: =P8*D8 -> 195000 | R8: =IFERROR(P8/P$49,0) -> 0.063094545 | S8: 659 | T8: =IFERROR(P8/S8,0) -> 0.49317147 | U8: =MAX(0,S8-P8) -> 334 | V8: =P8-S8 -> -334 | W8: =IF(V8>0,"会期中に在庫切れ",IF(T8>=0.9,"要注意(90%超)",IF(T8>=0.5,"適正","在庫余剰"))) -> 在庫余剰
A9: 3 | B9: 4515142545105 | C9: 呪術廻戦 懐玉・玉折 ポストカードセット（5枚入） | D9: 1000 | E9: 92 | F9: 280 | G9: 368 | H9: =IF(F9=0,"",G9/F9) -> 1.3142857 | I9: 904 | J9: 1063 | K9: =IF(I9=0,"",J9/I9) -> 1.175885 | L9: 116 | M9: 152 | N9: =IF(L9=0,"",M9/L9) -> 1.3103448 | O9: =IFERROR((IF(H9="",0,H9*前提・入力!$B$7)+IF(K9="",0,K9*前提・入力!$B$8)+IF(N9="",0,N9*前提・入力!$B$9))/(IF(H9="",0,前提・入力!$B$7)+IF(K9="",0,前提・入力!$B$8)+IF(N9="",0,前提・入力!$B$9)),前提・入力!$B$11) -> 1.2777151 | P9: =ROUND(E9*O9,0) -> 118 | Q9: =P9*D9 -> 118000 | R9: =IFERROR(P9/P$49,0) -> 0.022908173 | S9: 381 | T9: =IFERROR(P9/S9,0) -> 0.30971129 | U9: =MAX(0,S9-P9) -> 263 | V9: =P9-S9 -> -263 | W9: =IF(V9>0,"会期中に在庫切れ",IF(T9>=0.9,"要注意(90%超)",IF(T9>=0.5,"適正","在庫余剰"))) -> 在庫余剰
A10: 4 | B10: 4515142545112 | C10: 呪術廻戦 渋谷事変 ポストカードセット（9枚入） | D10: 1800 | E10: 110 | F10: 353 | G10: 427 | H10: =IF(F10=0,"",G10/F10) -> 1.2096317 | I10: 1012 | J10: 1209 | K10: =IF(I10=0,"",J10/I10) -> 1.194664 | L10: 170 | M10: 209 | N10: =IF(L10=0,"",M10/L10) -> 1.2294118 | O10: =IFERROR((IF(H10="",0,H10*前提・入力!$B$7)+IF(K10="",0,K10*前提・入力!$B$8)+IF(N10="",0,N10*前提・入力!$B$9))/(IF(H10="",0,前提・入力!$B$7)+IF(K10="",0,前提・入力!$B$8)+IF(N10="",0,前提・入力!$B$9)),前提・入力!$B$11) -> 1.2157798 | P10: =ROUND(E10*O10,0) -> 134 | Q10: =P10*D10 -> 241200 | R10: =IFERROR(P10/P$49,0) -> 0.026014366 | S10: 772 | T10: =IFERROR(P10/S10,0) -> 0.17357513 | U10: =MAX(0,S10-P10) -> 638 | V10: =P10-S10 -> -638 | W10: =IF(V10>0,"会期中に在庫切れ",IF(T10>=0.9,"要注意(90%超)",IF(T10>=0.5,"適正","在庫余剰"))) -> 在庫余剰
A11: 5 | B11: 4515142545129 | C11: 呪術廻戦 懐玉・玉折 ブラインド缶バッジ（全5種） | D11: 600 | E11: 226 | F11: 3298 | G11: 5127 | H11: =IF(F11=0,"",G11/F11) -> 1.5545785 | I11: 7193 | J11: 8539 | K11: =IF(I11=0,"",J11/I11) -> 1.1871264 | L11: 322 | M11: 394 | N11: =IF(L11=0,"",M11/L11) -> 1.2236025 | O11: =IFERROR((IF(H11="",0,H11*前提・入力!$B$7)+IF(K11="",0,K11*前提・入力!$B$8)+IF(N11="",0,N11*前提・入力!$B$9))/(IF(H11="",0,前提・入力!$B$7)+IF(K11="",0,前提・入力!$B$8)+IF(N11="",0,前提・入力!$B$9)),前提・入力!$B$11) -> 1.2972275 | P11: =ROUND(E11*O11,0) -> 293 | Q11: =P11*D11 -> 175800 | R11: =IFERROR(P11/P$49,0) -> 0.056882159 | S11: 8790 | T11: =IFERROR(P11/S11,0) -> 0.033333333 | U11: =MAX(0,S11-P11) -> 8497 | V11: =P11-S11 -> -8497 | W11: =IF(V11>0,"会期中に在庫切れ",IF(T11>=0.9,"要注意(90%超)",IF(T11>=0.5,"適正","在庫余剰"))) -> 在庫余剰
A12: 6 | B12: 4515142545136 | C12: 呪術廻戦 渋谷事変 ブラインド缶バッジ（全9種） | D12: 600 | E12: 439 | F12: 4238 | G12: 6491 | H12: =IF(F12=0,"",G12/F12) -> 1.5316187 | I12: 13071 | J12: 17062 | K12: =IF(I12=0,"",J12/I12) -> 1.3053324 | L12: 860 | M12: 995 | N12: =IF(L12=0,"",M12/L12) -> 1.1569767 | O12: =IFERROR((IF(H12="",0,H12*前提・入力!$B$7)+IF(K12="",0,K12*前提・入力!$B$8)+IF(N12="",0,N12*前提・入力!$B$9))/(IF(H12="",0,前提・入力!$B$7)+IF(K12="",0,前提・入力!$B$8)+IF(N12="",0,前提・入力!$B$9)),前提・入力!$B$11) -> 1.2877261 | P12: =ROUND(E12*O12,0) -> 565 | Q12: =P12*D12 -> 339000 | R12: =IFERROR(P12/P$49,0) -> 0.10968744 | S12: 13249 | T12: =IFERROR(P12/S12,0) -> 0.042644728 | U12: =MAX(0,S12-P12) -> 12684 | V12: =P12-S12 -> -12684 | W12: =IF(V12>0,"会期中に在庫切れ",IF(T12>=0.9,"要注意(90%超)",IF(T12>=0.5,"適正","在庫余剰"))) -> 在庫余剰
A13: 7 | B13: 4515142545143 | C13: 呪術廻戦 懐玉・玉折 ブラインドダイカットステッカー（全5種） | D13: 600 | E13: 130 | F13: 239 | G13: 321 | H13: =IF(F13=0,"",G13/F13) -> 1.3430962 | I13: 727 | J13: 880 | K13: =IF(I13=0,"",J13/I13) -> 1.2104539 | L13: 134 | M13: 169 | N13: =IF(L13=0,"",M13/L13) -> 1.261194 | O13: =IFERROR((IF(H13="",0,H13*前提・入力!$B$7)+IF(K13="",0,K13*前提・入力!$B$8)+IF(N13="",0,N13*前提・入力!$B$9))/(IF(H13="",0,前提・入力!$B$7)+IF(K13="",0,前提・入力!$B$8)+IF(N13="",0,前提・入力!$B$9)),前提・入力!$B$11) -> 1.2689846 | P13: =ROUND(E13*O13,0) -> 165 | Q13: =P13*D13 -> 99000 | R13: =IFERROR(P13/P$49,0) -> 0.032032615 | S13: 463 | T13: =IFERROR(P13/S13,0) -> 0.35637149 | U13: =MAX(0,S13-P13) -> 298 | V13: =P13-S13 -> -298 | W13: =IF(V13>0,"会期中に在庫切れ",IF(T13>=0.9,"要注意(90%超)",IF(T13>=0.5,"適正","在庫余剰"))) -> 在庫余剰
A14: 8 | B14: 4515142545150 | C14: 呪術廻戦 渋谷事変 ブラインドダイカットステッカー（全9種） | D14: 600 | E14: 207 | F14: 435 | G14: 581 | H14: =IF(F14=0,"",G14/F14) -> 1.3356322 | I14: 1388 | J14: 1642 | K14: =IF(I14=0,"",J14/I14) -> 1.1829971 | L14: 222 | M14: 291 | N14: =IF(L14=0,"",M14/L14) -> 1.3108108 | O14: =IFERROR((IF(H14="",0,H14*前提・入力!$B$7)+IF(K14="",0,K14*前提・入力!$B$8)+IF(N14="",0,N14*前提・入力!$B$9))/(IF(H14="",0,前提・入力!$B$7)+IF(K14="",0,前提・入力!$B$8)+IF(N14="",0,前提・入力!$B$9)),前提・入力!$B$11) -> 1.2850627 | P14: =ROUND(E14*O14,0) -> 266 | Q14: =P14*D14 -> 159600 | R14: =IFERROR(P14/P$49,0) -> 0.051640458 | S14: 778 | T14: =IFERROR(P14/S14,0) -> 0.34190231 | U14: =MAX(0,S14-P14) -> 512 | V14: =P14-S14 -> -512 | W14: =IF(V14>0,"会期中に在庫切れ",IF(T14>=0.9,"要注意(90%超)",IF(T14>=0.5,"適正","在庫余剰"))) -> 在庫余剰
A15: 9 | B15: 4515142545372 | C15: 呪術廻戦 懐玉・玉折 クリアファイル（五条 悟） | D15: 600 | E15: 41 | F15: 223 | G15: 261 | H15: =IF(F15=0,"",G15/F15) -> 1.1704036 | I15: 615 | J15: 697 | K15: =IF(I15=0,"",J15/I15) -> 1.1333333 | L15: 106 | M15: 144 | N15: =IF(L15=0,"",M15/L15) -> 1.3584906 | O15: =IFERROR((IF(H15="",0,H15*前提・入力!$B$7)+IF(K15="",0,K15*前提・入力!$B$8)+IF(N15="",0,N15*前提・入力!$B$9))/(IF(H15="",0,前提・入力!$B$7)+IF(K15="",0,前提・入力!$B$8)+IF(N15="",0,前提・入力!$B$9)),前提・入力!$B$11) -> 1.2551795 | P15: =ROUND(E15*O15,0) -> 51 | Q15: =P15*D15 -> 30600 | R15: =IFERROR(P15/P$49,0) -> 0.0099009901 | S15: 740 | T15: =IFERROR(P15/S15,0) -> 0.068918919 | U15: =MAX(0,S15-P15) -> 689 | V15: =P15-S15 -> -689 | W15: =IF(V15>0,"会期中に在庫切れ",IF(T15>=0.9,"要注意(90%超)",IF(T15>=0.5,"適正","在庫余剰"))) -> 在庫余剰
A16: 10 | B16: 4515142545389 | C16: 呪術廻戦 懐玉・玉折 クリアファイル（夏油 傑） | D16: 600 | E16: 16 | F16: 93 | G16: 104 | H16: =IF(F16=0,"",G16/F16) -> 1.1182796 | I16: 219 | J16: 254 | K16: =IF(I16=0,"",J16/I16) -> 1.1598174 | L16: 38 | M16: 53 | N16: =IF(L16=0,"",M16/L16) -> 1.3947368 | O16: =IFERROR((IF(H16="",0,H16*前提・入力!$B$7)+IF(K16="",0,K16*前提・入力!$B$8)+IF(N16="",0,N16*前提・入力!$B$9))/(IF(H16="",0,前提・入力!$B$7)+IF(K16="",0,前提・入力!$B$8)+IF(N16="",0,前提・入力!$B$9)),前提・入力!$B$11) -> 1.2668927 | P16: =ROUND(E16*O16,0) -> 20 | Q16: =P16*D16 -> 12000 | R16: =IFERROR(P16/P$49,0) -> 0.0038827412 | S16: 541 | T16: =IFERROR(P16/S16,0) -> 0.036968577 | U16: =MAX(0,S16-P16) -> 521 | V16: =P16-S16 -> -521 | W16: =IF(V16>0,"会期中に在庫切れ",IF(T16>=0.9,"要注意(90%超)",IF(T16>=0.5,"適正","在庫余剰"))) -> 在庫余剰
A17: 11 | B17: 4515142545396 | C17: 呪術廻戦 懐玉・玉折 クリアファイル（家入 硝子） | D17: 600 | E17: 6 | F17: 27 | G17: 30 | H17: =IF(F17=0,"",G17/F17) -> 1.1111111 | I17: 54 | J17: 69 | K17: =IF(I17=0,"",J17/I17) -> 1.2777778 | L17: 11 | M17: 16 | N17: =IF(L17=0,"",M17/L17) -> 1.4545455 | O17: =IFERROR((IF(H17="",0,H17*前提・入力!$B$7)+IF(K17="",0,K17*前提・入力!$B$8)+IF(N17="",0,N17*前提・入力!$B$9))/(IF(H17="",0,前提・入力!$B$7)+IF(K17="",0,前提・入力!$B$8)+IF(N17="",0,前提・入力!$B$9)),前提・入力!$B$11) -> 1.3244949 | P17: =ROUND(E17*O17,0) -> 8 | Q17: =P17*D17 -> 4800 | R17: =IFERROR(P17/P$49,0) -> 0.0015530965 | S17: 79 | T17: =IFERROR(P17/S17,0) -> 0.10126582 | U17: =MAX(0,S17-P17) -> 71 | V17: =P17-S17 -> -71 | W17: =IF(V17>0,"会期中に在庫切れ",IF(T17>=0.9,"要注意(90%超)",IF(T17>=0.5,"適正","在庫余剰"))) -> 在庫余剰
A18: 12 | B18: 4515142545402 | C18: 呪術廻戦 懐玉・玉折 クリアファイル（七海 建人） | D18: 600 | E18: 13 | F18: 32 | G18: 42 | H18: =IF(F18=0,"",G18/F18) -> 1.3125 | I18: 107 | J18: 126 | K18: =IF(I18=0,"",J18/I18) -> 1.1775701 | L18: 27 | M18: 36 | N18: =IF(L18=0,"",M18/L18) -> 1.3333333 | O18: =IFERROR((IF(H18="",0,H18*前提・入力!$B$7)+IF(K18="",0,K18*前提・入力!$B$8)+IF(N18="",0,N18*前提・入力!$B$9))/(IF(H18="",0,前提・入力!$B$7)+IF(K18="",0,前提・入力!$B$8)+IF(N18="",0,前提・入力!$B$9)),前提・入力!$B$11) -> 1.2891842 | P18: =ROUND(E18*O18,0) -> 17 | Q18: =P18*D18 -> 10200 | R18: =IFERROR(P18/P$49,0) -> 0.00330033 | S18: 107 | T18: =IFERROR(P18/S18,0) -> 0.1588785 | U18: =MAX(0,S18-P18) -> 90 | V18: =P18-S18 -> -90 | W18: =IF(V18>0,"会期中に在庫切れ",IF(T18>=0.9,"要注意(90%超)",IF(T18>=0.5,"適正","在庫余剰"))) -> 在庫余剰
... A48: 42 | B48: 4515142545365 | C48: 伏黒 恵 イメージフラグメントケース | D48: 25000 | E48: 0 | F48: 2 | G48: 2 | H48: =IF(F48=0,"",G48/F48) -> 1 | I48: 5 | J48: 6 | K48: =IF(I48=0,"",J48/I48) -> 1.2 | L48: 1 | M48: 1 | N48: =IF(L48=0,"",M48/L48) -> 1 | O48: =IFERROR((IF(H48="",0,H48*前提・入力!$B$7)+IF(K48="",0,K48*前提・入力!$B$8)+IF(N48="",0,N48*前提・入力!$B$9))/(IF(H48="",0,前提・入力!$B$7)+IF(K48="",0,前提・入力!$B$8)+IF(N48="",0,前提・入力!$B$9)),前提・入力!$B$11) -> 1.05 | P48: =ROUND(E48*O48,0) -> 0 | Q48: =P48*D48 -> 0 | R48: =IFERROR(P48/P$49,0) -> 0 | S48: 15 | T48: =IFERROR(P48/S48,0) -> 0 | U48: =MAX(0,S48-P48) -> 15 | V48: =P48-S48 -> -15 | W48: =IF(V48>0,"会期中に在庫切れ",IF(T48>=0.9,"要注意(90%超)",IF(T48>=0.5,"適正","在庫余剰"))) -> 在庫余剰
C49: 合計（LEGS 42SKU） | E49: =SUM(E7:E48) -> 4022 | F49: =SUM(F7:F48) -> 19983 | G49: =SUM(G7:G48) -> 28231 | I49: =SUM(I7:I48) -> 48303 | J49: =SUM(J7:J48) -> 59166 | L49: =SUM(L7:L48) -> 6422 | M49: =SUM(M7:M48) -> 8179 | O49: =IFERROR(P49/E49,0) -> 1.2807061 | P49: =SUM(P7:P48) -> 5151 | Q49: =SUM(Q7:Q48) -> 4292200 | R49: 1 | S49: =SUM(S7:S48) -> 46928 | T49: =IFERROR(P49/S49,0) -> 0.10976389 | U49: =SUM(U7:U48) -> 41810 | V49: =SUM(V7:V48) -> -41777 | W49: =COUNTIF(W7:W48,"会期中に在庫切れ")&"品目" -> 3品目

Sheet ②会場別構成比
A1: ② 会場別 物販実績とLEGS構成比／東京対比 会場比率
A2: 物販売上＝レジ袋代・音声ガイド・当日券を除く商品売上（税込）。LEGS＝本42SKU（各会場の商品分類「レッグス」と完全一致）
A4: ■ 会場別 実績・予測サマリー
A5: 項目 | B5: 東京対比 算出根拠 | C5: 東京 | D5: 名古屋 | E5: 博多 | F5: 大阪 | G5: 札幌 | H5: 石川 | I5: 石川(予測) | J5: 仙台 Ebeans | K5: 神戸阪急 | L5: 鳥取島根 夢みなとタワー | M5: 東京凱旋 東京建物ぴあホール
A6: 会期 | C6: 25/12/5(金)-12/29(月) 池袋サンシャインシティ | D6: 26/3/18(水)-4/5(日) 松坂屋 | E6: 26/4/23(木)-5/18(月) 博多阪急 | F6: 26/6/10(水)-6/29(月) 阪急梅田 | G6: 26/7/22(水)-8/10(月) 札幌大丸 | H6: 26/8/14(金)-8/31(月) 香林坊大和(金沢) | I6: 26/8/14(金)-8/31(月) 会期18日 予測 | J6: 26/9/5(土)-10/4(日) 仙台 Ebeans | K6: 26/12/16(水)-27/1/7(木) 神戸阪急 | L6: 27/3/15-4/4 鳥取島根 夢みなとタワー | M6: 27年4-5月 東京凱旋 東京建物ぴあホール
A7: 会期日数 | C7: 25 | D7: 19 | E7: 26 | F7: 20 | G7: 20 | H7: 18 | I7: 18 | J7: 30 | K7: 21 | L7: 21 | M7: 25
A8: データ実績日数 | C8: 25 | D8: 19 | E8: 26 | F8: 20 | G8: 20 | H8: 12 | I8: 予測 | J8: 予測 | K8: 予測 | L8: 予測 | M8: 予測
A9: 入場者数 | C9: 47339 | D9: 19764 | E9: 18993 | F9: 31267 | G9: 10270 | H9: 5304 | I9: 8923
A10: 全物販 販売数量 | C10: 383342 | D10: 169802 | E10: 112198 | F10: 238658 | G10: 40818 | H10: 19113 | I10: =H10*1.284925 -> 24558.772 | J10: =前提・入力!$B$14*前提・入力!$B$23 -> 49834.46 | K10: =前提・入力!$B$14*前提・入力!$B$24 -> 46001.04 | L10: =前提・入力!$B$14*前提・入力!$B$25 -> 34500.78 | M10: =前提・入力!$B$14*前提・入力!$B$26 -> 191671
A11: 全物販 販売金額(税込) | C11: 358193925 | D11: 138575410 | E11: 105540655 | F11: 215184570 | G11: 41120210 | H11: 19691300 | I11: =H11*1.27778 -> 25161149 | J11: =前提・入力!$B$13*前提・入力!$B$23 -> 46565210 | K11: =前提・入力!$B$13*前提・入力!$B$24 -> 42983271 | L11: =前提・入力!$B$13*前提・入力!$B$25 -> 32237453 | M11: =前提・入力!$B$13*前提・入力!$B$26 -> 1.7909696e+08
A12: LEGS 販売数量 | C12: 148185 | D12: 58600 | E12: 44871 | F12: 63740 | G12: 8891 | H12: 4022 | I12: =①石川予測確定!P49 -> 5151 | J12: =ROUND(J13/前提・入力!$B$30,0) -> 9536 | K12: =ROUND(K13/前提・入力!$B$30,0) -> 8802 | L12: =ROUND(L13/前提・入力!$B$30,0) -> 6602 | M12: =ROUND(M13/前提・入力!$B$30,0) -> 36677
A13: LEGS 販売金額(税込) | C13: 102186200 | D13: 41479600 | E13: 31026800 | F13: 45507600 | G13: 7217000 | H13: 3388400 | I13: =①石川予測確定!Q49 -> 4292200 | J13: =J11*前提・入力!$B$29 -> 7943484.4 | K13: =K11*前提・入力!$B$29 -> 7332447.2 | L13: =L11*前提・入力!$B$29 -> 5499335.4 | M13: =M11*前提・入力!$B$29 -> 30551863
A14: LEGS 数量構成比 | C14: =C12/C10 -> 0.38656083 | D14: =D12/D10 -> 0.34510783 | E14: =E12/E10 -> 0.39992691 | F14: =F12/F10 -> 0.26707674 | G14: =G12/G10 -> 0.21782057 | H14: =H12/H10 -> 0.21043269 | I14: =I12/I10 -> 0.20974176 | J14: =J12/J10 -> 0.19135353 | ... M14: =M12/M10 -> 0.19135393
A15: LEGS 金額構成比 | C15: =C13/C11 -> 0.28528178 | D15: =D13/D11 -> 0.29932872 | E15: =E13/E11 -> 0.2939796 | F15: =F13/F11 -> 0.21148171 | G15: =G13/G11 -> 0.1755098 | H15: =H13/H11 -> 0.17207599 | I15: =I13/I11 -> 0.17058839 | J15: =J13/J11 -> 0.17058839 | ... M15: =M13/M11 -> 0.17058839
A16: 東京対比（数量） | C16: =C10/$C$10 -> 1 | D16: =D10/$C$10 -> 0.44295172 | E16: =E10/$C$10 -> 0.29268382 | F16: =F10/$C$10 -> 0.62257201 | G16: =G10/$C$10 -> 0.10647933 | H16: =H10/$C$10 -> 0.049858873 | I16: =I10/$C$10 -> 0.064064912 | J16: =J10/$C$10 -> 0.13 | ... M16: =M10/$C$10 -> 0.5
A17: 東京対比（金額） | B17: ユーザー指定／入力値 | C17: =C11/$C$11 -> 1 | D17: =D11/$C$11 -> 0.38687259 | E17: =E11/$C$11 -> 0.29464669 | F17: =F11/$C$11 -> 0.6007488 | G17: =G11/$C$11 -> 0.11479874 | H17: =H11/$C$11 -> 0.054973853 | I17: =I11/$C$11 -> 0.070244489 | J17: =前提・入力!$B$23 -> 0.13 | K17: =前提・入力!$B$24 -> 0.12 | L17: =前提・入力!$B$25 -> 0.09 | M17: =前提・入力!$B$26 -> 0.5
A18: LEGS平均単価 | C18: =IFERROR(C13/C12,0) -> 689.58532 | D18: =IFERROR(D13/D12,0) -> 707.843 | E18: =IFERROR(E13/E12,0) -> 691.46665 | F18: =IFERROR(F13/F12,0) -> 713.9567 | G18: =IFERROR(G13/G12,0) -> 811.71972 | H18: =IFERROR(H13/H12,0) -> 842.46643 | I18: =I13/I12 -> 833.27509 | J18: =J13/J12 -> 832.99962 | K18: =K13/K12 -> 833.0433 | L18: =L13/L12 -> 832.98021 | M18: =M13/M12 -> 832.99788
A21: ■ 供給元別 金額構成比（各会場 会期全体。石川は初12日実績）
A22: 供給元 | C22: 東京 | D22: 名古屋 | E22: 博多 | F22: 大阪 | G22: 札幌 | H22: 石川
A23: LEGS(42SKU) | C23: 0.28528178 | D23: 0.29932872 | E23: 0.2939796 | F23: 0.21148171 | G23: 0.1755098 | H23: 0.17207599
A24: ムービック | C24: 0.53383923 | D24: 0.35138442 | E24: 0.32105543 | F24: 0.41894519 | G24: 0.39083993 | H24: 0.41503303
A25: 東宝 | C25: 0.092163721 | D25: 0.078365491 | E25: 0.078289309 | F25: 0.15216207 | G25: 0.16841256 | H25: 0.1499901
A26: MAPPA | C26: 0 | D26: 0.23618072 | E26: 0.23252348 | F26: 0.14301109 | G26: 0.18539399 | H26: 0.17836202
A27: MBS | C27: 0.033272116 | D27: 0.034740651 | E27: 0.074152183 | F27: 0.074399944 | G27: 0.079843707 | H27: 0.084538857
A28: 書籍 | C28: 0.055443151 | D28: 0 | E28: 0 | F28: 0 | G28: 0 | H28: 0
A29: その他 | C29: 0 | D29: 0 | E29: 0 | F29: 0 | G29: 0 | H29: 0
A30: 合計 | C30: =SUM(C23:C29) -> 1 | D30: =SUM(D23:D29) -> 1 | E30: =SUM(E23:E29) -> 1 | F30: =SUM(F23:F29) -> 1 | G30: =SUM(G23:G29) -> 1 | H30: =SUM(H23:H29) -> 1
A32: ■ 新規SKU投入状況（前会場までに存在しなかったJAN）
A33: 会場 | C33: 総SKU数 | D33: 新規SKU数 | E33: 新規の金額シェア(初12日) | F33: LEGS金額構成比(初12日) | G33: 備考
A34: 東京 | C34: 332 | D34: 332 | E34: 1 | F34: 0.29591818 | G34: 初回会場
A35: 名古屋 | C35: 416 | D35: 85 | E35: 0.21120858 | F35: 0.30653237 | G35: MAPPA記念商品26SKU等を追加投入
A36: 博多 | C36: 435 | D36: 19 | E36: 0.14640066 | F36: 0.24448655 | G36: 小幅追加
A37: 大阪 | C37: 515 | D37: 106 | E37: 0.19145772 | F37: 0.20698479 | G37: ★新商品106SKU投入（東宝一般66・ムービック23・MAPPA16）
A38: 札幌 | C38: 382 | D38: 0 | E38: 0 | F38: 0.17555848 | G38: 新規なし。品揃えは大阪と同一
A39: 石川 | C39: 382 | D39: 0 | E39: 0 | F39: 0.17207599 | G39: 新規なし。品揃えは大阪と同一

Sheet ③仙台以降予測
A1: ③ 仙台会場以降 4会場 LEGS商品 需要予測
A2: 会場物販売上＝東京(初回)実績 × 東京対比比率 ／ LEGS売上＝会場物販売上 × LEGS金額構成比 ／ LEGS数量＝LEGS売上 ÷ LEGS平均単価
A3: 商品別按分＝札幌20日実績の数量構成比 × ウェイト ＋ 石川18日予測の数量構成比 × ウェイト（「前提・入力」で調整可）
A4: ※商品別表の必要数合計は、会場×商品ごとに整数丸めを行うため会場別表の合計と数個の差が生じる（発注判断に影響しない範囲）
A5: ■ 会場別 需要予測
A6: 会場 | B6: 会期 | C6: 日数 | D6: 東京対比 | E6: 会場 全物販売上 | F6: LEGS 売上 | G6: LEGS 数量 | H6: 構成比根拠
A7: 仙台 Ebeans | B7: 26/9/5(土)-10/4(日) | C7: 30 | D7: =前提・入力!$B$23 -> 0.13 | E7: =前提・入力!$B$13*D7 -> 46565210 | F7: =E7*前提・入力!$B$29 -> 7943484.4 | G7: =ROUND(F7/前提・入力!$B$30,0) -> 9536 | H7: ユーザー指定（コナン実績は10.5%）
A8: 神戸阪急 | B8: 26/12/16(水)-27/1/7(木) | C8: 21 | D8: =前提・入力!$B$24 -> 0.12 | E8: =前提・入力!$B$13*D8 -> 42983271 | F8: =E8*前提・入力!$B$29 -> 7332447.2 | G8: =ROUND(F8/前提・入力!$B$30,0) -> 8802 | H8: ★要確認：指定なきため仮置き
A9: 鳥取島根 夢みなとタワー | B9: 27/3/15-4/4 | C9: 21 | D9: =前提・入力!$B$25 -> 0.09 | E9: =前提・入力!$B$13*D9 -> 32237453 | F9: =E9*前提・入力!$B$29 -> 5499335.4 | G9: =ROUND(F9/前提・入力!$B$30,0) -> 6602 | H9: ユーザー指定
A10: 東京凱旋 東京建物ぴあホール | B10: 27年4-5月 | C10: 25 | D10: =前提・入力!$B$26 -> 0.5 | E10: =前提・入力!$B$13*D10 -> 1.7909696e+08 | F10: =E10*前提・入力!$B$29 -> 30551863 | G10: =ROUND(F10/前提・入力!$B$30,0) -> 36677 | H10: ユーザー指定（初回東京の50%）
A11: 仙台以降 4会場 合計 | D11: =SUM(D7:D10) -> 0.84 | E11: =SUM(E7:E10) -> 300882897 | F11: =SUM(F7:F10) -> 51327130 | G11: =SUM(G7:G10) -> 61617
A13: ■ 在庫収支（LEGS 42SKU 合計）
A14: 残在庫想定（台帳 梅田まで(SET)／総計） | B14: 276521 | C14: 在庫フロー台帳の最終「実在庫」列。会場ごとの追加発注→販売→検品を積み上げた値
A15: うち札幌会場へ納品 | B15: 50506 | C15: 札幌の販売可能数。台帳・ロジ在庫はこの出荷までを反映している
A16: ★倉庫残（札幌出荷後） | B16: =Q73 -> 197962 | C16: ロジ（倉庫WMS）2026/8/5時点の実棚を採用。台帳から計算した 226,015個 との差 -28053個
A17: 札幌 会期20日 実績販売数 | B17: 8891 | C17: 会期終了済みの確定値
A18: 札幌 会期末 残（実績） | B18: =R73 -> 41615 | C18: 販売可能数 − 実績販売数。石川会場へ転送された分と倉庫へ戻った分の合計
A19: うち販売不可（日報未反映の持出） | B19: 0 | C19: 日報に載っていない持出がある場合のみここで控除する。現在なし
A20: ［参考］会場での持出・不良・ｻﾝﾌﾟﾙ | B20: 58 | C20: 日報の「販売可能数＝納品数−持出・不良・ｻﾝﾌﾟﾙ」で既に控除済み。二重に引かないため供給可能在庫の計算には入れていない。内訳：東京 16個／名古屋 21個／博多 4個／大阪 13個／札幌 4個
A21: 石川へ納品（初回＋転送＋追納） | B21: =①石川予測確定!S49 -> 46928 | C21: 2026/8 石川(金沢)会場への札幌転送分＋8/22追納（日報の販売可能数に反映済み）を含む
A22: 石川 会期18日 予測販売数 | B22: =①石川予測確定!P49 -> 5151
A23: 仙台以降 供給可能在庫 合計 | B23: =B16+B18-B19-B22 -> 234426 | C23: ＝倉庫残 ＋ 札幌会期末残 − 販売不可 − 石川会期予測販売。石川への納品はこの2つから出ているので相殺される
A24: 確定済み追加発注（入荷予定） | B24: 1200 | C24: 発注判断済みの分。宿儺の指風お菓子 1,200SET（鳥取島根 夢みなとタワー入荷）
A25: 仙台以降 4会場 必要数 | B25: =G11 -> 61617
A26: 全体過不足（供給可能＋確定発注−必要） | B26: =B23+B24-B25 -> 174009 | C26: プラス＝全体では在庫充足。ただし商品別には過不足が生じる
A27: 追加生産 必要数（商品別不足の合計） | B27: =Y73 -> 3384 | C27: 下表の商品別「追加生産必要数」の合計。全体余剰でも品目別には不足が出る
A29: ■ 商品別 仙台以降 必要数と在庫過不足
A30: No. | B30: JAN | C30: 商品名 | D30: 札幌⑤ 20日実績 | E30: 札幌 構成比 | F30: 石川⑥ 18日予測 | G30: 石川 構成比 | H30: 採用 按分構成比 | I30: 仙台 必要数 | J30: 神戸阪急 必要数 | K30: 鳥取島根 必要数 | L30: 東京凱旋 必要数 | M30: 仙台以降 必要数 計 | N30: ★残在庫想定 (台帳 梅田まで) | O30: うち札幌 へ納品 | P30: ★ロジ在庫 (2026/8/5 実棚) | Q30: 差引 倉庫残 | R30: 札幌会期末 残（実績） | S30: 販売不可 (日報未反映) | T30: 石川へ納品 (初回+転送+追納) | U30: 石川 会期18日 予測販売 | V30: 仙台以降 供給可能計 | W30: 確定発注 (入荷予定) | X30: 過不足 (必要−供給可能−確定) | Y30: 追加生産 必要数 | Z30: 推奨発注数 (安全率込)
A31: 1 | B31: 4515142545082 | C31: 呪術廻戦 メタリックポストカード 展示会キービジュアル | D31: 507 | E31: =IFERROR(D31/D$73,0) -> 0.057023957 | F31: =①石川予測確定!P7 -> 272 | G31: =IFERROR(F31/F$73,0) -> 0.052805281 | H31: =E31*前提・入力!$B$31+G31*前提・入力!$B$32 -> 0.054914619 | I31: =ROUND($H31*③仙台以降予測!$G$7,0) -> 524 | J31: =ROUND($H31*③仙台以降予測!$G$8,0) -> 483 | K31: =ROUND($H31*③仙台以降予測!$G$9,0) -> 363 | L31: =ROUND($H31*③仙台以降予測!$G$10,0) -> 2014 | M31: =SUM(I31:L31) -> 3384 | N31: 3271 | O31: 1000 | P31: 2268 | Q31: =IF(P31="",N31-O31,P31) -> 2268 | R31: 493 | S31: 0 | T31: =①石川予測確定!S7 -> 693 | U31: =①石川予測確定!P7 -> 272 | V31: =Q31+R31-S31-U31 -> 2489 | W31: 0 | X31: =M31-V31-W31 -> 895 | Y31: =MAX(0,X31) -> 895 | Z31: =IF(Y31>0,ROUNDUP(Y31*(1+前提・入力!$B$34),0),0) -> 985
A32: 2 | B32: 4515142545099 | C32: 呪術廻戦 クリアファイル 展示会キービジュアル | D32: 541 | E32: =IFERROR(D32/D$73,0) -> 0.060848049 | F32: =①石川予測確定!P8 -> 325 | G32: =IFERROR(F32/F$73,0) -> 0.063094545 | H32: =E32*前提・入力!$B$31+G32*前提・入力!$B$32 -> 0.061971297 | I32: =ROUND($H32*③仙台以降予測!$G$7,0) -> 591 | J32: =ROUND($H32*③仙台以降予測!$G$8,0) -> 545 | K32: =ROUND($H32*③仙台以降予測!$G$9,0) -> 409 | L32: =ROUND($H32*③仙台以降予測!$G$10,0) -> 2273 | M32: =SUM(I32:L32) -> 3818 | N32: 5038 | O32: 1000 | P32: 4036 | Q32: =IF(P32="",N32-O32,P32) -> 4036 | R32: 459 | S32: 0 | T32: =①石川予測確定!S8 -> 659 | U32: =①石川予測確定!P8 -> 325 | V32: =Q32+R32-S32-U32 -> 4170 | W32: 0 | X32: =M32-V32-W32 -> -352 | Y32: =MAX(0,X32) -> 0 | Z32: =IF(Y32>0,ROUNDUP(Y32*(1+前提・入力!$B$34),0),0) -> 0
A33: 3 | B33: 4515142545105 | C33: 呪術廻戦 懐玉・玉折 ポストカードセット（5枚入） | D33: 169 | E33: =IFERROR(D33/D$73,0) -> 0.019007986 | F33: =①石川予測確定!P9 -> 118 | G33: =IFERROR(F33/F$73,0) -> 0.022908173 | H33: =E33*前提・入力!$B$31+G33*前提・入力!$B$32 -> 0.020958079 | I33: =ROUND($H33*③仙台以降予測!$G$7,0) -> 200 | J33: =ROUND($H33*③仙台以降予測!$G$8,0) -> 184 | K33: =ROUND($H33*③仙台以降予測!$G$9,0) -> 138 | L33: =ROUND($H33*③仙台以降予測!$G$10,0) -> 769 | M33: =SUM(I33:L33) -> 1291 | N33: 6140 | O33: 450 | P33: 1694 | Q33: =IF(P33="",N33-O33,P33) -> 1694 | R33: 281 | S33: 0 | T33: =①石川予測確定!S9 -> 381 | U33: =①石川予測確定!P9 -> 118 | V33: =Q33+R33-S33-U33 -> 1857 | W33: 0 | X33: =M33-V33-W33 -> -566 | Y33: =MAX(0,X33) -> 0 | Z33: =IF(Y33>0,ROUNDUP(Y33*(1+前提・入力!$B$34),0),0) -> 0
A34: 4 | B34: 4515142545112 | C34: 呪術廻戦 渋谷事変 ポストカードセット（9枚入） | D34: 228 | E34: =IFERROR(D34/D$73,0) -> 0.02564391 | F34: =①石川予測確定!P10 -> 134 | G34: =IFERROR(F34/F$73,0) -> 0.026014366 | H34: =E34*前提・入力!$B$31+G34*前提・入力!$B$32 -> 0.025829138 | I34: =ROUND($H34*③仙台以降予測!$G$7,0) -> 246 | J34: =ROUND($H34*③仙台以降予測!$G$8,0) -> 227 | K34: =ROUND($H34*③仙台以降予測!$G$9,0) -> 171 | L34: =ROUND($H34*③仙台以降予測!$G$10,0) -> 947 | M34: =SUM(I34:L34) -> 1591 | N34: 27511 | O34: 800 | P34: 2715 | Q34: =IF(P34="",N34-O34,P34) -> 2715 | R34: 572 | S34: 0 | T34: =①石川予測確定!S10 -> 772 | U34: =①石川予測確定!P10 -> 134 | V34: =Q34+R34-S34-U34 -> 3153 | W34: 0 | X34: =M34-V34-W34 -> -1562 | Y34: =MAX(0,X34) -> 0 | Z34: =IF(Y34>0,ROUNDUP(Y34*(1+前提・入力!$B$34),0),0) -> 0
A35: 5 | B35: 4515142545129 | C35: 呪術廻戦 懐玉・玉折 ブラインド缶バッジ（全5種） | D35: 410 | E35: =IFERROR(D35/D$73,0) -> 0.046114048 | F35: =①石川予測確定!P11 -> 293 | G35: =IFERROR(F35/F$73,0) -> 0.056882159 | H35: =E35*前提・入力!$B$31+G35*前提・入力!$B$32 -> 0.051498103 | I35: =ROUND($H35*③仙台以降予測!$G$7,0) -> 491 | J35: =ROUND($H35*③仙台以降予測!$G$8,0) -> 453 | K35: =ROUND($H35*③仙台以降予測!$G$9,0) -> 340 | L35: =ROUND($H35*③仙台以降予測!$G$10,0) -> 1889 | M35: =SUM(I35:L35) -> 3173 | N35: 40108 | O35: 9000 | P35: 31095 | Q35: =IF(P35="",N35-O35,P35) -> 31095 | R35: 8590 | S35: 0 | T35: =①石川予測確定!S11 -> 8790 | U35: =①石川予測確定!P11 -> 293 | V35: =Q35+R35-S35-U35 -> 39392 | W35: 0 | X35: =M35-V35-W35 -> -36219 | Y35: =MAX(0,X35) -> 0 | Z35: =IF(Y35>0,ROUNDUP(Y35*(1+前提・入力!$B$34),0),0) -> 0
A36: 6 | B36: 4515142545136 | C36: 呪術廻戦 渋谷事変 ブラインド缶バッジ（全9種） | D36: 1042 | E36: =IFERROR(D36/D$73,0) -> 0.11719717 | F36: =①石川予測確定!P12 -> 565 | G36: =IFERROR(F36/F$73,0) -> 0.10968744 | H36: =E36*前提・入力!$B$31+G36*前提・入力!$B$32 -> 0.1134423 | I36: =ROUND($H36*③仙台以降予測!$G$7,0) -> 1082 | J36: =ROUND($H36*③仙台以降予測!$G$8,0) -> 999 | K36: =ROUND($H36*③仙台以降予測!$G$9,0) -> 749 | L36: =ROUND($H36*③仙台以降予測!$G$10,0) -> 4161 | M36: =SUM(I36:L36) -> 6991 | N36: 51840 | O36: 13991 | P36: 37844 | Q36: =IF(P36="",N36-O36,P36) -> 37844 | R36: 12949 | S36: 0 | T36: =①石川予測確定!S12 -> 13249 | U36: =①石川予測確定!P12 -> 565 | V36: =Q36+R36-S36-U36 -> 50228 | W36: 0 | X36: =M36-V36-W36 -> -43237 | Y36: =MAX(0,X36) -> 0 | Z36: =IF(Y36>0,ROUNDUP(Y36*(1+前提・入力!$B$34),0),0) -> 0
A37: 7 | B37: 4515142545143 | C37: 呪術廻戦 懐玉・玉折 ブラインドダイカットステッカー（全5種） | D37: 187 | E37: =IFERROR(D37/D$73,0) -> 0.021032505 | F37: =①石川予測確定!P13 -> 165 | G37: =IFERROR(F37/F$73,0) -> 0.032032615 | H37: =E37*前提・入力!$B$31+G37*前提・入力!$B$32 -> 0.02653256 | I37: =ROUND($H37*③仙台以降予測!$G$7,0) -> 253 | J37: =ROUND($H37*③仙台以降予測!$G$8,0) -> 234 | K37: =ROUND($H37*③仙台以降予測!$G$9,0) -> 175 | L37: =ROUND($H37*③仙台以降予測!$G$10,0) -> 973 | M37: =SUM(I37:L37) -> 1635 | N37: 4601 | O37: 350 | P37: 4251 | Q37: =IF(P37="",N37-O37,P37) -> 4251 | R37: 163 | S37: 0 | T37: =①石川予測確定!S13 -> 463 | U37: =①石川予測確定!P13 -> 165 | V37: =Q37+R37-S37-U37 -> 4249 | W37: 0 | X37: =M37-V37-W37 -> -2614 | Y37: =MAX(0,X37) -> 0 | Z37: =IF(Y37>0,ROUNDUP(Y37*(1+前提・入力!$B$34),0),0) -> 0
A38: 8 | B38: 4515142545150 | C38: 呪術廻戦 渋谷事変 ブラインドダイカットステッカー（全9種） | D38: 322 | E38: =IFERROR(D38/D$73,0) -> 0.036216399 | F38: =①石川予測確定!P14 -> 266 | G38: =IFERROR(F38/F$73,0) -> 0.051640458 | H38: =E38*前提・入力!$B$31+G38*前提・入力!$B$32 -> 0.043928428 | I38: =ROUND($H38*③仙台以降予測!$G$7,0) -> 419 | J38: =ROUND($H38*③仙台以降予測!$G$8,0) -> 387 | K38: =ROUND($H38*③仙台以降予測!$G$9,0) -> 290 | L38: =ROUND($H38*③仙台以降予測!$G$10,0) -> 1611 | M38: =SUM(I38:L38) -> 2707 | N38: 8622 | O38: 900 | P38: 7722 | Q38: =IF(P38="",N38-O38,P38) -> 7722 | R38: 578 | S38: 0 | T38: =①石川予測確定!S14 -> 778 | U38: =①石川予測確定!P14 -> 266 | V38: =Q38+R38-S38-U38 -> 8034 | W38: 0 | X38: =M38-V38-W38 -> -5327 | Y38: =MAX(0,X38) -> 0 | Z38: =IF(Y38>0,ROUNDUP(Y38*(1+前提・入力!$B$34),0),0) -> 0
A39: 9 | B39: 4515142545372 | C39: 呪術廻戦 懐玉・玉折 クリアファイル（五条 悟） | D39: 160 | E39: =IFERROR(D39/D$73,0) -> 0.017995726 | F39: =①石川予測確定!P15 -> 51 | G39: =IFERROR(F39/F$73,0) -> 0.0099009901 | H39: =E39*前提・入力!$B$31+G39*前提・入力!$B$32 -> 0.013948358 | I39: =ROUND($H39*③仙台以降予測!$G$7,0) -> 133 | J39: =ROUND($H39*③仙台以降予測!$G$8,0) -> 123 | K39: =ROUND($H39*③仙台以降予測!$G$9,0) -> 92 | L39: =ROUND($H39*③仙台以降予測!$G$10,0) -> 512 | M39: =SUM(I39:L39) -> 860 | N39: 8760 | O39: 300 | P39: 8458 | Q39: =IF(P39="",N39-O39,P39) -> 8458 | R39: 140 | S39: 0 | T39: =①石川予測確定!S15 -> 740 | U39: =①石川予測確定!P15 -> 51 | V39: =Q39+R39-S39-U39 -> 8547 | W39: 0 | X39: =M39-V39-W39 -> -7687 | Y39: =MAX(0,X39) -> 0 | Z39: =IF(Y39>0,ROUNDUP(Y39*(1+前提・入力!$B$34),0),0) -> 0
A40: 10 | B40: 4515142545389 | C40: 呪術廻戦 懐玉・玉折 クリアファイル（夏油 傑） | D40: 59 | E40: =IFERROR(D40/D$73,0) -> 0.006635924 | F40: =①石川予測確定!P16 -> 20 | G40: =IFERROR(F40/F$73,0) -> 0.0038827412 | H40: =E40*前提・入力!$B$31+G40*前提・入力!$B$32 -> 0.0052593326 | I40: =ROUND($H40*③仙台以降予測!$G$7,0) -> 50 | J40: =ROUND($H40*③仙台以降予測!$G$8,0) -> 46 | K40: =ROUND($H40*③仙台以降予測!$G$9,0) -> 35 | L40: =ROUND($H40*③仙台以降予測!$G$10,0) -> 193 | M40: =SUM(I40:L40) -> 324 | N40: 4934 | O40: 100 | P40: 4835 | Q40: =IF(P40="",N40-O40,P40) -> 4835 | R40: 41 | S40: 0 | T40: =①石川予測確定!S16 -> 541 | U40: =①石川予測確定!P16 -> 20 | V40: =Q40+R40-S40-U40 -> 4856 | W40: 0 | X40: =M40-V40-W40 -> -4532 | Y40: =MAX(0,X40) -> 0 | Z40: =IF(Y40>0,ROUNDUP(Y40*(1+前提・入力!$B$34),0),0) -> 0
A41: 11 | B41: 4515142545396 | C41: 呪術廻戦 懐玉・玉折 クリアファイル（家入 硝子） | D41: 21 | E41: =IFERROR(D41/D$73,0) -> 0.002361939 | F41: =①石川予測確定!P17 -> 8 | G41: =IFERROR(F41/F$73,0) -> 0.0015530965 | H41: =E41*前提・入力!$B$31+G41*前提・入力!$B$32 -> 0.0019575178 | I41: =ROUND($H41*③仙台以降予測!$G$7,0) -> 19 | J41: =ROUND($H41*③仙台以降予測!$G$8,0) -> 17 | K41: =ROUND($H41*③仙台以降予測!$G$9,0) -> 13 | L41: =ROUND($H41*③仙台以降予測!$G$10,0) -> 72 | M41: =SUM(I41:L41) -> 121 | N41: 640 | O41: 50 | P41: 588 | Q41: =IF(P41="",N41-O41,P41) -> 588 | R41: 29 | S41: 0 | T41: =①石川予測確定!S17 -> 79 | U41: =①石川予測確定!P17 -> 8 | V41: =Q41+R41-S41-U41 -> 609 | W41: 0 | X41: =M41-V41-W41 -> -488 | Y41: =MAX(0,X41) -> 0 | Z41: =IF(Y41>0,ROUNDUP(Y41*(1+前提・入力!$B$34),0),0) -> 0
A42: 12 | B42: 4515142545402 | C42: 呪術廻戦 懐玉・玉折 クリアファイル（七海 建人） | D42: 43 | E42: =IFERROR(D42/D$73,0) -> 0.0048363514 | F42: =①石川予測確定!P18 -> 17 | G42: =IFERROR(F42/F$73,0) -> 0.00330033 | H42: =E42*前提・入力!$B$31+G42*前提・入力!$B$32 -> 0.0040683407 | I42: =ROUND($H42*③仙台以降予測!$G$7,0) -> 39 | J42: =ROUND($H42*③仙台以降予測!$G$8,0) -> 36 | K42: =ROUND($H42*③仙台以降予測!$G$9,0) -> 27 | L42: =ROUND($H42*③仙台以降予測!$G$10,0) -> 149 | M42: =SUM(I42:L42) -> 251 | N42: 953 | O42: 50 | P42: 901 | Q42: =IF(P42="",N42-O42,P42) -> 901 | R42: 7 | S42: 0 | T42: =①石川予測確定!S18 -> 107 | U42: =①石川予測確定!P18 -> 17 | V42: =Q42+R42-S42-U42 -> 891 | W42: 0 | X42: =M42-V42-W42 -> -640 | Y42: =MAX(0,X42) -> 0 | Z42: =IF(Y42>0,ROUNDUP(Y42*(1+前提・入力!$B$34),0),0) -> 0
... A57: 27 | B57: 4515142545211 | C57: 反転術式絆創膏 | D57: 50 | E57: =IFERROR(D57/D$73,0) -> 0.0056236644 | F57: =①石川予測確定!P33 -> 18 | G57: =IFERROR(F57/F$73,0) -> 0.0034944671 | H57: =E57*前提・入力!$B$31+G57*前提・入力!$B$32 -> 0.0045590657 | I57: =ROUND($H57*③仙台以降予測!$G$7,0) -> 43 | J57: =ROUND($H57*③仙台以降予測!$G$8,0) -> 40 | K57: =ROUND($H57*③仙台以降予測!$G$9,0) -> 30 | L57: =ROUND($H57*③仙台以降予測!$G$10,0) -> 167 | M57: =SUM(I57:L57) -> 280 | N57: 1199 | O57: 70 | P57: 1129 | Q57: =IF(P57="",N57-O57,P57) -> 1129 | R57: 20 | S57: 0 | T57: =①石川予測確定!S33 -> 70 | U57: =①石川予測確定!P33 -> 18 | V57: =Q57+R57-S57-U57 -> 1131 | W57: 0 | X57: =M57-V57-W57 -> -851 | Y57: =MAX(0,X57) -> 0 | Z57: =IF(Y57>0,ROUNDUP(Y57*(1+前提・入力!$B$34),0),0) -> 0
A58: 28 | B58: 4515142545228 | C58: 宿儺の指風お菓子 | D58: 300 | E58: =IFERROR(D58/D$73,0) -> 0.033741986 | F58: =①石川予測確定!P34 -> 92 | G58: =IFERROR(F58/F$73,0) -> 0.01786061 | H58: =E58*前提・入力!$B$31+G58*前提・入力!$B$32 -> 0.025801298 | I58: =ROUND($H58*③仙台以降予測!$G$7,0) -> 246 | J58: =ROUND($H58*③仙台以降予測!$G$8,0) -> 227 | K58: =ROUND($H58*③仙台以降予測!$G$9,0) -> 170 | L58: =ROUND($H58*③仙台以降予測!$G$10,0) -> 946 | M58: =SUM(I58:L58) -> 1589 | N58: 460 | O58: 300 | Q58: =IF(P58="",N58-O58,P58) -> 160 | R58: 0 | S58: 0 | T58: =①石川予測確定!S34 -> 80 | U58: =①石川予測確定!P34 -> 92 | V58: =Q58+R58-S58-U58 -> 68 | W58: 1200 | X58: =M58-V58-W58 -> 321 | Y58: =MAX(0,X58) -> 321 | Z58: =IF(Y58>0,ROUNDUP(Y58*(1+前提・入力!$B$34),0),0) -> 354
A59: 29 | B59: 4515142545235 | C59: 脱兎！ポーチ入りクリップセット | D59: 160 | E59: =IFERROR(D59/D$73,0) -> 0.017995726 | F59: =①石川予測確定!P35 -> 83 | G59: =IFERROR(F59/F$73,0) -> 0.016113376 | H59: =E59*前提・入力!$B$31+G59*前提・入力!$B$32 -> 0.017054551 | I59: =ROUND($H59*③仙台以降予測!$G$7,0) -> 163 | J59: =ROUND($H59*③仙台以降予測!$G$8,0) -> 150 | K59: =ROUND($H59*③仙台以降予測!$G$9,0) -> 113 | L59: =ROUND($H59*③仙台以降予測!$G$10,0) -> 626 | M59: =SUM(I59:L59) -> 1052 | N59: 421 | O59: 160 | P59: 260 | Q59: =IF(P59="",N59-O59,P59) -> 260 | R59: 0 | S59: 0 | T59: =①石川予測確定!S35 -> 120 | U59: =①石川予測確定!P35 -> 83 | V59: =Q59+R59-S59-U59 -> 177 | W59: 0 | X59: =M59-V59-W59 -> 875 | Y59: =MAX(0,X59) -> 875 | Z59: =IF(Y59>0,ROUNDUP(Y59*(1+前提・入力!$B$34),0),0) -> 963
A60: 30 | B60: 4515142545242 | C60: 釘崎のポーチ風エコバッグ | D60: 72 | E60: =IFERROR(D60/D$73,0) -> 0.0080980767 | F60: =①石川予測確定!P36 -> 45 | G60: =IFERROR(F60/F$73,0) -> 0.0087361677 | H60: =E60*前提・入力!$B$31+G60*前提・入力!$B$32 -> 0.0084171222 | I60: =ROUND($H60*③仙台以降予測!$G$7,0) -> 80 | J60: =ROUND($H60*③仙台以降予測!$G$8,0) -> 74 | K60: =ROUND($H60*③仙台以降予測!$G$9,0) -> 56 | L60: =ROUND($H60*③仙台以降予測!$G$10,0) -> 309 | M60: =SUM(I60:L60) -> 519 | N60: 900 | O60: 250 | P60: 648 | Q60: =IF(P60="",N60-O60,P60) -> 648 | R60: 178 | S60: 0 | T60: =①石川予測確定!S36 -> 278 | U60: =①石川予測確定!P36 -> 45 | V60: =Q60+R60-S60-U60 -> 781 | W60: 0 | X60: =M60-V60-W60 -> -262 | Y60: =MAX(0,X60) -> 0 | Z60: =IF(Y60>0,ROUNDUP(Y60*(1+前提・入力!$B$34),0),0) -> 0
A61: 31 | B61: 4515142545259 | C61: 半年分の情報が書き込める手帳 | D61: 101 | E61: =IFERROR(D61/D$73,0) -> 0.011359802 | F61: =①石川予測確定!P37 -> 61 | G61: =IFERROR(F61/F$73,0) -> 0.011842361 | H61: =E61*前提・入力!$B$31+G61*前提・入力!$B$32 -> 0.011601081 | I61: =ROUND($H61*③仙台以降予測!$G$7,0) -> 111 | J61: =ROUND($H61*③仙台以降予測!$G$8,0) -> 102 | K61: =ROUND($H61*③仙台以降予測!$G$9,0) -> 77 | L61: =ROUND($H61*③仙台以降予測!$G$10,0) -> 425 | M61: =SUM(I61:L61) -> 715 | N61: 927 | O61: 200 | P61: 727 | Q61: =IF(P61="",N61-O61,P61) -> 727 | R61: 99 | S61: 0 | T61: =①石川予測確定!S37 -> 249 | U61: =①石川予測確定!P37 -> 61 | V61: =Q61+R61-S61-U61 -> 765 | W61: 0 | X61: =M61-V61-W61 -> -50 | Y61: =MAX(0,X61) -> 0 | Z61: =IF(Y61>0,ROUNDUP(Y61*(1+前提・入力!$B$34),0),0) -> 0
A62: 32 | B62: 4515142545266 | C62: 気分リフレッシュオルゴール | D62: 10 | E62: =IFERROR(D62/D$73,0) -> 0.0011247329 | F62: =①石川予測確定!P38 -> 5 | G62: =IFERROR(F62/F$73,0) -> 0.0009706853 | H62: =E62*前提・入力!$B$31+G62*前提・入力!$B$32 -> 0.0010477091 | I62: =ROUND($H62*③仙台以降予測!$G$7,0) -> 10 | J62: =ROUND($H62*③仙台以降予測!$G$8,0) -> 9 | K62: =ROUND($H62*③仙台以降予測!$G$9,0) -> 7 | L62: =ROUND($H62*③仙台以降予測!$G$10,0) -> 38 | M62: =SUM(I62:L62) -> 64 | N62: 33 | O62: 10 | P62: 20 | Q62: =IF(P62="",N62-O62,P62) -> 20 | R62: 0 | S62: 0 | T62: =①石川予測確定!S38 -> 5 | U62: =①石川予測確定!P38 -> 5 | V62: =Q62+R62-S62-U62 -> 15 | W62: 0 | X62: =M62-V62-W62 -> 49 | Y62: =MAX(0,X62) -> 49 | Z62: =IF(Y62>0,ROUNDUP(Y62*(1+前提・入力!$B$34),0),0) -> 54
A63: 33 | B63: 4515142545273 | C63: 五条 悟 イメージリング（#11） | D63: 3 | E63: =IFERROR(D63/D$73,0) -> 0.00033741986 | F63: =①石川予測確定!P39 -> 5 | G63: =IFERROR(F63/F$73,0) -> 0.0009706853 | H63: =E63*前提・入力!$B$31+G63*前提・入力!$B$32 -> 0.00065405258 | I63: =ROUND($H63*③仙台以降予測!$G$7,0) -> 6 | J63: =ROUND($H63*③仙台以降予測!$G$8,0) -> 6 | K63: =ROUND($H63*③仙台以降予測!$G$9,0) -> 4 | L63: =ROUND($H63*③仙台以降予測!$G$10,0) -> 24 | M63: =SUM(I63:L63) -> 40 | N63: 106 | O63: 15 | P63: 91 | Q63: =IF(P63="",N63-O63,P63) -> 91 | R63: 12 | S63: 0 | T63: =①石川予測確定!S39 -> 21 | U63: =①石川予測確定!P39 -> 5 | V63: =Q63+R63-S63-U63 -> 98 | W63: 0 | X63: =M63-V63-W63 -> -58 | Y63: =MAX(0,X63) -> 0 | Z63: =IF(Y63>0,ROUNDUP(Y63*(1+前提・入力!$B$34),0),0) -> 0
A64: 34 | B64: 4515142545280 | C64: 五条 悟 イメージリング（#13） | D64: 2 | E64: =IFERROR(D64/D$73,0) -> 0.00022494658 | F64: =①石川予測確定!P40 -> 1 | G64: =IFERROR(F64/F$73,0) -> 0.00019413706 | H64: =E64*前提・入力!$B$31+G64*前提・入力!$B$32 -> 0.00020954182 | I64: =ROUND($H64*③仙台以降予測!$G$7,0) -> 2 | J64: =ROUND($H64*③仙台以降予測!$G$8,0) -> 2 | K64: =ROUND($H64*③仙台以降予測!$G$9,0) -> 1 | L64: =ROUND($H64*③仙台以降予測!$G$10,0) -> 8 | M64: =SUM(I64:L64) -> 13 | N64: 4 | O64: 2 | P64: 2 | Q64: =IF(P64="",N64-O64,P64) -> 2 | R64: 0 | S64: 0 | T64: =①石川予測確定!S40 -> 1 | U64: =①石川予測確定!P40 -> 1 | V64: =Q64+R64-S64-U64 -> 1 | W64: 0 | X64: =M64-V64-W64 -> 12 | Y64: =MAX(0,X64) -> 12 | Z64: =IF(Y64>0,ROUNDUP(Y64*(1+前提・入力!$B$34),0),0) -> 14
A65: 35 | B65: 4515142545297 | C65: 五条 悟 イメージリング（#15） | D65: 1 | E65: =IFERROR(D65/D$73,0) -> 0.00011247329 | F65: =①石川予測確定!P41 -> 1 | G65: =IFERROR(F65/F$73,0) -> 0.00019413706 | H65: =E65*前提・入力!$B$31+G65*前提・入力!$B$32 -> 0.00015330517 | I65: =ROUND($H65*③仙台以降予測!$G$7,0) -> 1 | J65: =ROUND($H65*③仙台以降予測!$G$8,0) -> 1 | K65: =ROUND($H65*③仙台以降予測!$G$9,0) -> 1 | L65: =ROUND($H65*③仙台以降予測!$G$10,0) -> 6 | M65: =SUM(I65:L65) -> 9 | N65: 4 | O65: 2 | P65: 2 | Q65: =IF(P65="",N65-O65,P65) -> 2 | R65: 1 | S65: 0 | T65: =①石川予測確定!S41 -> 1 | U65: =①石川予測確定!P41 -> 1 | V65: =Q65+R65-S65-U65 -> 2 | W65: 0 | X65: =M65-V65-W65 -> 7 | Y65: =MAX(0,X65) -> 7 | Z65: =IF(Y65>0,ROUNDUP(Y65*(1+前提・入力!$B$34),0),0) -> 8
A66: 36 | B66: 4515142545303 | C66: 五条 悟 イメージリング（#17） | D66: 1 | E66: =IFERROR(D66/D$73,0) -> 0.00011247329 | F66: =①石川予測確定!P42 -> 1 | G66: =IFERROR(F66/F$73,0) -> 0.00019413706 | H66: =E66*前提・入力!$B$31+G66*前提・入力!$B$32 -> 0.00015330517 | I66: =ROUND($H66*③仙台以降予測!$G$7,0) -> 1 | J66: =ROUND($H66*③仙台以降予測!$G$8,0) -> 1 | K66: =ROUND($H66*③仙台以降予測!$G$9,0) -> 1 | L66: =ROUND($H66*③仙台以降予測!$G$10,0) -> 6 | M66: =SUM(I66:L66) -> 9 | N66: 4 | O66: 2 | P66: 2 | Q66: =IF(P66="",N66-O66,P66) -> 2 | R66: 1 | S66: 0 | T66: =①石川予測確定!S42 -> 1 | U66: =①石川予測確定!P42 -> 1 | V66: =Q66+R66-S66-U66 -> 2 | W66: 0 | X66: =M66-V66-W66 -> 7 | Y66: =MAX(0,X66) -> 7 | Z66: =IF(Y66>0,ROUNDUP(Y66*(1+前提・入力!$B$34),0),0) -> 8
A67: 37 | B67: 4515142545310 | C67: 夏油 傑 イメージリング（#11） | D67: 1 | E67: =IFERROR(D67/D$73,0) -> 0.00011247329 | F67: =①石川予測確定!P43 -> 5 | G67: =IFERROR(F67/F$73,0) -> 0.0009706853 | H67: =E67*前提・入力!$B$31+G67*前提・入力!$B$32 -> 0.0005415793 | I67: =ROUND($H67*③仙台以降予測!$G$7,0) -> 5 | J67: =ROUND($H67*③仙台以降予測!$G$8,0) -> 5 | K67: =ROUND($H67*③仙台以降予測!$G$9,0) -> 4 | L67: =ROUND($H67*③仙台以降予測!$G$10,0) -> 20 | M67: =SUM(I67:L67) -> 34 | N67: 43 | O67: 8 | P67: 26 | Q67: =IF(P67="",N67-O67,P67) -> 26 | R67: 7 | S67: 0 | T67: =①石川予測確定!S43 -> 17 | U67: =①石川予測確定!P43 -> 5 | V67: =Q67+R67-S67-U67 -> 28 | W67: 0 | X67: =M67-V67-W67 -> 6 | Y67: =MAX(0,X67) -> 6 | Z67: =IF(Y67>0,ROUNDUP(Y67*(1+前提・入力!$B$34),0),0) -> 7
A68: 38 | B68: 4515142545327 | C68: 夏油 傑 イメージリング（#13） | D68: 2 | E68: =IFERROR(D68/D$73,0) -> 0.00022494658 | F68: =①石川予測確定!P44 -> 1 | G68: =IFERROR(F68/F$73,0) -> 0.00019413706 | H68: =E68*前提・入力!$B$31+G68*前提・入力!$B$32 -> 0.00020954182 | I68: =ROUND($H68*③仙台以降予測!$G$7,0) -> 2 | J68: =ROUND($H68*③仙台以降予測!$G$8,0) -> 2 | K68: =ROUND($H68*③仙台以降予測!$G$9,0) -> 1 | L68: =ROUND($H68*③仙台以降予測!$G$10,0) -> 8 | M68: =SUM(I68:L68) -> 13 | N68: 4 | O68: 2 | P68: 2 | Q68: =IF(P68="",N68-O68,P68) -> 2 | R68: 0 | S68: 0 | T68: =①石川予測確定!S44 -> 1 | U68: =①石川予測確定!P44 -> 1 | V68: =Q68+R68-S68-U68 -> 1 | W68: 0 | X68: =M68-V68-W68 -> 12 | Y68: =MAX(0,X68) -> 12 | Z68: =IF(Y68>0,ROUNDUP(Y68*(1+前提・入力!$B$34),0),0) -> 14
A69: 39 | B69: 4515142545334 | C69: 夏油 傑 イメージリング（#15） | D69: 2 | E69: =IFERROR(D69/D$73,0) -> 0.00022494658 | F69: =①石川予測確定!P45 -> 2 | G69: =IFERROR(F69/F$73,0) -> 0.00038827412 | H69: =E69*前提・入力!$B$31+G69*前提・入力!$B$32 -> 0.00030661035 | I69: =ROUND($H69*③仙台以降予測!$G$7,0) -> 3 | J69: =ROUND($H69*③仙台以降予測!$G$8,0) -> 3 | K69: =ROUND($H69*③仙台以降予測!$G$9,0) -> 2 | L69: =ROUND($H69*③仙台以降予測!$G$10,0) -> 11 | M69: =SUM(I69:L69) -> 19 | N69: 5 | O69: 2 | P69: 2 | Q69: =IF(P69="",N69-O69,P69) -> 2 | R69: 0 | S69: 0 | T69: =①石川予測確定!S45 -> 1 | U69: =①石川予測確定!P45 -> 2 | V69: =Q69+R69-S69-U69 -> 0 | W69: 0 | X69: =M69-V69-W69 -> 19 | Y69: =MAX(0,X69) -> 19 | Z69: =IF(Y69>0,ROUNDUP(Y69*(1+前提・入力!$B$34),0),0) -> 21
A70: 40 | B70: 4515142545341 | C70: 夏油 傑 イメージリング（#17） | D70: 0 | E70: =IFERROR(D70/D$73,0) -> 0 | F70: =①石川予測確定!P46 -> 1 | G70: =IFERROR(F70/F$73,0) -> 0.00019413706 | H70: =E70*前提・入力!$B$31+G70*前提・入力!$B$32 -> 9.706853e-05 | I70: =ROUND($H70*③仙台以降予測!$G$7,0) -> 1 | J70: =ROUND($H70*③仙台以降予測!$G$8,0) -> 1 | K70: =ROUND($H70*③仙台以降予測!$G$9,0) -> 1 | L70: =ROUND($H70*③仙台以降予測!$G$10,0) -> 4 | M70: =SUM(I70:L70) -> 7 | N70: 4 | O70: 2 | P70: 2 | Q70: =IF(P70="",N70-O70,P70) -> 2 | R70: 2 | S70: 0 | T70: =①石川予測確定!S46 -> 3 | U70: =①石川予測確定!P46 -> 1 | V70: =Q70+R70-S70-U70 -> 3 | W70: 0 | X70: =M70-V70-W70 -> 4 | Y70: =MAX(0,X70) -> 4 | Z70: =IF(Y70>0,ROUNDUP(Y70*(1+前提・入力!$B$34),0),0) -> 5
... A72: 42 | B72: 4515142545365 | C72: 伏黒 恵 イメージフラグメントケース | D72: 1 | E72: =IFERROR(D72/D$73,0) -> 0.00011247329 | F72: =①石川予測確定!P48 -> 0 | G72: =IFERROR(F72/F$73,0) -> 0 | H72: =E72*前提・入力!$B$31+G72*前提・入力!$B$32 -> 5.6236644e-05 | I72: =ROUND($H72*③仙台以降予測!$G$7,0) -> 1 | J72: =ROUND($H72*③仙台以降予測!$G$8,0) -> 0 | K72: =ROUND($H72*③仙台以降予測!$G$9,0) -> 0 | L72: =ROUND($H72*③仙台以降予測!$G$10,0) -> 2 | M72: =SUM(I72:L72) -> 3 | N72: 49 | O72: 6 | P72: 43 | Q72: =IF(P72="",N72-O72,P72) -> 43 | R72: 5 | S72: 0 | T72: =①石川予測確定!S48 -> 15 | U72: =①石川予測確定!P48 -> 0 | V72: =Q72+R72-S72-U72 -> 48 | W72: 0 | X72: =M72-V72-W72 -> -45 | Y72: =MAX(0,X72) -> 0 | Z72: =IF(Y72>0,ROUNDUP(Y72*(1+前提・入力!$B$34),0),0) -> 0
C73: 合計（LEGS 42SKU） | D73: =SUM(D31:D72) -> 8891 | E73: =SUM(E31:E72) -> 1 | F73: =SUM(F31:F72) -> 5151 | G73: =SUM(G31:G72) -> 1 | H73: =SUM(H31:H72) -> 1 | I73: =SUM(I31:I72) -> 9536 | J73: =SUM(J31:J72) -> 8800 | K73: =SUM(K31:K72) -> 6602 | ... Z73: =SUM(Z31:Z72) -> 3729

Sheet ④追加発注判定
A1: ④ 追加発注 必要有無の判定（石川会期中 ＋ 仙台以降4会場）
A2: 【石川会期中】会期18日予測 vs 石川への納品済 販売可能数 ／ 【仙台以降】4会場必要数 vs 倉庫在庫＋石川会期末残在庫
A3: 推奨発注数＝不足数×(1+安全率10%)を切り上げ。欠品発生会場・最終発注期限（会期初日−生産日数−バッファ）・残日数・緊急度を右側に記載
A6: No. | B6: JAN | C6: 商品名 | D6: 税込単価 | E6: 石川 初12日実績 | F6: 石川 会期18日予測 | G6: 石川 販売可能数 (転送・追納込) | H6: 石川 予測消化率 | I6: 石川会期中 過不足 | J6: 石川会期中 判定 | K6: 石川会期中 推奨発注数 | L6: 仙台以降 必要数 | M6: 仙台以降 供給可能在庫 | N6: 確定発注 (入荷予定) | O6: 仙台以降 過不足 | P6: 仙台以降 判定 | Q6: 仙台以降 推奨発注数 | R6: 発注合計 (石川+仙台以降) | S6: 発注金額 (税込小売換算) | T6: 欠品発生 会場 | U6: 最終発注期限 | V6: 基準日からの 残日数 | W6: 発注の緊急度 | X6: 優先度 | Y6: 運営 欠品報告 (受領なし) | Z6: モデル×現場 突合 | AA6: 備考
A7: 1 | B7: 4515142545082 | C7: 呪術廻戦 メタリックポストカード 展示会キービジュアル | D7: 500 | E7: =①石川予測確定!E7 -> 210 | F7: =①石川予測確定!P7 -> 272 | G7: =①石川予測確定!S7 -> 693 | H7: =IFERROR(F7/G7,0) -> 0.39249639 | I7: =F7-G7 -> -421 | J7: =IF(I7>0,"要 追加発注",IF(H7>=0.9,"要注意(90%超)",IF(H7>=0.5,"適正","在庫余剰"))) -> 在庫余剰 | K7: =IF(I7>0,ROUNDUP(I7*(1+前提・入力!$B$34),0),0) -> 0 | L7: =③仙台以降予測!M31 -> 3384 | M7: =③仙台以降予測!V31 -> 2489 | N7: =③仙台以降予測!W31 -> 0 | O7: =L7-M7-N7 -> 895 | P7: =IF(O7>0,"要 追加生産",IF(L7=0,"—","在庫で充足")) -> 要 追加生産 | Q7: =③仙台以降予測!Z31 -> 985 | R7: =K7+Q7 -> 985 | S7: =R7*D7 -> 492500 | T7: 東京凱旋 東京建物ぴあホール | U7: =DATE(2027,4,1)-30-前提・入力!$B$37 -> 46434 | V7: =IF(OR(U7="",U7="再生産不可"),"",U7-前提・入力!$B$38) -> 174 | W7: =IF(T7="—","—",IF(U7="再生産不可","×再生産不可",_xlfn.IFS(V7<0,"★期限超過",V7<=30,"★至急(30日以内)",V7<=90,"要着手(90日以内)",TRUE(),"余裕あり"))) -> 余裕あり | X7: =IF(Y7<>"",IF(FALSE(),"S:現場欠品(追納不可)","S:現場欠品"),IF(I7>0,"A:会期中欠品",IF(O7>1000,"B:大口",IF(O7>0,"C:通常","D:不要")))) -> C:通常 | Z7: =IF(Y7<>"",IF(I7>0,"◎ 一致（モデルも会期中欠品を検知）",IF(H7>=0.7,"○ 整合（予測消化率70%超）","△ モデル未検知：現場報告を優先")),IF(I7>0,"▲ モデルのみ検知：現場に在庫状況を確認","—")) -> — | AA7: 博多会場で完売（実績が在庫上限で頭打ち＝予測は控えめ）
A8: 2 | B8: 4515142545099 | C8: 呪術廻戦 クリアファイル 展示会キービジュアル | D8: 600 | E8: =①石川予測確定!E8 -> 250 | F8: =①石川予測確定!P8 -> 325 | G8: =①石川予測確定!S8 -> 659 | H8: =IFERROR(F8/G8,0) -> 0.49317147 | I8: =F8-G8 -> -334 | J8: =IF(I8>0,"要 追加発注",IF(H8>=0.9,"要注意(90%超)",IF(H8>=0.5,"適正","在庫余剰"))) -> 在庫余剰 | K8: =IF(I8>0,ROUNDUP(I8*(1+前提・入力!$B$34),0),0) -> 0 | L8: =③仙台以降予測!M32 -> 3818 | M8: =③仙台以降予測!V32 -> 4170 | N8: =③仙台以降予測!W32 -> 0 | O8: =L8-M8-N8 -> -352 | P8: =IF(O8>0,"要 追加生産",IF(L8=0,"—","在庫で充足")) -> 在庫で充足 | Q8: =③仙台以降予測!Z32 -> 0 | R8: =K8+Q8 -> 0 | S8: =R8*D8 -> 0 | T8: — | V8: =IF(OR(U8="",U8="再生産不可"),"",U8-前提・入力!$B$38) | W8: =IF(T8="—","—",IF(U8="再生産不可","×再生産不可",_xlfn.IFS(V8<0,"★期限超過",V8<=30,"★至急(30日以内)",V8<=90,"要着手(90日以内)",TRUE(),"余裕あり"))) -> — | X8: =IF(Y8<>"",IF(FALSE(),"S:現場欠品(追納不可)","S:現場欠品"),IF(I8>0,"A:会期中欠品",IF(O8>1000,"B:大口",IF(O8>0,"C:通常","D:不要")))) -> D:不要 | Z8: =IF(Y8<>"",IF(I8>0,"◎ 一致（モデルも会期中欠品を検知）",IF(H8>=0.7,"○ 整合（予測消化率70%超）","△ モデル未検知：現場報告を優先")),IF(I8>0,"▲ モデルのみ検知：現場に在庫状況を確認","—")) -> —
A9: 3 | B9: 4515142545105 | C9: 呪術廻戦 懐玉・玉折 ポストカードセット（5枚入） | D9: 1000 | E9: =①石川予測確定!E9 -> 92 | F9: =①石川予測確定!P9 -> 118 | G9: =①石川予測確定!S9 -> 381 | H9: =IFERROR(F9/G9,0) -> 0.30971129 | I9: =F9-G9 -> -263 | J9: =IF(I9>0,"要 追加発注",IF(H9>=0.9,"要注意(90%超)",IF(H9>=0.5,"適正","在庫余剰"))) -> 在庫余剰 | K9: =IF(I9>0,ROUNDUP(I9*(1+前提・入力!$B$34),0),0) -> 0 | L9: =③仙台以降予測!M33 -> 1291 | M9: =③仙台以降予測!V33 -> 1857 | N9: =③仙台以降予測!W33 -> 0 | O9: =L9-M9-N9 -> -566 | P9: =IF(O9>0,"要 追加生産",IF(L9=0,"—","在庫で充足")) -> 在庫で充足 | Q9: =③仙台以降予測!Z33 -> 0 | R9: =K9+Q9 -> 0 | S9: =R9*D9 -> 0 | T9: — | V9: =IF(OR(U9="",U9="再生産不可"),"",U9-前提・入力!$B$38) | W9: =IF(T9="—","—",IF(U9="再生産不可","×再生産不可",_xlfn.IFS(V9<0,"★期限超過",V9<=30,"★至急(30日以内)",V9<=90,"要着手(90日以内)",TRUE(),"余裕あり"))) -> — | X9: =IF(Y9<>"",IF(FALSE(),"S:現場欠品(追納不可)","S:現場欠品"),IF(I9>0,"A:会期中欠品",IF(O9>1000,"B:大口",IF(O9>0,"C:通常","D:不要")))) -> D:不要 | Z9: =IF(Y9<>"",IF(I9>0,"◎ 一致（モデルも会期中欠品を検知）",IF(H9>=0.7,"○ 整合（予測消化率70%超）","△ モデル未検知：現場報告を優先")),IF(I9>0,"▲ モデルのみ検知：現場に在庫状況を確認","—")) -> —
A10: 4 | B10: 4515142545112 | C10: 呪術廻戦 渋谷事変 ポストカードセット（9枚入） | D10: 1800 | E10: =①石川予測確定!E10 -> 110 | F10: =①石川予測確定!P10 -> 134 | G10: =①石川予測確定!S10 -> 772 | H10: =IFERROR(F10/G10,0) -> 0.17357513 | I10: =F10-G10 -> -638 | J10: =IF(I10>0,"要 追加発注",IF(H10>=0.9,"要注意(90%超)",IF(H10>=0.5,"適正","在庫余剰"))) -> 在庫余剰 | K10: =IF(I10>0,ROUNDUP(I10*(1+前提・入力!$B$34),0),0) -> 0 | L10: =③仙台以降予測!M34 -> 1591 | M10: =③仙台以降予測!V34 -> 3153 | N10: =③仙台以降予測!W34 -> 0 | O10: =L10-M10-N10 -> -1562 | P10: =IF(O10>0,"要 追加生産",IF(L10=0,"—","在庫で充足")) -> 在庫で充足 | Q10: =③仙台以降予測!Z34 -> 0 | R10: =K10+Q10 -> 0 | S10: =R10*D10 -> 0 | T10: — | V10: =IF(OR(U10="",U10="再生産不可"),"",U10-前提・入力!$B$38) | W10: =IF(T10="—","—",IF(U10="再生産不可","×再生産不可",_xlfn.IFS(V10<0,"★期限超過",V10<=30,"★至急(30日以内)",V10<=90,"要着手(90日以内)",TRUE(),"余裕あり"))) -> — | X10: =IF(Y10<>"",IF(FALSE(),"S:現場欠品(追納不可)","S:現場欠品"),IF(I10>0,"A:会期中欠品",IF(O10>1000,"B:大口",IF(O10>0,"C:通常","D:不要")))) -> D:不要 | Z10: =IF(Y10<>"",IF(I10>0,"◎ 一致（モデルも会期中欠品を検知）",IF(H10>=0.7,"○ 整合（予測消化率70%超）","△ モデル未検知：現場報告を優先")),IF(I10>0,"▲ モデルのみ検知：現場に在庫状況を確認","—")) -> —
A11: 5 | B11: 4515142545129 | C11: 呪術廻戦 懐玉・玉折 ブラインド缶バッジ（全5種） | D11: 600 | E11: =①石川予測確定!E11 -> 226 | F11: =①石川予測確定!P11 -> 293 | G11: =①石川予測確定!S11 -> 8790 | H11: =IFERROR(F11/G11,0) -> 0.033333333 | I11: =F11-G11 -> -8497 | J11: =IF(I11>0,"要 追加発注",IF(H11>=0.9,"要注意(90%超)",IF(H11>=0.5,"適正","在庫余剰"))) -> 在庫余剰 | K11: =IF(I11>0,ROUNDUP(I11*(1+前提・入力!$B$34),0),0) -> 0 | L11: =③仙台以降予測!M35 -> 3173 | M11: =③仙台以降予測!V35 -> 39392 | N11: =③仙台以降予測!W35 -> 0 | O11: =L11-M11-N11 -> -36219 | P11: =IF(O11>0,"要 追加生産",IF(L11=0,"—","在庫で充足")) -> 在庫で充足 | Q11: =③仙台以降予測!Z35 -> 0 | R11: =K11+Q11 -> 0 | S11: =R11*D11 -> 0 | T11: — | V11: =IF(OR(U11="",U11="再生産不可"),"",U11-前提・入力!$B$38) | W11: =IF(T11="—","—",IF(U11="再生産不可","×再生産不可",_xlfn.IFS(V11<0,"★期限超過",V11<=30,"★至急(30日以内)",V11<=90,"要着手(90日以内)",TRUE(),"余裕あり"))) -> — | X11: =IF(Y11<>"",IF(FALSE(),"S:現場欠品(追納不可)","S:現場欠品"),IF(I11>0,"A:会期中欠品",IF(O11>1000,"B:大口",IF(O11>0,"C:通常","D:不要")))) -> D:不要 | Z11: =IF(Y11<>"",IF(I11>0,"◎ 一致（モデルも会期中欠品を検知）",IF(H11>=0.7,"○ 整合（予測消化率70%超）","△ モデル未検知：現場報告を優先")),IF(I11>0,"▲ モデルのみ検知：現場に在庫状況を確認","—")) -> — | AA11: 博多会場で完売（実績が在庫上限で頭打ち＝予測は控えめ）
A12: 6 | B12: 4515142545136 | C12: 呪術廻戦 渋谷事変 ブラインド缶バッジ（全9種） | D12: 600 | E12: =①石川予測確定!E12 -> 439 | F12: =①石川予測確定!P12 -> 565 | G12: =①石川予測確定!S12 -> 13249 | H12: =IFERROR(F12/G12,0) -> 0.042644728 | I12: =F12-G12 -> -12684 | J12: =IF(I12>0,"要 追加発注",IF(H12>=0.9,"要注意(90%超)",IF(H12>=0.5,"適正","在庫余剰"))) -> 在庫余剰 | K12: =IF(I12>0,ROUNDUP(I12*(1+前提・入力!$B$34),0),0) -> 0 | L12: =③仙台以降予測!M36 -> 6991 | M12: =③仙台以降予測!V36 -> 50228 | N12: =③仙台以降予測!W36 -> 0 | O12: =L12-M12-N12 -> -43237 | P12: =IF(O12>0,"要 追加生産",IF(L12=0,"—","在庫で充足")) -> 在庫で充足 | Q12: =③仙台以降予測!Z36 -> 0 | R12: =K12+Q12 -> 0 | S12: =R12*D12 -> 0 | T12: — | V12: =IF(OR(U12="",U12="再生産不可"),"",U12-前提・入力!$B$38) | W12: =IF(T12="—","—",IF(U12="再生産不可","×再生産不可",_xlfn.IFS(V12<0,"★期限超過",V12<=30,"★至急(30日以内)",V12<=90,"要着手(90日以内)",TRUE(),"余裕あり"))) -> — | X12: =IF(Y12<>"",IF(FALSE(),"S:現場欠品(追納不可)","S:現場欠品"),IF(I12>0,"A:会期中欠品",IF(O12>1000,"B:大口",IF(O12>0,"C:通常","D:不要")))) -> D:不要 | Z12: =IF(Y12<>"",IF(I12>0,"◎ 一致（モデルも会期中欠品を検知）",IF(H12>=0.7,"○ 整合（予測消化率70%超）","△ モデル未検知：現場報告を優先")),IF(I12>0,"▲ モデルのみ検知：現場に在庫状況を確認","—")) -> — | AA12: 博多会場で完売（実績が在庫上限で頭打ち＝予測は控えめ）
A13: 7 | B13: 4515142545143 | C13: 呪術廻戦 懐玉・玉折 ブラインドダイカットステッカー（全5種） | D13: 600 | E13: =①石川予測確定!E13 -> 130 | F13: =①石川予測確定!P13 -> 165 | G13: =①石川予測確定!S13 -> 463 | H13: =IFERROR(F13/G13,0) -> 0.35637149 | I13: =F13-G13 -> -298 | J13: =IF(I13>0,"要 追加発注",IF(H13>=0.9,"要注意(90%超)",IF(H13>=0.5,"適正","在庫余剰"))) -> 在庫余剰 | K13: =IF(I13>0,ROUNDUP(I13*(1+前提・入力!$B$34),0),0) -> 0 | L13: =③仙台以降予測!M37 -> 1635 | M13: =③仙台以降予測!V37 -> 4249 | N13: =③仙台以降予測!W37 -> 0 | O13: =L13-M13-N13 -> -2614 | P13: =IF(O13>0,"要 追加生産",IF(L13=0,"—","在庫で充足")) -> 在庫で充足 | Q13: =③仙台以降予測!Z37 -> 0 | R13: =K13+Q13 -> 0 | S13: =R13*D13 -> 0 | T13: — | V13: =IF(OR(U13="",U13="再生産不可"),"",U13-前提・入力!$B$38) | W13: =IF(T13="—","—",IF(U13="再生産不可","×再生産不可",_xlfn.IFS(V13<0,"★期限超過",V13<=30,"★至急(30日以内)",V13<=90,"要着手(90日以内)",TRUE(),"余裕あり"))) -> — | X13: =IF(Y13<>"",IF(FALSE(),"S:現場欠品(追納不可)","S:現場欠品"),IF(I13>0,"A:会期中欠品",IF(O13>1000,"B:大口",IF(O13>0,"C:通常","D:不要")))) -> D:不要 | Z13: =IF(Y13<>"",IF(I13>0,"◎ 一致（モデルも会期中欠品を検知）",IF(H13>=0.7,"○ 整合（予測消化率70%超）","△ モデル未検知：現場報告を優先")),IF(I13>0,"▲ モデルのみ検知：現場に在庫状況を確認","—")) -> — | AA13: 博多会場で完売（実績が在庫上限で頭打ち＝予測は控えめ）
A14: 8 | B14: 4515142545150 | C14: 呪術廻戦 渋谷事変 ブラインドダイカットステッカー（全9種） | D14: 600 | E14: =①石川予測確定!E14 -> 207 | F14: =①石川予測確定!P14 -> 266 | G14: =①石川予測確定!S14 -> 778 | H14: =IFERROR(F14/G14,0) -> 0.34190231 | I14: =F14-G14 -> -512 | J14: =IF(I14>0,"要 追加発注",IF(H14>=0.9,"要注意(90%超)",IF(H14>=0.5,"適正","在庫余剰"))) -> 在庫余剰 | K14: =IF(I14>0,ROUNDUP(I14*(1+前提・入力!$B$34),0),0) -> 0 | L14: =③仙台以降予測!M38 -> 2707 | M14: =③仙台以降予測!V38 -> 8034 | N14: =③仙台以降予測!W38 -> 0 | O14: =L14-M14-N14 -> -5327 | P14: =IF(O14>0,"要 追加生産",IF(L14=0,"—","在庫で充足")) -> 在庫で充足 | Q14: =③仙台以降予測!Z38 -> 0 | R14: =K14+Q14 -> 0 | S14: =R14*D14 -> 0 | T14: — | V14: =IF(OR(U14="",U14="再生産不可"),"",U14-前提・入力!$B$38) | W14: =IF(T14="—","—",IF(U14="再生産不可","×再生産不可",_xlfn.IFS(V14<0,"★期限超過",V14<=30,"★至急(30日以内)",V14<=90,"要着手(90日以内)",TRUE(),"余裕あり"))) -> — | X14: =IF(Y14<>"",IF(FALSE(),"S:現場欠品(追納不可)","S:現場欠品"),IF(I14>0,"A:会期中欠品",IF(O14>1000,"B:大口",IF(O14>0,"C:通常","D:不要")))) -> D:不要 | Z14: =IF(Y14<>"",IF(I14>0,"◎ 一致（モデルも会期中欠品を検知）",IF(H14>=0.7,"○ 整合（予測消化率70%超）","△ モデル未検知：現場報告を優先")),IF(I14>0,"▲ モデルのみ検知：現場に在庫状況を確認","—")) -> — | AA14: 博多会場で完売（実績が在庫上限で頭打ち＝予測は控えめ）
A15: 9 | B15: 4515142545372 | C15: 呪術廻戦 懐玉・玉折 クリアファイル（五条 悟） | D15: 600 | E15: =①石川予測確定!E15 -> 41 | F15: =①石川予測確定!P15 -> 51 | G15: =①石川予測確定!S15 -> 740 | H15: =IFERROR(F15/G15,0) -> 0.068918919 | I15: =F15-G15 -> -689 | J15: =IF(I15>0,"要 追加発注",IF(H15>=0.9,"要注意(90%超)",IF(H15>=0.5,"適正","在庫余剰"))) -> 在庫余剰 | K15: =IF(I15>0,ROUNDUP(I15*(1+前提・入力!$B$34),0),0) -> 0 | L15: =③仙台以降予測!M39 -> 860 | M15: =③仙台以降予測!V39 -> 8547 | N15: =③仙台以降予測!W39 -> 0 | O15: =L15-M15-N15 -> -7687 | P15: =IF(O15>0,"要 追加生産",IF(L15=0,"—","在庫で充足")) -> 在庫で充足 | Q15: =③仙台以降予測!Z39 -> 0 | R15: =K15+Q15 -> 0 | S15: =R15*D15 -> 0 | T15: — | V15: =IF(OR(U15="",U15="再生産不可"),"",U15-前提・入力!$B$38) | W15: =IF(T15="—","—",IF(U15="再生産不可","×再生産不可",_xlfn.IFS(V15<0,"★期限超過",V15<=30,"★至急(30日以内)",V15<=90,"要着手(90日以内)",TRUE(),"余裕あり"))) -> — | X15: =IF(Y15<>"",IF(FALSE(),"S:現場欠品(追納不可)","S:現場欠品"),IF(I15>0,"A:会期中欠品",IF(O15>1000,"B:大口",IF(O15>0,"C:通常","D:不要")))) -> D:不要 | Z15: =IF(Y15<>"",IF(I15>0,"◎ 一致（モデルも会期中欠品を検知）",IF(H15>=0.7,"○ 整合（予測消化率70%超）","△ モデル未検知：現場報告を優先")),IF(I15>0,"▲ モデルのみ検知：現場に在庫状況を確認","—")) -> — | AA15: 博多会場で完売（実績が在庫上限で頭打ち＝予測は控えめ）
A16: 10 | B16: 4515142545389 | C16: 呪術廻戦 懐玉・玉折 クリアファイル（夏油 傑） | D16: 600 | E16: =①石川予測確定!E16 -> 16 | F16: =①石川予測確定!P16 -> 20 | G16: =①石川予測確定!S16 -> 541 | H16: =IFERROR(F16/G16,0) -> 0.036968577 | I16: =F16-G16 -> -521 | J16: =IF(I16>0,"要 追加発注",IF(H16>=0.9,"要注意(90%超)",IF(H16>=0.5,"適正","在庫余剰"))) -> 在庫余剰 | K16: =IF(I16>0,ROUNDUP(I16*(1+前提・入力!$B$34),0),0) -> 0 | L16: =③仙台以降予測!M40 -> 324 | M16: =③仙台以降予測!V40 -> 4856 | N16: =③仙台以降予測!W40 -> 0 | O16: =L16-M16-N16 -> -4532 | P16: =IF(O16>0,"要 追加生産",IF(L16=0,"—","在庫で充足")) -> 在庫で充足 | Q16: =③仙台以降予測!Z40 -> 0 | R16: =K16+Q16 -> 0 | S16: =R16*D16 -> 0 | T16: — | V16: =IF(OR(U16="",U16="再生産不可"),"",U16-前提・入力!$B$38) | W16: =IF(T16="—","—",IF(U16="再生産不可","×再生産不可",_xlfn.IFS(V16<0,"★期限超過",V16<=30,"★至急(30日以内)",V16<=90,"要着手(90日以内)",TRUE(),"余裕あり"))) -> — | X16: =IF(Y16<>"",IF(FALSE(),"S:現場欠品(追納不可)","S:現場欠品"),IF(I16>0,"A:会期中欠品",IF(O16>1000,"B:大口",IF(O16>0,"C:通常","D:不要")))) -> D:不要 | Z16: =IF(Y16<>"",IF(I16>0,"◎ 一致（モデルも会期中欠品を検知）",IF(H16>=0.7,"○ 整合（予測消化率70%超）","△ モデル未検知：現場報告を優先")),IF(I16>0,"▲ モデルのみ検知：現場に在庫状況を確認","—")) -> —
A17: 11 | B17: 4515142545396 | C17: 呪術廻戦 懐玉・玉折 クリアファイル（家入 硝子） | D17: 600 | E17: =①石川予測確定!E17 -> 6 | F17: =①石川予測確定!P17 -> 8 | G17: =①石川予測確定!S17 -> 79 | H17: =IFERROR(F17/G17,0) -> 0.10126582 | I17: =F17-G17 -> -71 | J17: =IF(I17>0,"要 追加発注",IF(H17>=0.9,"要注意(90%超)",IF(H17>=0.5,"適正","在庫余剰"))) -> 在庫余剰 | K17: =IF(I17>0,ROUNDUP(I17*(1+前提・入力!$B$34),0),0) -> 0 | L17: =③仙台以降予測!M41 -> 121 | M17: =③仙台以降予測!V41 -> 609 | N17: =③仙台以降予測!W41 -> 0 | O17: =L17-M17-N17 -> -488 | P17: =IF(O17>0,"要 追加生産",IF(L17=0,"—","在庫で充足")) -> 在庫で充足 | Q17: =③仙台以降予測!Z41 -> 0 | R17: =K17+Q17 -> 0 | S17: =R17*D17 -> 0 | T17: — | V17: =IF(OR(U17="",U17="再生産不可"),"",U17-前提・入力!$B$38) | W17: =IF(T17="—","—",IF(U17="再生産不可","×再生産不可",_xlfn.IFS(V17<0,"★期限超過",V17<=30,"★至急(30日以内)",V17<=90,"要着手(90日以内)",TRUE(),"余裕あり"))) -> — | X17: =IF(Y17<>"",IF(FALSE(),"S:現場欠品(追納不可)","S:現場欠品"),IF(I17>0,"A:会期中欠品",IF(O17>1000,"B:大口",IF(O17>0,"C:通常","D:不要")))) -> D:不要 | Z17: =IF(Y17<>"",IF(I17>0,"◎ 一致（モデルも会期中欠品を検知）",IF(H17>=0.7,"○ 整合（予測消化率70%超）","△ モデル未検知：現場報告を優先")),IF(I17>0,"▲ モデルのみ検知：現場に在庫状況を確認","—")) -> — | AA17: 博多会場で完売（実績が在庫上限で頭打ち＝予測は控えめ）
A18: 12 | B18: 4515142545402 | C18: 呪術廻戦 懐玉・玉折 クリアファイル（七海 建人） | D18: 600 | E18: =①石川予測確定!E18 -> 13 | F18: =①石川予測確定!P18 -> 17 | G18: =①石川予測確定!S18 -> 107 | H18: =IFERROR(F18/G18,0) -> 0.1588785 | I18: =F18-G18 -> -90 | J18: =IF(I18>0,"要 追加発注",IF(H18>=0.9,"要注意(90%超)",IF(H18>=0.5,"適正","在庫余剰"))) -> 在庫余剰 | K18: =IF(I18>0,ROUNDUP(I18*(1+前提・入力!$B$34),0),0) -> 0 | L18: =③仙台以降予測!M42 -> 251 | M18: =③仙台以降予測!V42 -> 891 | N18: =③仙台以降予測!W42 -> 0 | O18: =L18-M18-N18 -> -640 | P18: =IF(O18>0,"要 追加生産",IF(L18=0,"—","在庫で充足")) -> 在庫で充足 | Q18: =③仙台以降予測!Z42 -> 0 | R18: =K18+Q18 -> 0 | S18: =R18*D18 -> 0 | T18: — | V18: =IF(OR(U18="",U18="再生産不可"),"",U18-前提・入力!$B$38) | W18: =IF(T18="—","—",IF(U18="再生産不可","×再生産不可",_xlfn.IFS(V18<0,"★期限超過",V18<=30,"★至急(30日以内)",V18<=90,"要着手(90日以内)",TRUE(),"余裕あり"))) -> — | X18: =IF(Y18<>"",IF(FALSE(),"S:現場欠品(追納不可)","S:現場欠品"),IF(I18>0,"A:会期中欠品",IF(O18>1000,"B:大口",IF(O18>0,"C:通常","D:不要")))) -> D:不要 | Z18: =IF(Y18<>"",IF(I18>0,"◎ 一致（モデルも会期中欠品を検知）",IF(H18>=0.7,"○ 整合（予測消化率70%超）","△ モデル未検知：現場報告を優先")),IF(I18>0,"▲ モデルのみ検知：現場に在庫状況を確認","—")) -> —
A19: 13 | B19: 4515142545419 | C19: 呪術廻戦 懐玉・玉折 クリアファイル（灰原 雄） | D19: 600 | E19: =①石川予測確定!E19 -> 5 | F19: =①石川予測確定!P19 -> 6 | G19: =①石川予測確定!S19 -> 52 | H19: =IFERROR(F19/G19,0) -> 0.11538462 | I19: =F19-G19 -> -46 | J19: =IF(I19>0,"要 追加発注",IF(H19>=0.9,"要注意(90%超)",IF(H19>=0.5,"適正","在庫余剰"))) -> 在庫余剰 | K19: =IF(I19>0,ROUNDUP(I19*(1+前提・入力!$B$34),0),0) -> 0 | L19: =③仙台以降予測!M43 -> 64 | M19: =③仙台以降予測!V43 -> 305 | N19: =③仙台以降予測!W43 -> 0 | O19: =L19-M19-N19 -> -241 | P19: =IF(O19>0,"要 追加生産",IF(L19=0,"—","在庫で充足")) -> 在庫で充足 | Q19: =③仙台以降予測!Z43 -> 0 | R19: =K19+Q19 -> 0 | S19: =R19*D19 -> 0 | T19: — | V19: =IF(OR(U19="",U19="再生産不可"),"",U19-前提・入力!$B$38) | W19: =IF(T19="—","—",IF(U19="再生産不可","×再生産不可",_xlfn.IFS(V19<0,"★期限超過",V19<=30,"★至急(30日以内)",V19<=90,"要着手(90日以内)",TRUE(),"余裕あり"))) -> — | X19: =IF(Y19<>"",IF(FALSE(),"S:現場欠品(追納不可)","S:現場欠品"),IF(I19>0,"A:会期中欠品",IF(O19>1000,"B:大口",IF(O19>0,"C:通常","D:不要")))) -> D:不要 | Z19: =IF(Y19<>"",IF(I19>0,"◎ 一致（モデルも会期中欠品を検知）",IF(H19>=0.7,"○ 整合（予測消化率70%超）","△ モデル未検知：現場報告を優先")),IF(I19>0,"▲ モデルのみ検知：現場に在庫状況を確認","—")) -> —
A20: 14 | B20: 4515142545426 | C20: 呪術廻戦 渋谷事変 クリアファイル（虎杖 悠仁） | D20: 600 | E20: =①石川予測確定!E20 -> 10 | F20: =①石川予測確定!P20 -> 14 | G20: =①石川予測確定!S20 -> 53 | H20: =IFERROR(F20/G20,0) -> 0.26415094 | I20: =F20-G20 -> -39 | J20: =IF(I20>0,"要 追加発注",IF(H20>=0.9,"要注意(90%超)",IF(H20>=0.5,"適正","在庫余剰"))) -> 在庫余剰 | K20: =IF(I20>0,ROUNDUP(I20*(1+前提・入力!$B$34),0),0) -> 0 | L20: =③仙台以降予測!M44 -> 246 | M20: =③仙台以降予測!V44 -> 1729 | N20: =③仙台以降予測!W44 -> 0 | O20: =L20-M20-N20 -> -1483 | P20: =IF(O20>0,"要 追加生産",IF(L20=0,"—","在庫で充足")) -> 在庫で充足 | Q20: =③仙台以降予測!Z44 -> 0 | R20: =K20+Q20 -> 0 | S20: =R20*D20 -> 0 | T20: — | V20: =IF(OR(U20="",U20="再生産不可"),"",U20-前提・入力!$B$38) | W20: =IF(T20="—","—",IF(U20="再生産不可","×再生産不可",_xlfn.IFS(V20<0,"★期限超過",V20<=30,"★至急(30日以内)",V20<=90,"要着手(90日以内)",TRUE(),"余裕あり"))) -> — | X20: =IF(Y20<>"",IF(FALSE(),"S:現場欠品(追納不可)","S:現場欠品"),IF(I20>0,"A:会期中欠品",IF(O20>1000,"B:大口",IF(O20>0,"C:通常","D:不要")))) -> D:不要 | Z20: =IF(Y20<>"",IF(I20>0,"◎ 一致（モデルも会期中欠品を検知）",IF(H20>=0.7,"○ 整合（予測消化率70%超）","△ モデル未検知：現場報告を優先")),IF(I20>0,"▲ モデルのみ検知：現場に在庫状況を確認","—")) -> — | AA20: 博多会場で完売（実績が在庫上限で頭打ち＝予測は控えめ）
A21: 15 | B21: 4515142545433 | C21: 呪術廻戦 渋谷事変 クリアファイル（伏黒 恵） | D21: 600 | E21: =①石川予測確定!E21 -> 17 | F21: =①石川予測確定!P21 -> 23 | G21: =①石川予測確定!S21 -> 96 | H21: =IFERROR(F21/G21,0) -> 0.23958333 | I21: =F21-G21 -> -73 | J21: =IF(I21>0,"要 追加発注",IF(H21>=0.9,"要注意(90%超)",IF(H21>=0.5,"適正","在庫余剰"))) -> 在庫余剰 | K21: =IF(I21>0,ROUNDUP(I21*(1+前提・入力!$B$34),0),0) -> 0 | L21: =③仙台以降予測!M45 -> 324 | M21: =③仙台以降予測!V45 -> 2054 | N21: =③仙台以降予測!W45 -> 0 | O21: =L21-M21-N21 -> -1730 | P21: =IF(O21>0,"要 追加生産",IF(L21=0,"—","在庫で充足")) -> 在庫で充足 | Q21: =③仙台以降予測!Z45 -> 0 | R21: =K21+Q21 -> 0 | S21: =R21*D21 -> 0 | T21: — | V21: =IF(OR(U21="",U21="再生産不可"),"",U21-前提・入力!$B$38) | W21: =IF(T21="—","—",IF(U21="再生産不可","×再生産不可",_xlfn.IFS(V21<0,"★期限超過",V21<=30,"★至急(30日以内)",V21<=90,"要着手(90日以内)",TRUE(),"余裕あり"))) -> — | X21: =IF(Y21<>"",IF(FALSE(),"S:現場欠品(追納不可)","S:現場欠品"),IF(I21>0,"A:会期中欠品",IF(O21>1000,"B:大口",IF(O21>0,"C:通常","D:不要")))) -> D:不要 | Z21: =IF(Y21<>"",IF(I21>0,"◎ 一致（モデルも会期中欠品を検知）",IF(H21>=0.7,"○ 整合（予測消化率70%超）","△ モデル未検知：現場報告を優先")),IF(I21>0,"▲ モデルのみ検知：現場に在庫状況を確認","—")) -> — | AA21: 博多会場で完売（実績が在庫上限で頭打ち＝予測は控えめ）
A22: 16 | B22: 4515142545440 | C22: 呪術廻戦 渋谷事変 クリアファイル（釘崎 野薔薇） | D22: 600 | E22: =①石川予測確定!E22 -> 4 | F22: =①石川予測確定!P22 -> 6 | G22: =①石川予測確定!S22 -> 78 | H22: =IFERROR(F22/G22,0) -> 0.076923077 | I22: =F22-G22 -> -72 | J22: =IF(I22>0,"要 追加発注",IF(H22>=0.9,"要注意(90%超)",IF(H22>=0.5,"適正","在庫余剰"))) -> 在庫余剰 | K22: =IF(I22>0,ROUNDUP(I22*(1+前提・入力!$B$34),0),0) -> 0 | L22: =③仙台以降予測!M46 -> 112 | M22: =③仙台以降予測!V46 -> 744 | N22: =③仙台以降予測!W46 -> 0 | O22: =L22-M22-N22 -> -632 | P22: =IF(O22>0,"要 追加生産",IF(L22=0,"—","在庫で充足")) -> 在庫で充足 | Q22: =③仙台以降予測!Z46 -> 0 | R22: =K22+Q22 -> 0 | S22: =R22*D22 -> 0 | T22: — | V22: =IF(OR(U22="",U22="再生産不可"),"",U22-前提・入力!$B$38) | W22: =IF(T22="—","—",IF(U22="再生産不可","×再生産不可",_xlfn.IFS(V22<0,"★期限超過",V22<=30,"★至急(30日以内)",V22<=90,"要着手(90日以内)",TRUE(),"余裕あり"))) -> — | X22: =IF(Y22<>"",IF(FALSE(),"S:現場欠品(追納不可)","S:現場欠品"),IF(I22>0,"A:会期中欠品",IF(O22>1000,"B:大口",IF(O22>0,"C:通常","D:不要")))) -> D:不要 | Z22: =IF(Y22<>"",IF(I22>0,"◎ 一致（モデルも会期中欠品を検知）",IF(H22>=0.7,"○ 整合（予測消化率70%超）","△ モデル未検知：現場報告を優先")),IF(I22>0,"▲ モデルのみ検知：現場に在庫状況を確認","—")) -> — | AA22: 名古屋会場で完売（実績が在庫上限で頭打ち＝予測は控えめ） ／ 博多会場で完売（実績が在庫上限で頭打ち＝予測は控えめ）
A23: 17 | B23: 4515142545457 | C23: 呪術廻戦 渋谷事変 クリアファイル（七海 建人） | D23: 600 | E23: =①石川予測確定!E23 -> 30 | F23: =①石川予測確定!P23 -> 41 | G23: =①石川予測確定!S23 -> 200 | H23: =IFERROR(F23/G23,0) -> 0.205 | I23: =F23-G23 -> -159 | J23: =IF(I23>0,"要 追加発注",IF(H23>=0.9,"要注意(90%超)",IF(H23>=0.5,"適正","在庫余剰"))) -> 在庫余剰 | K23: =IF(I23>0,ROUNDUP(I23*(1+前提・入力!$B$34),0),0) -> 0 | L23: =③仙台以降予測!M47 -> 592 | M23: =③仙台以降予測!V47 -> 2380 | N23: =③仙台以降予測!W47 -> 0 | O23: =L23-M23-N23 -> -1788 | P23: =IF(O23>0,"要 追加生産",IF(L23=0,"—","在庫で充足")) -> 在庫で充足 | Q23: =③仙台以降予測!Z47 -> 0 | R23: =K23+Q23 -> 0 | S23: =R23*D23 -> 0 | T23: — | V23: =IF(OR(U23="",U23="再生産不可"),"",U23-前提・入力!$B$38) | W23: =IF(T23="—","—",IF(U23="再生産不可","×再生産不可",_xlfn.IFS(V23<0,"★期限超過",V23<=30,"★至急(30日以内)",V23<=90,"要着手(90日以内)",TRUE(),"余裕あり"))) -> — | X23: =IF(Y23<>"",IF(FALSE(),"S:現場欠品(追納不可)","S:現場欠品"),IF(I23>0,"A:会期中欠品",IF(O23>1000,"B:大口",IF(O23>0,"C:通常","D:不要")))) -> D:不要 | Z23: =IF(Y23<>"",IF(I23>0,"◎ 一致（モデルも会期中欠品を検知）",IF(H23>=0.7,"○ 整合（予測消化率70%超）","△ モデル未検知：現場報告を優先")),IF(I23>0,"▲ モデルのみ検知：現場に在庫状況を確認","—")) -> — | AA23: 博多会場で完売（実績が在庫上限で頭打ち＝予測は控えめ）
A24: 18 | B24: 4515142545464 | C24: 呪術廻戦 渋谷事変 クリアファイル（五条 悟） | D24: 600 | E24: =①石川予測確定!E24 -> 122 | F24: =①石川予測確定!P24 -> 152 | G24: =①石川予測確定!S24 -> 1157 | H24: =IFERROR(F24/G24,0) -> 0.13137424 | I24: =F24-G24 -> -1005 | J24: =IF(I24>0,"要 追加発注",IF(H24>=0.9,"要注意(90%超)",IF(H24>=0.5,"適正","在庫余剰"))) -> 在庫余剰 | K24: =IF(I24>0,ROUNDUP(I24*(1+前提・入力!$B$34),0),0) -> 0 | L24: =③仙台以降予測!M48 -> 2444 | M24: =③仙台以降予測!V48 -> 9130 | N24: =③仙台以降予測!W48 -> 0 | O24: =L24-M24-N24 -> -6686 | P24: =IF(O24>0,"要 追加生産",IF(L24=0,"—","在庫で充足")) -> 在庫で充足 | Q24: =③仙台以降予測!Z48 -> 0 | R24: =K24+Q24 -> 0 | S24: =R24*D24 -> 0 | T24: — | V24: =IF(OR(U24="",U24="再生産不可"),"",U24-前提・入力!$B$38) | W24: =IF(T24="—","—",IF(U24="再生産不可","×再生産不可",_xlfn.IFS(V24<0,"★期限超過",V24<=30,"★至急(30日以内)",V24<=90,"要着手(90日以内)",TRUE(),"余裕あり"))) -> — | X24: =IF(Y24<>"",IF(FALSE(),"S:現場欠品(追納不可)","S:現場欠品"),IF(I24>0,"A:会期中欠品",IF(O24>1000,"B:大口",IF(O24>0,"C:通常","D:不要")))) -> D:不要 | Z24: =IF(Y24<>"",IF(I24>0,"◎ 一致（モデルも会期中欠品を検知）",IF(H24>=0.7,"○ 整合（予測消化率70%超）","△ モデル未検知：現場報告を優先")),IF(I24>0,"▲ モデルのみ検知：現場に在庫状況を確認","—")) -> — | AA24: 博多会場で完売（実績が在庫上限で頭打ち＝予測は控えめ）
A25: 19 | B25: 4515142545471 | C25: 呪術廻戦 渋谷事変 クリアファイル（夏油 傑） | D25: 600 | E25: =①石川予測確定!E25 -> 4 | F25: =①石川予測確定!P25 -> 5 | G25: =①石川予測確定!S25 -> 129 | H25: =IFERROR(F25/G25,0) -> 0.03875969 | I25: =F25-G25 -> -124 | J25: =IF(I25>0,"要 追加発注",IF(H25>=0.9,"要注意(90%超)",IF(H25>=0.5,"適正","在庫余剰"))) -> 在庫余剰 | K25: =IF(I25>0,ROUNDUP(I25*(1+前提・入力!$B$34),0),0) -> 0 | L25: =③仙台以降予測!M49 -> 103 | M25: =③仙台以降予測!V49 -> 2214 | N25: =③仙台以降予測!W49 -> 0 | O25: =L25-M25-N25 -> -2111 | P25: =IF(O25>0,"要 追加生産",IF(L25=0,"—","在庫で充足")) -> 在庫で充足 | Q25: =③仙台以降予測!Z49 -> 0 | R25: =K25+Q25 -> 0 | S25: =R25*D25 -> 0 | T25: — | V25: =IF(OR(U25="",U25="再生産不可"),"",U25-前提・入力!$B$38) | W25: =IF(T25="—","—",IF(U25="再生産不可","×再生産不可",_xlfn.IFS(V25<0,"★期限超過",V25<=30,"★至急(30日以内)",V25<=90,"要着手(90日以内)",TRUE(),"余裕あり"))) -> — | X25: =IF(Y25<>"",IF(FALSE(),"S:現場欠品(追納不可)","S:現場欠品"),IF(I25>0,"A:会期中欠品",IF(O25>1000,"B:大口",IF(O25>0,"C:通常","D:不要")))) -> D:不要 | Z25: =IF(Y25<>"",IF(I25>0,"◎ 一致（モデルも会期中欠品を検知）",IF(H25>=0.7,"○ 整合（予測消化率70%超）","△ モデル未検知：現場報告を優先")),IF(I25>0,"▲ モデルのみ検知：現場に在庫状況を確認","—")) -> — | AA25: 博多会場で完売（実績が在庫上限で頭打ち＝予測は控えめ）
A26: 20 | B26: 4515142545488 | C26: 呪術廻戦 渋谷事変 クリアファイル（真人） | D26: 600 | E26: =①石川予測確定!E26 -> 5 | F26: =①石川予測確定!P26 -> 7 | G26: =①石川予測確定!S26 -> 17 | H26: =IFERROR(F26/G26,0) -> 0.41176471 | I26: =F26-G26 -> -10 | J26: =IF(I26>0,"要 追加発注",IF(H26>=0.9,"要注意(90%超)",IF(H26>=0.5,"適正","在庫余剰"))) -> 在庫余剰 | K26: =IF(I26>0,ROUNDUP(I26*(1+前提・入力!$B$34),0),0) -> 0 | L26: =③仙台以降予測!M50 -> 104 | M26: =③仙台以降予測!V50 -> 276 | N26: =③仙台以降予測!W50 -> 0 | O26: =L26-M26-N26 -> -172 | P26: =IF(O26>0,"要 追加生産",IF(L26=0,"—","在庫で充足")) -> 在庫で充足 | Q26: =③仙台以降予測!Z50 -> 0 | R26: =K26+Q26 -> 0 | S26: =R26*D26 -> 0 | T26: — | V26: =IF(OR(U26="",U26="再生産不可"),"",U26-前提・入力!$B$38) | W26: =IF(T26="—","—",IF(U26="再生産不可","×再生産不可",_xlfn.IFS(V26<0,"★期限超過",V26<=30,"★至急(30日以内)",V26<=90,"要着手(90日以内)",TRUE(),"余裕あり"))) -> — | X26: =IF(Y26<>"",IF(FALSE(),"S:現場欠品(追納不可)","S:現場欠品"),IF(I26>0,"A:会期中欠品",IF(O26>1000,"B:大口",IF(O26>0,"C:通常","D:不要")))) -> D:不要 | Z26: =IF(Y26<>"",IF(I26>0,"◎ 一致（モデルも会期中欠品を検知）",IF(H26>=0.7,"○ 整合（予測消化率70%超）","△ モデル未検知：現場報告を優先")),IF(I26>0,"▲ モデルのみ検知：現場に在庫状況を確認","—")) -> — | AA26: 博多会場で完売（実績が在庫上限で頭打ち＝予測は控えめ）
A27: 21 | B27: 4515142545495 | C27: 呪術廻戦 渋谷事変 クリアファイル（脹相） | D27: 600 | E27: =①石川予測確定!E27 -> 23 | F27: =①石川予測確定!P27 -> 30 | G27: =①石川予測確定!S27 -> 32 | H27: =IFERROR(F27/G27,0) -> 0.9375 | I27: =F27-G27 -> -2 | J27: =IF(I27>0,"要 追加発注",IF(H27>=0.9,"要注意(90%超)",IF(H27>=0.5,"適正","在庫余剰"))) -> 要注意(90%超) | K27: =IF(I27>0,ROUNDUP(I27*(1+前提・入力!$B$34),0),0) -> 0 | L27: =③仙台以降予測!M51 -> 484 | M27: =③仙台以降予測!V51 -> 190 | N27: =③仙台以降予測!W51 -> 0 | O27: =L27-M27-N27 -> 294 | P27: =IF(O27>0,"要 追加生産",IF(L27=0,"—","在庫で充足")) -> 要 追加生産 | Q27: =③仙台以降予測!Z51 -> 324 | R27: =K27+Q27 -> 324 | S27: =R27*D27 -> 194400 | T27: 鳥取島根 夢みなとタワー | U27: =DATE(2027,3,15)-30-前提・入力!$B$37 -> 46417 | V27: =IF(OR(U27="",U27="再生産不可"),"",U27-前提・入力!$B$38) -> 157 | W27: =IF(T27="—","—",IF(U27="再生産不可","×再生産不可",_xlfn.IFS(V27<0,"★期限超過",V27<=30,"★至急(30日以内)",V27<=90,"要着手(90日以内)",TRUE(),"余裕あり"))) -> 余裕あり | X27: =IF(Y27<>"",IF(FALSE(),"S:現場欠品(追納不可)","S:現場欠品"),IF(I27>0,"A:会期中欠品",IF(O27>1000,"B:大口",IF(O27>0,"C:通常","D:不要")))) -> C:通常 | Z27: =IF(Y27<>"",IF(I27>0,"◎ 一致（モデルも会期中欠品を検知）",IF(H27>=0.7,"○ 整合（予測消化率70%超）","△ モデル未検知：現場報告を優先")),IF(I27>0,"▲ モデルのみ検知：現場に在庫状況を確認","—")) -> — | AA27: 名古屋会場で完売（実績が在庫上限で頭打ち＝予測は控えめ） ／ 博多会場で完売（実績が在庫上限で頭打ち＝予測は控えめ）
A28: 22 | B28: 4515142545501 | C28: 呪術廻戦 渋谷事変 クリアファイル（宿儺） | D28: 600 | E28: =①石川予測確定!E28 -> 19 | F28: =①石川予測確定!P28 -> 27 | G28: =①石川予測確定!S28 -> 150 | H28: =IFERROR(F28/G28,0) -> 0.18 | I28: =F28-G28 -> -123 | J28: =IF(I28>0,"要 追加発注",IF(H28>=0.9,"要注意(90%超)",IF(H28>=0.5,"適正","在庫余剰"))) -> 在庫余剰 | K28: =IF(I28>0,ROUNDUP(I28*(1+前提・入力!$B$34),0),0) -> 0 | L28: =③仙台以降予測!M52 -> 335 | M28: =③仙台以降予測!V52 -> 1254 | N28: =③仙台以降予測!W52 -> 0 | O28: =L28-M28-N28 -> -919 | P28: =IF(O28>0,"要 追加生産",IF(L28=0,"—","在庫で充足")) -> 在庫で充足 | Q28: =③仙台以降予測!Z52 -> 0 | R28: =K28+Q28 -> 0 | S28: =R28*D28 -> 0 | T28: — | V28: =IF(OR(U28="",U28="再生産不可"),"",U28-前提・入力!$B$38) | W28: =IF(T28="—","—",IF(U28="再生産不可","×再生産不可",_xlfn.IFS(V28<0,"★期限超過",V28<=30,"★至急(30日以内)",V28<=90,"要着手(90日以内)",TRUE(),"余裕あり"))) -> — | X28: =IF(Y28<>"",IF(FALSE(),"S:現場欠品(追納不可)","S:現場欠品"),IF(I28>0,"A:会期中欠品",IF(O28>1000,"B:大口",IF(O28>0,"C:通常","D:不要")))) -> D:不要 | Z28: =IF(Y28<>"",IF(I28>0,"◎ 一致（モデルも会期中欠品を検知）",IF(H28>=0.7,"○ 整合（予測消化率70%超）","△ モデル未検知：現場報告を優先")),IF(I28>0,"▲ モデルのみ検知：現場に在庫状況を確認","—")) -> — | AA28: 博多会場で完売（実績が在庫上限で頭打ち＝予測は控えめ）
A29: 23 | B29: 4515142545174 | C29: 呪術廻戦 懐玉・玉折 ブラインドミニ色紙（全5種） | D29: 600 | E29: =①石川予測確定!E29 -> 1018 | F29: =①石川予測確定!P29 -> 1292 | G29: =①石川予測確定!S29 -> 9325 | H29: =IFERROR(F29/G29,0) -> 0.13855228 | I29: =F29-G29 -> -8033 | J29: =IF(I29>0,"要 追加発注",IF(H29>=0.9,"要注意(90%超)",IF(H29>=0.5,"適正","在庫余剰"))) -> 在庫余剰 | K29: =IF(I29>0,ROUNDUP(I29*(1+前提・入力!$B$34),0),0) -> 0 | L29: =③仙台以降予測!M53 -> 15263 | M29: =③仙台以降予測!V53 -> 48729 | N29: =③仙台以降予測!W53 -> 0 | O29: =L29-M29-N29 -> -33466 | P29: =IF(O29>0,"要 追加生産",IF(L29=0,"—","在庫で充足")) -> 在庫で充足 | Q29: =③仙台以降予測!Z53 -> 0 | R29: =K29+Q29 -> 0 | S29: =R29*D29 -> 0 | T29: — | V29: =IF(OR(U29="",U29="再生産不可"),"",U29-前提・入力!$B$38) | W29: =IF(T29="—","—",IF(U29="再生産不可","×再生産不可",_xlfn.IFS(V29<0,"★期限超過",V29<=30,"★至急(30日以内)",V29<=90,"要着手(90日以内)",TRUE(),"余裕あり"))) -> — | X29: =IF(Y29<>"",IF(FALSE(),"S:現場欠品(追納不可)","S:現場欠品"),IF(I29>0,"A:会期中欠品",IF(O29>1000,"B:大口",IF(O29>0,"C:通常","D:不要")))) -> D:不要 | Z29: =IF(Y29<>"",IF(I29>0,"◎ 一致（モデルも会期中欠品を検知）",IF(H29>=0.7,"○ 整合（予測消化率70%超）","△ モデル未検知：現場報告を優先")),IF(I29>0,"▲ モデルのみ検知：現場に在庫状況を確認","—")) -> —
A30: 24 | B30: 4515142545181 | C30: 呪術廻戦 渋谷事変 ブラインドミニ色紙（全5種） | D30: 600 | E30: =①石川予測確定!E30 -> 668 | F30: =①石川予測確定!P30 -> 865 | G30: =①石川予測確定!S30 -> 7284 | H30: =IFERROR(F30/G30,0) -> 0.11875343 | I30: =F30-G30 -> -6419 | J30: =IF(I30>0,"要 追加発注",IF(H30>=0.9,"要注意(90%超)",IF(H30>=0.5,"適正","在庫余剰"))) -> 在庫余剰 | K30: =IF(I30>0,ROUNDUP(I30*(1+前提・入力!$B$34),0),0) -> 0 | L30: =③仙台以降予測!M54 -> 9388 | M30: =③仙台以降予測!V54 -> 30130 | N30: =③仙台以降予測!W54 -> 0 | O30: =L30-M30-N30 -> -20742 | P30: =IF(O30>0,"要 追加生産",IF(L30=0,"—","在庫で充足")) -> 在庫で充足 | Q30: =③仙台以降予測!Z54 -> 0 | R30: =K30+Q30 -> 0 | S30: =R30*D30 -> 0 | T30: — | V30: =IF(OR(U30="",U30="再生産不可"),"",U30-前提・入力!$B$38) | W30: =IF(T30="—","—",IF(U30="再生産不可","×再生産不可",_xlfn.IFS(V30<0,"★期限超過",V30<=30,"★至急(30日以内)",V30<=90,"要着手(90日以内)",TRUE(),"余裕あり"))) -> — | X30: =IF(Y30<>"",IF(FALSE(),"S:現場欠品(追納不可)","S:現場欠品"),IF(I30>0,"A:会期中欠品",IF(O30>1000,"B:大口",IF(O30>0,"C:通常","D:不要")))) -> D:不要 | Z30: =IF(Y30<>"",IF(I30>0,"◎ 一致（モデルも会期中欠品を検知）",IF(H30>=0.7,"○ 整合（予測消化率70%超）","△ モデル未検知：現場報告を優先")),IF(I30>0,"▲ モデルのみ検知：現場に在庫状況を確認","—")) -> —
A31: 25 | B31: 4515142545198 | C31: 虚式『茈』バスボール | D31: 1500 | E31: =①石川予測確定!E31 -> 43 | F31: =①石川予測確定!P31 -> 58 | G31: =①石川予測確定!S31 -> 176 | H31: =IFERROR(F31/G31,0) -> 0.32954545 | I31: =F31-G31 -> -118 | J31: =IF(I31>0,"要 追加発注",IF(H31>=0.9,"要注意(90%超)",IF(H31>=0.5,"適正","在庫余剰"))) -> 在庫余剰 | K31: =IF(I31>0,ROUNDUP(I31*(1+前提・入力!$B$34),0),0) -> 0 | L31: =③仙台以降予測!M55 -> 534 | M31: =③仙台以降予測!V55 -> 3393 | N31: =③仙台以降予測!W55 -> 0 | O31: =L31-M31-N31 -> -2859 | P31: =IF(O31>0,"要 追加生産",IF(L31=0,"—","在庫で充足")) -> 在庫で充足 | Q31: =③仙台以降予測!Z55 -> 0 | R31: =K31+Q31 -> 0 | S31: =R31*D31 -> 0 | T31: — | V31: =IF(OR(U31="",U31="再生産不可"),"",U31-前提・入力!$B$38) | W31: =IF(T31="—","—",IF(U31="再生産不可","×再生産不可",_xlfn.IFS(V31<0,"★期限超過",V31<=30,"★至急(30日以内)",V31<=90,"要着手(90日以内)",TRUE(),"余裕あり"))) -> — | X31: =IF(Y31<>"",IF(FALSE(),"S:現場欠品(追納不可)","S:現場欠品"),IF(I31>0,"A:会期中欠品",IF(O31>1000,"B:大口",IF(O31>0,"C:通常","D:不要")))) -> D:不要 | Z31: =IF(Y31<>"",IF(I31>0,"◎ 一致（モデルも会期中欠品を検知）",IF(H31>=0.7,"○ 整合（予測消化率70%超）","△ モデル未検知：現場報告を優先")),IF(I31>0,"▲ モデルのみ検知：現場に在庫状況を確認","—")) -> — | AA31: 博多会場で完売（実績が在庫上限で頭打ち＝予測は控えめ）
A32: 26 | B32: 4515142545204 | C32: 前髪ヘアバンド | D32: 2200 | E32: =①石川予測確定!E32 -> 50 | F32: =①石川予測確定!P32 -> 70 | G32: =①石川予測確定!S32 -> 50 | H32: =IFERROR(F32/G32,0) -> 1.4 | I32: =F32-G32 -> 20 | J32: =IF(I32>0,"要 追加発注",IF(H32>=0.9,"要注意(90%超)",IF(H32>=0.5,"適正","在庫余剰"))) -> 要 追加発注 | K32: =IF(I32>0,ROUNDUP(I32*(1+前提・入力!$B$34),0),0) -> 22 | L32: =③仙台以降予測!M56 -> 1112 | M32: =③仙台以降予測!V56 -> 229 | N32: =③仙台以降予測!W56 -> 0 | O32: =L32-M32-N32 -> 883 | P32: =IF(O32>0,"要 追加生産",IF(L32=0,"—","在庫で充足")) -> 要 追加生産 | Q32: =③仙台以降予測!Z56 -> 972 | R32: =K32+Q32 -> 994 | S32: =R32*D32 -> 2186800 | T32: 神戸阪急 | U32: =DATE(2026,12,16)-75-前提・入力!$B$37 -> 46283 | V32: =IF(OR(U32="",U32="再生産不可"),"",U32-前提・入力!$B$38) -> 23 | W32: =IF(T32="—","—",IF(U32="再生産不可","×再生産不可",_xlfn.IFS(V32<0,"★期限超過",V32<=30,"★至急(30日以内)",V32<=90,"要着手(90日以内)",TRUE(),"余裕あり"))) -> ★至急(30日以内) | X32: =IF(Y32<>"",IF(FALSE(),"S:現場欠品(追納不可)","S:現場欠品"),IF(I32>0,"A:会期中欠品",IF(O32>1000,"B:大口",IF(O32>0,"C:通常","D:不要")))) -> A:会期中欠品 | Z32: =IF(Y32<>"",IF(I32>0,"◎ 一致（モデルも会期中欠品を検知）",IF(H32>=0.7,"○ 整合（予測消化率70%超）","△ モデル未検知：現場報告を優先")),IF(I32>0,"▲ モデルのみ検知：現場に在庫状況を確認","—")) -> ▲ モデルのみ検知：現場に在庫状況を確認 | AA32: 石川会期中に欠品見込。至急スライド納品または追加発注 ／ 名古屋会場で完売（実績が在庫上限で頭打ち＝予測は控えめ）
A33: 27 | B33: 4515142545211 | C33: 反転術式絆創膏 | D33: 1100 | E33: =①石川予測確定!E33 -> 13 | F33: =①石川予測確定!P33 -> 18 | G33: =①石川予測確定!S33 -> 70 | H33: =IFERROR(F33/G33,0) -> 0.25714286 | I33: =F33-G33 -> -52 | J33: =IF(I33>0,"要 追加発注",IF(H33>=0.9,"要注意(90%超)",IF(H33>=0.5,"適正","在庫余剰"))) -> 在庫余剰 | K33: =IF(I33>0,ROUNDUP(I33*(1+前提・入力!$B$34),0),0) -> 0 | L33: =③仙台以降予測!M57 -> 280 | M33: =③仙台以降予測!V57 -> 1131 | N33: =③仙台以降予測!W57 -> 0 | O33: =L33-M33-N33 -> -851 | P33: =IF(O33>0,"要 追加生産",IF(L33=0,"—","在庫で充足")) -> 在庫で充足 | Q33: =③仙台以降予測!Z57 -> 0 | R33: =K33+Q33 -> 0 | S33: =R33*D33 -> 0 | T33: — | V33: =IF(OR(U33="",U33="再生産不可"),"",U33-前提・入力!$B$38) | W33: =IF(T33="—","—",IF(U33="再生産不可","×再生産不可",_xlfn.IFS(V33<0,"★期限超過",V33<=30,"★至急(30日以内)",V33<=90,"要着手(90日以内)",TRUE(),"余裕あり"))) -> — | X33: =IF(Y33<>"",IF(FALSE(),"S:現場欠品(追納不可)","S:現場欠品"),IF(I33>0,"A:会期中欠品",IF(O33>1000,"B:大口",IF(O33>0,"C:通常","D:不要")))) -> D:不要 | Z33: =IF(Y33<>"",IF(I33>0,"◎ 一致（モデルも会期中欠品を検知）",IF(H33>=0.7,"○ 整合（予測消化率70%超）","△ モデル未検知：現場報告を優先")),IF(I33>0,"▲ モデルのみ検知：現場に在庫状況を確認","—")) -> — | AA33: 博多会場で完売（実績が在庫上限で頭打ち＝予測は控えめ）
A34: 28 | B34: 4515142545228 | C34: 宿儺の指風お菓子 | D34: 1800 | E34: =①石川予測確定!E34 -> 80 | F34: =①石川予測確定!P34 -> 92 | G34: =①石川予測確定!S34 -> 80 | H34: =IFERROR(F34/G34,0) -> 1.15 | I34: =F34-G34 -> 12 | J34: =IF(I34>0,"要 追加発注",IF(H34>=0.9,"要注意(90%超)",IF(H34>=0.5,"適正","在庫余剰"))) -> 要 追加発注 | K34: =IF(I34>0,ROUNDUP(I34*(1+前提・入力!$B$34),0),0) -> 14 | L34: =③仙台以降予測!M58 -> 1589 | M34: =③仙台以降予測!V58 -> 68 | N34: =③仙台以降予測!W58 -> 1200 | O34: =L34-M34-N34 -> 321 | P34: =IF(O34>0,"要 追加生産",IF(L34=0,"—","在庫で充足")) -> 要 追加生産 | Q34: =③仙台以降予測!Z58 -> 354 | R34: =K34+Q34 -> 368 | S34: =R34*D34 -> 662400 | T34: 仙台 Ebeans | U34: =DATE(2026,9,5)-90-前提・入力!$B$37 -> 46166 | V34: =IF(OR(U34="",U34="再生産不可"),"",U34-前提・入力!$B$38) -> -94 | W34: ◎発注確定済 | X34: =IF(Y34<>"",IF(FALSE(),"S:現場欠品(追納不可)","S:現場欠品"),IF(I34>0,"A:会期中欠品",IF(O34>1000,"B:大口",IF(O34>0,"C:通常","D:不要")))) -> A:会期中欠品 | Z34: =IF(Y34<>"",IF(I34>0,"◎ 一致（モデルも会期中欠品を検知）",IF(H34>=0.7,"○ 整合（予測消化率70%超）","△ モデル未検知：現場報告を優先")),IF(I34>0,"▲ モデルのみ検知：現場に在庫状況を確認","—")) -> ▲ モデルのみ検知：現場に在庫状況を確認 | AA34: 石川会期中に欠品見込。至急スライド納品または追加発注 ／ 名古屋会場で完売（実績が在庫上限で頭打ち＝予測は控えめ） ／ 博多会場で完売（実績が在庫上限で頭打ち＝予測は控えめ） ／ 大阪会場で完売（実績が在庫上限で頭打ち＝予測は控えめ）
A35: 29 | B35: 4515142545235 | C35: 脱兎！ポーチ入りクリップセット | D35: 1500 | E35: =①石川予測確定!E35 -> 71 | F35: =①石川予測確定!P35 -> 83 | G35: =①石川予測確定!S35 -> 120 | H35: =IFERROR(F35/G35,0) -> 0.69166667 | I35: =F35-G35 -> -37 | J35: =IF(I35>0,"要 追加発注",IF(H35>=0.9,"要注意(90%超)",IF(H35>=0.5,"適正","在庫余剰"))) -> 適正 | K35: =IF(I35>0,ROUNDUP(I35*(1+前提・入力!$B$34),0),0) -> 0 | L35: =③仙台以降予測!M59 -> 1052 | M35: =③仙台以降予測!V59 -> 177 | N35: =③仙台以降予測!W59 -> 0 | O35: =L35-M35-N35 -> 875 | P35: =IF(O35>0,"要 追加生産",IF(L35=0,"—","在庫で充足")) -> 要 追加生産 | Q35: =③仙台以降予測!Z59 -> 963 | R35: =K35+Q35 -> 963 | S35: =R35*D35 -> 1444500 | T35: 神戸阪急 | U35: =DATE(2026,12,16)-90-前提・入力!$B$37 -> 46268 | V35: =IF(OR(U35="",U35="再生産不可"),"",U35-前提・入力!$B$38) -> 8 | W35: =IF(T35="—","—",IF(U35="再生産不可","×再生産不可",_xlfn.IFS(V35<0,"★期限超過",V35<=30,"★至急(30日以内)",V35<=90,"要着手(90日以内)",TRUE(),"余裕あり"))) -> ★至急(30日以内) | X35: =IF(Y35<>"",IF(FALSE(),"S:現場欠品(追納不可)","S:現場欠品"),IF(I35>0,"A:会期中欠品",IF(O35>1000,"B:大口",IF(O35>0,"C:通常","D:不要")))) -> C:通常 | Z35: =IF(Y35<>"",IF(I35>0,"◎ 一致（モデルも会期中欠品を検知）",IF(H35>=0.7,"○ 整合（予測消化率70%超）","△ モデル未検知：現場報告を優先")),IF(I35>0,"▲ モデルのみ検知：現場に在庫状況を確認","—")) -> — | AA35: 名古屋会場で完売（実績が在庫上限で頭打ち＝予測は控えめ） ／ 博多会場で完売（実績が在庫上限で頭打ち＝予測は控えめ） ／ 大阪会場で完売（実績が在庫上限で頭打ち＝予測は控えめ）
A36: 30 | B36: 4515142545242 | C36: 釘崎のポーチ風エコバッグ | D36: 3300 | E36: =①石川予測確定!E36 -> 34 | F36: =①石川予測確定!P36 -> 45 | G36: =①石川予測確定!S36 -> 278 | H36: =IFERROR(F36/G36,0) -> 0.1618705 | I36: =F36-G36 -> -233 | J36: =IF(I36>0,"要 追加発注",IF(H36>=0.9,"要注意(90%超)",IF(H36>=0.5,"適正","在庫余剰"))) -> 在庫余剰 | K36: =IF(I36>0,ROUNDUP(I36*(1+前提・入力!$B$34),0),0) -> 0 | L36: =③仙台以降予測!M60 -> 519 | M36: =③仙台以降予測!V60 -> 781 | N36: =③仙台以降予測!W60 -> 0 | O36: =L36-M36-N36 -> -262 | P36: =IF(O36>0,"要 追加生産",IF(L36=0,"—","在庫で充足")) -> 在庫で充足 | Q36: =③仙台以降予測!Z60 -> 0 | R36: =K36+Q36 -> 0 | S36: =R36*D36 -> 0 | T36: — | V36: =IF(OR(U36="",U36="再生産不可"),"",U36-前提・入力!$B$38) | W36: =IF(T36="—","—",IF(U36="再生産不可","×再生産不可",_xlfn.IFS(V36<0,"★期限超過",V36<=30,"★至急(30日以内)",V36<=90,"要着手(90日以内)",TRUE(),"余裕あり"))) -> — | X36: =IF(Y36<>"",IF(FALSE(),"S:現場欠品(追納不可)","S:現場欠品"),IF(I36>0,"A:会期中欠品",IF(O36>1000,"B:大口",IF(O36>0,"C:通常","D:不要")))) -> D:不要 | Z36: =IF(Y36<>"",IF(I36>0,"◎ 一致（モデルも会期中欠品を検知）",IF(H36>=0.7,"○ 整合（予測消化率70%超）","△ モデル未検知：現場報告を優先")),IF(I36>0,"▲ モデルのみ検知：現場に在庫状況を確認","—")) -> — | AA36: 博多会場で完売（実績が在庫上限で頭打ち＝予測は控えめ）
A37: 31 | B37: 4515142545259 | C37: 半年分の情報が書き込める手帳 | D37: 1300 | E37: =①石川予測確定!E37 -> 47 | F37: =①石川予測確定!P37 -> 61 | G37: =①石川予測確定!S37 -> 249 | H37: =IFERROR(F37/G37,0) -> 0.24497992 | I37: =F37-G37 -> -188 | J37: =IF(I37>0,"要 追加発注",IF(H37>=0.9,"要注意(90%超)",IF(H37>=0.5,"適正","在庫余剰"))) -> 在庫余剰 | K37: =IF(I37>0,ROUNDUP(I37*(1+前提・入力!$B$34),0),0) -> 0 | L37: =③仙台以降予測!M61 -> 715 | M37: =③仙台以降予測!V61 -> 765 | N37: =③仙台以降予測!W61 -> 0 | O37: =L37-M37-N37 -> -50 | P37: =IF(O37>0,"要 追加生産",IF(L37=0,"—","在庫で充足")) -> 在庫で充足 | Q37: =③仙台以降予測!Z61 -> 0 | R37: =K37+Q37 -> 0 | S37: =R37*D37 -> 0 | T37: — | V37: =IF(OR(U37="",U37="再生産不可"),"",U37-前提・入力!$B$38) | W37: =IF(T37="—","—",IF(U37="再生産不可","×再生産不可",_xlfn.IFS(V37<0,"★期限超過",V37<=30,"★至急(30日以内)",V37<=90,"要着手(90日以内)",TRUE(),"余裕あり"))) -> — | X37: =IF(Y37<>"",IF(FALSE(),"S:現場欠品(追納不可)","S:現場欠品"),IF(I37>0,"A:会期中欠品",IF(O37>1000,"B:大口",IF(O37>0,"C:通常","D:不要")))) -> D:不要 | Z37: =IF(Y37<>"",IF(I37>0,"◎ 一致（モデルも会期中欠品を検知）",IF(H37>=0.7,"○ 整合（予測消化率70%超）","△ モデル未検知：現場報告を優先")),IF(I37>0,"▲ モデルのみ検知：現場に在庫状況を確認","—")) -> — | AA37: 博多会場で完売（実績が在庫上限で頭打ち＝予測は控えめ）
A38: 32 | B38: 4515142545266 | C38: 気分リフレッシュオルゴール | D38: 8800 | E38: =①石川予測確定!E38 -> 5 | F38: =①石川予測確定!P38 -> 5 | G38: =①石川予測確定!S38 -> 5 | H38: =IFERROR(F38/G38,0) -> 1 | I38: =F38-G38 -> 0 | J38: =IF(I38>0,"要 追加発注",IF(H38>=0.9,"要注意(90%超)",IF(H38>=0.5,"適正","在庫余剰"))) -> 要注意(90%超) | K38: =IF(I38>0,ROUNDUP(I38*(1+前提・入力!$B$34),0),0) -> 0 | L38: =③仙台以降予測!M62 -> 64 | M38: =③仙台以降予測!V62 -> 15 | N38: =③仙台以降予測!W62 -> 0 | O38: =L38-M38-N38 -> 49 | P38: =IF(O38>0,"要 追加生産",IF(L38=0,"—","在庫で充足")) -> 要 追加生産 | Q38: =③仙台以降予測!Z62 -> 54 | R38: =K38+Q38 -> 54 | S38: =R38*D38 -> 475200 | T38: 神戸阪急 | U38: =DATE(2026,12,16)-90-前提・入力!$B$37 -> 46268 | V38: =IF(OR(U38="",U38="再生産不可"),"",U38-前提・入力!$B$38) -> 8 | W38: =IF(T38="—","—",IF(U38="再生産不可","×再生産不可",_xlfn.IFS(V38<0,"★期限超過",V38<=30,"★至急(30日以内)",V38<=90,"要着手(90日以内)",TRUE(),"余裕あり"))) -> ★至急(30日以内) | X38: =IF(Y38<>"",IF(FALSE(),"S:現場欠品(追納不可)","S:現場欠品"),IF(I38>0,"A:会期中欠品",IF(O38>1000,"B:大口",IF(O38>0,"C:通常","D:不要")))) -> C:通常 | Z38: =IF(Y38<>"",IF(I38>0,"◎ 一致（モデルも会期中欠品を検知）",IF(H38>=0.7,"○ 整合（予測消化率70%超）","△ モデル未検知：現場報告を優先")),IF(I38>0,"▲ モデルのみ検知：現場に在庫状況を確認","—")) -> — | AA38: 石川納品数が極小(5個) ／ 名古屋会場で完売（実績が在庫上限で頭打ち＝予測は控えめ） ／ 博多会場で完売（実績が在庫上限で頭打ち＝予測は控えめ） ／ 大阪会場で完売（実績が在庫上限で頭打ち＝予測は控えめ）
A39: 33 | B39: 4515142545273 | C39: 五条 悟 イメージリング（#11） | D39: 27500 | E39: =①石川予測確定!E39 -> 4 | F39: =①石川予測確定!P39 -> 5 | G39: =①石川予測確定!S39 -> 21 | H39: =IFERROR(F39/G39,0) -> 0.23809524 | I39: =F39-G39 -> -16 | J39: =IF(I39>0,"要 追加発注",IF(H39>=0.9,"要注意(90%超)",IF(H39>=0.5,"適正","在庫余剰"))) -> 在庫余剰 | K39: =IF(I39>0,ROUNDUP(I39*(1+前提・入力!$B$34),0),0) -> 0 | L39: =③仙台以降予測!M63 -> 40 | M39: =③仙台以降予測!V63 -> 98 | N39: =③仙台以降予測!W63 -> 0 | O39: =L39-M39-N39 -> -58 | P39: =IF(O39>0,"要 追加生産",IF(L39=0,"—","在庫で充足")) -> 在庫で充足 | Q39: =③仙台以降予測!Z63 -> 0 | R39: =K39+Q39 -> 0 | S39: =R39*D39 -> 0 | T39: — | V39: =IF(OR(U39="",U39="再生産不可"),"",U39-前提・入力!$B$38) | W39: =IF(T39="—","—",IF(U39="再生産不可","×再生産不可",_xlfn.IFS(V39<0,"★期限超過",V39<=30,"★至急(30日以内)",V39<=90,"要着手(90日以内)",TRUE(),"余裕あり"))) -> — | X39: =IF(Y39<>"",IF(FALSE(),"S:現場欠品(追納不可)","S:現場欠品"),IF(I39>0,"A:会期中欠品",IF(O39>1000,"B:大口",IF(O39>0,"C:通常","D:不要")))) -> D:不要 | Z39: =IF(Y39<>"",IF(I39>0,"◎ 一致（モデルも会期中欠品を検知）",IF(H39>=0.7,"○ 整合（予測消化率70%超）","△ モデル未検知：現場報告を優先")),IF(I39>0,"▲ モデルのみ検知：現場に在庫状況を確認","—")) -> —
A40: 34 | B40: 4515142545280 | C40: 五条 悟 イメージリング（#13） | D40: 27500 | E40: =①石川予測確定!E40 -> 1 | F40: =①石川予測確定!P40 -> 1 | G40: =①石川予測確定!S40 -> 1 | H40: =IFERROR(F40/G40,0) -> 1 | I40: =F40-G40 -> 0 | J40: =IF(I40>0,"要 追加発注",IF(H40>=0.9,"要注意(90%超)",IF(H40>=0.5,"適正","在庫余剰"))) -> 要注意(90%超) | K40: =IF(I40>0,ROUNDUP(I40*(1+前提・入力!$B$34),0),0) -> 0 | L40: =③仙台以降予測!M64 -> 13 | M40: =③仙台以降予測!V64 -> 1 | N40: =③仙台以降予測!W64 -> 0 | O40: =L40-M40-N40 -> 12 | P40: =IF(O40>0,"要 追加生産",IF(L40=0,"—","在庫で充足")) -> 要 追加生産 | Q40: =③仙台以降予測!Z64 -> 14 | R40: =K40+Q40 -> 14 | S40: =R40*D40 -> 385000 | T40: 仙台 Ebeans | U40: =DATE(2026,9,5)-90-前提・入力!$B$37 -> 46166 | V40: =IF(OR(U40="",U40="再生産不可"),"",U40-前提・入力!$B$38) -> -94 | W40: =IF(T40="—","—",IF(U40="再生産不可","×再生産不可",_xlfn.IFS(V40<0,"★期限超過",V40<=30,"★至急(30日以内)",V40<=90,"要着手(90日以内)",TRUE(),"余裕あり"))) -> ★期限超過 | X40: =IF(Y40<>"",IF(FALSE(),"S:現場欠品(追納不可)","S:現場欠品"),IF(I40>0,"A:会期中欠品",IF(O40>1000,"B:大口",IF(O40>0,"C:通常","D:不要")))) -> C:通常 | Z40: =IF(Y40<>"",IF(I40>0,"◎ 一致（モデルも会期中欠品を検知）",IF(H40>=0.7,"○ 整合（予測消化率70%超）","△ モデル未検知：現場報告を優先")),IF(I40>0,"▲ モデルのみ検知：現場に在庫状況を確認","—")) -> — | AA40: 石川納品数が極小(1個) ／ 名古屋会場で完売（実績が在庫上限で頭打ち＝予測は控えめ） ／ 博多会場で完売（実績が在庫上限で頭打ち＝予測は控えめ） ／ 大阪会場で完売（実績が在庫上限で頭打ち＝予測は控えめ）
A41: 35 | B41: 4515142545297 | C41: 五条 悟 イメージリング（#15） | D41: 27500 | E41: =①石川予測確定!E41 -> 1 | F41: =①石川予測確定!P41 -> 1 | G41: =①石川予測確定!S41 -> 1 | H41: =IFERROR(F41/G41,0) -> 1 | I41: =F41-G41 -> 0 | J41: =IF(I41>0,"要 追加発注",IF(H41>=0.9,"要注意(90%超)",IF(H41>=0.5,"適正","在庫余剰"))) -> 要注意(90%超) | K41: =IF(I41>0,ROUNDUP(I41*(1+前提・入力!$B$34),0),0) -> 0 | L41: =③仙台以降予測!M65 -> 9 | M41: =③仙台以降予測!V65 -> 2 | N41: =③仙台以降予測!W65 -> 0 | O41: =L41-M41-N41 -> 7 | P41: =IF(O41>0,"要 追加生産",IF(L41=0,"—","在庫で充足")) -> 要 追加生産 | Q41: =③仙台以降予測!Z65 -> 8 | R41: =K41+Q41 -> 8 | S41: =R41*D41 -> 220000 | T41: 鳥取島根 夢みなとタワー | U41: =DATE(2027,3,15)-90-前提・入力!$B$37 -> 46357 | V41: =IF(OR(U41="",U41="再生産不可"),"",U41-前提・入力!$B$38) -> 97 | W41: =IF(T41="—","—",IF(U41="再生産不可","×再生産不可",_xlfn.IFS(V41<0,"★期限超過",V41<=30,"★至急(30日以内)",V41<=90,"要着手(90日以内)",TRUE(),"余裕あり"))) -> 余裕あり | X41: =IF(Y41<>"",IF(FALSE(),"S:現場欠品(追納不可)","S:現場欠品"),IF(I41>0,"A:会期中欠品",IF(O41>1000,"B:大口",IF(O41>0,"C:通常","D:不要")))) -> C:通常 | Z41: =IF(Y41<>"",IF(I41>0,"◎ 一致（モデルも会期中欠品を検知）",IF(H41>=0.7,"○ 整合（予測消化率70%超）","△ モデル未検知：現場報告を優先")),IF(I41>0,"▲ モデルのみ検知：現場に在庫状況を確認","—")) -> — | AA41: 石川納品数が極小(1個) ／ 名古屋会場で完売（実績が在庫上限で頭打ち＝予測は控えめ） ／ 博多会場で完売（実績が在庫上限で頭打ち＝予測は控えめ） ／ 大阪会場で完売（実績が在庫上限で頭打ち＝予測は控えめ）
A42: 36 | B42: 4515142545303 | C42: 五条 悟 イメージリング（#17） | D42: 27500 | E42: =①石川予測確定!E42 -> 1 | F42: =①石川予測確定!P42 -> 1 | G42: =①石川予測確定!S42 -> 1 | H42: =IFERROR(F42/G42,0) -> 1 | I42: =F42-G42 -> 0 | J42: =IF(I42>0,"要 追加発注",IF(H42>=0.9,"要注意(90%超)",IF(H42>=0.5,"適正","在庫余剰"))) -> 要注意(90%超) | K42: =IF(I42>0,ROUNDUP(I42*(1+前提・入力!$B$34),0),0) -> 0 | L42: =③仙台以降予測!M66 -> 9 | M42: =③仙台以降予測!V66 -> 2 | N42: =③仙台以降予測!W66 -> 0 | O42: =L42-M42-N42 -> 7 | P42: =IF(O42>0,"要 追加生産",IF(L42=0,"—","在庫で充足")) -> 要 追加生産 | Q42: =③仙台以降予測!Z66 -> 8 | R42: =K42+Q42 -> 8 | S42: =R42*D42 -> 220000 | T42: 鳥取島根 夢みなとタワー | U42: =DATE(2027,3,15)-90-前提・入力!$B$37 -> 46357 | V42: =IF(OR(U42="",U42="再生産不可"),"",U42-前提・入力!$B$38) -> 97 | W42: =IF(T42="—","—",IF(U42="再生産不可","×再生産不可",_xlfn.IFS(V42<0,"★期限超過",V42<=30,"★至急(30日以内)",V42<=90,"要着手(90日以内)",TRUE(),"余裕あり"))) -> 余裕あり | X42: =IF(Y42<>"",IF(FALSE(),"S:現場欠品(追納不可)","S:現場欠品"),IF(I42>0,"A:会期中欠品",IF(O42>1000,"B:大口",IF(O42>0,"C:通常","D:不要")))) -> C:通常 | Z42: =IF(Y42<>"",IF(I42>0,"◎ 一致（モデルも会期中欠品を検知）",IF(H42>=0.7,"○ 整合（予測消化率70%超）","△ モデル未検知：現場報告を優先")),IF(I42>0,"▲ モデルのみ検知：現場に在庫状況を確認","—")) -> — | AA42: 石川納品数が極小(1個) ／ 名古屋会場で完売（実績が在庫上限で頭打ち＝予測は控えめ） ／ 博多会場で完売（実績が在庫上限で頭打ち＝予測は控えめ） ／ 大阪会場で完売（実績が在庫上限で頭打ち＝予測は控えめ）
A43: 37 | B43: 4515142545310 | C43: 夏油 傑 イメージリング（#11） | D43: 27500 | E43: =①石川予測確定!E43 -> 4 | F43: =①石川予測確定!P43 -> 5 | G43: =①石川予測確定!S43 -> 17 | H43: =IFERROR(F43/G43,0) -> 0.29411765 | I43: =F43-G43 -> -12 | J43: =IF(I43>0,"要 追加発注",IF(H43>=0.9,"要注意(90%超)",IF(H43>=0.5,"適正","在庫余剰"))) -> 在庫余剰 | K43: =IF(I43>0,ROUNDUP(I43*(1+前提・入力!$B$34),0),0) -> 0 | L43: =③仙台以降予測!M67 -> 34 | M43: =③仙台以降予測!V67 -> 28 | N43: =③仙台以降予測!W67 -> 0 | O43: =L43-M43-N43 -> 6 | P43: =IF(O43>0,"要 追加生産",IF(L43=0,"—","在庫で充足")) -> 要 追加生産 | Q43: =③仙台以降予測!Z67 -> 7 | R43: =K43+Q43 -> 7 | S43: =R43*D43 -> 192500 | T43: 東京凱旋 東京建物ぴあホール | U43: =DATE(2027,4,1)-90-前提・入力!$B$37 -> 46374 | V43: =IF(OR(U43="",U43="再生産不可"),"",U43-前提・入力!$B$38) -> 114 | W43: =IF(T43="—","—",IF(U43="再生産不可","×再生産不可",_xlfn.IFS(V43<0,"★期限超過",V43<=30,"★至急(30日以内)",V43<=90,"要着手(90日以内)",TRUE(),"余裕あり"))) -> 余裕あり | X43: =IF(Y43<>"",IF(FALSE(),"S:現場欠品(追納不可)","S:現場欠品"),IF(I43>0,"A:会期中欠品",IF(O43>1000,"B:大口",IF(O43>0,"C:通常","D:不要")))) -> C:通常 | Z43: =IF(Y43<>"",IF(I43>0,"◎ 一致（モデルも会期中欠品を検知）",IF(H43>=0.7,"○ 整合（予測消化率70%超）","△ モデル未検知：現場報告を優先")),IF(I43>0,"▲ モデルのみ検知：現場に在庫状況を確認","—")) -> — | AA43: 名古屋会場で完売（実績が在庫上限で頭打ち＝予測は控えめ）
A44: 38 | B44: 4515142545327 | C44: 夏油 傑 イメージリング（#13） | D44: 27500 | E44: =①石川予測確定!E44 -> 1 | F44: =①石川予測確定!P44 -> 1 | G44: =①石川予測確定!S44 -> 1 | H44: =IFERROR(F44/G44,0) -> 1 | I44: =F44-G44 -> 0 | J44: =IF(I44>0,"要 追加発注",IF(H44>=0.9,"要注意(90%超)",IF(H44>=0.5,"適正","在庫余剰"))) -> 要注意(90%超) | K44: =IF(I44>0,ROUNDUP(I44*(1+前提・入力!$B$34),0),0) -> 0 | L44: =③仙台以降予測!M68 -> 13 | M44: =③仙台以降予測!V68 -> 1 | N44: =③仙台以降予測!W68 -> 0 | O44: =L44-M44-N44 -> 12 | P44: =IF(O44>0,"要 追加生産",IF(L44=0,"—","在庫で充足")) -> 要 追加生産 | Q44: =③仙台以降予測!Z68 -> 14 | R44: =K44+Q44 -> 14 | S44: =R44*D44 -> 385000 | T44: 仙台 Ebeans | U44: =DATE(2026,9,5)-90-前提・入力!$B$37 -> 46166 | V44: =IF(OR(U44="",U44="再生産不可"),"",U44-前提・入力!$B$38) -> -94 | W44: =IF(T44="—","—",IF(U44="再生産不可","×再生産不可",_xlfn.IFS(V44<0,"★期限超過",V44<=30,"★至急(30日以内)",V44<=90,"要着手(90日以内)",TRUE(),"余裕あり"))) -> ★期限超過 | X44: =IF(Y44<>"",IF(FALSE(),"S:現場欠品(追納不可)","S:現場欠品"),IF(I44>0,"A:会期中欠品",IF(O44>1000,"B:大口",IF(O44>0,"C:通常","D:不要")))) -> C:通常 | Z44: =IF(Y44<>"",IF(I44>0,"◎ 一致（モデルも会期中欠品を検知）",IF(H44>=0.7,"○ 整合（予測消化率70%超）","△ モデル未検知：現場報告を優先")),IF(I44>0,"▲ モデルのみ検知：現場に在庫状況を確認","—")) -> — | AA44: 石川納品数が極小(1個) ／ 名古屋会場で完売（実績が在庫上限で頭打ち＝予測は控えめ） ／ 博多会場で完売（実績が在庫上限で頭打ち＝予測は控えめ） ／ 大阪会場で完売（実績が在庫上限で頭打ち＝予測は控えめ）
A45: 39 | B45: 4515142545334 | C45: 夏油 傑 イメージリング（#15） | D45: 27500 | E45: =①石川予測確定!E45 -> 1 | F45: =①石川予測確定!P45 -> 2 | G45: =①石川予測確定!S45 -> 1 | H45: =IFERROR(F45/G45,0) -> 2 | I45: =F45-G45 -> 1 | J45: =IF(I45>0,"要 追加発注",IF(H45>=0.9,"要注意(90%超)",IF(H45>=0.5,"適正","在庫余剰"))) -> 要 追加発注 | K45: =IF(I45>0,ROUNDUP(I45*(1+前提・入力!$B$34),0),0) -> 2 | L45: =③仙台以降予測!M69 -> 19 | M45: =③仙台以降予測!V69 -> 0 | N45: =③仙台以降予測!W69 -> 0 | O45: =L45-M45-N45 -> 19 | P45: =IF(O45>0,"要 追加生産",IF(L45=0,"—","在庫で充足")) -> 要 追加生産 | Q45: =③仙台以降予測!Z69 -> 21 | R45: =K45+Q45 -> 23 | S45: =R45*D45 -> 632500 | T45: 仙台 Ebeans | U45: =DATE(2026,9,5)-90-前提・入力!$B$37 -> 46166 | V45: =IF(OR(U45="",U45="再生産不可"),"",U45-前提・入力!$B$38) -> -94 | W45: =IF(T45="—","—",IF(U45="再生産不可","×再生産不可",_xlfn.IFS(V45<0,"★期限超過",V45<=30,"★至急(30日以内)",V45<=90,"要着手(90日以内)",TRUE(),"余裕あり"))) -> ★期限超過 | X45: =IF(Y45<>"",IF(FALSE(),"S:現場欠品(追納不可)","S:現場欠品"),IF(I45>0,"A:会期中欠品",IF(O45>1000,"B:大口",IF(O45>0,"C:通常","D:不要")))) -> A:会期中欠品 | Z45: =IF(Y45<>"",IF(I45>0,"◎ 一致（モデルも会期中欠品を検知）",IF(H45>=0.7,"○ 整合（予測消化率70%超）","△ モデル未検知：現場報告を優先")),IF(I45>0,"▲ モデルのみ検知：現場に在庫状況を確認","—")) -> ▲ モデルのみ検知：現場に在庫状況を確認 | AA45: 石川会期中に欠品見込。至急スライド納品または追加発注 ／ 石川納品数が極小(1個) ／ 名古屋会場で完売（実績が在庫上限で頭打ち＝予測は控えめ） ／ 博多会場で完売（実績が在庫上限で頭打ち＝予測は控えめ） ／ 大阪会場で完売（実績が在庫上限で頭打ち＝予測は控えめ）
A46: 40 | B46: 4515142545341 | C46: 夏油 傑 イメージリング（#17） | D46: 27500 | E46: =①石川予測確定!E46 -> 1 | F46: =①石川予測確定!P46 -> 1 | G46: =①石川予測確定!S46 -> 3 | H46: =IFERROR(F46/G46,0) -> 0.33333333 | I46: =F46-G46 -> -2 | J46: =IF(I46>0,"要 追加発注",IF(H46>=0.9,"要注意(90%超)",IF(H46>=0.5,"適正","在庫余剰"))) -> 在庫余剰 | K46: =IF(I46>0,ROUNDUP(I46*(1+前提・入力!$B$34),0),0) -> 0 | L46: =③仙台以降予測!M70 -> 7 | M46: =③仙台以降予測!V70 -> 3 | N46: =③仙台以降予測!W70 -> 0 | O46: =L46-M46-N46 -> 4 | P46: =IF(O46>0,"要 追加生産",IF(L46=0,"—","在庫で充足")) -> 要 追加生産 | Q46: =③仙台以降予測!Z70 -> 5 | R46: =K46+Q46 -> 5 | S46: =R46*D46 -> 137500 | T46: 東京凱旋 東京建物ぴあホール | U46: =DATE(2027,4,1)-90-前提・入力!$B$37 -> 46374 | V46: =IF(OR(U46="",U46="再生産不可"),"",U46-前提・入力!$B$38) -> 114 | W46: =IF(T46="—","—",IF(U46="再生産不可","×再生産不可",_xlfn.IFS(V46<0,"★期限超過",V46<=30,"★至急(30日以内)",V46<=90,"要着手(90日以内)",TRUE(),"余裕あり"))) -> 余裕あり | X46: =IF(Y46<>"",IF(FALSE(),"S:現場欠品(追納不可)","S:現場欠品"),IF(I46>0,"A:会期中欠品",IF(O46>1000,"B:大口",IF(O46>0,"C:通常","D:不要")))) -> C:通常 | Z46: =IF(Y46<>"",IF(I46>0,"◎ 一致（モデルも会期中欠品を検知）",IF(H46>=0.7,"○ 整合（予測消化率70%超）","△ モデル未検知：現場報告を優先")),IF(I46>0,"▲ モデルのみ検知：現場に在庫状況を確認","—")) -> — | AA46: 石川納品数が極小(3個) ／ 名古屋会場で完売（実績が在庫上限で頭打ち＝予測は控えめ） ／ 博多会場で完売（実績が在庫上限で頭打ち＝予測は控えめ） ／ 大阪会場で完売（実績が在庫上限で頭打ち＝予測は控えめ）
A47: 41 | B47: 4515142545358 | C47: 虎杖 悠仁 イメージフラグメントケース | D47: 25000 | E47: =①石川予測確定!E47 -> 0 | F47: =①石川予測確定!P47 -> 0 | G47: =①石川予測確定!S47 -> 14 | H47: =IFERROR(F47/G47,0) -> 0 | I47: =F47-G47 -> -14 | J47: =IF(I47>0,"要 追加発注",IF(H47>=0.9,"要注意(90%超)",IF(H47>=0.5,"適正","在庫余剰"))) -> 在庫余剰 | K47: =IF(I47>0,ROUNDUP(I47*(1+前提・入力!$B$34),0),0) -> 0 | L47: =③仙台以降予測!M71 -> 0 | M47: =③仙台以降予測!V71 -> 74 | N47: =③仙台以降予測!W71 -> 0 | O47: =L47-M47-N47 -> -74 | P47: =IF(O47>0,"要 追加生産",IF(L47=0,"—","在庫で充足")) -> — | Q47: =③仙台以降予測!Z71 -> 0 | R47: =K47+Q47 -> 0 | S47: =R47*D47 -> 0 | T47: — | V47: =IF(OR(U47="",U47="再生産不可"),"",U47-前提・入力!$B$38) | W47: =IF(T47="—","—",IF(U47="再生産不可","×再生産不可",_xlfn.IFS(V47<0,"★期限超過",V47<=30,"★至急(30日以内)",V47<=90,"要着手(90日以内)",TRUE(),"余裕あり"))) -> — | X47: =IF(Y47<>"",IF(FALSE(),"S:現場欠品(追納不可)","S:現場欠品"),IF(I47>0,"A:会期中欠品",IF(O47>1000,"B:大口",IF(O47>0,"C:通常","D:不要")))) -> D:不要 | Z47: =IF(Y47<>"",IF(I47>0,"◎ 一致（モデルも会期中欠品を検知）",IF(H47>=0.7,"○ 整合（予測消化率70%超）","△ モデル未検知：現場報告を優先")),IF(I47>0,"▲ モデルのみ検知：現場に在庫状況を確認","—")) -> — | AA47: 石川初12日の販売実績ゼロ（予測は大阪・博多構成比で按分）
A48: 42 | B48: 4515142545365 | C48: 伏黒 恵 イメージフラグメントケース | D48: 25000 | E48: =①石川予測確定!E48 -> 0 | F48: =①石川予測確定!P48 -> 0 | G48: =①石川予測確定!S48 -> 15 | H48: =IFERROR(F48/G48,0) -> 0 | I48: =F48-G48 -> -15 | J48: =IF(I48>0,"要 追加発注",IF(H48>=0.9,"要注意(90%超)",IF(H48>=0.5,"適正","在庫余剰"))) -> 在庫余剰 | K48: =IF(I48>0,ROUNDUP(I48*(1+前提・入力!$B$34),0),0) -> 0 | L48: =③仙台以降予測!M72 -> 3 | M48: =③仙台以降予測!V72 -> 48 | N48: =③仙台以降予測!W72 -> 0 | O48: =L48-M48-N48 -> -45 | P48: =IF(O48>0,"要 追加生産",IF(L48=0,"—","在庫で充足")) -> 在庫で充足 | Q48: =③仙台以降予測!Z72 -> 0 | R48: =K48+Q48 -> 0 | S48: =R48*D48 -> 0 | T48: — | V48: =IF(OR(U48="",U48="再生産不可"),"",U48-前提・入力!$B$38) | W48: =IF(T48="—","—",IF(U48="再生産不可","×再生産不可",_xlfn.IFS(V48<0,"★期限超過",V48<=30,"★至急(30日以内)",V48<=90,"要着手(90日以内)",TRUE(),"余裕あり"))) -> — | X48: =IF(Y48<>"",IF(FALSE(),"S:現場欠品(追納不可)","S:現場欠品"),IF(I48>0,"A:会期中欠品",IF(O48>1000,"B:大口",IF(O48>0,"C:通常","D:不要")))) -> D:不要 | Z48: =IF(Y48<>"",IF(I48>0,"◎ 一致（モデルも会期中欠品を検知）",IF(H48>=0.7,"○ 整合（予測消化率70%超）","△ モデル未検知：現場報告を優先")),IF(I48>0,"▲ モデルのみ検知：現場に在庫状況を確認","—")) -> — | AA48: 石川初12日の販売実績ゼロ（予測は大阪・博多構成比で按分）
C49: 合計（LEGS 42SKU） | E49: =SUM(E7:E48) -> 4022 | F49: =SUM(F7:F48) -> 5151 | G49: =SUM(G7:G48) -> 46928 | H49: =IFERROR(F49/G49,0) -> 0.10976389 | I49: =SUM(I7:I48) -> -41777 | J49: =COUNTIF(J7:J48,"要 追加発注")&"品目" -> 3品目 | K49: =SUM(K7:K48) -> 38 | L49: =SUM(L7:L48) -> 61617 | M49: =SUM(M7:M48) -> 234426 | N49: =SUM(N7:N48) -> 1200 | O49: =SUM(O7:O48) -> -174009 | P49: =COUNTIF(P7:P48,"要 追加生産")&"品目" -> 13品目 | Q49: =SUM(Q7:Q48) -> 3729 | R49: =SUM(R7:R48) -> 3767 | S49: =SUM(S7:S48) -> 7628300 | U49: =IF(COUNT(U7:U48)=0,"",TEXT(MIN(U7:U48),"yyyy/m/d")&" が最短期限") -> 2026/5/24 が最短期限 | W49: =COUNTIF(W7:W48,"★期限超過")&"品目が期限超過／"&COUNTIF(W7:W48,"★至急(30日以内)")&"品目が至急" -> 3品目が期限超過／3品目が至急 | Y49: =COUNTIF(Y7:Y48,"<>")&"品目 報告あり" -> 0品目 報告あり

Sheet ⑤全データ統合リスト
A1: ⑤ 商品別 全データ統合リスト（6会場実績 ＋ 石川予測 ＋ 仙台以降予測）
A2: 構成比＝LEGS 42SKU内シェア（数量・金額）。消化率＝販売数÷販売可能数。石川のみ8/25(12日目)時点の実績
A3: ※イメージリング8種は東京¥22,000→名古屋以降¥27,500に改定。販売金額は各会場の実売単価で算出している
A5: 基本情報 | E5: 東京（25/12/5(金)・25日） | L5: 名古屋（26/3/18(水)・19日） | S5: 博多（26/4/23(木)・26日） | Z5: 大阪（26/6/10(水)・20日） | AG5: 札幌（26/7/22(水)・20日） | AN5: 石川（8/14-8/25 実績12日） | AU5: 石川 会期18日予測 | AZ5: 仙台以降 4会場 | BD5: 発注判定
A6: No. | B6: JAN | C6: 商品名 | D6: 現行 税込単価 | E6: 税込 単価 | F6: 販売数 | G6: 数量 構成比 | H6: 販売金額 | I6: 金額 構成比 | J6: 販売 可能数 | K6: 消化率 | L6: 税込 単価 | M6: 販売数 | N6: 数量 構成比 | O6: 販売金額 | P6: 金額 構成比 | Q6: 販売 可能数 | R6: 消化率 | S6: 税込 単価 | T6: 販売数 | U6: 数量 構成比 | V6: 販売金額 | W6: 金額 構成比 | X6: 販売 可能数 | Y6: 消化率 | Z6: 税込 単価 | AA6: 販売数 | AB6: 数量 構成比 | AC6: 販売金額 | AD6: 金額 構成比 | AE6: 販売 可能数 | AF6: 消化率 | AG6: 税込 単価 | AH6: 販売数 | AI6: 数量 構成比 | AJ6: 販売金額 | AK6: 金額 構成比 | AL6: 販売 可能数 | AM6: 消化率 | AN6: 税込 単価 | AO6: 販売数 | AP6: 数量 構成比 | AQ6: 販売金額 | AR6: 金額 構成比 | AS6: 販売 可能数 | AT6: 消化率 | AU6: 採用 倍率g | AV6: 予測 販売数 | AW6: 予測 販売金額 | AX6: 予測 消化率 | AY6: 会期末 残在庫 | AZ6: 必要数 | BA6: 供給可能 在庫 | BB6: 過不足 | BC6: 追加生産 必要数 | BD6: 石川会期中 判定 | BE6: 仙台以降 判定 | BF6: 発注合計 | BG6: 優先度
A7: 1 | B7: 4515142545082 | C7: 呪術廻戦 メタリックポストカード 展示会キービジュアル | D7: 500 | E7: 500 | F7: 4965 | G7: =IFERROR(F7/F$49,0) -> 0.033505416 | H7: =F7*E7 -> 2482500 | I7: =IFERROR(H7/H$49,0) -> 0.024293887 | J7: 6000 | K7: =IFERROR(F7/J7,0) -> 0.8275 | L7: 500 | M7: 1316 | N7: =IFERROR(M7/M$49,0) -> 0.022457338 | O7: =M7*L7 -> 658000 | P7: =IFERROR(O7/O$49,0) -> 0.01586322 | Q7: 1998 | R7: =IFERROR(M7/Q7,0) -> 0.65865866 | S7: 500 | T7: 1092 | U7: =IFERROR(T7/T$49,0) -> 0.024336431 | V7: =T7*S7 -> 546000 | W7: =IFERROR(V7/V$49,0) -> 0.01759769 | X7: 1099 | Y7: =IFERROR(T7/X7,0) -> 0.99363057 | Z7: 500 | AA7: 2325 | AB7: =IFERROR(AA7/AA$49,0) -> 0.03647631 | AC7: =AA7*Z7 -> 1162500 | AD7: =IFERROR(AC7/AC$49,0) -> 0.025545184 | AE7: 3000 | AF7: =IFERROR(AA7/AE7,0) -> 0.775 | AG7: 500 | AH7: 507 | AI7: =IFERROR(AH7/AH$49,0) -> 0.057023957 | AJ7: =AH7*AG7 -> 253500 | AK7: =IFERROR(AJ7/AJ$49,0) -> 0.035125398 | AL7: 1000 | AM7: =IFERROR(AH7/AL7,0) -> 0.507 | AN7: 500 | AO7: 210 | AP7: =IFERROR(AO7/AO$49,0) -> 0.052212829 | AQ7: =AO7*AN7 -> 105000 | AR7: =IFERROR(AQ7/AQ$49,0) -> 0.030988077 | AS7: 693 | AT7: =IFERROR(AO7/AS7,0) -> 0.3030303 | AU7: =①石川予測確定!O7 -> 1.2953342 | AV7: =①石川予測確定!P7 -> 272 | AW7: =①石川予測確定!Q7 -> 136000 | AX7: =①石川予測確定!T7 -> 0.39249639 | AY7: =①石川予測確定!U7 -> 421 | AZ7: =③仙台以降予測!M31 -> 3384 | BA7: =③仙台以降予測!V31 -> 2489 | BB7: =③仙台以降予測!X31 -> 895 | BC7: =③仙台以降予測!Y31 -> 895 | BD7: =④追加発注判定!J7 -> 在庫余剰 | BE7: =④追加発注判定!P7 -> 要 追加生産 | BF7: =④追加発注判定!R7 -> 985 | BG7: =④追加発注判定!X7 -> C:通常
A8: 2 | B8: 4515142545099 | C8: 呪術廻戦 クリアファイル 展示会キービジュアル | D8: 600 | E8: 600 | F8: 4902 | G8: =IFERROR(F8/F$49,0) -> 0.033080271 | H8: =F8*E8 -> 2941200 | I8: =IFERROR(H8/H$49,0) -> 0.028782751 | J8: 5699 | K8: =IFERROR(F8/J8,0) -> 0.8601509 | L8: 600 | M8: 1466 | N8: =IFERROR(M8/M$49,0) -> 0.025017065 | O8: =M8*L8 -> 879600 | P8: =IFERROR(O8/O$49,0) -> 0.021205605 | Q8: 1999 | R8: =IFERROR(M8/Q8,0) -> 0.73336668 | S8: 600 | T8: 1132 | U8: =IFERROR(T8/T$49,0) -> 0.025227875 | V8: =T8*S8 -> 679200 | W8: =IFERROR(V8/V$49,0) -> 0.021890753 | X8: 1200 | Y8: =IFERROR(T8/X8,0) -> 0.94333333 | Z8: 600 | AA8: 1965 | AB8: =IFERROR(AA8/AA$49,0) -> 0.030828365 | AC8: =AA8*Z8 -> 1179000 | AD8: =IFERROR(AC8/AC$49,0) -> 0.02590776 | AE8: 3000 | AF8: =IFERROR(AA8/AE8,0) -> 0.655 | AG8: 600 | AH8: 541 | AI8: =IFERROR(AH8/AH$49,0) -> 0.060848049 | AJ8: =AH8*AG8 -> 324600 | AK8: =IFERROR(AJ8/AJ$49,0) -> 0.044977137 | AL8: 1000 | AM8: =IFERROR(AH8/AL8,0) -> 0.541 | AN8: 600 | AO8: 250 | AP8: =IFERROR(AO8/AO$49,0) -> 0.06215813 | AQ8: =AO8*AN8 -> 150000 | AR8: =IFERROR(AQ8/AQ$49,0) -> 0.044268681 | AS8: 659 | AT8: =IFERROR(AO8/AS8,0) -> 0.37936267 | AU8: =①石川予測確定!O8 -> 1.3018125 | AV8: =①石川予測確定!P8 -> 325 | AW8: =①石川予測確定!Q8 -> 195000 | AX8: =①石川予測確定!T8 -> 0.49317147 | AY8: =①石川予測確定!U8 -> 334 | AZ8: =③仙台以降予測!M32 -> 3818 | BA8: =③仙台以降予測!V32 -> 4170 | BB8: =③仙台以降予測!X32 -> -352 | BC8: =③仙台以降予測!Y32 -> 0 | BD8: =④追加発注判定!J8 -> 在庫余剰 | BE8: =④追加発注判定!P8 -> 在庫で充足 | BF8: =④追加発注判定!R8 -> 0 | BG8: =④追加発注判定!X8 -> D:不要
A9: 3 | B9: 4515142545105 | C9: 呪術廻戦 懐玉・玉折 ポストカードセット（5枚入） | D9: 1000 | E9: 1000 | F9: 2956 | G9: =IFERROR(F9/F$49,0) -> 0.019948038 | H9: =F9*E9 -> 2956000 | I9: =IFERROR(H9/H$49,0) -> 0.028927585 | J9: 3700 | K9: =IFERROR(F9/J9,0) -> 0.79891892 | L9: 1000 | M9: 601 | N9: =IFERROR(M9/M$49,0) -> 0.010255973 | O9: =M9*L9 -> 601000 | P9: =IFERROR(O9/O$49,0) -> 0.01448905 | Q9: 1200 | R9: =IFERROR(M9/Q9,0) -> 0.50083333 | S9: 1000 | T9: 454 | U9: =IFERROR(T9/T$49,0) -> 0.010117894 | V9: =T9*S9 -> 454000 | W9: =IFERROR(V9/V$49,0) -> 0.014632511 | X9: 500 | Y9: =IFERROR(T9/X9,0) -> 0.908 | Z9: 1000 | AA9: 1132 | AB9: =IFERROR(AA9/AA$49,0) -> 0.017759649 | AC9: =AA9*Z9 -> 1132000 | AD9: =IFERROR(AC9/AC$49,0) -> 0.024874966 | AE9: 2000 | AF9: =IFERROR(AA9/AE9,0) -> 0.566 | AG9: 1000 | AH9: 169 | AI9: =IFERROR(AH9/AH$49,0) -> 0.019007986 | AJ9: =AH9*AG9 -> 169000 | AK9: =IFERROR(AJ9/AJ$49,0) -> 0.023416932 | AL9: 450 | AM9: =IFERROR(AH9/AL9,0) -> 0.37555556 | AN9: 1000 | AO9: 92 | AP9: =IFERROR(AO9/AO$49,0) -> 0.022874192 | AQ9: =AO9*AN9 -> 92000 | AR9: =IFERROR(AQ9/AQ$49,0) -> 0.027151458 | AS9: 381 | AT9: =IFERROR(AO9/AS9,0) -> 0.24146982 | AU9: =①石川予測確定!O9 -> 1.2777151 | AV9: =①石川予測確定!P9 -> 118 | AW9: =①石川予測確定!Q9 -> 118000 | AX9: =①石川予測確定!T9 -> 0.30971129 | AY9: =①石川予測確定!U9 -> 263 | AZ9: =③仙台以降予測!M33 -> 1291 | BA9: =③仙台以降予測!V33 -> 1857 | BB9: =③仙台以降予測!X33 -> -566 | BC9: =③仙台以降予測!Y33 -> 0 | BD9: =④追加発注判定!J9 -> 在庫余剰 | BE9: =④追加発注判定!P9 -> 在庫で充足 | BF9: =④追加発注判定!R9 -> 0 | BG9: =④追加発注判定!X9 -> D:不要
A10: 4 | B10: 4515142545112 | C10: 呪術廻戦 渋谷事変 ポストカードセット（9枚入） | D10: 1800 | E10: 1800 | F10: 1819 | G10: =IFERROR(F10/F$49,0) -> 0.012275197 | H10: =F10*E10 -> 3274200 | I10: =IFERROR(H10/H$49,0) -> 0.032041509 | J10: 2620 | K10: =IFERROR(F10/J10,0) -> 0.69427481 | L10: 1800 | M10: 922 | N10: =IFERROR(M10/M$49,0) -> 0.015733788 | O10: =M10*L10 -> 1659600 | P10: =IFERROR(O10/O$49,0) -> 0.040010029 | Q10: 1330 | R10: =IFERROR(M10/Q10,0) -> 0.69323308 | S10: 1800 | T10: 539 | U10: =IFERROR(T10/T$49,0) -> 0.012012213 | V10: =T10*S10 -> 970200 | W10: =IFERROR(V10/V$49,0) -> 0.031269741 | X10: 800 | Y10: =IFERROR(T10/X10,0) -> 0.67375 | Z10: 1800 | AA10: 1310 | AB10: =IFERROR(AA10/AA$49,0) -> 0.020552243 | AC10: =AA10*Z10 -> 2358000 | AD10: =IFERROR(AC10/AC$49,0) -> 0.051815521 | AE10: 2000 | AF10: =IFERROR(AA10/AE10,0) -> 0.655 | AG10: 1800 | AH10: 228 | AI10: =IFERROR(AH10/AH$49,0) -> 0.02564391 | AJ10: =AH10*AG10 -> 410400 | AK10: =IFERROR(AJ10/AJ$49,0) -> 0.056865734 | AL10: 800 | AM10: =IFERROR(AH10/AL10,0) -> 0.285 | AN10: 1800 | AO10: 110 | AP10: =IFERROR(AO10/AO$49,0) -> 0.027349577 | AQ10: =AO10*AN10 -> 198000 | AR10: =IFERROR(AQ10/AQ$49,0) -> 0.058434659 | AS10: 772 | AT10: =IFERROR(AO10/AS10,0) -> 0.14248705 | AU10: =①石川予測確定!O10 -> 1.2157798 | AV10: =①石川予測確定!P10 -> 134 | AW10: =①石川予測確定!Q10 -> 241200 | AX10: =①石川予測確定!T10 -> 0.17357513 | AY10: =①石川予測確定!U10 -> 638 | AZ10: =③仙台以降予測!M34 -> 1591 | BA10: =③仙台以降予測!V34 -> 3153 | BB10: =③仙台以降予測!X34 -> -1562 | BC10: =③仙台以降予測!Y34 -> 0 | BD10: =④追加発注判定!J10 -> 在庫余剰 | BE10: =④追加発注判定!P10 -> 在庫で充足 | BF10: =④追加発注判定!R10 -> 0 | BG10: =④追加発注判定!X10 -> D:不要
A11: 5 | B11: 4515142545129 | C11: 呪術廻戦 懐玉・玉折 ブラインド缶バッジ（全5種） | D11: 600 | E11: 600 | F11: 18759 | G11: =IFERROR(F11/F$49,0) -> 0.12659176 | H11: =F11*E11 -> 11255400 | I11: =IFERROR(H11/H$49,0) -> 0.11014599 | J11: 24996 | K11: =IFERROR(F11/J11,0) -> 0.75048008 | L11: 600 | M11: 10777 | N11: =IFERROR(M11/M$49,0) -> 0.18390785 | O11: =M11*L11 -> 6466200 | P11: =IFERROR(O11/O$49,0) -> 0.15588868 | Q11: 16500 | R11: =IFERROR(M11/Q11,0) -> 0.65315152 | S11: 600 | T11: 8991 | U11: =IFERROR(T11/T$49,0) -> 0.20037441 | V11: =T11*S11 -> 5394600 | W11: =IFERROR(V11/V$49,0) -> 0.17386904 | X11: 9000 | Y11: =IFERROR(T11/X11,0) -> 0.999 | Z11: 600 | AA11: 8936 | AB11: =IFERROR(AA11/AA$49,0) -> 0.14019454 | AC11: =AA11*Z11 -> 5361600 | AD11: =IFERROR(AC11/AC$49,0) -> 0.11781768 | AE11: 24996 | AF11: =IFERROR(AA11/AE11,0) -> 0.3574972 | AG11: 600 | AH11: 410 | AI11: =IFERROR(AH11/AH$49,0) -> 0.046114048 | AJ11: =AH11*AG11 -> 246000 | AK11: =IFERROR(AJ11/AJ$49,0) -> 0.034086185 | AL11: 9000 | AM11: =IFERROR(AH11/AL11,0) -> 0.045555556 | AN11: 600 | AO11: 226 | AP11: =IFERROR(AO11/AO$49,0) -> 0.05619095 | AQ11: =AO11*AN11 -> 135600 | AR11: =IFERROR(AQ11/AQ$49,0) -> 0.040018888 | AS11: 8790 | AT11: =IFERROR(AO11/AS11,0) -> 0.025711035 | AU11: =①石川予測確定!O11 -> 1.2972275 | AV11: =①石川予測確定!P11 -> 293 | AW11: =①石川予測確定!Q11 -> 175800 | AX11: =①石川予測確定!T11 -> 0.033333333 | AY11: =①石川予測確定!U11 -> 8497 | AZ11: =③仙台以降予測!M35 -> 3173 | BA11: =③仙台以降予測!V35 -> 39392 | BB11: =③仙台以降予測!X35 -> -36219 | BC11: =③仙台以降予測!Y35 -> 0 | BD11: =④追加発注判定!J11 -> 在庫余剰 | BE11: =④追加発注判定!P11 -> 在庫で充足 | BF11: =④追加発注判定!R11 -> 0 | BG11: =④追加発注判定!X11 -> D:不要
A12: 6 | B12: 4515142545136 | C12: 呪術廻戦 渋谷事変 ブラインド缶バッジ（全9種） | D12: 600 | E12: 600 | F12: 31070 | G12: =IFERROR(F12/F$49,0) -> 0.20967034 | H12: =F12*E12 -> 18642000 | I12: =IFERROR(H12/H$49,0) -> 0.18243168 | J12: 44999 | K12: =IFERROR(F12/J12,0) -> 0.69045979 | L12: 600 | M12: 15602 | N12: =IFERROR(M12/M$49,0) -> 0.26624573 | O12: =M12*L12 -> 9361200 | P12: =IFERROR(O12/O$49,0) -> 0.22568202 | Q12: 21439 | R12: =IFERROR(M12/Q12,0) -> 0.72773917 | S12: 600 | T12: 13877 | U12: =IFERROR(T12/T$49,0) -> 0.30926434 | V12: =T12*S12 -> 8326200 | W12: =IFERROR(V12/V$49,0) -> 0.2683551 | X12: 13986 | Y12: =IFERROR(T12/X12,0) -> 0.99220649 | Z12: 600 | AA12: 18611 | AB12: =IFERROR(AA12/AA$49,0) -> 0.29198306 | AC12: =AA12*Z12 -> 11166600 | AD12: =IFERROR(AC12/AC$49,0) -> 0.24537879 | AE12: 35999 | AF12: =IFERROR(AA12/AE12,0) -> 0.51698658 | AG12: 600 | AH12: 1042 | AI12: =IFERROR(AH12/AH$49,0) -> 0.11719717 | AJ12: =AH12*AG12 -> 625200 | AK12: =IFERROR(AJ12/AJ$49,0) -> 0.086628793 | AL12: 13991 | AM12: =IFERROR(AH12/AL12,0) -> 0.074476449 | AN12: 600 | AO12: 439 | AP12: =IFERROR(AO12/AO$49,0) -> 0.10914968 | AQ12: =AO12*AN12 -> 263400 | AR12: =IFERROR(AQ12/AQ$49,0) -> 0.077735805 | AS12: 13249 | AT12: =IFERROR(AO12/AS12,0) -> 0.033134576 | AU12: =①石川予測確定!O12 -> 1.2877261 | AV12: =①石川予測確定!P12 -> 565 | AW12: =①石川予測確定!Q12 -> 339000 | AX12: =①石川予測確定!T12 -> 0.042644728 | AY12: =①石川予測確定!U12 -> 12684 | AZ12: =③仙台以降予測!M36 -> 6991 | BA12: =③仙台以降予測!V36 -> 50228 | BB12: =③仙台以降予測!X36 -> -43237 | BC12: =③仙台以降予測!Y36 -> 0 | BD12: =④追加発注判定!J12 -> 在庫余剰 | BE12: =④追加発注判定!P12 -> 在庫で充足 | BF12: =④追加発注判定!R12 -> 0 | BG12: =④追加発注判定!X12 -> D:不要
A13: 7 | B13: 4515142545143 | C13: 呪術廻戦 懐玉・玉折 ブラインドダイカットステッカー（全5種） | D13: 600 | E13: 600 | F13: 3471 | G13: =IFERROR(F13/F$49,0) -> 0.023423423 | H13: =F13*E13 -> 2082600 | I13: =IFERROR(H13/H$49,0) -> 0.020380443 | J13: 7000 | K13: =IFERROR(F13/J13,0) -> 0.49585714 | L13: 600 | M13: 520 | N13: =IFERROR(M13/M$49,0) -> 0.0088737201 | O13: =M13*L13 -> 312000 | P13: =IFERROR(O13/O$49,0) -> 0.0075217697 | Q13: 1390 | R13: =IFERROR(M13/Q13,0) -> 0.37410072 | S13: 600 | T13: 384 | U13: =IFERROR(T13/T$49,0) -> 0.0085578659 | V13: =T13*S13 -> 230400 | W13: =IFERROR(V13/V$49,0) -> 0.0074258383 | X13: 400 | Y13: =IFERROR(T13/X13,0) -> 0.96 | Z13: 600 | AA13: 940 | AB13: =IFERROR(AA13/AA$49,0) -> 0.014747411 | AC13: =AA13*Z13 -> 564000 | AD13: =IFERROR(AC13/AC$49,0) -> 0.012393534 | AE13: 2000 | AF13: =IFERROR(AA13/AE13,0) -> 0.47 | AG13: 600 | AH13: 187 | AI13: =IFERROR(AH13/AH$49,0) -> 0.021032505 | AJ13: =AH13*AG13 -> 112200 | AK13: =IFERROR(AJ13/AJ$49,0) -> 0.015546626 | AL13: 350 | AM13: =IFERROR(AH13/AL13,0) -> 0.53428571 | AN13: 600 | AO13: 130 | AP13: =IFERROR(AO13/AO$49,0) -> 0.032322228 | AQ13: =AO13*AN13 -> 78000 | AR13: =IFERROR(AQ13/AQ$49,0) -> 0.023019714 | AS13: 463 | AT13: =IFERROR(AO13/AS13,0) -> 0.28077754 | AU13: =①石川予測確定!O13 -> 1.2689846 | AV13: =①石川予測確定!P13 -> 165 | AW13: =①石川予測確定!Q13 -> 99000 | AX13: =①石川予測確定!T13 -> 0.35637149 | AY13: =①石川予測確定!U13 -> 298 | AZ13: =③仙台以降予測!M37 -> 1635 | BA13: =③仙台以降予測!V37 -> 4249 | BB13: =③仙台以降予測!X37 -> -2614 | BC13: =③仙台以降予測!Y37 -> 0 | BD13: =④追加発注判定!J13 -> 在庫余剰 | BE13: =④追加発注判定!P13 -> 在庫で充足 | BF13: =④追加発注判定!R13 -> 0 | BG13: =④追加発注判定!X13 -> D:不要
A14: 8 | B14: 4515142545150 | C14: 呪術廻戦 渋谷事変 ブラインドダイカットステッカー（全9種） | D14: 600 | E14: 600 | F14: 5596 | G14: =IFERROR(F14/F$49,0) -> 0.037763606 | H14: =F14*E14 -> 3357600 | I14: =IFERROR(H14/H$49,0) -> 0.032857666 | J14: 12600 | K14: =IFERROR(F14/J14,0) -> 0.44412698 | L14: 600 | M14: 1107 | N14: =IFERROR(M14/M$49,0) -> 0.018890785 | O14: =M14*L14 -> 664200 | P14: =IFERROR(O14/O$49,0) -> 0.016012691 | Q14: 2240 | R14: =IFERROR(M14/Q14,0) -> 0.49419643 | S14: 600 | T14: 799 | U14: =IFERROR(T14/T$49,0) -> 0.017806601 | V14: =T14*S14 -> 479400 | W14: =IFERROR(V14/V$49,0) -> 0.015451158 | X14: 840 | Y14: =IFERROR(T14/X14,0) -> 0.95119048 | Z14: 600 | AA14: 1758 | AB14: =IFERROR(AA14/AA$49,0) -> 0.027580797 | AC14: =AA14*Z14 -> 1054800 | AD14: =IFERROR(AC14/AC$49,0) -> 0.023178546 | AE14: 3000 | AF14: =IFERROR(AA14/AE14,0) -> 0.586 | AG14: 600 | AH14: 322 | AI14: =IFERROR(AH14/AH$49,0) -> 0.036216399 | AJ14: =AH14*AG14 -> 193200 | AK14: =IFERROR(AJ14/AJ$49,0) -> 0.026770126 | AL14: 900 | AM14: =IFERROR(AH14/AL14,0) -> 0.35777778 | AN14: 600 | AO14: 207 | AP14: =IFERROR(AO14/AO$49,0) -> 0.051466932 | AQ14: =AO14*AN14 -> 124200 | AR14: =IFERROR(AQ14/AQ$49,0) -> 0.036654468 | AS14: 778 | AT14: =IFERROR(AO14/AS14,0) -> 0.26606684 | AU14: =①石川予測確定!O14 -> 1.2850627 | AV14: =①石川予測確定!P14 -> 266 | AW14: =①石川予測確定!Q14 -> 159600 | AX14: =①石川予測確定!T14 -> 0.34190231 | AY14: =①石川予測確定!U14 -> 512 | AZ14: =③仙台以降予測!M38 -> 2707 | BA14: =③仙台以降予測!V38 -> 8034 | BB14: =③仙台以降予測!X38 -> -5327 | BC14: =③仙台以降予測!Y38 -> 0 | BD14: =④追加発注判定!J14 -> 在庫余剰 | BE14: =④追加発注判定!P14 -> 在庫で充足 | BF14: =④追加発注判定!R14 -> 0 | BG14: =④追加発注判定!X14 -> D:不要
A15: 9 | B15: 4515142545372 | C15: 呪術廻戦 懐玉・玉折 クリアファイル（五条 悟） | D15: 600 | E15: 600 | F15: 2381 | G15: =IFERROR(F15/F$49,0) -> 0.016067753 | H15: =F15*E15 -> 1428600 | I15: =IFERROR(H15/H$49,0) -> 0.013980361 | J15: 8749 | K15: =IFERROR(F15/J15,0) -> 0.27214539 | L15: 600 | M15: 313 | N15: =IFERROR(M15/M$49,0) -> 0.0053412969 | O15: =M15*L15 -> 187800 | P15: =IFERROR(O15/O$49,0) -> 0.0045275268 | Q15: 950 | R15: =IFERROR(M15/Q15,0) -> 0.32947368 | S15: 600 | T15: 301 | U15: =IFERROR(T15/T$49,0) -> 0.0067081188 | V15: =T15*S15 -> 180600 | W15: =IFERROR(V15/V$49,0) -> 0.0058207743 | X15: 300 | Y15: =IFERROR(T15/X15,0) -> 1.0033333 | Z15: 600 | AA15: 743 | AB15: =IFERROR(AA15/AA$49,0) -> 0.01165673 | AC15: =AA15*Z15 -> 445800 | AD15: =IFERROR(AC15/AC$49,0) -> 0.0097961659 | AE15: 1500 | AF15: =IFERROR(AA15/AE15,0) -> 0.49533333 | AG15: 600 | AH15: 160 | AI15: =IFERROR(AH15/AH$49,0) -> 0.017995726 | AJ15: =AH15*AG15 -> 96000 | AK15: =IFERROR(AJ15/AJ$49,0) -> 0.013301926 | AL15: 300 | AM15: =IFERROR(AH15/AL15,0) -> 0.53333333 | AN15: 600 | AO15: 41 | AP15: =IFERROR(AO15/AO$49,0) -> 0.010193933 | AQ15: =AO15*AN15 -> 24600 | AR15: =IFERROR(AQ15/AQ$49,0) -> 0.0072600637 | AS15: 740 | AT15: =IFERROR(AO15/AS15,0) -> 0.055405405 | AU15: =①石川予測確定!O15 -> 1.2551795 | AV15: =①石川予測確定!P15 -> 51 | AW15: =①石川予測確定!Q15 -> 30600 | AX15: =①石川予測確定!T15 -> 0.068918919 | AY15: =①石川予測確定!U15 -> 689 | AZ15: =③仙台以降予測!M39 -> 860 | BA15: =③仙台以降予測!V39 -> 8547 | BB15: =③仙台以降予測!X39 -> -7687 | BC15: =③仙台以降予測!Y39 -> 0 | BD15: =④追加発注判定!J15 -> 在庫余剰 | BE15: =④追加発注判定!P15 -> 在庫で充足 | BF15: =④追加発注判定!R15 -> 0 | BG15: =④追加発注判定!X15 -> D:不要
A16: 10 | B16: 4515142545389 | C16: 呪術廻戦 懐玉・玉折 クリアファイル（夏油 傑） | D16: 600 | E16: 600 | F16: 1025 | G16: =IFERROR(F16/F$49,0) -> 0.0069170294 | H16: =F16*E16 -> 615000 | I16: =IFERROR(H16/H$49,0) -> 0.0060184252 | J16: 4549 | K16: =IFERROR(F16/J16,0) -> 0.22532425 | L16: 600 | M16: 141 | N16: =IFERROR(M16/M$49,0) -> 0.0024061433 | O16: =M16*L16 -> 84600 | P16: =IFERROR(O16/O$49,0) -> 0.0020395568 | Q16: 410 | R16: =IFERROR(M16/Q16,0) -> 0.34390244 | S16: 600 | T16: 123 | U16: =IFERROR(T16/T$49,0) -> 0.0027411914 | V16: =T16*S16 -> 73800 | W16: =IFERROR(V16/V$49,0) -> 0.0023785888 | X16: 180 | Y16: =IFERROR(T16/X16,0) -> 0.68333333 | Z16: 600 | AA16: 277 | AB16: =IFERROR(AA16/AA$49,0) -> 0.0043457797 | AC16: =AA16*Z16 -> 166200 | AD16: =IFERROR(AC16/AC$49,0) -> 0.0036521372 | AE16: 500 | AF16: =IFERROR(AA16/AE16,0) -> 0.554 | AG16: 600 | AH16: 59 | AI16: =IFERROR(AH16/AH$49,0) -> 0.006635924 | AJ16: =AH16*AG16 -> 35400 | AK16: =IFERROR(AJ16/AJ$49,0) -> 0.0049050852 | AL16: 100 | AM16: =IFERROR(AH16/AL16,0) -> 0.59 | AN16: 600 | AO16: 16 | AP16: =IFERROR(AO16/AO$49,0) -> 0.0039781203 | AQ16: =AO16*AN16 -> 9600 | AR16: =IFERROR(AQ16/AQ$49,0) -> 0.0028331956 | AS16: 541 | AT16: =IFERROR(AO16/AS16,0) -> 0.029574861 | AU16: =①石川予測確定!O16 -> 1.2668927 | AV16: =①石川予測確定!P16 -> 20 | AW16: =①石川予測確定!Q16 -> 12000 | AX16: =①石川予測確定!T16 -> 0.036968577 | AY16: =①石川予測確定!U16 -> 521 | AZ16: =③仙台以降予測!M40 -> 324 | BA16: =③仙台以降予測!V40 -> 4856 | BB16: =③仙台以降予測!X40 -> -4532 | BC16: =③仙台以降予測!Y40 -> 0 | BD16: =④追加発注判定!J16 -> 在庫余剰 | BE16: =④追加発注判定!P16 -> 在庫で充足 | BF16: =④追加発注判定!R16 -> 0 | BG16: =④追加発注判定!X16 -> D:不要
A17: 11 | B17: 4515142545396 | C17: 呪術廻戦 懐玉・玉折 クリアファイル（家入 硝子） | D17: 600 | E17: 600 | F17: 215 | G17: =IFERROR(F17/F$49,0) -> 0.0014508891 | H17: =F17*E17 -> 129000 | I17: =IFERROR(H17/H$49,0) -> 0.0012624014 | J17: 699 | K17: =IFERROR(F17/J17,0) -> 0.30758226 | L17: 600 | M17: 37 | N17: =IFERROR(M17/M$49,0) -> 0.00063139932 | O17: =M17*L17 -> 22200 | P17: =IFERROR(O17/O$49,0) -> 0.00053520285 | Q17: 90 | R17: =IFERROR(M17/Q17,0) -> 0.41111111 | S17: 600 | T17: 30 | U17: =IFERROR(T17/T$49,0) -> 0.00066858327 | V17: =T17*S17 -> 18000 | W17: =IFERROR(V17/V$49,0) -> 0.00058014362 | X17: 30 | Y17: =IFERROR(T17/X17,0) -> 1 | Z17: 600 | AA17: 78 | AB17: =IFERROR(AA17/AA$49,0) -> 0.0012237214 | AC17: =AA17*Z17 -> 46800 | AD17: =IFERROR(AC17/AC$49,0) -> 0.0010283997 | AE17: 100 | AF17: =IFERROR(AA17/AE17,0) -> 0.78 | AG17: 600 | AH17: 21 | AI17: =IFERROR(AH17/AH$49,0) -> 0.002361939 | AJ17: =AH17*AG17 -> 12600 | AK17: =IFERROR(AJ17/AJ$49,0) -> 0.0017458778 | AL17: 50 | AM17: =IFERROR(AH17/AL17,0) -> 0.42 | AN17: 600 | AO17: 6 | AP17: =IFERROR(AO17/AO$49,0) -> 0.0014917951 | AQ17: =AO17*AN17 -> 3600 | AR17: =IFERROR(AQ17/AQ$49,0) -> 0.0010624484 | AS17: 79 | AT17: =IFERROR(AO17/AS17,0) -> 0.075949367 | AU17: =①石川予測確定!O17 -> 1.3244949 | AV17: =①石川予測確定!P17 -> 8 | AW17: =①石川予測確定!Q17 -> 4800 | AX17: =①石川予測確定!T17 -> 0.10126582 | AY17: =①石川予測確定!U17 -> 71 | AZ17: =③仙台以降予測!M41 -> 121 | BA17: =③仙台以降予測!V41 -> 609 | BB17: =③仙台以降予測!X41 -> -488 | BC17: =③仙台以降予測!Y41 -> 0 | BD17: =④追加発注判定!J17 -> 在庫余剰 | BE17: =④追加発注判定!P17 -> 在庫で充足 | BF17: =④追加発注判定!R17 -> 0 | BG17: =④追加発注判定!X17 -> D:不要
A18: 12 | B18: 4515142545402 | C18: 呪術廻戦 懐玉・玉折 クリアファイル（七海 建人） | D18: 600 | E18: 600 | F18: 291 | G18: =IFERROR(F18/F$49,0) -> 0.0019637615 | H18: =F18*E18 -> 174600 | I18: =IFERROR(H18/H$49,0) -> 0.0017086456 | J18: 1049 | K18: =IFERROR(F18/J18,0) -> 0.27740705 | L18: 600 | M18: 58 | N18: =IFERROR(M18/M$49,0) -> 0.00098976109 | O18: =M18*L18 -> 34800 | P18: =IFERROR(O18/O$49,0) -> 0.00083896662 | Q18: 119 | R18: =IFERROR(M18/Q18,0) -> 0.48739496 | S18: 600 | T18: 54 | U18: =IFERROR(T18/T$49,0) -> 0.0012034499 | V18: =T18*S18 -> 32400 | W18: =IFERROR(V18/V$49,0) -> 0.0010442585 | X18: 80 | Y18: =IFERROR(T18/X18,0) -> 0.675 | Z18: 600 | AA18: 142 | AB18: =IFERROR(AA18/AA$49,0) -> 0.0022278004 | AC18: =AA18*Z18 -> 85200 | AD18: =IFERROR(AC18/AC$49,0) -> 0.0018722148 | AE18: 150 | AF18: =IFERROR(AA18/AE18,0) -> 0.94666667 | AG18: 600 | AH18: 43 | AI18: =IFERROR(AH18/AH$49,0) -> 0.0048363514 | AJ18: =AH18*AG18 -> 25800 | AK18: =IFERROR(AJ18/AJ$49,0) -> 0.0035748926 | AL18: 50 | AM18: =IFERROR(AH18/AL18,0) -> 0.86 | AN18: 600 | AO18: 13 | AP18: =IFERROR(AO18/AO$49,0) -> 0.0032322228 | AQ18: =AO18*AN18 -> 7800 | AR18: =IFERROR(AQ18/AQ$49,0) -> 0.0023019714 | AS18: 107 | AT18: =IFERROR(AO18/AS18,0) -> 0.12149533 | AU18: =①石川予測確定!O18 -> 1.2891842 | AV18: =①石川予測確定!P18 -> 17 | AW18: =①石川予測確定!Q18 -> 10200 | AX18: =①石川予測確定!T18 -> 0.1588785 | AY18: =①石川予測確定!U18 -> 90 | AZ18: =③仙台以降予測!M42 -> 251 | BA18: =③仙台以降予測!V42 -> 891 | BB18: =③仙台以降予測!X42 -> -640 | BC18: =③仙台以降予測!Y42 -> 0 | BD18: =④追加発注判定!J18 -> 在庫余剰 | BE18: =④追加発注判定!P18 -> 在庫で充足 | BF18: =④追加発注判定!R18 -> 0 | BG18: =④追加発注判定!X18 -> D:不要
... A48: 42 | B48: 4515142545365 | C48: 伏黒 恵 イメージフラグメントケース | D48: 25000 | E48: 25000 | F48: 24 | G48: =IFERROR(F48/F$49,0) -> 0.00016195971 | H48: =F48*E48 -> 600000 | I48: =IFERROR(H48/H$49,0) -> 0.0058716343 | J48: 38 | K48: =IFERROR(F48/J48,0) -> 0.63157895 | L48: 25000 | M48: 8 | N48: =IFERROR(M48/M$49,0) -> 0.00013651877 | O48: =M48*L48 -> 200000 | P48: =IFERROR(O48/O$49,0) -> 0.0048216473 | Q48: 10 | R48: =IFERROR(M48/Q48,0) -> 0.8 | S48: 25000 | T48: 3 | U48: =IFERROR(T48/T$49,0) -> 6.6858327e-05 | V48: =T48*S48 -> 75000 | W48: =IFERROR(V48/V$49,0) -> 0.0024172651 | X48: 5 | Y48: =IFERROR(T48/X48,0) -> 0.6 | Z48: 25000 | AA48: 8 | AB48: =IFERROR(AA48/AA$49,0) -> 0.00012550988 | AC48: =AA48*Z48 -> 200000 | AD48: =IFERROR(AC48/AC$49,0) -> 0.0043948703 | AE48: 20 | AF48: =IFERROR(AA48/AE48,0) -> 0.4 | AG48: 25000 | AH48: 1 | AI48: =IFERROR(AH48/AH$49,0) -> 0.00011247329 | AJ48: =AH48*AG48 -> 25000 | AK48: =IFERROR(AJ48/AJ$49,0) -> 0.0034640432 | AL48: 6 | AM48: =IFERROR(AH48/AL48,0) -> 0.16666667 | AN48: 25000 | AO48: 0 | AP48: =IFERROR(AO48/AO$49,0) -> 0 | AQ48: =AO48*AN48 -> 0 | AR48: =IFERROR(AQ48/AQ$49,0) -> 0 | AS48: 15 | AT48: =IFERROR(AO48/AS48,0) -> 0 | AU48: =①石川予測確定!O48 -> 1.05 | AV48: =①石川予測確定!P48 -> 0 | AW48: =①石川予測確定!Q48 -> 0 | AX48: =①石川予測確定!T48 -> 0 | AY48: =①石川予測確定!U48 -> 15 | AZ48: =③仙台以降予測!M72 -> 3 | BA48: =③仙台以降予測!V72 -> 48 | BB48: =③仙台以降予測!X72 -> -45 | BC48: =③仙台以降予測!Y72 -> 0 | BD48: =④追加発注判定!J48 -> 在庫余剰 | BE48: =④追加発注判定!P48 -> 在庫で充足 | BF48: =④追加発注判定!R48 -> 0 | BG48: =④追加発注判定!X48 -> D:不要
C49: 合計（LEGS 42SKU） | F49: =SUM(F7:F48) -> 148185 | H49: =SUM(H7:H48) -> 102186200 | J49: =SUM(J7:J48) -> 211152 | M49: =SUM(M7:M48) -> 58600 | O49: =SUM(O7:O48) -> 41479600 | Q49: =SUM(Q7:Q48) -> 83271 | T49: =SUM(T7:T48) -> 44871 | V49: =SUM(V7:V48) -> 31026800 | X49: =SUM(X7:X48) -> 49598 | AA49: =SUM(AA7:AA48) -> 63740 | AC49: =SUM(AC7:AC48) -> 45507600 | AE49: =SUM(AE7:AE48) -> 137560 | AH49: =SUM(AH7:AH48) -> 8891 | AJ49: =SUM(AJ7:AJ48) -> 7217000 | AL49: =SUM(AL7:AL48) -> 50506 | AO49: =SUM(AO7:AO48) -> 4022 | AQ49: =SUM(AQ7:AQ48) -> 3388400 | AS49: =SUM(AS7:AS48) -> 46928 | AV49: =SUM(AV7:AV48) -> 5151 | AW49: =SUM(AW7:AW48) -> 4292200 | AY49: =SUM(AY7:AY48) -> 41810 | AZ49: =SUM(AZ7:AZ48) -> 61617 | BA49: =SUM(BA7:BA48) -> 234426 | BB49: =SUM(BB7:BB48) -> -174009 | BC49: =SUM(BC7:BC48) -> 3384 | BF49: =SUM(BF7:BF48) -> 3767

Sheet ⑥商品別 会場推移
A1: ⑥ 商品別 会場推移（LEGS 42SKU内 数量構成比の会場間トレンド）
A2: 各会場の会期全体（石川は初12日実績と18日予測）。構成比の伸び／減退から仙台以降の重点商品を判断
A5: No. | B5: JAN | C5: 商品名 | D5: 東京 販売数 | E5: 名古屋 販売数 | F5: 博多 販売数 | G5: 大阪 販売数 | H5: 札幌 販売数 | I5: 石川 販売数 | J5: 東京 構成比 | K5: 名古屋 構成比 | L5: 博多 構成比 | M5: 大阪 構成比 | N5: 札幌 構成比 | O5: 石川 構成比 | P5: 石川18日 予測構成比 | Q5: 札幌→石川 構成比変化 | R5: 東京→大阪 構成比変化 | S5: トレンド
A6: 1 | B6: 4515142545082 | C6: 呪術廻戦 メタリックポストカード 展示会キービジュアル | D6: 4965 | E6: 1316 | F6: 1092 | G6: 2325 | H6: 507 | I6: 210 | J6: =IFERROR(E6/E$48,0) -> 0.022457338 | K6: =IFERROR(F6/F$48,0) -> 0.024336431 | L6: =IFERROR(G6/G$48,0) -> 0.03647631 | M6: =IFERROR(H6/H$48,0) -> 0.057023957 | N6: =①石川予測確定!R7 -> 0.052805281 | O6: =N6-L6 -> 0.016328971 | P6: =L6-I6 -> -209.96352 | Q6: =IF(O6>=0.005,"↑ 伸長",IF(O6<=-0.005,"↓ 減退","→ 横ばい")) -> ↑ 伸長
A7: 2 | B7: 4515142545099 | C7: 呪術廻戦 クリアファイル 展示会キービジュアル | D7: 4902 | E7: 1466 | F7: 1132 | G7: 1965 | H7: 541 | I7: 250 | J7: =IFERROR(E7/E$48,0) -> 0.025017065 | K7: =IFERROR(F7/F$48,0) -> 0.025227875 | L7: =IFERROR(G7/G$48,0) -> 0.030828365 | M7: =IFERROR(H7/H$48,0) -> 0.060848049 | N7: =①石川予測確定!R8 -> 0.063094545 | O7: =N7-L7 -> 0.03226618 | P7: =L7-I7 -> -249.96917 | Q7: =IF(O7>=0.005,"↑ 伸長",IF(O7<=-0.005,"↓ 減退","→ 横ばい")) -> ↑ 伸長
A8: 3 | B8: 4515142545105 | C8: 呪術廻戦 懐玉・玉折 ポストカードセット（5枚入） | D8: 2956 | E8: 601 | F8: 454 | G8: 1132 | H8: 169 | I8: 92 | J8: =IFERROR(E8/E$48,0) -> 0.010255973 | K8: =IFERROR(F8/F$48,0) -> 0.010117894 | L8: =IFERROR(G8/G$48,0) -> 0.017759649 | M8: =IFERROR(H8/H$48,0) -> 0.019007986 | N8: =①石川予測確定!R9 -> 0.022908173 | O8: =N8-L8 -> 0.0051485246 | P8: =L8-I8 -> -91.98224 | Q8: =IF(O8>=0.005,"↑ 伸長",IF(O8<=-0.005,"↓ 減退","→ 横ばい")) -> ↑ 伸長
A9: 4 | B9: 4515142545112 | C9: 呪術廻戦 渋谷事変 ポストカードセット（9枚入） | D9: 1819 | E9: 922 | F9: 539 | G9: 1310 | H9: 228 | I9: 110 | J9: =IFERROR(E9/E$48,0) -> 0.015733788 | K9: =IFERROR(F9/F$48,0) -> 0.012012213 | L9: =IFERROR(G9/G$48,0) -> 0.020552243 | M9: =IFERROR(H9/H$48,0) -> 0.02564391 | N9: =①石川予測確定!R10 -> 0.026014366 | O9: =N9-L9 -> 0.0054621227 | P9: =L9-I9 -> -109.97945 | Q9: =IF(O9>=0.005,"↑ 伸長",IF(O9<=-0.005,"↓ 減退","→ 横ばい")) -> ↑ 伸長
A10: 5 | B10: 4515142545129 | C10: 呪術廻戦 懐玉・玉折 ブラインド缶バッジ（全5種） | D10: 18759 | E10: 10777 | F10: 8991 | G10: 8936 | H10: 410 | I10: 226 | J10: =IFERROR(E10/E$48,0) -> 0.18390785 | K10: =IFERROR(F10/F$48,0) -> 0.20037441 | L10: =IFERROR(G10/G$48,0) -> 0.14019454 | M10: =IFERROR(H10/H$48,0) -> 0.046114048 | N10: =①石川予測確定!R11 -> 0.056882159 | O10: =N10-L10 -> -0.083312382 | P10: =L10-I10 -> -225.85981 | Q10: =IF(O10>=0.005,"↑ 伸長",IF(O10<=-0.005,"↓ 減退","→ 横ばい")) -> ↓ 減退
A11: 6 | B11: 4515142545136 | C11: 呪術廻戦 渋谷事変 ブラインド缶バッジ（全9種） | D11: 31070 | E11: 15602 | F11: 13877 | G11: 18611 | H11: 1042 | I11: 439 | J11: =IFERROR(E11/E$48,0) -> 0.26624573 | K11: =IFERROR(F11/F$48,0) -> 0.30926434 | L11: =IFERROR(G11/G$48,0) -> 0.29198306 | M11: =IFERROR(H11/H$48,0) -> 0.11719717 | N11: =①石川予測確定!R12 -> 0.10968744 | O11: =N11-L11 -> -0.18229562 | P11: =L11-I11 -> -438.70802 | Q11: =IF(O11>=0.005,"↑ 伸長",IF(O11<=-0.005,"↓ 減退","→ 横ばい")) -> ↓ 減退
A12: 7 | B12: 4515142545143 | C12: 呪術廻戦 懐玉・玉折 ブラインドダイカットステッカー（全5種） | D12: 3471 | E12: 520 | F12: 384 | G12: 940 | H12: 187 | I12: 130 | J12: =IFERROR(E12/E$48,0) -> 0.0088737201 | K12: =IFERROR(F12/F$48,0) -> 0.0085578659 | L12: =IFERROR(G12/G$48,0) -> 0.014747411 | M12: =IFERROR(H12/H$48,0) -> 0.021032505 | N12: =①石川予測確定!R13 -> 0.032032615 | O12: =N12-L12 -> 0.017285204 | P12: =L12-I12 -> -129.98525 | Q12: =IF(O12>=0.005,"↑ 伸長",IF(O12<=-0.005,"↓ 減退","→ 横ばい")) -> ↑ 伸長
A13: 8 | B13: 4515142545150 | C13: 呪術廻戦 渋谷事変 ブラインドダイカットステッカー（全9種） | D13: 5596 | E13: 1107 | F13: 799 | G13: 1758 | H13: 322 | I13: 207 | J13: =IFERROR(E13/E$48,0) -> 0.018890785 | K13: =IFERROR(F13/F$48,0) -> 0.017806601 | L13: =IFERROR(G13/G$48,0) -> 0.027580797 | M13: =IFERROR(H13/H$48,0) -> 0.036216399 | N13: =①石川予測確定!R14 -> 0.051640458 | O13: =N13-L13 -> 0.024059661 | P13: =L13-I13 -> -206.97242 | Q13: =IF(O13>=0.005,"↑ 伸長",IF(O13<=-0.005,"↓ 減退","→ 横ばい")) -> ↑ 伸長
A14: 9 | B14: 4515142545372 | C14: 呪術廻戦 懐玉・玉折 クリアファイル（五条 悟） | D14: 2381 | E14: 313 | F14: 301 | G14: 743 | H14: 160 | I14: 41 | J14: =IFERROR(E14/E$48,0) -> 0.0053412969 | K14: =IFERROR(F14/F$48,0) -> 0.0067081188 | L14: =IFERROR(G14/G$48,0) -> 0.01165673 | M14: =IFERROR(H14/H$48,0) -> 0.017995726 | N14: =①石川予測確定!R15 -> 0.0099009901 | O14: =N14-L14 -> -0.0017557404 | P14: =L14-I14 -> -40.988343 | Q14: =IF(O14>=0.005,"↑ 伸長",IF(O14<=-0.005,"↓ 減退","→ 横ばい")) -> → 横ばい
A15: 10 | B15: 4515142545389 | C15: 呪術廻戦 懐玉・玉折 クリアファイル（夏油 傑） | D15: 1025 | E15: 141 | F15: 123 | G15: 277 | H15: 59 | I15: 16 | J15: =IFERROR(E15/E$48,0) -> 0.0024061433 | K15: =IFERROR(F15/F$48,0) -> 0.0027411914 | L15: =IFERROR(G15/G$48,0) -> 0.0043457797 | M15: =IFERROR(H15/H$48,0) -> 0.006635924 | N15: =①石川予測確定!R16 -> 0.0038827412 | O15: =N15-L15 -> -0.00046303851 | P15: =L15-I15 -> -15.995654 | Q15: =IF(O15>=0.005,"↑ 伸長",IF(O15<=-0.005,"↓ 減退","→ 横ばい")) -> → 横ばい
A16: 11 | B16: 4515142545396 | C16: 呪術廻戦 懐玉・玉折 クリアファイル（家入 硝子） | D16: 215 | E16: 37 | F16: 30 | G16: 78 | H16: 21 | I16: 6 | J16: =IFERROR(E16/E$48,0) -> 0.00063139932 | K16: =IFERROR(F16/F$48,0) -> 0.00066858327 | L16: =IFERROR(G16/G$48,0) -> 0.0012237214 | M16: =IFERROR(H16/H$48,0) -> 0.002361939 | N16: =①石川予測確定!R17 -> 0.0015530965 | O16: =N16-L16 -> 0.00032937512 | P16: =L16-I16 -> -5.9987763 | Q16: =IF(O16>=0.005,"↑ 伸長",IF(O16<=-0.005,"↓ 減退","→ 横ばい")) -> → 横ばい
A17: 12 | B17: 4515142545402 | C17: 呪術廻戦 懐玉・玉折 クリアファイル（七海 建人） | D17: 291 | E17: 58 | F17: 54 | G17: 142 | H17: 43 | I17: 13 | J17: =IFERROR(E17/E$48,0) -> 0.00098976109 | K17: =IFERROR(F17/F$48,0) -> 0.0012034499 | L17: =IFERROR(G17/G$48,0) -> 0.0022278004 | M17: =IFERROR(H17/H$48,0) -> 0.0048363514 | N17: =①石川予測確定!R18 -> 0.00330033 | O17: =N17-L17 -> 0.0010725296 | P17: =L17-I17 -> -12.997772 | Q17: =IF(O17>=0.005,"↑ 伸長",IF(O17<=-0.005,"↓ 減退","→ 横ばい")) -> → 横ばい
... A47: 42 | B47: 4515142545365 | C47: 伏黒 恵 イメージフラグメントケース | D47: 24 | E47: 8 | F47: 3 | G47: 8 | H47: 1 | I47: 0 | J47: =IFERROR(E47/E$48,0) -> 0.00013651877 | K47: =IFERROR(F47/F$48,0) -> 6.6858327e-05 | L47: =IFERROR(G47/G$48,0) -> 0.00012550988 | M47: =IFERROR(H47/H$48,0) -> 0.00011247329 | N47: =①石川予測確定!R48 -> 0 | O47: =N47-L47 -> -0.00012550988 | P47: =L47-I47 -> 0.00012550988 | Q47: =IF(O47>=0.005,"↑ 伸長",IF(O47<=-0.005,"↓ 減退","→ 横ばい")) -> → 横ばい
C48: 合計（LEGS 42SKU） | D48: =SUM(D6:D47) -> 148185 | E48: =SUM(E6:E47) -> 58600 | F48: =SUM(F6:F47) -> 44871 | G48: =SUM(G6:G47) -> 63740 | H48: =SUM(H6:H47) -> 8891 | I48: =SUM(I6:I47) -> 4022 | J48: 1 | K48: 1 | L48: 1 | M48: 1 | N48: 1

Sheet ⑦新商品影響分析
A1: ⑦ 梅田(大阪)会場以降の追加商品による LEGS売上低下の要因分析
A2: 会場ごとに規模が違うため、すべて「入場者1人あたり売上（円/人）」に正規化して比較する（石川は8/25までの12日実績）
A4: ■ 結論：市場は縮んでいない。LEGSの財布が新商品に奪われた（カニバリゼーション）
A5: ・物販客単価（全商品）は名古屋7,012円/人 → 大阪6,882円/人 と ▲1.8% でほぼ横ばい。
A6: ・同期間にLEGSは2,099円/人 → 1,455円/人 と ▲30.7%（▲643円/人）。会場全体の購買力は落ちていない。
A7: ・大阪の新商品106SKUは1,360円/人を稼いでおり、LEGSの減少分643円/人はその約47%に相当する。
A8: ・つまり新商品売上のおよそ半分は「純増」ではなく既存商品（特にLEGSとMAPPA）からの移動である。
A10: ■ ① 入場者1人あたり売上（円/人）の会場推移 供給元別
A11: 供給元 | B11: 東京 | C11: 名古屋 | D11: 博多 | E11: 大阪 | F11: 札幌 | G11: 名古屋→大阪 増減 | H11: 増減率 | I11: 評価
A12: LEGS(42SKU) | B12: 2159 | C12: 2099 | D12: 1634 | E12: 1455 | F12: 703 | G12: =E12-C12 -> -644 | H12: =IFERROR(G12/C12,"") -> -0.30681277 | I12: ★最大の被害。新商品に置き換わった
A13: ムービック | B13: 4039 | C13: 2464 | D13: 1784 | E13: 2883 | F13: 1565 | G13: =E13-C13 -> 419 | H13: =IFERROR(G13/C13,"") -> 0.1700487 | I13: 新商品投入側。大きく増加
A14: 東宝 | B14: 697 | C14: 549 | D14: 435 | E14: 1047 | F14: 674 | G14: =E14-C14 -> 498 | H14: =IFERROR(G14/C14,"") -> 0.90710383 | I14: 新商品投入側。ほぼ倍増
A15: MAPPA | B15: 0 | C15: 1656 | D15: 1292 | E15: 984 | F15: 742 | G15: =E15-C15 -> -672 | H15: =IFERROR(G15/C15,"") -> -0.4057971 | I15: LEGSと並ぶ被害。自社新商品にも食われた
A16: MBS | B16: 252 | C16: 244 | D16: 412 | E16: 512 | F16: 320 | G16: =E16-C16 -> 268 | H16: =IFERROR(G16/C16,"") -> 1.0983607 | I16: 新商品投入側。増加
A17: 書籍 | B17: 420 | C17: 0 | D17: 0 | E17: 0 | F17: 0 | G17: =E17-C17 -> 0 | H17: =IFERROR(G17/C17,"") | I17: 大阪では取扱なし
A18: 物販客単価（全商品計） | B18: 7567 | C18: 7012 | D18: 5557 | E18: 6882 | F18: 4004 | G18: =E18-C18 -> -130 | H18: =IFERROR(G18/C18,"") -> -0.018539646 | I18: 会場全体では ほぼ横ばい ＝ 市場は縮んでいない
A20: ■ ② 会場ごとの新商品投入と1人あたり売上（LEGSがいつ削られ始めたか）
A21: 会場 | B21: 新規SKU数 | C21: 新商品 売上(円/人) | D21: LEGS 売上(円/人) | E21: LEGS 前会場差 | F21: 物販客単価 (全商品) | G21: 主な新商品
A22: 東京 | B22: 332 | C22: 7567 | D22: 2159 | F22: 7567 | G22: （初回：全商品が新規）
A23: 名古屋 | B23: 85 | C23: 1480 | D23: 2099 | E23: =D23-D22 -> -60 | F23: 7012 | G23: MAPPAブラインドカード4種（フォト風カード・原画クリアカード）＝1,014円/人
A24: 博多 | B24: 19 | C24: 712 | D24: 1634 | E24: =D24-D23 -> -465 | F24: 5557 | G24: ★おすわりぬいぐるみ全8種（230円/人）、アクリルカードスタンド（233円/人）、原画ポストカードセット（178円/人）
A25: 大阪 | B25: 106 | C25: 1360 | D25: 1455 | E25: =D25-D24 -> -179 | F25: 6882 | G25: ★うちわ14種（195円/人）、アクリル系39種（450円/人）、劇場版ED系カード/ファイル（500円/人）、ぐみっとシール（101円/人）
A26: 札幌 | B26: 0 | C26: 0 | D26: 703 | E26: =D26-D25 -> -752 | F26: 4004 | G26: 新規なし（品揃えは大阪と同一）
A27: 石川 | B27: 0 | C27: 0 | D27: 639 | E27: =D27-D26 -> -64 | F27: 3713 | G27: 新規なし（品揃えは大阪と同一）
A30: ■ ③ LEGS 商品タイプ別 1人あたり売上（円/人）— どのタイプが削られたか
A31: LEGS 商品タイプ | B31: 東京 | C31: 名古屋 | D31: 博多 | E31: 大阪 | F31: 札幌 | G31: 名古屋→大阪 増減 | H31: LEGS減少への 寄与度 | I31: 競合した新商品
A32: ブラインド缶バッジ | B32: 632 | C32: 801 | D32: 722 | E32: 529 | F32: 85 | G32: =E32-C32 -> -272 | H32: =IFERROR(G32/G$39,"") -> 0.42301711 | I32: ★アクリル系39SKU（450円/人）・ぬいぐるみ全8種。同じ「引く／集める」コレクション需要が直撃
A33: ブラインドミニ色紙 | B33: 712 | C33: 662 | D33: 442 | E33: 378 | F33: 198 | G33: =E33-C33 -> -284 | H33: =IFERROR(G33/G$39,"") -> 0.44167963 | I33: ★アクリル系・劇場版EDカード類（293円/人）。ブラインド飽和＋新規コレクション商材へ移行
A34: クリアファイル | B34: 215 | C34: 117 | D34: 99 | E34: 124 | F34: 98 | G34: =E34-C34 -> 7 | H34: =IFERROR(G34/G$39,"") -> -0.01088647 | I34: 劇場版EDクリアファイル10SKU（207円/人）と競合するが、LEGS側は横ばいを維持
A35: ポストカード類 | B35: 184 | C35: 148 | D35: 104 | E35: 149 | F35: 81 | G35: =E35-C35 -> 1 | H35: =IFERROR(G35/G$39,"") -> -0.00155521 | I35: 劇場版EDポストカード/Pictas（199円/人）と競合。LEGS側は横ばい
A36: ブラインドステッカー | B36: 115 | C36: 49 | D36: 37 | E36: 52 | F36: 30 | G36: =E36-C36 -> 3 | H36: =IFERROR(G36/G$39,"") -> -0.0046656299 | I36: ぐみっとシール等9SKU（121円/人）。影響軽微
A37: 雑貨・その他 | B37: 247 | C37: 203 | D37: 161 | E37: 159 | F37: 177 | G37: =E37-C37 -> -44 | H37: =IFERROR(G37/G$39,"") -> 0.068429238 | I37: うちわ14SKU（195円/人）が近い衝動買い枠。バスボール・お菓子等が微減
A38: アクセサリー(リング等) | B38: 54 | C38: 119 | D38: 68 | E38: 65 | F38: 35 | G38: =E38-C38 -> -54 | H38: =IFERROR(G38/G$39,"") -> 0.083981337 | I38: 高単価アクセ。ぬいぐるみコンプリート(¥19,840)等の高単価枠と競合
A39: LEGS 合計 | B39: =SUM(B32:B38) -> 2159 | C39: =SUM(C32:C38) -> 2099 | D39: =SUM(D32:D38) -> 1633 | E39: =SUM(E32:E38) -> 1456 | F39: =SUM(F32:F38) -> 704 | G39: =E39-C39 -> -643 | H39: 1
A41: ■ ④ 大阪 新商品106SKU の内訳（タイプ別）
A42: 新商品タイプ | B42: SKU数 | C42: 販売数量 | D42: 販売金額(税込) | E42: 会場売上 構成比 | F42: 1人あたり 売上 | G42: 競合するLEGS商品
A43: アクリル系（コレクション） | B43: 39 | C43: 11147 | D43: 14080770 | E43: =D43/215184570 -> 0.065435779 | F43: =ROUND(D43/31267,0) -> 450 | G43: ★ブラインド缶バッジ・ブラインドミニ色紙（直接競合）
A44: カード・ポストカード類 | B44: 7 | C44: 17060 | D44: 9360615 | E44: =D44/215184570 -> 0.043500401 | F44: =ROUND(D44/31267,0) -> 299 | G44: ポストカードセット2種・メタリックポストカード
A45: クリアファイル | B45: 10 | C45: 11836 | D45: 6460410 | E45: =D45/215184570 -> 0.030022645 | F45: =ROUND(D45/31267,0) -> 207 | G45: クリアファイル14種（展示会KV・キャラ別）
A46: うちわ（新カテゴリ） | B46: 14 | C46: 5531 | D46: 6084100 | E46: =D46/215184570 -> 0.028273867 | F46: =ROUND(D46/31267,0) -> 195 | G46: 直接競合なし。ただし1,100円の衝動買い枠を奪う
A47: シール・ステッカー | B47: 9 | C47: 5528 | D47: 3778060 | E47: =D47/215184570 -> 0.0175573 | F47: =ROUND(D47/31267,0) -> 121 | G47: ブラインドダイカットステッカー2種
A48: その他新商品 | B48: 16 | C48: 1561 | D48: 1814100 | E48: =D48/215184570 -> 0.0084304372 | F48: =ROUND(D48/31267,0) -> 58 | G48: 雑貨・その他
A49: 缶バッジ | B49: 11 | C49: 1719 | D49: 945450 | E49: =D49/215184570 -> 0.00439367 | F49: =ROUND(D49/31267,0) -> 30 | G49: ★ブラインド缶バッジ2種（直接競合）
A50: 新商品 合計 | B50: =SUM(B43:B49) -> 106 | C50: =SUM(C43:C49) -> 54382 | D50: =SUM(D43:D49) -> 42523505 | E50: =D50/215184570 -> 0.1976141 | F50: =ROUND(D50/31267,0) -> 1360 | G50: うち約47%がLEGSからの移動と推定
A52: ■ ⑤ 仙台会場以降への示唆
A53: LEGS構成比は底打ちの見込み | B53: 札幌・石川は新規SKU 0で品揃えが大阪と同一。LEGS金額構成比は17.1%まで下がったが減少幅は縮小しており、仙台以降も新商品の追加が無ければこの水準で安定すると想定。③の予測はこれを採用している。
A54: ★最大のリスクは「仙台以降の新商品追加」 | B54: 大阪の実績では新商品1,360円/人の投入に対しLEGSが643円/人失われた。同規模の新商品を仙台以降に投入すると、LEGS構成比はさらに5〜7pt下がり、③の必要数86,000個は最大で30%程度過大になる。
A55: → 発注前の必須確認事項 | B55: 仙台以降に新商品（ぬいぐるみ第2弾・うちわ第2弾等）の投入計画があるか、あるなら規模はどの程度か。これを確認せずに追加生産46,000個を確定するのは危険。
A56: ブラインド系は減産、定番系は維持 | B56: ブラインド缶バッジ▲272円/人・ミニ色紙▲284円/人でLEGS減少の87%を占める一方、クリアファイル・ポストカード類はほぼ横ばい。追加生産はブラインド系を抑え、クリアファイル系を優先すべき。
A57: 高単価コレクション商材が主戦場 | B57: おすわりぬいぐるみコンプリート(¥19,840)が大阪で203個、アクリル系39SKUで450円/人。「引く」から「選んで揃える」へ需要が移行している。LEGS側もブラインド偏重の見直しが必要。

Sheet ⑧実在庫(7-8)明細
A1: ⑧ 残在庫想定（梅田まで(SET)）の明細と欠品算出
A2: 残在庫想定 ＝ 在庫フロー台帳（【清算(卸値67％)】…_検品差異）の「梅田まで(SET)」列。会場ごとの 追加発注→販売→レッグス検品 を積み上げた最終値で、梅田会場後の検品結果まで反映済み
A3: 仙台以降に使えるのは「倉庫残（札幌出荷後） ＋ 札幌会期末の残 − 石川会期18日の予測販売」。★倉庫残は2026/8/5時点のロジ（WMS）実棚を採用している（ロジ在庫データ（WMS）CZ05001／「在庫数(引当数を含む)」列）。台帳から計算した値との差は備考欄に明記した
A4: ※同ファイルの「元データ」「在庫合算」「在庫元データ(12月清算後)」シートは池袋終了時点の古いスナップショット（合計183,696個）であり、残在庫として使ってはいけない。ポストカードセット2種・宿儺の指風お菓子はSET商品で、台帳の発注数はバラ単位・実在庫はSET単位
A5: ※過不足には確定済み追加発注（宿儺の指風お菓子 1,200SET）を加算している
A6: No. | B6: JAN | C6: 商品名 | D6: 税込単価 | E6: 実在庫 池袋まで | F6: 実在庫 名古屋まで | G6: 実在庫 福岡まで | H6: ★残在庫想定 梅田まで | I6: ★ロジ在庫 (2026/8/5 実棚) | J6: 残在庫 金額(税込) | K6: 札幌へ納品 | L6: 札幌 会期末 残（実績） | M6: 販売不可 (日報未反映) | N6: 石川へ納品 (初回+転送+追納) | O6: 石川 会期18日 予測販売 | P6: 差引 倉庫残 (即出荷可) | Q6: 仙台以降 供給可能計 | R6: 仙台以降 必要数 | S6: 過不足 (供給+確定−必要) | T6: 欠品 (追加生産必要数) | U6: 推奨発注数 (安全率込) | V6: 欠品発生 会場 | W6: 最終発注期限 | X6: 発注の緊急度 | Y6: 判定 | Z6: 運営欠品報告 (受領なし) | AA6: 備考
A7: 1 | B7: 4515142545082 | C7: 呪術廻戦 メタリックポストカード 展示会キービジュアル | D7: 500 | E7: 4024 | F7: 2696 | G7: 5597 | H7: 3271 | I7: 2268 | J7: =H7*D7 -> 1635500 | K7: 1000 | L7: 493 | M7: 0 | N7: =①石川予測確定!S7 -> 693 | O7: =①石川予測確定!P7 -> 272 | P7: =IF(I7="",H7-K7,I7) -> 2268 | Q7: =P7+L7-M7-O7 -> 2489 | R7: =③仙台以降予測!M31 -> 3384 | S7: =Q7-R7 -> -895 | T7: =MAX(0,-S7) -> 895 | U7: =IF(T7>0,ROUNDUP(T7*(1+前提・入力!$B$34),0),0) -> 985 | V7: 東京凱旋 東京建物ぴあホール | W7: =DATE(2027,4,1)-30-前提・入力!$B$37 -> 46434 | X7: =IF(V7="—","—",IF(W7="再生産不可","×再生産不可",_xlfn.IFS(W7-前提・入力!$B$38<0,"★期限超過",W7-前提・入力!$B$38<=30,"★至急(30日以内)",W7-前提・入力!$B$38<=90,"要着手(90日以内)",TRUE(),"余裕あり"))) -> 余裕あり | Y7: =IF(T7>0,"★欠品：追加生産が必要",IF(S7>=R7*2,"大幅余剰","在庫で充足")) -> ★欠品：追加生産が必要 | AA7: 会場で持出・不良・ｻﾝﾌﾟﾙ 3個（名古屋2個／博多1個）。日報の販売可能数で控除済みのため供給可能在庫では二重に引いていない
A8: 2 | B8: 4515142545099 | C8: 呪術廻戦 クリアファイル 展示会キービジュアル | D8: 600 | E8: 1096 | F8: 5136 | G8: 7003 | H8: 5038 | I8: 4036 | J8: =H8*D8 -> 3022800 | K8: 1000 | L8: 459 | M8: 0 | N8: =①石川予測確定!S8 -> 659 | O8: =①石川予測確定!P8 -> 325 | P8: =IF(I8="",H8-K8,I8) -> 4036 | Q8: =P8+L8-M8-O8 -> 4170 | R8: =③仙台以降予測!M32 -> 3818 | S8: =Q8-R8 -> 352 | T8: =MAX(0,-S8) -> 0 | U8: =IF(T8>0,ROUNDUP(T8*(1+前提・入力!$B$34),0),0) -> 0 | V8: — | X8: =IF(V8="—","—",IF(W8="再生産不可","×再生産不可",_xlfn.IFS(W8-前提・入力!$B$38<0,"★期限超過",W8-前提・入力!$B$38<=30,"★至急(30日以内)",W8-前提・入力!$B$38<=90,"要着手(90日以内)",TRUE(),"余裕あり"))) -> — | Y8: =IF(T8>0,"★欠品：追加生産が必要",IF(S8>=R8*2,"大幅余剰","在庫で充足")) -> 在庫で充足 | AA8: 会場で持出・不良・ｻﾝﾌﾟﾙ 2個（東京1個／名古屋1個）。日報の販売可能数で控除済みのため供給可能在庫では二重に引いていない
A9: 3 | B9: 4515142545105 | C9: 呪術廻戦 懐玉・玉折 ポストカードセット（5枚入） | D9: 1000 | E9: 3340 | F9: 2735 | G9: 7280 | H9: 6140 | I9: 1694 | J9: =H9*D9 -> 6140000 | K9: 450 | L9: 281 | M9: 0 | N9: =①石川予測確定!S9 -> 381 | O9: =①石川予測確定!P9 -> 118 | P9: =IF(I9="",H9-K9,I9) -> 1694 | Q9: =P9+L9-M9-O9 -> 1857 | R9: =③仙台以降予測!M33 -> 1291 | S9: =Q9-R9 -> 566 | T9: =MAX(0,-S9) -> 0 | U9: =IF(T9>0,ROUNDUP(T9*(1+前提・入力!$B$34),0),0) -> 0 | V9: — | X9: =IF(V9="—","—",IF(W9="再生産不可","×再生産不可",_xlfn.IFS(W9-前提・入力!$B$38<0,"★期限超過",W9-前提・入力!$B$38<=30,"★至急(30日以内)",W9-前提・入力!$B$38<=90,"要着手(90日以内)",TRUE(),"余裕あり"))) -> — | Y9: =IF(T9>0,"★欠品：追加生産が必要",IF(S9>=R9*2,"大幅余剰","在庫で充足")) -> 在庫で充足 | AA9: SET商品（1販売単位＝5個）。台帳の発注数はバラ単位 ／ ★ロジ実棚1,694個と台帳計算5,690個が乖離。ロジ側を採用（SET/バラの単位差の可能性）
A10: 4 | B10: 4515142545112 | C10: 呪術廻戦 渋谷事変 ポストカードセット（9枚入） | D10: 1800 | E10: 3297 | F10: 2368 | G10: 28823 | H10: 27511 | I10: 2715 | J10: =H10*D10 -> 49519800 | K10: 800 | L10: 572 | M10: 0 | N10: =①石川予測確定!S10 -> 772 | O10: =①石川予測確定!P10 -> 134 | P10: =IF(I10="",H10-K10,I10) -> 2715 | Q10: =P10+L10-M10-O10 -> 3153 | R10: =③仙台以降予測!M34 -> 1591 | S10: =Q10-R10 -> 1562 | T10: =MAX(0,-S10) -> 0 | U10: =IF(T10>0,ROUNDUP(T10*(1+前提・入力!$B$34),0),0) -> 0 | V10: — | X10: =IF(V10="—","—",IF(W10="再生産不可","×再生産不可",_xlfn.IFS(W10-前提・入力!$B$38<0,"★期限超過",W10-前提・入力!$B$38<=30,"★至急(30日以内)",W10-前提・入力!$B$38<=90,"要着手(90日以内)",TRUE(),"余裕あり"))) -> — | Y10: =IF(T10>0,"★欠品：追加生産が必要",IF(S10>=R10*2,"大幅余剰","在庫で充足")) -> 在庫で充足 | AA10: SET商品（1販売単位＝9個）。台帳の発注数はバラ単位 ／ ★ロジ実棚2,715個と台帳計算26,711個が乖離。ロジ側を採用（SET/バラの単位差の可能性）
A11: 5 | B11: 4515142545129 | C11: 呪術廻戦 懐玉・玉折 ブラインド缶バッジ（全5種） | D11: 600 | E11: 5958 | F11: 11154 | G11: 49154 | H11: 40108 | I11: 31095 | J11: =H11*D11 -> 24064800 | K11: 9000 | L11: 8590 | M11: 0 | N11: =①石川予測確定!S11 -> 8790 | O11: =①石川予測確定!P11 -> 293 | P11: =IF(I11="",H11-K11,I11) -> 31095 | Q11: =P11+L11-M11-O11 -> 39392 | R11: =③仙台以降予測!M35 -> 3173 | S11: =Q11-R11 -> 36219 | T11: =MAX(0,-S11) -> 0 | U11: =IF(T11>0,ROUNDUP(T11*(1+前提・入力!$B$34),0),0) -> 0 | V11: — | X11: =IF(V11="—","—",IF(W11="再生産不可","×再生産不可",_xlfn.IFS(W11-前提・入力!$B$38<0,"★期限超過",W11-前提・入力!$B$38<=30,"★至急(30日以内)",W11-前提・入力!$B$38<=90,"要着手(90日以内)",TRUE(),"余裕あり"))) -> — | Y11: =IF(T11>0,"★欠品：追加生産が必要",IF(S11>=R11*2,"大幅余剰","在庫で充足")) -> 大幅余剰 | AA11: 会場で持出・不良・ｻﾝﾌﾟﾙ 13個（東京4個／名古屋5個／大阪4個）。日報の販売可能数で控除済みのため供給可能在庫では二重に引いていない
A12: 6 | B12: 4515142545136 | C12: 呪術廻戦 渋谷事変 ブラインド缶バッジ（全9種） | D12: 600 | E12: 12913 | F12: 19601 | G12: 70595 | H12: 51840 | I12: 37844 | J12: =H12*D12 -> 31104000 | K12: 13991 | L12: 12949 | M12: 0 | N12: =①石川予測確定!S12 -> 13249 | O12: =①石川予測確定!P12 -> 565 | P12: =IF(I12="",H12-K12,I12) -> 37844 | Q12: =P12+L12-M12-O12 -> 50228 | R12: =③仙台以降予測!M36 -> 6991 | S12: =Q12-R12 -> 43237 | T12: =MAX(0,-S12) -> 0 | U12: =IF(T12>0,ROUNDUP(T12*(1+前提・入力!$B$34),0),0) -> 0 | V12: — | X12: =IF(V12="—","—",IF(W12="再生産不可","×再生産不可",_xlfn.IFS(W12-前提・入力!$B$38<0,"★期限超過",W12-前提・入力!$B$38<=30,"★至急(30日以内)",W12-前提・入力!$B$38<=90,"要着手(90日以内)",TRUE(),"余裕あり"))) -> — | Y12: =IF(T12>0,"★欠品：追加生産が必要",IF(S12>=R12*2,"大幅余剰","在庫で充足")) -> 大幅余剰 | AA12: 会場で持出・不良・ｻﾝﾌﾟﾙ 6個（東京1個／大阪1個／札幌4個）。日報の販売可能数で控除済みのため供給可能在庫では二重に引いていない
A13: 7 | B13: 4515142545143 | C13: 呪術廻戦 懐玉・玉折 ブラインドダイカットステッカー（全5種） | D13: 600 | E13: 6467 | F13: 5943 | G13: 5543 | H13: 4601 | I13: 4251 | J13: =H13*D13 -> 2760600 | K13: 350 | L13: 163 | M13: 0 | N13: =①石川予測確定!S13 -> 463 | O13: =①石川予測確定!P13 -> 165 | P13: =IF(I13="",H13-K13,I13) -> 4251 | Q13: =P13+L13-M13-O13 -> 4249 | R13: =③仙台以降予測!M37 -> 1635 | S13: =Q13-R13 -> 2614 | T13: =MAX(0,-S13) -> 0 | U13: =IF(T13>0,ROUNDUP(T13*(1+前提・入力!$B$34),0),0) -> 0 | V13: — | X13: =IF(V13="—","—",IF(W13="再生産不可","×再生産不可",_xlfn.IFS(W13-前提・入力!$B$38<0,"★期限超過",W13-前提・入力!$B$38<=30,"★至急(30日以内)",W13-前提・入力!$B$38<=90,"要着手(90日以内)",TRUE(),"余裕あり"))) -> — | Y13: =IF(T13>0,"★欠品：追加生産が必要",IF(S13>=R13*2,"大幅余剰","在庫で充足")) -> 在庫で充足
A14: 8 | B14: 4515142545150 | C14: 呪術廻戦 渋谷事変 ブラインドダイカットステッカー（全9種） | D14: 600 | E14: 12329 | F14: 11216 | G14: 10388 | H14: 8622 | I14: 7722 | J14: =H14*D14 -> 5173200 | K14: 900 | L14: 578 | M14: 0 | N14: =①石川予測確定!S14 -> 778 | O14: =①石川予測確定!P14 -> 266 | P14: =IF(I14="",H14-K14,I14) -> 7722 | Q14: =P14+L14-M14-O14 -> 8034 | R14: =③仙台以降予測!M38 -> 2707 | S14: =Q14-R14 -> 5327 | T14: =MAX(0,-S14) -> 0 | U14: =IF(T14>0,ROUNDUP(T14*(1+前提・入力!$B$34),0),0) -> 0 | V14: — | X14: =IF(V14="—","—",IF(W14="再生産不可","×再生産不可",_xlfn.IFS(W14-前提・入力!$B$38<0,"★期限超過",W14-前提・入力!$B$38<=30,"★至急(30日以内)",W14-前提・入力!$B$38<=90,"要着手(90日以内)",TRUE(),"余裕あり"))) -> — | Y14: =IF(T14>0,"★欠品：追加生産が必要",IF(S14>=R14*2,"大幅余剰","在庫で充足")) -> 在庫で充足
A15: 9 | B15: 4515142545372 | C15: 呪術廻戦 懐玉・玉折 クリアファイル（五条 悟） | D15: 600 | E15: 10118 | F15: 9803 | G15: 9503 | H15: 8760 | I15: 8458 | J15: =H15*D15 -> 5256000 | K15: 300 | L15: 140 | M15: 0 | N15: =①石川予測確定!S15 -> 740 | O15: =①石川予測確定!P15 -> 51 | P15: =IF(I15="",H15-K15,I15) -> 8458 | Q15: =P15+L15-M15-O15 -> 8547 | R15: =③仙台以降予測!M39 -> 860 | S15: =Q15-R15 -> 7687 | T15: =MAX(0,-S15) -> 0 | U15: =IF(T15>0,ROUNDUP(T15*(1+前提・入力!$B$34),0),0) -> 0 | V15: — | X15: =IF(V15="—","—",IF(W15="再生産不可","×再生産不可",_xlfn.IFS(W15-前提・入力!$B$38<0,"★期限超過",W15-前提・入力!$B$38<=30,"★至急(30日以内)",W15-前提・入力!$B$38<=90,"要着手(90日以内)",TRUE(),"余裕あり"))) -> — | Y15: =IF(T15>0,"★欠品：追加生産が必要",IF(S15>=R15*2,"大幅余剰","在庫で充足")) -> 大幅余剰 | AA15: 会場で持出・不良・ｻﾝﾌﾟﾙ 1個（東京1個）。日報の販売可能数で控除済みのため供給可能在庫では二重に引いていない
A16: 10 | B16: 4515142545389 | C16: 呪術廻戦 懐玉・玉折 クリアファイル（夏油 傑） | D16: 600 | E16: 5476 | F16: 5334 | G16: 5212 | H16: 4934 | I16: 4835 | J16: =H16*D16 -> 2960400 | K16: 100 | L16: 41 | M16: 0 | N16: =①石川予測確定!S16 -> 541 | O16: =①石川予測確定!P16 -> 20 | P16: =IF(I16="",H16-K16,I16) -> 4835 | Q16: =P16+L16-M16-O16 -> 4856 | R16: =③仙台以降予測!M40 -> 324 | S16: =Q16-R16 -> 4532 | T16: =MAX(0,-S16) -> 0 | U16: =IF(T16>0,ROUNDUP(T16*(1+前提・入力!$B$34),0),0) -> 0 | V16: — | X16: =IF(V16="—","—",IF(W16="再生産不可","×再生産不可",_xlfn.IFS(W16-前提・入力!$B$38<0,"★期限超過",W16-前提・入力!$B$38<=30,"★至急(30日以内)",W16-前提・入力!$B$38<=90,"要着手(90日以内)",TRUE(),"余裕あり"))) -> — | Y16: =IF(T16>0,"★欠品：追加生産が必要",IF(S16>=R16*2,"大幅余剰","在庫で充足")) -> 大幅余剰 | AA16: 会場で持出・不良・ｻﾝﾌﾟﾙ 1個（東京1個）。日報の販売可能数で控除済みのため供給可能在庫では二重に引いていない
A17: 11 | B17: 4515142545396 | C17: 呪術廻戦 懐玉・玉折 クリアファイル（家入 硝子） | D17: 600 | E17: 785 | F17: 748 | G17: 718 | H17: 640 | I17: 588 | J17: =H17*D17 -> 384000 | K17: 50 | L17: 29 | M17: 0 | N17: =①石川予測確定!S17 -> 79 | O17: =①石川予測確定!P17 -> 8 | P17: =IF(I17="",H17-K17,I17) -> 588 | Q17: =P17+L17-M17-O17 -> 609 | R17: =③仙台以降予測!M41 -> 121 | S17: =Q17-R17 -> 488 | T17: =MAX(0,-S17) -> 0 | U17: =IF(T17>0,ROUNDUP(T17*(1+前提・入力!$B$34),0),0) -> 0 | V17: — | X17: =IF(V17="—","—",IF(W17="再生産不可","×再生産不可",_xlfn.IFS(W17-前提・入力!$B$38<0,"★期限超過",W17-前提・入力!$B$38<=30,"★至急(30日以内)",W17-前提・入力!$B$38<=90,"要着手(90日以内)",TRUE(),"余裕あり"))) -> — | Y17: =IF(T17>0,"★欠品：追加生産が必要",IF(S17>=R17*2,"大幅余剰","在庫で充足")) -> 大幅余剰 | AA17: 会場で持出・不良・ｻﾝﾌﾟﾙ 1個（東京1個）。日報の販売可能数で控除済みのため供給可能在庫では二重に引いていない
A18: 12 | B18: 4515142545402 | C18: 呪術廻戦 懐玉・玉折 クリアファイル（七海 建人） | D18: 600 | E18: 1209 | F18: 1149 | G18: 1095 | H18: 953 | I18: 901 | J18: =H18*D18 -> 571800 | K18: 50 | L18: 7 | M18: 0 | N18: =①石川予測確定!S18 -> 107 | O18: =①石川予測確定!P18 -> 17 | P18: =IF(I18="",H18-K18,I18) -> 901 | Q18: =P18+L18-M18-O18 -> 891 | R18: =③仙台以降予測!M42 -> 251 | S18: =Q18-R18 -> 640 | T18: =MAX(0,-S18) -> 0 | U18: =IF(T18>0,ROUNDUP(T18*(1+前提・入力!$B$34),0),0) -> 0 | V18: — | X18: =IF(V18="—","—",IF(W18="再生産不可","×再生産不可",_xlfn.IFS(W18-前提・入力!$B$38<0,"★期限超過",W18-前提・入力!$B$38<=30,"★至急(30日以内)",W18-前提・入力!$B$38<=90,"要着手(90日以内)",TRUE(),"余裕あり"))) -> — | Y18: =IF(T18>0,"★欠品：追加生産が必要",IF(S18>=R18*2,"大幅余剰","在庫で充足")) -> 大幅余剰 | AA18: 会場で持出・不良・ｻﾝﾌﾟﾙ 2個（東京1個／名古屋1個）。日報の販売可能数で控除済みのため供給可能在庫では二重に引いていない
A19: 13 | B19: 4515142545419 | C19: 呪術廻戦 懐玉・玉折 クリアファイル（灰原 雄） | D19: 600 | E19: 401 | F19: 385 | G19: 363 | H19: 320 | I19: 269 | J19: =H19*D19 -> 192000 | K19: 50 | L19: 42 | M19: 0 | N19: =①石川予測確定!S19 -> 52 | O19: =①石川予測確定!P19 -> 6 | P19: =IF(I19="",H19-K19,I19) -> 269 | Q19: =P19+L19-M19-O19 -> 305 | R19: =③仙台以降予測!M43 -> 64 | S19: =Q19-R19 -> 241 | T19: =MAX(0,-S19) -> 0 | U19: =IF(T19>0,ROUNDUP(T19*(1+前提・入力!$B$34),0),0) -> 0 | V19: — | X19: =IF(V19="—","—",IF(W19="再生産不可","×再生産不可",_xlfn.IFS(W19-前提・入力!$B$38<0,"★期限超過",W19-前提・入力!$B$38<=30,"★至急(30日以内)",W19-前提・入力!$B$38<=90,"要着手(90日以内)",TRUE(),"余裕あり"))) -> — | Y19: =IF(T19>0,"★欠品：追加生産が必要",IF(S19>=R19*2,"大幅余剰","在庫で充足")) -> 大幅余剰 | AA19: 会場で持出・不良・ｻﾝﾌﾟﾙ 1個（東京1個）。日報の販売可能数で控除済みのため供給可能在庫では二重に引いていない
A20: 14 | B20: 4515142545426 | C20: 呪術廻戦 渋谷事変 クリアファイル（虎杖 悠仁） | D20: 600 | E20: 2089 | F20: 2016 | G20: 1936 | H20: 1790 | I20: 1740 | J20: =H20*D20 -> 1074000 | K20: 50 | L20: 3 | M20: 0 | N20: =①石川予測確定!S20 -> 53 | O20: =①石川予測確定!P20 -> 14 | P20: =IF(I20="",H20-K20,I20) -> 1740 | Q20: =P20+L20-M20-O20 -> 1729 | R20: =③仙台以降予測!M44 -> 246 | S20: =Q20-R20 -> 1483 | T20: =MAX(0,-S20) -> 0 | U20: =IF(T20>0,ROUNDUP(T20*(1+前提・入力!$B$34),0),0) -> 0 | V20: — | X20: =IF(V20="—","—",IF(W20="再生産不可","×再生産不可",_xlfn.IFS(W20-前提・入力!$B$38<0,"★期限超過",W20-前提・入力!$B$38<=30,"★至急(30日以内)",W20-前提・入力!$B$38<=90,"要着手(90日以内)",TRUE(),"余裕あり"))) -> — | Y20: =IF(T20>0,"★欠品：追加生産が必要",IF(S20>=R20*2,"大幅余剰","在庫で充足")) -> 大幅余剰
A21: 15 | B21: 4515142545433 | C21: 呪術廻戦 渋谷事変 クリアファイル（伏黒 恵） | D21: 600 | E21: 2529 | F21: 2429 | G21: 2329 | H21: 2131 | I21: 2031 | J21: =H21*D21 -> 1278600 | K21: 100 | L21: 46 | M21: 0 | N21: =①石川予測確定!S21 -> 96 | O21: =①石川予測確定!P21 -> 23 | P21: =IF(I21="",H21-K21,I21) -> 2031 | Q21: =P21+L21-M21-O21 -> 2054 | R21: =③仙台以降予測!M45 -> 324 | S21: =Q21-R21 -> 1730 | T21: =MAX(0,-S21) -> 0 | U21: =IF(T21>0,ROUNDUP(T21*(1+前提・入力!$B$34),0),0) -> 0 | V21: — | X21: =IF(V21="—","—",IF(W21="再生産不可","×再生産不可",_xlfn.IFS(W21-前提・入力!$B$38<0,"★期限超過",W21-前提・入力!$B$38<=30,"★至急(30日以内)",W21-前提・入力!$B$38<=90,"要着手(90日以内)",TRUE(),"余裕あり"))) -> — | Y21: =IF(T21>0,"★欠品：追加生産が必要",IF(S21>=R21*2,"大幅余剰","在庫で充足")) -> 大幅余剰
A22: 16 | B22: 4515142545440 | C22: 呪術廻戦 渋谷事変 クリアファイル（釘崎 野薔薇） | D22: 600 | E22: 905 | F22: 867 | G22: 837 | H22: 772 | I22: 722 | J22: =H22*D22 -> 463200 | K22: 50 | L22: 28 | M22: 0 | N22: =①石川予測確定!S22 -> 78 | O22: =①石川予測確定!P22 -> 6 | P22: =IF(I22="",H22-K22,I22) -> 722 | Q22: =P22+L22-M22-O22 -> 744 | R22: =③仙台以降予測!M46 -> 112 | S22: =Q22-R22 -> 632 | T22: =MAX(0,-S22) -> 0 | U22: =IF(T22>0,ROUNDUP(T22*(1+前提・入力!$B$34),0),0) -> 0 | V22: — | X22: =IF(V22="—","—",IF(W22="再生産不可","×再生産不可",_xlfn.IFS(W22-前提・入力!$B$38<0,"★期限超過",W22-前提・入力!$B$38<=30,"★至急(30日以内)",W22-前提・入力!$B$38<=90,"要着手(90日以内)",TRUE(),"余裕あり"))) -> — | Y22: =IF(T22>0,"★欠品：追加生産が必要",IF(S22>=R22*2,"大幅余剰","在庫で充足")) -> 大幅余剰
A23: 17 | B23: 4515142545457 | C23: 呪術廻戦 渋谷事変 クリアファイル（七海 建人） | D23: 600 | E23: 3008 | F23: 2885 | G23: 2785 | H23: 2523 | I23: 2421 | J23: =H23*D23 -> 1513800 | K23: 100 | L23: 0 | M23: 0 | N23: =①石川予測確定!S23 -> 200 | O23: =①石川予測確定!P23 -> 41 | P23: =IF(I23="",H23-K23,I23) -> 2421 | Q23: =P23+L23-M23-O23 -> 2380 | R23: =③仙台以降予測!M47 -> 592 | S23: =Q23-R23 -> 1788 | T23: =MAX(0,-S23) -> 0 | U23: =IF(T23>0,ROUNDUP(T23*(1+前提・入力!$B$34),0),0) -> 0 | V23: — | X23: =IF(V23="—","—",IF(W23="再生産不可","×再生産不可",_xlfn.IFS(W23-前提・入力!$B$38<0,"★期限超過",W23-前提・入力!$B$38<=30,"★至急(30日以内)",W23-前提・入力!$B$38<=90,"要着手(90日以内)",TRUE(),"余裕あり"))) -> — | Y23: =IF(T23>0,"★欠品：追加生産が必要",IF(S23>=R23*2,"大幅余剰","在庫で充足")) -> 大幅余剰 | AA23: 会場で持出・不良・ｻﾝﾌﾟﾙ 2個（名古屋2個）。日報の販売可能数で控除済みのため供給可能在庫では二重に引いていない
A24: 18 | B24: 4515142545464 | C24: 呪術廻戦 渋谷事変 クリアファイル（五条 悟） | D24: 600 | E24: 6837 | F24: 12650 | G24: 11750 | H24: 9725 | I24: 8225 | J24: =H24*D24 -> 5835000 | K24: 1500 | L24: 1057 | M24: 0 | N24: =①石川予測確定!S24 -> 1157 | O24: =①石川予測確定!P24 -> 152 | P24: =IF(I24="",H24-K24,I24) -> 8225 | Q24: =P24+L24-M24-O24 -> 9130 | R24: =③仙台以降予測!M48 -> 2444 | S24: =Q24-R24 -> 6686 | T24: =MAX(0,-S24) -> 0 | U24: =IF(T24>0,ROUNDUP(T24*(1+前提・入力!$B$34),0),0) -> 0 | V24: — | X24: =IF(V24="—","—",IF(W24="再生産不可","×再生産不可",_xlfn.IFS(W24-前提・入力!$B$38<0,"★期限超過",W24-前提・入力!$B$38<=30,"★至急(30日以内)",W24-前提・入力!$B$38<=90,"要着手(90日以内)",TRUE(),"余裕あり"))) -> — | Y24: =IF(T24>0,"★欠品：追加生産が必要",IF(S24>=R24*2,"大幅余剰","在庫で充足")) -> 大幅余剰
A25: 19 | B25: 4515142545471 | C25: 呪術廻戦 渋谷事変 クリアファイル（夏油 傑） | D25: 600 | E25: 2332 | F25: 2305 | G25: 2285 | H25: 2240 | I25: 2190 | J25: =H25*D25 -> 1344000 | K25: 50 | L25: 29 | M25: 0 | N25: =①石川予測確定!S25 -> 129 | O25: =①石川予測確定!P25 -> 5 | P25: =IF(I25="",H25-K25,I25) -> 2190 | Q25: =P25+L25-M25-O25 -> 2214 | R25: =③仙台以降予測!M49 -> 103 | S25: =Q25-R25 -> 2111 | T25: =MAX(0,-S25) -> 0 | U25: =IF(T25>0,ROUNDUP(T25*(1+前提・入力!$B$34),0),0) -> 0 | V25: — | X25: =IF(V25="—","—",IF(W25="再生産不可","×再生産不可",_xlfn.IFS(W25-前提・入力!$B$38<0,"★期限超過",W25-前提・入力!$B$38<=30,"★至急(30日以内)",W25-前提・入力!$B$38<=90,"要着手(90日以内)",TRUE(),"余裕あり"))) -> — | Y25: =IF(T25>0,"★欠品：追加生産が必要",IF(S25>=R25*2,"大幅余剰","在庫で充足")) -> 大幅余剰
A26: 20 | B26: 4515142545488 | C26: 呪術廻戦 渋谷事変 クリアファイル（真人） | D26: 600 | E26: 382 | F26: 359 | G26: 344 | H26: 302 | I26: 271 | J26: =H26*D26 -> 181200 | K26: 30 | L26: 12 | M26: 0 | N26: =①石川予測確定!S26 -> 17 | O26: =①石川予測確定!P26 -> 7 | P26: =IF(I26="",H26-K26,I26) -> 271 | Q26: =P26+L26-M26-O26 -> 276 | R26: =③仙台以降予測!M50 -> 104 | S26: =Q26-R26 -> 172 | T26: =MAX(0,-S26) -> 0 | U26: =IF(T26>0,ROUNDUP(T26*(1+前提・入力!$B$34),0),0) -> 0 | V26: — | X26: =IF(V26="—","—",IF(W26="再生産不可","×再生産不可",_xlfn.IFS(W26-前提・入力!$B$38<0,"★期限超過",W26-前提・入力!$B$38<=30,"★至急(30日以内)",W26-前提・入力!$B$38<=90,"要着手(90日以内)",TRUE(),"余裕あり"))) -> — | Y26: =IF(T26>0,"★欠品：追加生産が必要",IF(S26>=R26*2,"大幅余剰","在庫で充足")) -> 在庫で充足 | AA26: 会場で持出・不良・ｻﾝﾌﾟﾙ 1個（名古屋1個）。日報の販売可能数で控除済みのため供給可能在庫では二重に引いていない
A27: 21 | B27: 4515142545495 | C27: 呪術廻戦 渋谷事変 クリアファイル（脹相） | D27: 600 | E27: 150 | F27: 710 | G27: 560 | H27: 308 | I27: 208 | J27: =H27*D27 -> 184800 | K27: 100 | L27: 12 | M27: 0 | N27: =①石川予測確定!S27 -> 32 | O27: =①石川予測確定!P27 -> 30 | P27: =IF(I27="",H27-K27,I27) -> 208 | Q27: =P27+L27-M27-O27 -> 190 | R27: =③仙台以降予測!M51 -> 484 | S27: =Q27-R27 -> -294 | T27: =MAX(0,-S27) -> 294 | U27: =IF(T27>0,ROUNDUP(T27*(1+前提・入力!$B$34),0),0) -> 324 | V27: 鳥取島根 夢みなとタワー | W27: =DATE(2027,3,15)-30-前提・入力!$B$37 -> 46417 | X27: =IF(V27="—","—",IF(W27="再生産不可","×再生産不可",_xlfn.IFS(W27-前提・入力!$B$38<0,"★期限超過",W27-前提・入力!$B$38<=30,"★至急(30日以内)",W27-前提・入力!$B$38<=90,"要着手(90日以内)",TRUE(),"余裕あり"))) -> 余裕あり | Y27: =IF(T27>0,"★欠品：追加生産が必要",IF(S27>=R27*2,"大幅余剰","在庫で充足")) -> ★欠品：追加生産が必要
A28: 22 | B28: 4515142545501 | C28: 呪術廻戦 渋谷事変 クリアファイル（宿儺） | D28: 600 | E28: 1681 | F28: 1582 | G28: 1502 | H28: 1331 | I28: 1281 | J28: =H28*D28 -> 798600 | K28: 50 | L28: 0 | M28: 0 | N28: =①石川予測確定!S28 -> 150 | O28: =①石川予測確定!P28 -> 27 | P28: =IF(I28="",H28-K28,I28) -> 1281 | Q28: =P28+L28-M28-O28 -> 1254 | R28: =③仙台以降予測!M52 -> 335 | S28: =Q28-R28 -> 919 | T28: =MAX(0,-S28) -> 0 | U28: =IF(T28>0,ROUNDUP(T28*(1+前提・入力!$B$34),0),0) -> 0 | V28: — | X28: =IF(V28="—","—",IF(W28="再生産不可","×再生産不可",_xlfn.IFS(W28-前提・入力!$B$38<0,"★期限超過",W28-前提・入力!$B$38<=30,"★至急(30日以内)",W28-前提・入力!$B$38<=90,"要着手(90日以内)",TRUE(),"余裕あり"))) -> — | Y28: =IF(T28>0,"★欠品：追加生産が必要",IF(S28>=R28*2,"大幅余剰","在庫で充足")) -> 大幅余剰
A29: 23 | B29: 4515142545174 | C29: 呪術廻戦 懐玉・玉折 ブラインドミニ色紙（全5種） | D29: 600 | E29: 3581 | F29: 34570 | G29: 64969 | H29: 52199 | I29: 41196 | J29: =H29*D29 -> 31319400 | K29: 11000 | L29: 8825 | M29: 0 | N29: =①石川予測確定!S29 -> 9325 | O29: =①石川予測確定!P29 -> 1292 | P29: =IF(I29="",H29-K29,I29) -> 41196 | Q29: =P29+L29-M29-O29 -> 48729 | R29: =③仙台以降予測!M53 -> 15263 | S29: =Q29-R29 -> 33466 | T29: =MAX(0,-S29) -> 0 | U29: =IF(T29>0,ROUNDUP(T29*(1+前提・入力!$B$34),0),0) -> 0 | V29: — | X29: =IF(V29="—","—",IF(W29="再生産不可","×再生産不可",_xlfn.IFS(W29-前提・入力!$B$38<0,"★期限超過",W29-前提・入力!$B$38<=30,"★至急(30日以内)",W29-前提・入力!$B$38<=90,"要着手(90日以内)",TRUE(),"余裕あり"))) -> — | Y29: =IF(T29>0,"★欠品：追加生産が必要",IF(S29>=R29*2,"大幅余剰","在庫で充足")) -> 大幅余剰 | AA29: 会場で持出・不良・ｻﾝﾌﾟﾙ 3個（大阪3個）。日報の販売可能数で控除済みのため供給可能在庫では二重に引いていない
A30: 24 | B30: 4515142545181 | C30: 呪術廻戦 渋谷事変 ブラインドミニ色紙（全5種） | D30: 600 | E30: 0 | F30: 9454 | G30: 39226 | H30: 32220 | I30: 24211 | J30: =H30*D30 -> 19332000 | K30: 8000 | L30: 6784 | M30: 0 | N30: =①石川予測確定!S30 -> 7284 | O30: =①石川予測確定!P30 -> 865 | P30: =IF(I30="",H30-K30,I30) -> 24211 | Q30: =P30+L30-M30-O30 -> 30130 | R30: =③仙台以降予測!M54 -> 9388 | S30: =Q30-R30 -> 20742 | T30: =MAX(0,-S30) -> 0 | U30: =IF(T30>0,ROUNDUP(T30*(1+前提・入力!$B$34),0),0) -> 0 | V30: — | X30: =IF(V30="—","—",IF(W30="再生産不可","×再生産不可",_xlfn.IFS(W30-前提・入力!$B$38<0,"★期限超過",W30-前提・入力!$B$38<=30,"★至急(30日以内)",W30-前提・入力!$B$38<=90,"要着手(90日以内)",TRUE(),"余裕あり"))) -> — | Y30: =IF(T30>0,"★欠品：追加生産が必要",IF(S30>=R30*2,"大幅余剰","在庫で充足")) -> 大幅余剰 | AA30: 会場で持出・不良・ｻﾝﾌﾟﾙ 9個（名古屋6個／博多1個／大阪2個）。日報の販売可能数で控除済みのため供給可能在庫では二重に引いていない
A31: 25 | B31: 4515142545198 | C31: 虚式『茈』バスボール | D31: 1500 | E31: 4137 | F31: 3916 | G31: 3748 | H31: 3505 | I31: 3305 | J31: =H31*D31 -> 5257500 | K31: 200 | L31: 146 | M31: 0 | N31: =①石川予測確定!S31 -> 176 | O31: =①石川予測確定!P31 -> 58 | P31: =IF(I31="",H31-K31,I31) -> 3305 | Q31: =P31+L31-M31-O31 -> 3393 | R31: =③仙台以降予測!M55 -> 534 | S31: =Q31-R31 -> 2859 | T31: =MAX(0,-S31) -> 0 | U31: =IF(T31>0,ROUNDUP(T31*(1+前提・入力!$B$34),0),0) -> 0 | V31: — | X31: =IF(V31="—","—",IF(W31="再生産不可","×再生産不可",_xlfn.IFS(W31-前提・入力!$B$38<0,"★期限超過",W31-前提・入力!$B$38<=30,"★至急(30日以内)",W31-前提・入力!$B$38<=90,"要着手(90日以内)",TRUE(),"余裕あり"))) -> — | Y31: =IF(T31>0,"★欠品：追加生産が必要",IF(S31>=R31*2,"大幅余剰","在庫で充足")) -> 大幅余剰
A32: 26 | B32: 4515142545204 | C32: 前髪ヘアバンド | D32: 2200 | E32: 692 | F32: 1787 | G32: 1343 | H32: 500 | I32: 299 | J32: =H32*D32 -> 1100000 | K32: 200 | L32: 0 | M32: 0 | N32: =①石川予測確定!S32 -> 50 | O32: =①石川予測確定!P32 -> 70 | P32: =IF(I32="",H32-K32,I32) -> 299 | Q32: =P32+L32-M32-O32 -> 229 | R32: =③仙台以降予測!M56 -> 1112 | S32: =Q32-R32 -> -883 | T32: =MAX(0,-S32) -> 883 | U32: =IF(T32>0,ROUNDUP(T32*(1+前提・入力!$B$34),0),0) -> 972 | V32: 神戸阪急 | W32: =DATE(2026,12,16)-75-前提・入力!$B$37 -> 46283 | X32: =IF(V32="—","—",IF(W32="再生産不可","×再生産不可",_xlfn.IFS(W32-前提・入力!$B$38<0,"★期限超過",W32-前提・入力!$B$38<=30,"★至急(30日以内)",W32-前提・入力!$B$38<=90,"要着手(90日以内)",TRUE(),"余裕あり"))) -> ★至急(30日以内) | Y32: =IF(T32>0,"★欠品：追加生産が必要",IF(S32>=R32*2,"大幅余剰","在庫で充足")) -> ★欠品：追加生産が必要 | AA32: 会場で持出・不良・ｻﾝﾌﾟﾙ 1個（東京1個）。日報の販売可能数で控除済みのため供給可能在庫では二重に引いていない
A33: 27 | B33: 4515142545211 | C33: 反転術式絆創膏 | D33: 1100 | E33: 1518 | F33: 1414 | G33: 1344 | H33: 1199 | I33: 1129 | J33: =H33*D33 -> 1318900 | K33: 70 | L33: 20 | M33: 0 | N33: =①石川予測確定!S33 -> 70 | O33: =①石川予測確定!P33 -> 18 | P33: =IF(I33="",H33-K33,I33) -> 1129 | Q33: =P33+L33-M33-O33 -> 1131 | R33: =③仙台以降予測!M57 -> 280 | S33: =Q33-R33 -> 851 | T33: =MAX(0,-S33) -> 0 | U33: =IF(T33>0,ROUNDUP(T33*(1+前提・入力!$B$34),0),0) -> 0 | V33: — | X33: =IF(V33="—","—",IF(W33="再生産不可","×再生産不可",_xlfn.IFS(W33-前提・入力!$B$38<0,"★期限超過",W33-前提・入力!$B$38<=30,"★至急(30日以内)",W33-前提・入力!$B$38<=90,"要着手(90日以内)",TRUE(),"余裕あり"))) -> — | Y33: =IF(T33>0,"★欠品：追加生産が必要",IF(S33>=R33*2,"大幅余剰","在庫で充足")) -> 大幅余剰
A34: 28 | B34: 4515142545228 | C34: 宿儺の指風お菓子 | D34: 1800 | E34: 440 | F34: 1193 | G34: 860 | H34: 460 | J34: =H34*D34 -> 828000 | K34: 300 | L34: 0 | M34: 0 | N34: =①石川予測確定!S34 -> 80 | O34: =①石川予測確定!P34 -> 92 | P34: =IF(I34="",H34-K34,I34) -> 160 | Q34: =P34+L34-M34-O34 -> 68 | R34: =③仙台以降予測!M58 -> 1589 | S34: =Q34-R34+1200 -> -321 | T34: =MAX(0,-S34) -> 321 | U34: =IF(T34>0,ROUNDUP(T34*(1+前提・入力!$B$34),0),0) -> 354 | V34: 仙台 Ebeans | W34: =DATE(2026,9,5)-90-前提・入力!$B$37 -> 46166 | X34: ◎発注確定済 | Y34: =IF(T34>0,"★欠品：追加生産が必要",IF(S34>=R34*2,"大幅余剰","在庫で充足")) -> ★欠品：追加生産が必要 | AA34: ◎追加発注 確定済 1,200SET（鳥取島根 夢みなとタワー入荷）を過不足に加算済／ミニマム1,200〜1,500SET（12,000〜15,000本） ／ 【賞味期限】賞味期限4か月以内は販売不可。現在庫は金沢(石川)会場までが販売期限。金沢は8/25時点で納品80個が完売済みのため、倉庫に残る分は販売機会が無く廃棄リスク。仙台・神戸は現在庫では供給できず、9月発注分（納品11/20〜11/25）は鳥取以降に充当する ／ SET商品（1販売単位＝10個）。台帳の発注数はバラ単位 ／ ★ロジ在庫データに無い品。倉庫残は台帳の残在庫−札幌納品で代用（要確認） ／ 会場で持出・不良・ｻﾝﾌﾟﾙ 3個（東京3個）。日報の販売可能数で控除済みのため供給可能在庫では二重に引いていない
A35: 29 | B35: 4515142545235 | C35: 脱兎！ポーチ入りクリップセット | D35: 1500 | E35: 1190 | F35: 871 | G35: 621 | H35: 421 | I35: 260 | J35: =H35*D35 -> 631500 | K35: 160 | L35: 0 | M35: 0 | N35: =①石川予測確定!S35 -> 120 | O35: =①石川予測確定!P35 -> 83 | P35: =IF(I35="",H35-K35,I35) -> 260 | Q35: =P35+L35-M35-O35 -> 177 | R35: =③仙台以降予測!M59 -> 1052 | S35: =Q35-R35 -> -875 | T35: =MAX(0,-S35) -> 875 | U35: =IF(T35>0,ROUNDUP(T35*(1+前提・入力!$B$34),0),0) -> 963 | V35: 神戸阪急 | W35: =DATE(2026,12,16)-90-前提・入力!$B$37 -> 46268 | X35: =IF(V35="—","—",IF(W35="再生産不可","×再生産不可",_xlfn.IFS(W35-前提・入力!$B$38<0,"★期限超過",W35-前提・入力!$B$38<=30,"★至急(30日以内)",W35-前提・入力!$B$38<=90,"要着手(90日以内)",TRUE(),"余裕あり"))) -> ★至急(30日以内) | Y35: =IF(T35>0,"★欠品：追加生産が必要",IF(S35>=R35*2,"大幅余剰","在庫で充足")) -> ★欠品：追加生産が必要 | AA35: 会場で持出・不良・ｻﾝﾌﾟﾙ 1個（名古屋1個）。日報の販売可能数で控除済みのため供給可能在庫では二重に引いていない
A36: 30 | B36: 4515142545242 | C36: 釘崎のポーチ風エコバッグ | D36: 3300 | E36: 1364 | F36: 1195 | G36: 1105 | H36: 900 | I36: 648 | J36: =H36*D36 -> 2970000 | K36: 250 | L36: 178 | M36: 0 | N36: =①石川予測確定!S36 -> 278 | O36: =①石川予測確定!P36 -> 45 | P36: =IF(I36="",H36-K36,I36) -> 648 | Q36: =P36+L36-M36-O36 -> 781 | R36: =③仙台以降予測!M60 -> 519 | S36: =Q36-R36 -> 262 | T36: =MAX(0,-S36) -> 0 | U36: =IF(T36>0,ROUNDUP(T36*(1+前提・入力!$B$34),0),0) -> 0 | V36: — | X36: =IF(V36="—","—",IF(W36="再生産不可","×再生産不可",_xlfn.IFS(W36-前提・入力!$B$38<0,"★期限超過",W36-前提・入力!$B$38<=30,"★至急(30日以内)",W36-前提・入力!$B$38<=90,"要着手(90日以内)",TRUE(),"余裕あり"))) -> — | Y36: =IF(T36>0,"★欠品：追加生産が必要",IF(S36>=R36*2,"大幅余剰","在庫で充足")) -> 在庫で充足 | AA36: 会場で持出・不良・ｻﾝﾌﾟﾙ 2個（東京1個／大阪1個）。日報の販売可能数で控除済みのため供給可能在庫では二重に引いていない
A37: 31 | B37: 4515142545259 | C37: 半年分の情報が書き込める手帳 | D37: 1300 | E37: 1769 | F37: 1534 | G37: 1354 | H37: 927 | I37: 727 | J37: =H37*D37 -> 1205100 | K37: 200 | L37: 99 | M37: 0 | N37: =①石川予測確定!S37 -> 249 | O37: =①石川予測確定!P37 -> 61 | P37: =IF(I37="",H37-K37,I37) -> 727 | Q37: =P37+L37-M37-O37 -> 765 | R37: =③仙台以降予測!M61 -> 715 | S37: =Q37-R37 -> 50 | T37: =MAX(0,-S37) -> 0 | U37: =IF(T37>0,ROUNDUP(T37*(1+前提・入力!$B$34),0),0) -> 0 | V37: — | X37: =IF(V37="—","—",IF(W37="再生産不可","×再生産不可",_xlfn.IFS(W37-前提・入力!$B$38<0,"★期限超過",W37-前提・入力!$B$38<=30,"★至急(30日以内)",W37-前提・入力!$B$38<=90,"要着手(90日以内)",TRUE(),"余裕あり"))) -> — | Y37: =IF(T37>0,"★欠品：追加生産が必要",IF(S37>=R37*2,"大幅余剰","在庫で充足")) -> 在庫で充足
A38: 32 | B38: 4515142545266 | C38: 気分リフレッシュオルゴール | D38: 8800 | E38: 38 | F38: 102 | G38: 73 | H38: 33 | I38: 20 | J38: =H38*D38 -> 290400 | K38: 10 | L38: 0 | M38: 0 | N38: =①石川予測確定!S38 -> 5 | O38: =①石川予測確定!P38 -> 5 | P38: =IF(I38="",H38-K38,I38) -> 20 | Q38: =P38+L38-M38-O38 -> 15 | R38: =③仙台以降予測!M62 -> 64 | S38: =Q38-R38 -> -49 | T38: =MAX(0,-S38) -> 49 | U38: =IF(T38>0,ROUNDUP(T38*(1+前提・入力!$B$34),0),0) -> 54 | V38: 神戸阪急 | W38: =DATE(2026,12,16)-90-前提・入力!$B$37 -> 46268 | X38: =IF(V38="—","—",IF(W38="再生産不可","×再生産不可",_xlfn.IFS(W38-前提・入力!$B$38<0,"★期限超過",W38-前提・入力!$B$38<=30,"★至急(30日以内)",W38-前提・入力!$B$38<=90,"要着手(90日以内)",TRUE(),"余裕あり"))) -> ★至急(30日以内) | Y38: =IF(T38>0,"★欠品：追加生産が必要",IF(S38>=R38*2,"大幅余剰","在庫で充足")) -> ★欠品：追加生産が必要 | AA38: 会場で持出・不良・ｻﾝﾌﾟﾙ 3個（名古屋2個／博多1個）。日報の販売可能数で控除済みのため供給可能在庫では二重に引いていない
A39: 33 | B39: 4515142545273 | C39: 五条 悟 イメージリング（#11） | D39: 27500 | E39: 13 | F39: 141 | G39: 127 | H39: 106 | I39: 91 | J39: =H39*D39 -> 2915000 | K39: 15 | L39: 12 | M39: 0 | N39: =①石川予測確定!S39 -> 21 | O39: =①石川予測確定!P39 -> 5 | P39: =IF(I39="",H39-K39,I39) -> 91 | Q39: =P39+L39-M39-O39 -> 98 | R39: =③仙台以降予測!M63 -> 40 | S39: =Q39-R39 -> 58 | T39: =MAX(0,-S39) -> 0 | U39: =IF(T39>0,ROUNDUP(T39*(1+前提・入力!$B$34),0),0) -> 0 | V39: — | X39: =IF(V39="—","—",IF(W39="再生産不可","×再生産不可",_xlfn.IFS(W39-前提・入力!$B$38<0,"★期限超過",W39-前提・入力!$B$38<=30,"★至急(30日以内)",W39-前提・入力!$B$38<=90,"要着手(90日以内)",TRUE(),"余裕あり"))) -> — | Y39: =IF(T39>0,"★欠品：追加生産が必要",IF(S39>=R39*2,"大幅余剰","在庫で充足")) -> 在庫で充足
A40: 34 | B40: 4515142545280 | C40: 五条 悟 イメージリング（#13） | D40: 27500 | E40: 13 | F40: 10 | G40: 7 | H40: 4 | I40: 2 | J40: =H40*D40 -> 110000 | K40: 2 | L40: 0 | M40: 0 | N40: =①石川予測確定!S40 -> 1 | O40: =①石川予測確定!P40 -> 1 | P40: =IF(I40="",H40-K40,I40) -> 2 | Q40: =P40+L40-M40-O40 -> 1 | R40: =③仙台以降予測!M64 -> 13 | S40: =Q40-R40 -> -12 | T40: =MAX(0,-S40) -> 12 | U40: =IF(T40>0,ROUNDUP(T40*(1+前提・入力!$B$34),0),0) -> 14 | V40: 仙台 Ebeans | W40: =DATE(2026,9,5)-90-前提・入力!$B$37 -> 46166 | X40: =IF(V40="—","—",IF(W40="再生産不可","×再生産不可",_xlfn.IFS(W40-前提・入力!$B$38<0,"★期限超過",W40-前提・入力!$B$38<=30,"★至急(30日以内)",W40-前提・入力!$B$38<=90,"要着手(90日以内)",TRUE(),"余裕あり"))) -> ★期限超過 | Y40: =IF(T40>0,"★欠品：追加生産が必要",IF(S40>=R40*2,"大幅余剰","在庫で充足")) -> ★欠品：追加生産が必要
A41: 35 | B41: 4515142545297 | C41: 五条 悟 イメージリング（#15） | D41: 27500 | E41: 13 | F41: 10 | G41: 7 | H41: 4 | I41: 2 | J41: =H41*D41 -> 110000 | K41: 2 | L41: 1 | M41: 0 | N41: =①石川予測確定!S41 -> 1 | O41: =①石川予測確定!P41 -> 1 | P41: =IF(I41="",H41-K41,I41) -> 2 | Q41: =P41+L41-M41-O41 -> 2 | R41: =③仙台以降予測!M65 -> 9 | S41: =Q41-R41 -> -7 | T41: =MAX(0,-S41) -> 7 | U41: =IF(T41>0,ROUNDUP(T41*(1+前提・入力!$B$34),0),0) -> 8 | V41: 鳥取島根 夢みなとタワー | W41: =DATE(2027,3,15)-90-前提・入力!$B$37 -> 46357 | X41: =IF(V41="—","—",IF(W41="再生産不可","×再生産不可",_xlfn.IFS(W41-前提・入力!$B$38<0,"★期限超過",W41-前提・入力!$B$38<=30,"★至急(30日以内)",W41-前提・入力!$B$38<=90,"要着手(90日以内)",TRUE(),"余裕あり"))) -> 余裕あり | Y41: =IF(T41>0,"★欠品：追加生産が必要",IF(S41>=R41*2,"大幅余剰","在庫で充足")) -> ★欠品：追加生産が必要
A42: 36 | B42: 4515142545303 | C42: 五条 悟 イメージリング（#17） | D42: 27500 | E42: 13 | F42: 10 | G42: 7 | H42: 4 | I42: 2 | J42: =H42*D42 -> 110000 | K42: 2 | L42: 1 | M42: 0 | N42: =①石川予測確定!S42 -> 1 | O42: =①石川予測確定!P42 -> 1 | P42: =IF(I42="",H42-K42,I42) -> 2 | Q42: =P42+L42-M42-O42 -> 2 | R42: =③仙台以降予測!M66 -> 9 | S42: =Q42-R42 -> -7 | T42: =MAX(0,-S42) -> 7 | U42: =IF(T42>0,ROUNDUP(T42*(1+前提・入力!$B$34),0),0) -> 8 | V42: 鳥取島根 夢みなとタワー | W42: =DATE(2027,3,15)-90-前提・入力!$B$37 -> 46357 | X42: =IF(V42="—","—",IF(W42="再生産不可","×再生産不可",_xlfn.IFS(W42-前提・入力!$B$38<0,"★期限超過",W42-前提・入力!$B$38<=30,"★至急(30日以内)",W42-前提・入力!$B$38<=90,"要着手(90日以内)",TRUE(),"余裕あり"))) -> 余裕あり | Y42: =IF(T42>0,"★欠品：追加生産が必要",IF(S42>=R42*2,"大幅余剰","在庫で充足")) -> ★欠品：追加生産が必要
A43: 37 | B43: 4515142545310 | C43: 夏油 傑 イメージリング（#11） | D43: 27500 | E43: 13 | F43: 81 | G43: 69 | H43: 43 | I43: 26 | J43: =H43*D43 -> 1182500 | K43: 8 | L43: 7 | M43: 0 | N43: =①石川予測確定!S43 -> 17 | O43: =①石川予測確定!P43 -> 5 | P43: =IF(I43="",H43-K43,I43) -> 26 | Q43: =P43+L43-M43-O43 -> 28 | R43: =③仙台以降予測!M67 -> 34 | S43: =Q43-R43 -> -6 | T43: =MAX(0,-S43) -> 6 | U43: =IF(T43>0,ROUNDUP(T43*(1+前提・入力!$B$34),0),0) -> 7 | V43: 東京凱旋 東京建物ぴあホール | W43: =DATE(2027,4,1)-90-前提・入力!$B$37 -> 46374 | X43: =IF(V43="—","—",IF(W43="再生産不可","×再生産不可",_xlfn.IFS(W43-前提・入力!$B$38<0,"★期限超過",W43-前提・入力!$B$38<=30,"★至急(30日以内)",W43-前提・入力!$B$38<=90,"要着手(90日以内)",TRUE(),"余裕あり"))) -> 余裕あり | Y43: =IF(T43>0,"★欠品：追加生産が必要",IF(S43>=R43*2,"大幅余剰","在庫で充足")) -> ★欠品：追加生産が必要 | AA43: ★ロジ実棚26個と台帳計算35個が乖離。ロジ側を採用（要確認） ／ 会場で持出・不良・ｻﾝﾌﾟﾙ 2個（大阪2個）。日報の販売可能数で控除済みのため供給可能在庫では二重に引いていない
A44: 38 | B44: 4515142545327 | C44: 夏油 傑 イメージリング（#13） | D44: 27500 | E44: 13 | F44: 10 | G44: 7 | H44: 4 | I44: 2 | J44: =H44*D44 -> 110000 | K44: 2 | L44: 0 | M44: 0 | N44: =①石川予測確定!S44 -> 1 | O44: =①石川予測確定!P44 -> 1 | P44: =IF(I44="",H44-K44,I44) -> 2 | Q44: =P44+L44-M44-O44 -> 1 | R44: =③仙台以降予測!M68 -> 13 | S44: =Q44-R44 -> -12 | T44: =MAX(0,-S44) -> 12 | U44: =IF(T44>0,ROUNDUP(T44*(1+前提・入力!$B$34),0),0) -> 14 | V44: 仙台 Ebeans | W44: =DATE(2026,9,5)-90-前提・入力!$B$37 -> 46166 | X44: =IF(V44="—","—",IF(W44="再生産不可","×再生産不可",_xlfn.IFS(W44-前提・入力!$B$38<0,"★期限超過",W44-前提・入力!$B$38<=30,"★至急(30日以内)",W44-前提・入力!$B$38<=90,"要着手(90日以内)",TRUE(),"余裕あり"))) -> ★期限超過 | Y44: =IF(T44>0,"★欠品：追加生産が必要",IF(S44>=R44*2,"大幅余剰","在庫で充足")) -> ★欠品：追加生産が必要
A45: 39 | B45: 4515142545334 | C45: 夏油 傑 イメージリング（#15） | D45: 27500 | E45: 13 | F45: 10 | G45: 8 | H45: 5 | I45: 2 | J45: =H45*D45 -> 137500 | K45: 2 | L45: 0 | M45: 0 | N45: =①石川予測確定!S45 -> 1 | O45: =①石川予測確定!P45 -> 2 | P45: =IF(I45="",H45-K45,I45) -> 2 | Q45: =P45+L45-M45-O45 -> 0 | R45: =③仙台以降予測!M69 -> 19 | S45: =Q45-R45 -> -19 | T45: =MAX(0,-S45) -> 19 | U45: =IF(T45>0,ROUNDUP(T45*(1+前提・入力!$B$34),0),0) -> 21 | V45: 仙台 Ebeans | W45: =DATE(2026,9,5)-90-前提・入力!$B$37 -> 46166 | X45: =IF(V45="—","—",IF(W45="再生産不可","×再生産不可",_xlfn.IFS(W45-前提・入力!$B$38<0,"★期限超過",W45-前提・入力!$B$38<=30,"★至急(30日以内)",W45-前提・入力!$B$38<=90,"要着手(90日以内)",TRUE(),"余裕あり"))) -> ★期限超過 | Y45: =IF(T45>0,"★欠品：追加生産が必要",IF(S45>=R45*2,"大幅余剰","在庫で充足")) -> ★欠品：追加生産が必要 | AA45: 会場で持出・不良・ｻﾝﾌﾟﾙ 1個（博多1個）。日報の販売可能数で控除済みのため供給可能在庫では二重に引いていない
A46: 40 | B46: 4515142545341 | C46: 夏油 傑 イメージリング（#17） | D46: 27500 | E46: 13 | F46: 10 | G46: 7 | H46: 4 | I46: 2 | J46: =H46*D46 -> 110000 | K46: 2 | L46: 2 | M46: 0 | N46: =①石川予測確定!S46 -> 3 | O46: =①石川予測確定!P46 -> 1 | P46: =IF(I46="",H46-K46,I46) -> 2 | Q46: =P46+L46-M46-O46 -> 3 | R46: =③仙台以降予測!M70 -> 7 | S46: =Q46-R46 -> -4 | T46: =MAX(0,-S46) -> 4 | U46: =IF(T46>0,ROUNDUP(T46*(1+前提・入力!$B$34),0),0) -> 5 | V46: 東京凱旋 東京建物ぴあホール | W46: =DATE(2027,4,1)-90-前提・入力!$B$37 -> 46374 | X46: =IF(V46="—","—",IF(W46="再生産不可","×再生産不可",_xlfn.IFS(W46-前提・入力!$B$38<0,"★期限超過",W46-前提・入力!$B$38<=30,"★至急(30日以内)",W46-前提・入力!$B$38<=90,"要着手(90日以内)",TRUE(),"余裕あり"))) -> 余裕あり | Y46: =IF(T46>0,"★欠品：追加生産が必要",IF(S46>=R46*2,"大幅余剰","在庫で充足")) -> ★欠品：追加生産が必要
A47: 41 | B47: 4515142545358 | C47: 虎杖 悠仁 イメージフラグメントケース | D47: 25000 | E47: 81 | F47: 76 | G47: 75 | H47: 74 | I47: 70 | J47: =H47*D47 -> 1850000 | K47: 4 | L47: 4 | M47: 0 | N47: =①石川予測確定!S47 -> 14 | O47: =①石川予測確定!P47 -> 0 | P47: =IF(I47="",H47-K47,I47) -> 70 | Q47: =P47+L47-M47-O47 -> 74 | R47: =③仙台以降予測!M71 -> 0 | S47: =Q47-R47 -> 74 | T47: =MAX(0,-S47) -> 0 | U47: =IF(T47>0,ROUNDUP(T47*(1+前提・入力!$B$34),0),0) -> 0 | V47: — | X47: =IF(V47="—","—",IF(W47="再生産不可","×再生産不可",_xlfn.IFS(W47-前提・入力!$B$38<0,"★期限超過",W47-前提・入力!$B$38<=30,"★至急(30日以内)",W47-前提・入力!$B$38<=90,"要着手(90日以内)",TRUE(),"余裕あり"))) -> — | Y47: =IF(T47>0,"★欠品：追加生産が必要",IF(S47>=R47*2,"大幅余剰","在庫で充足")) -> 大幅余剰
A48: 42 | B48: 4515142545365 | C48: 伏黒 恵 イメージフラグメントケース | D48: 25000 | E48: 69 | F48: 61 | G48: 58 | H48: 49 | I48: 43 | J48: =H48*D48 -> 1225000 | K48: 6 | L48: 5 | M48: 0 | N48: =①石川予測確定!S48 -> 15 | O48: =①石川予測確定!P48 -> 0 | P48: =IF(I48="",H48-K48,I48) -> 43 | Q48: =P48+L48-M48-O48 -> 48 | R48: =③仙台以降予測!M72 -> 3 | S48: =Q48-R48 -> 45 | T48: =MAX(0,-S48) -> 0 | U48: =IF(T48>0,ROUNDUP(T48*(1+前提・入力!$B$34),0),0) -> 0 | V48: — | X48: =IF(V48="—","—",IF(W48="再生産不可","×再生産不可",_xlfn.IFS(W48-前提・入力!$B$38<0,"★期限超過",W48-前提・入力!$B$38<=30,"★至急(30日以内)",W48-前提・入力!$B$38<=90,"要着手(90日以内)",TRUE(),"余裕あり"))) -> — | Y48: =IF(T48>0,"★欠品：追加生産が必要",IF(S48>=R48*2,"大幅余剰","在庫で充足")) -> 大幅余剰
C49: 合計（LEGS 42SKU） | E49: =SUM(E7:E48) -> 102309 | F49: =SUM(F7:F48) -> 160526 | G49: =SUM(G7:G48) -> 340617 | H49: =SUM(H7:H48) -> 276521 | I49: =SUM(I7:I48) -> 197802 | J49: =SUM(J7:J48) -> 217570900 | K49: =SUM(K7:K48) -> 50506 | L49: =SUM(L7:L48) -> 41615 | ... U49: =SUM(U7:U48) -> 3729 | X49: =COUNTIF(X7:X48,"★期限超過")&"品目が期限超過" -> 3品目が期限超過 | Y49: =COUNTIF(Y7:Y48,"★欠品：追加生産が必要")&"品目が欠品" -> 13品目が欠品 | Z49: =COUNTIF(Z7:Z48,"<>")&"品目" -> 0品目

Sheet ⑨過去5会場 予測vs実績
A1: ⑨ 過去4会場（①池袋・②名古屋・③博多阪急・④梅田阪急）商品別 販売予測 vs 実績販売・構成比の修正
A2: 販売予測＝各会場の「初12日実績 × 会期倍率g」。gはその時点で判明していた過去会場のみから算出（直近会場を2倍加重）。池袋は初回会場のため予測不能で、投入数（販売可能数）を計画値として表示
A3: 予測時構成比＝予測販売数のLEGS42SKU内シェア（池袋は投入数シェア）／実績構成比＝実績販売数のシェア／構成比修正＝実績構成比 − 予測時構成比（ポイント）
A4: 会期日数が異なるため、過去会場の累計は博多26日間の日次消化カーブで対象会場の会期日数に換算している／名古屋の販売可能数は元データに小数値が含まれるため整数に丸めている（3品目）
A6: ■ 会場別 予測精度サマリー（LEGS 42SKU 合計）
A7: 会場 | B7: 会期日数 | C7: 参照した過去会場（加重） | D7: 会期倍率g | E7: 投入数 (販売可能数) | F7: モデル 予測販売数 | G7: 実績 販売数 | H7: 予測誤差 (実績−予測) | I7: 誤差率 | J7: 商品別 絶対誤差率 | K7: 消化率 (実績/投入) | L7: 評価
A8: 東京 | B8: 25 | C8: —（初回会場） | E8: 211152 | G8: 148185 | K8: =IFERROR(G8/E8,0) -> 0.70179302 | L8: 初回会場。予測モデルの参照元が無いため投入数のみ
A9: 名古屋 | B9: 19 | C9: 東京×2 | D9: 1.211664 | E9: 83271 | F9: 57375 | G9: 58600 | H9: =G9-F9 -> 1225 | I9: =IFERROR(-H9/G9,"") -> -0.020904437 | J9: 0.05609215 | K9: =IFERROR(G9/E9,0) -> 0.70372639 | L9: 池袋のみを参照。実績が予測を上回り、やや保守的な予測だった
A10: 博多 | B10: 26 | C10: 東京×1・名古屋×2 | D10: 1.638209 | E10: 49598 | F10: 32672 | G10: 44871 | H10: =G10-F10 -> 12199 | I10: =IFERROR(-H10/G10,"") -> -0.27186824 | J10: 0.3006619 | K10: =IFERROR(G10/E10,0) -> 0.90469374 | L10: 26日間の長期会期で後半にブラインド系が伸び、予測を大きく上回った
A11: 大阪 | B11: 20 | C11: 東京×1・名古屋×1・博多×2 | D11: 1.4646201 | E11: 137560 | F11: 71187 | G11: 63740 | H11: =G11-F11 -> -7447 | I11: =IFERROR(-H11/G11,"") -> 0.11683401 | J11: 0.12947913 | K11: =IFERROR(G11/E11,0) -> 0.46336144 | L11: 博多の高い伸長率を引き継いだため予測が上振れ。新商品106SKU投入でLEGSが想定より抑制された
A12: 札幌 | B12: 20 | C12: 東京×1・名古屋×1・博多×1・大阪×2 | D12: 1.366898 | E12: 50506 | F12: 8524 | G12: 8891 | H12: =G12-F12 -> 367 | I12: =IFERROR(-H12/G12,"") -> -0.041277697 | J12: 0.10336295 | K12: =IFERROR(G12/E12,0) -> 0.17603849 | L12: 動員が計画を大きく下回り、実績が予測を下回った
A13: 4会場 合計 | E13: =SUM(E8:E12) -> 532087 | F13: =SUM(F8:F12) -> 169758 | G13: =SUM(G8:G12) -> 324287 | H13: =G13-F13 -> 154529 | I13: =IFERROR(-H13/G13,"") -> -0.47651926 | K13: =IFERROR(G13/E13,0) -> 0.60946236 | L13: 池袋は予測対象外のため、予測計・誤差は名古屋以降3会場の合計
A15: ■ 商品別 予測 vs 実績・構成比の修正
A16: No. | B16: JAN | C16: 商品名 | D16: 税込単価 | E16: 東京 投入数 | F16: 東京 予測販売数 | G16: 東京 実績販売数 | H16: 東京 予測誤差 | I16: 東京 予測時構成比 | J16: 東京 実績構成比 | K16: 東京 構成比修正 | L16: 名古屋 投入数 | M16: 名古屋 予測販売数 | N16: 名古屋 実績販売数 | O16: 名古屋 予測誤差 | P16: 名古屋 予測時構成比 | Q16: 名古屋 実績構成比 | R16: 名古屋 構成比修正 | S16: 博多 投入数 | T16: 博多 予測販売数 | U16: 博多 実績販売数 | V16: 博多 予測誤差 | W16: 博多 予測時構成比 | X16: 博多 実績構成比 | Y16: 博多 構成比修正 | Z16: 大阪 投入数 | AA16: 大阪 予測販売数 | AB16: 大阪 実績販売数 | AC16: 大阪 予測誤差 | AD16: 大阪 予測時構成比 | AE16: 大阪 実績構成比 | AF16: 大阪 構成比修正 | AG16: 札幌 投入数 | AH16: 札幌 予測販売数 | AI16: 札幌 実績販売数 | AJ16: 札幌 予測誤差 | AK16: 札幌 予測時構成比 | AL16: 札幌 実績構成比 | AM16: 札幌 構成比修正 | AN16: 4会場 実績合計 | AO16: 4会場 実績構成比 | AP16: 札幌 予測構成比 | AQ16: 仙台以降 適用構成比 | AR16: 構成比トレンド
A17: 1 | B17: 4515142545082 | C17: 呪術廻戦 メタリックポストカード 展示会キービジュアル | D17: 500 | E17: 6000 | F17: — | G17: 4965 | H17: — | I17: =IFERROR(E17/E$59,0) -> 0.028415549 | J17: =IFERROR(G17/G$59,0) -> 0.033505416 | K17: =J17-I17 -> 0.0050898665 | L17: 1998 | M17: 1047 | N17: 1316 | O17: =N17-M17 -> 269 | P17: =IFERROR(M17/M$59,0) -> 0.018248366 | Q17: =IFERROR(N17/N$59,0) -> 0.022457338 | R17: =Q17-P17 -> 0.0042089719 | S17: 1099 | T17: 1163 | U17: 1092 | V17: =U17-T17 -> -71 | W17: =IFERROR(T17/T$59,0) -> 0.035596229 | X17: =IFERROR(U17/U$59,0) -> 0.024336431 | Y17: =X17-W17 -> -0.011259798 | Z17: 3000 | AA17: 2184 | AB17: 2325 | AC17: =AB17-AA17 -> 141 | AD17: =IFERROR(AA17/AA$59,0) -> 0.030679759 | AE17: =IFERROR(AB17/AB$59,0) -> 0.03647631 | AF17: =AE17-AD17 -> 0.0057965511 | AG17: 1000 | AH17: 443 | AI17: 507 | AJ17: =AI17-AH17 -> 64 | AK17: =IFERROR(AH17/AH$59,0) -> 0.051970906 | AL17: =IFERROR(AI17/AI$59,0) -> 0.057023957 | AM17: =AL17-AK17 -> 0.0050530511 | AN17: =G17+N17+U17+AB17 -> 9698 | AO17: =IFERROR(AN17/AN$59,0) -> 0.030748646 | AP17: =①石川予測確定!R7 -> 0.052805281 | AQ17: =③仙台以降予測!H31 -> 0.054914619 | AR17: =IF(AQ17-AO17>=0.005,"↑ 上方修正",IF(AQ17-AO17<=-0.005,"↓ 下方修正","→ 据置")) -> ↑ 上方修正
A18: 2 | B18: 4515142545099 | C18: 呪術廻戦 クリアファイル 展示会キービジュアル | D18: 600 | E18: 5699 | F18: — | G18: 4902 | H18: — | I18: =IFERROR(E18/E$59,0) -> 0.026990036 | J18: =IFERROR(G18/G$59,0) -> 0.033080271 | K18: =J18-I18 -> 0.0060902357 | L18: 1999 | M18: 1379 | N18: 1466 | O18: =N18-M18 -> 87 | P18: =IFERROR(M18/M$59,0) -> 0.024034858 | Q18: =IFERROR(N18/N$59,0) -> 0.025017065 | R18: =Q18-P18 -> 0.00098220646 | S18: 1200 | T18: 1148 | U18: 1132 | V18: =U18-T18 -> -16 | W18: =IFERROR(T18/T$59,0) -> 0.03513712 | X18: =IFERROR(U18/U$59,0) -> 0.025227875 | Y18: =X18-W18 -> -0.009909245 | Z18: 3000 | AA18: 2028 | AB18: 1965 | AC18: =AB18-AA18 -> -63 | AD18: =IFERROR(AA18/AA$59,0) -> 0.028488348 | AE18: =IFERROR(AB18/AB$59,0) -> 0.030828365 | AF18: =AE18-AD18 -> 0.0023400176 | AG18: 1000 | AH18: 482 | AI18: 541 | AJ18: =AI18-AH18 -> 59 | AK18: =IFERROR(AH18/AH$59,0) -> 0.056546222 | AL18: =IFERROR(AI18/AI$59,0) -> 0.060848049 | AM18: =AL18-AK18 -> 0.0043018262 | AN18: =G18+N18+U18+AB18 -> 9465 | AO18: =IFERROR(AN18/AN$59,0) -> 0.030009892 | AP18: =①石川予測確定!R8 -> 0.063094545 | AQ18: =③仙台以降予測!H32 -> 0.061971297 | AR18: =IF(AQ18-AO18>=0.005,"↑ 上方修正",IF(AQ18-AO18<=-0.005,"↓ 下方修正","→ 据置")) -> ↑ 上方修正
A19: 3 | B19: 4515142545105 | C19: 呪術廻戦 懐玉・玉折 ポストカードセット（5枚入） | D19: 1000 | E19: 3700 | F19: — | G19: 2956 | H19: — | I19: =IFERROR(E19/E$59,0) -> 0.017522922 | J19: =IFERROR(G19/G$59,0) -> 0.019948038 | K19: =J19-I19 -> 0.002425116 | L19: 1200 | M19: 584 | N19: 601 | O19: =N19-M19 -> 17 | P19: =IFERROR(M19/M$59,0) -> 0.010178649 | Q19: =IFERROR(N19/N$59,0) -> 0.010255973 | R19: =Q19-P19 -> 7.7323459e-05 | S19: 500 | T19: 440 | U19: 454 | V19: =U19-T19 -> 14 | W19: =IFERROR(T19/T$59,0) -> 0.013467189 | X19: =IFERROR(U19/U$59,0) -> 0.010117894 | Y19: =X19-W19 -> -0.0033492955 | Z19: 2000 | AA19: 1164 | AB19: 1132 | AC19: =AB19-AA19 -> -32 | AD19: =IFERROR(AA19/AA$59,0) -> 0.0163513 | AE19: =IFERROR(AB19/AB$59,0) -> 0.017759649 | AF19: =AE19-AD19 -> 0.0014083485 | AG19: 450 | AH19: 146 | AI19: 169 | AJ19: =AI19-AH19 -> 23 | AK19: =IFERROR(AH19/AH$59,0) -> 0.017128109 | AL19: =IFERROR(AI19/AI$59,0) -> 0.019007986 | AM19: =AL19-AK19 -> 0.0018798767 | AN19: =G19+N19+U19+AB19 -> 5143 | AO19: =IFERROR(AN19/AN$59,0) -> 0.016306485 | AP19: =①石川予測確定!R9 -> 0.022908173 | AQ19: =③仙台以降予測!H33 -> 0.020958079 | AR19: =IF(AQ19-AO19>=0.005,"↑ 上方修正",IF(AQ19-AO19<=-0.005,"↓ 下方修正","→ 据置")) -> → 据置
A20: 4 | B20: 4515142545112 | C20: 呪術廻戦 渋谷事変 ポストカードセット（9枚入） | D20: 1800 | E20: 2620 | F20: — | G20: 1819 | H20: — | I20: =IFERROR(E20/E$59,0) -> 0.012408123 | J20: =IFERROR(G20/G$59,0) -> 0.012275197 | K20: =J20-I20 -> -0.00013292651 | L20: 1330 | M20: 784 | N20: 922 | O20: =N20-M20 -> 138 | P20: =IFERROR(M20/M$59,0) -> 0.013664488 | Q20: =IFERROR(N20/N$59,0) -> 0.015733788 | R20: =Q20-P20 -> 0.0020693004 | S20: 800 | T20: 589 | U20: 539 | V20: =U20-T20 -> -50 | W20: =IFERROR(T20/T$59,0) -> 0.018027669 | X20: =IFERROR(U20/U$59,0) -> 0.012012213 | Y20: =X20-W20 -> -0.0060154562 | Z20: 2000 | AA20: 1202 | AB20: 1310 | AC20: =AB20-AA20 -> 108 | AD20: =IFERROR(AA20/AA$59,0) -> 0.016885105 | AE20: =IFERROR(AB20/AB$59,0) -> 0.020552243 | AF20: =AE20-AD20 -> 0.0036671381 | AG20: 800 | AH20: 207 | AI20: 228 | AJ20: =AI20-AH20 -> 21 | AK20: =IFERROR(AH20/AH$59,0) -> 0.024284374 | AL20: =IFERROR(AI20/AI$59,0) -> 0.02564391 | AM20: =AL20-AK20 -> 0.001359536 | AN20: =G20+N20+U20+AB20 -> 4590 | AO20: =IFERROR(AN20/AN$59,0) -> 0.014553133 | AP20: =①石川予測確定!R10 -> 0.026014366 | AQ20: =③仙台以降予測!H34 -> 0.025829138 | AR20: =IF(AQ20-AO20>=0.005,"↑ 上方修正",IF(AQ20-AO20<=-0.005,"↓ 下方修正","→ 据置")) -> ↑ 上方修正
A21: 5 | B21: 4515142545129 | C21: 呪術廻戦 懐玉・玉折 ブラインド缶バッジ（全5種） | D21: 600 | E21: 24996 | F21: — | G21: 18759 | H21: — | I21: =IFERROR(E21/E$59,0) -> 0.11837918 | J21: =IFERROR(G21/G$59,0) -> 0.12659176 | K21: =J21-I21 -> 0.0082125832 | L21: 16500 | M21: 10536 | N21: 10777 | O21: =N21-M21 -> 241 | P21: =IFERROR(M21/M$59,0) -> 0.18363399 | Q21: =IFERROR(N21/N$59,0) -> 0.18390785 | R21: =Q21-P21 -> 0.0002738629 | S21: 9000 | T21: 5395 | U21: 8991 | V21: =U21-T21 -> 3596 | W21: =IFERROR(T21/T$59,0) -> 0.1651261 | X21: =IFERROR(U21/U$59,0) -> 0.20037441 | Y21: =X21-W21 -> 0.035248305 | Z21: 24996 | AA21: 12132 | AB21: 8936 | AC21: =AB21-AA21 -> -3196 | AD21: =IFERROR(AA21/AA$59,0) -> 0.17042438 | AE21: =IFERROR(AB21/AB$59,0) -> 0.14019454 | AF21: =AE21-AD21 -> -0.030229835 | AG21: 9000 | AH21: 459 | AI21: 410 | AJ21: =AI21-AH21 -> -49 | AK21: =IFERROR(AH21/AH$59,0) -> 0.053847959 | AL21: =IFERROR(AI21/AI$59,0) -> 0.046114048 | AM21: =AL21-AK21 -> -0.0077339108 | AN21: =G21+N21+U21+AB21 -> 47463 | AO21: =IFERROR(AN21/AN$59,0) -> 0.15048701 | AP21: =①石川予測確定!R11 -> 0.056882159 | AQ21: =③仙台以降予測!H35 -> 0.051498103 | AR21: =IF(AQ21-AO21>=0.005,"↑ 上方修正",IF(AQ21-AO21<=-0.005,"↓ 下方修正","→ 据置")) -> ↓ 下方修正
A22: 6 | B22: 4515142545136 | C22: 呪術廻戦 渋谷事変 ブラインド缶バッジ（全9種） | D22: 600 | E22: 44999 | F22: — | G22: 31070 | H22: — | I22: =IFERROR(E22/E$59,0) -> 0.21311188 | J22: =IFERROR(G22/G$59,0) -> 0.20967034 | K22: =J22-I22 -> -0.003441537 | L22: 21439 | M22: 15402 | N22: 15602 | O22: =N22-M22 -> 200 | P22: =IFERROR(M22/M$59,0) -> 0.26844444 | Q22: =IFERROR(N22/N$59,0) -> 0.26624573 | R22: =Q22-P22 -> -0.0021987107 | S22: 13986 | T22: 7036 | U22: 13877 | V22: =U22-T22 -> 6841 | W22: =IFERROR(T22/T$59,0) -> 0.2153526 | X22: =IFERROR(U22/U$59,0) -> 0.30926434 | Y22: =X22-W22 -> 0.09391174 | Z22: 35999 | AA22: 21195 | AB22: 18611 | AC22: =AB22-AA22 -> -2584 | AD22: =IFERROR(AA22/AA$59,0) -> 0.29773695 | AE22: =IFERROR(AB22/AB$59,0) -> 0.29198306 | AF22: =AE22-AD22 -> -0.0057538902 | AG22: 13991 | AH22: 1268 | AI22: 1042 | AJ22: =AI22-AH22 -> -226 | AK22: =IFERROR(AH22/AH$59,0) -> 0.14875645 | AL22: =IFERROR(AI22/AI$59,0) -> 0.11719717 | AM22: =AL22-AK22 -> -0.031559287 | AN22: =G22+N22+U22+AB22 -> 79160 | AO22: =IFERROR(AN22/AN$59,0) -> 0.25098606 | AP22: =①石川予測確定!R12 -> 0.10968744 | AQ22: =③仙台以降予測!H36 -> 0.1134423 | AR22: =IF(AQ22-AO22>=0.005,"↑ 上方修正",IF(AQ22-AO22<=-0.005,"↓ 下方修正","→ 据置")) -> ↓ 下方修正
A23: 7 | B23: 4515142545143 | C23: 呪術廻戦 懐玉・玉折 ブラインドダイカットステッカー（全5種） | D23: 600 | E23: 7000 | F23: — | G23: 3471 | H23: — | I23: =IFERROR(E23/E$59,0) -> 0.033151474 | J23: =IFERROR(G23/G$59,0) -> 0.023423423 | K23: =J23-I23 -> -0.0097280504 | L23: 1390 | M23: 548 | N23: 520 | O23: =N23-M23 -> -28 | P23: =IFERROR(M23/M$59,0) -> 0.0095511983 | Q23: =IFERROR(N23/N$59,0) -> 0.0088737201 | R23: =Q23-P23 -> -0.00067747812 | S23: 400 | T23: 436 | U23: 384 | V23: =U23-T23 -> -52 | W23: =IFERROR(T23/T$59,0) -> 0.01334476 | X23: =IFERROR(U23/U$59,0) -> 0.0085578659 | Y23: =X23-W23 -> -0.0047868942 | Z23: 2000 | AA23: 1048 | AB23: 940 | AC23: =AB23-AA23 -> -108 | AD23: =IFERROR(AA23/AA$59,0) -> 0.014721789 | AE23: =IFERROR(AB23/AB$59,0) -> 0.014747411 | AF23: =AE23-AD23 -> 2.5622268e-05 | AG23: 350 | AH23: 185 | AI23: 187 | AJ23: =AI23-AH23 -> 2 | AK23: =IFERROR(AH23/AH$59,0) -> 0.021703426 | AL23: =IFERROR(AI23/AI$59,0) -> 0.021032505 | AM23: =AL23-AK23 -> -0.00067092084 | AN23: =G23+N23+U23+AB23 -> 5315 | AO23: =IFERROR(AN23/AN$59,0) -> 0.016851831 | AP23: =①石川予測確定!R13 -> 0.032032615 | AQ23: =③仙台以降予測!H37 -> 0.02653256 | AR23: =IF(AQ23-AO23>=0.005,"↑ 上方修正",IF(AQ23-AO23<=-0.005,"↓ 下方修正","→ 据置")) -> ↑ 上方修正
A24: 8 | B24: 4515142545150 | C24: 呪術廻戦 渋谷事変 ブラインドダイカットステッカー（全9種） | D24: 600 | E24: 12600 | F24: — | G24: 5596 | H24: — | I24: =IFERROR(E24/E$59,0) -> 0.059672653 | J24: =IFERROR(G24/G$59,0) -> 0.037763606 | K24: =J24-I24 -> -0.021909047 | L24: 2240 | M24: 1141 | N24: 1107 | O24: =N24-M24 -> -34 | P24: =IFERROR(M24/M$59,0) -> 0.01988671 | Q24: =IFERROR(N24/N$59,0) -> 0.018890785 | R24: =Q24-P24 -> -0.00099592526 | S24: 840 | T24: 785 | U24: 799 | V24: =U24-T24 -> 14 | W24: =IFERROR(T24/T$59,0) -> 0.02402669 | X24: =IFERROR(U24/U$59,0) -> 0.017806601 | Y24: =X24-W24 -> -0.0062200884 | Z24: 3000 | AA24: 1937 | AB24: 1758 | AC24: =AB24-AA24 -> -179 | AD24: =IFERROR(AA24/AA$59,0) -> 0.027210024 | AE24: =IFERROR(AB24/AB$59,0) -> 0.027580797 | AF24: =AE24-AD24 -> 0.00037077269 | AG24: 900 | AH24: 298 | AI24: 322 | AJ24: =AI24-AH24 -> 24 | AK24: =IFERROR(AH24/AH$59,0) -> 0.034960113 | AL24: =IFERROR(AI24/AI$59,0) -> 0.036216399 | AM24: =AL24-AK24 -> 0.001256286 | AN24: =G24+N24+U24+AB24 -> 9260 | AO24: =IFERROR(AN24/AN$59,0) -> 0.029359916 | AP24: =①石川予測確定!R14 -> 0.051640458 | AQ24: =③仙台以降予測!H38 -> 0.043928428 | AR24: =IF(AQ24-AO24>=0.005,"↑ 上方修正",IF(AQ24-AO24<=-0.005,"↓ 下方修正","→ 据置")) -> ↑ 上方修正
A25: 9 | B25: 4515142545372 | C25: 呪術廻戦 懐玉・玉折 クリアファイル（五条 悟） | D25: 600 | E25: 8749 | F25: — | G25: 2381 | H25: — | I25: =IFERROR(E25/E$59,0) -> 0.041434606 | J25: =IFERROR(G25/G$59,0) -> 0.016067753 | K25: =J25-I25 -> -0.025366853 | L25: 950 | M25: 347 | N25: 313 | O25: =N25-M25 -> -34 | P25: =IFERROR(M25/M$59,0) -> 0.0060479303 | Q25: =IFERROR(N25/N$59,0) -> 0.0053412969 | R25: =Q25-P25 -> -0.00070663335 | S25: 300 | T25: 357 | U25: 301 | V25: =U25-T25 -> -56 | W25: =IFERROR(T25/T$59,0) -> 0.010926787 | X25: =IFERROR(U25/U$59,0) -> 0.0067081188 | Y25: =X25-W25 -> -0.0042186686 | Z25: 1500 | AA25: 761 | AB25: 743 | AC25: =AB25-AA25 -> -18 | AD25: =IFERROR(AA25/AA$59,0) -> 0.010690154 | AE25: =IFERROR(AB25/AB$59,0) -> 0.01165673 | AF25: =AE25-AD25 -> 0.00096657637 | AG25: 300 | AH25: 131 | AI25: 160 | AJ25: =AI25-AH25 -> 29 | AK25: =IFERROR(AH25/AH$59,0) -> 0.015368372 | AL25: =IFERROR(AI25/AI$59,0) -> 0.017995726 | AM25: =AL25-AK25 -> 0.0026273544 | AN25: =G25+N25+U25+AB25 -> 3738 | AO25: =IFERROR(AN25/AN$59,0) -> 0.011851767 | AP25: =①石川予測確定!R15 -> 0.0099009901 | AQ25: =③仙台以降予測!H39 -> 0.013948358 | AR25: =IF(AQ25-AO25>=0.005,"↑ 上方修正",IF(AQ25-AO25<=-0.005,"↓ 下方修正","→ 据置")) -> → 据置
A26: 10 | B26: 4515142545389 | C26: 呪術廻戦 懐玉・玉折 クリアファイル（夏油 傑） | D26: 600 | E26: 4549 | F26: — | G26: 1025 | H26: — | I26: =IFERROR(E26/E$59,0) -> 0.021543722 | J26: =IFERROR(G26/G$59,0) -> 0.0069170294 | K26: =J26-I26 -> -0.014626693 | L26: 410 | M26: 145 | N26: 141 | O26: =N26-M26 -> -4 | P26: =IFERROR(M26/M$59,0) -> 0.0025272331 | Q26: =IFERROR(N26/N$59,0) -> 0.0024061433 | R26: =Q26-P26 -> -0.00012108977 | S26: 180 | T26: 159 | U26: 123 | V26: =U26-T26 -> -36 | W26: =IFERROR(T26/T$59,0) -> 0.0048665524 | X26: =IFERROR(U26/U$59,0) -> 0.0027411914 | Y26: =X26-W26 -> -0.002125361 | Z26: 500 | AA26: 275 | AB26: 277 | AC26: =AB26-AA26 -> 2 | AD26: =IFERROR(AA26/AA$59,0) -> 0.0038630649 | AE26: =IFERROR(AB26/AB$59,0) -> 0.0043457797 | AF26: =AE26-AD26 -> 0.00048271484 | AG26: 100 | AH26: 49 | AI26: 59 | AJ26: =AI26-AH26 -> 10 | AK26: =IFERROR(AH26/AH$59,0) -> 0.0057484749 | AL26: =IFERROR(AI26/AI$59,0) -> 0.006635924 | AM26: =AL26-AK26 -> 0.00088744907 | AN26: =G26+N26+U26+AB26 -> 1566 | AO26: =IFERROR(AN26/AN$59,0) -> 0.0049651866 | AP26: =①石川予測確定!R16 -> 0.0038827412 | AQ26: =③仙台以降予測!H40 -> 0.0052593326 | AR26: =IF(AQ26-AO26>=0.005,"↑ 上方修正",IF(AQ26-AO26<=-0.005,"↓ 下方修正","→ 据置")) -> → 据置
A27: 11 | B27: 4515142545396 | C27: 呪術廻戦 懐玉・玉折 クリアファイル（家入 硝子） | D27: 600 | E27: 699 | F27: — | G27: 215 | H27: — | I27: =IFERROR(E27/E$59,0) -> 0.0033104115 | J27: =IFERROR(G27/G$59,0) -> 0.0014508891 | K27: =J27-I27 -> -0.0018595224 | L27: 90 | M27: 32 | N27: 37 | O27: =N27-M27 -> 5 | P27: =IFERROR(M27/M$59,0) -> 0.0005577342 | Q27: =IFERROR(N27/N$59,0) -> 0.00063139932 | R27: =Q27-P27 -> 7.3665113e-05 | S27: 30 | T27: 68 | U27: 30 | V27: =U27-T27 -> -38 | W27: =IFERROR(T27/T$59,0) -> 0.0020812929 | X27: =IFERROR(U27/U$59,0) -> 0.00066858327 | Y27: =X27-W27 -> -0.0014127096 | Z27: 100 | AA27: 81 | AB27: 78 | AC27: =AB27-AA27 -> -3 | AD27: =IFERROR(AA27/AA$59,0) -> 0.0011378482 | AE27: =IFERROR(AB27/AB$59,0) -> 0.0012237214 | AF27: =AE27-AD27 -> 8.5873165e-05 | AG27: 50 | AH27: 17 | AI27: 21 | AJ27: =AI27-AH27 -> 4 | AK27: =IFERROR(AH27/AH$59,0) -> 0.0019943688 | AL27: =IFERROR(AI27/AI$59,0) -> 0.002361939 | AM27: =AL27-AK27 -> 0.0003675702 | AN27: =G27+N27+U27+AB27 -> 360 | AO27: =IFERROR(AN27/AN$59,0) -> 0.0011414222 | AP27: =①石川予測確定!R17 -> 0.0015530965 | AQ27: =③仙台以降予測!H41 -> 0.0019575178 | AR27: =IF(AQ27-AO27>=0.005,"↑ 上方修正",IF(AQ27-AO27<=-0.005,"↓ 下方修正","→ 据置")) -> → 据置
A28: 12 | B28: 4515142545402 | C28: 呪術廻戦 懐玉・玉折 クリアファイル（七海 建人） | D28: 600 | E28: 1049 | F28: — | G28: 291 | H28: — | I28: =IFERROR(E28/E$59,0) -> 0.0049679851 | J28: =IFERROR(G28/G$59,0) -> 0.0019637615 | K28: =J28-I28 -> -0.0030042236 | L28: 119 | M28: 64 | N28: 58 | O28: =N28-M28 -> -6 | P28: =IFERROR(M28/M$59,0) -> 0.0011154684 | Q28: =IFERROR(N28/N$59,0) -> 0.00098976109 | R28: =Q28-P28 -> -0.00012570732 | S28: 80 | T28: 51 | U28: 54 | V28: =U28-T28 -> 3 | W28: =IFERROR(T28/T$59,0) -> 0.0015609696 | X28: =IFERROR(U28/U$59,0) -> 0.0012034499 | Y28: =X28-W28 -> -0.00035751975 | Z28: 150 | AA28: 140 | AB28: 142 | AC28: =AB28-AA28 -> 2 | AD28: =IFERROR(AA28/AA$59,0) -> 0.0019666512 | AE28: =IFERROR(AB28/AB$59,0) -> 0.0022278004 | AF28: =AE28-AD28 -> 0.00026114922 | AG28: 50 | AH28: 35 | AI28: 43 | AJ28: =AI28-AH28 -> 8 | AK28: =IFERROR(AH28/AH$59,0) -> 0.0041060535 | AL28: =IFERROR(AI28/AI$59,0) -> 0.0048363514 | AM28: =AL28-AK28 -> 0.00073029787 | AN28: =G28+N28+U28+AB28 -> 545 | AO28: =IFERROR(AN28/AN$59,0) -> 0.0017279864 | AP28: =①石川予測確定!R18 -> 0.00330033 | AQ28: =③仙台以降予測!H42 -> 0.0040683407 | AR28: =IF(AQ28-AO28>=0.005,"↑ 上方修正",IF(AQ28-AO28<=-0.005,"↓ 下方修正","→ 据置")) -> → 据置
... A58: 42 | B58: 4515142545365 | C58: 伏黒 恵 イメージフラグメントケース | D58: 25000 | E58: 38 | F58: — | G58: 24 | H58: — | I58: =IFERROR(E58/E$59,0) -> 0.00017996514 | J58: =IFERROR(G58/G$59,0) -> 0.00016195971 | K58: =J58-I58 -> -1.8005431e-05 | L58: 10 | M58: 8 | N58: 8 | O58: =N58-M58 -> 0 | P58: =IFERROR(M58/M$59,0) -> 0.00013943355 | Q58: =IFERROR(N58/N$59,0) -> 0.00013651877 | R58: =Q58-P58 -> -2.9147799e-06 | S58: 5 | T58: 3 | U58: 3 | V58: =U58-T58 -> 0 | W58: =IFERROR(T58/T$59,0) -> 9.1821743e-05 | X58: =IFERROR(U58/U$59,0) -> 6.6858327e-05 | Y58: =X58-W58 -> -2.4963416e-05 | Z58: 20 | AA58: 5 | AB58: 8 | AC58: =AB58-AA58 -> 3 | AD58: =IFERROR(AA58/AA$59,0) -> 7.0237543e-05 | AE58: =IFERROR(AB58/AB$59,0) -> 0.00012550988 | AF58: =AE58-AD58 -> 5.5272341e-05 | AG58: 6 | AH58: 1 | AI58: 1 | AJ58: =AI58-AH58 -> 0 | AK58: =IFERROR(AH58/AH$59,0) -> 0.00011731581 | AL58: =IFERROR(AI58/AI$59,0) -> 0.00011247329 | AM58: =AL58-AK58 -> -4.8425266e-06 | AN58: =G58+N58+U58+AB58 -> 43 | AO58: =IFERROR(AN58/AN$59,0) -> 0.00013633654 | AP58: =①石川予測確定!R48 -> 0 | AQ58: =③仙台以降予測!H72 -> 5.6236644e-05 | AR58: =IF(AQ58-AO58>=0.005,"↑ 上方修正",IF(AQ58-AO58<=-0.005,"↓ 下方修正","→ 据置")) -> → 据置
C59: 合計（LEGS 42SKU） | E59: =SUM(E17:E58) -> 211152 | G59: =SUM(G17:G58) -> 148185 | I59: 1 | J59: 1 | K59: 0 | L59: =SUM(L17:L58) -> 83271 | M59: =SUM(M17:M58) -> 57375 | N59: =SUM(N17:N58) -> 58600 | O59: =SUM(O17:O58) -> 1225 | P59: 1 | Q59: 1 | R59: 0 | S59: =SUM(S17:S58) -> 49598 | T59: =SUM(T17:T58) -> 32672 | U59: =SUM(U17:U58) -> 44871 | V59: =SUM(V17:V58) -> 12199 | W59: 1 | X59: 1 | Y59: 0 | Z59: =SUM(Z17:Z58) -> 137560 | AA59: =SUM(AA17:AA58) -> 71187 | AB59: =SUM(AB17:AB58) -> 63740 | AC59: =SUM(AC17:AC58) -> -7447 | AD59: 1 | AE59: 1 | AF59: 0 | AG59: =SUM(AG17:AG58) -> 50506 | AH59: =SUM(AH17:AH58) -> 8524 | AI59: =SUM(AI17:AI58) -> 8891 | AJ59: =SUM(AJ17:AJ58) -> 367 | AK59: 1 | AL59: 1 | AM59: 0 | AN59: =SUM(AN17:AN58) -> 315396 | AO59: 1 | AP59: 1 | AQ59: 1
A61: ■ 構成比修正の考え方と次会場への反映
A62: 予測時構成比 | B62: 各会場の会期前〜初12日時点で、過去会場の実績から見込んでいた商品別シェア。池袋のみ実績データが無いため投入数（販売可能数）のシェアを計画値として採用している。
A63: 実績構成比 | B63: 各会場の会期全体の実績販売数に基づく商品別シェア。
A64: 構成比修正 | B64: 実績構成比 − 予測時構成比（ポイント）。プラスは想定より売れた＝次会場で構成比を引き上げるべき商品。
A65: 仙台以降 適用構成比 | B65: 札幌20日実績のシェア50% ＋ 石川18日予測のシェア50% のブレンド（③シートで算出）。直近2会場は品揃えが同一のため、この2会場に絞って重み付けしている。
A66: モデル精度の読み方 | B66: 3会場の絶対誤差率は10〜27%。ブラインド系など会期後半に伸びる商品ほど予測が下振れしやすく、
B67: 定番のクリアファイル・ポストカード系は誤差が小さい。発注量は絶対誤差率を織り込んだ安全率で調整すること。

Sheet ⑩会場比率シナリオ比較
A1: ⑩ 仙台会場以降の 東京対比 会場比率 シナリオ比較
A2: 「前提・入力」シートのシナリオ選択セルで①〜④を切り替えると、③④⑤⑧シートの予測がすべて連動して再計算される。本シートは4シナリオを並べて比較するためのもの
A3: ②企画概要書ベースは、企画概要書「グッズ売上(LEGS予測値)」の 各会場÷東京 で算出（仙台 39,000千円÷250,000千円＝15.60%）
A4: ③石川実績連動は、②に石川の計画比達成率 56.3%（予測 東京対比7.02%）を乗じた保守シナリオ。東京凱旋のみ50%で据置
A6: ■ 企画概要書の計画値と実績の乖離（東京対比・物販売上ベース）
A7: 会場 | B7: 企画概要書 グッズ売上予測 | C7: 企画概要書 東京対比 | D7: 実績／予測 物販売上 | E7: 実績／予測 東京対比 | F7: 計画比 達成率 | G7: 評価
A8: 東京 | B8: 250000000 | C8: =B8/$B$8 -> 1 | D8: 358193925 | E8: =D8/$D$8 -> 1 | F8: =IFERROR(E8/C8,"") -> 1 | G8: 基準会場
A9: 名古屋 | B9: 72000000 | C9: =B9/$B$8 -> 0.288 | D9: 138575410 | E9: =D9/$D$8 -> 0.38687259 | F9: =IFERROR(E9/C9,"") -> 1.3433076 | G9: 計画を大幅超過
A10: 博多 | B10: 56000000 | C10: =B10/$B$8 -> 0.224 | D10: 105540655 | E10: =D10/$D$8 -> 0.29464669 | F10: =IFERROR(E10/C10,"") -> 1.315387 | G10: 計画を大幅超過
A11: 大阪 | B11: 80000000 | C11: =B11/$B$8 -> 0.32 | D11: 215184570 | E11: =D11/$D$8 -> 0.6007488 | F11: =IFERROR(E11/C11,"") -> 1.87734 | G11: 計画の1.9倍。新商品投入で会場全体が伸びた
A12: 札幌 | B12: 54600000 | C12: =B12/$B$8 -> 0.2184 | D12: 41120210 | E12: =D12/$D$8 -> 0.11479874 | F12: =IFERROR(E12/C12,"") -> 0.52563524 | G12: ★計画を大きく下回った
A13: 石川（予測） | B13: 31200000 | C13: =B13/$B$8 -> 0.1248 | D13: 25161149 | E13: =D13/$D$8 -> 0.070244488 | F13: =IFERROR(E13/C13,"") -> 0.56285648 | G13: 会期途中（12日実績→18日予測）
A14: 仙台 | B14: 39000000 | C14: =B14/$B$8 -> 0.156 | D14: — | E14: — | F14: — | G14: 実績未確定。②はこの計画値を採用
A16: ■ シナリオ別 東京対比比率と LEGS必要数
A17: 会場 | B17: 会期日数 | C17: ①ユーザー指定 東京対比 | D17: ①ユーザー指定 LEGS必要数 | E17: ②企画概要書ベース 東京対比 | F17: ②企画概要書ベース LEGS必要数 | G17: ③石川実績連動(保守) 東京対比 | H17: ③石川実績連動(保守) LEGS必要数 | I17: ④手動入力 東京対比 | J17: ④手動入力 LEGS必要数
A18: 仙台 Ebeans | B18: 30 | C18: =前提・入力!C17 -> 0.13 | D18: =ROUND(前提・入力!$B$13*C18*前提・入力!$B$29/前提・入力!$B$30,0) -> 9536 | E18: =前提・入力!D17 -> 0.156 | F18: =ROUND(前提・入力!$B$13*E18*前提・入力!$B$29/前提・入力!$B$30,0) -> 11443 | G18: =前提・入力!E17 -> 0.087805611 | H18: =ROUND(前提・入力!$B$13*G18*前提・入力!$B$29/前提・入力!$B$30,0) -> 6441 | I18: =前提・入力!F17 -> 0.13 | J18: =ROUND(前提・入力!$B$13*I18*前提・入力!$B$29/前提・入力!$B$30,0) -> 9536
A19: 神戸阪急 | B19: 21 | C19: =前提・入力!C18 -> 0.12 | D19: =ROUND(前提・入力!$B$13*C19*前提・入力!$B$29/前提・入力!$B$30,0) -> 8802 | E19: =前提・入力!D18 -> 0.12 | F19: =ROUND(前提・入力!$B$13*E19*前提・入力!$B$29/前提・入力!$B$30,0) -> 8802 | G19: =前提・入力!E18 -> 0.067542777 | H19: =ROUND(前提・入力!$B$13*G19*前提・入力!$B$29/前提・入力!$B$30,0) -> 4955 | I19: =前提・入力!F18 -> 0.12 | J19: =ROUND(前提・入力!$B$13*I19*前提・入力!$B$29/前提・入力!$B$30,0) -> 8802
A20: 鳥取島根 夢みなとタワー | B20: 21 | C20: =前提・入力!C19 -> 0.09 | D20: =ROUND(前提・入力!$B$13*C20*前提・入力!$B$29/前提・入力!$B$30,0) -> 6602 | E20: =前提・入力!D19 -> 0.09 | F20: =ROUND(前提・入力!$B$13*E20*前提・入力!$B$29/前提・入力!$B$30,0) -> 6602 | G20: =前提・入力!E19 -> 0.050657083 | H20: =ROUND(前提・入力!$B$13*G20*前提・入力!$B$29/前提・入力!$B$30,0) -> 3716 | I20: =前提・入力!F19 -> 0.09 | J20: =ROUND(前提・入力!$B$13*I20*前提・入力!$B$29/前提・入力!$B$30,0) -> 6602
A21: 東京凱旋 東京建物ぴあホール | B21: 25 | C21: =前提・入力!C20 -> 0.5 | D21: =ROUND(前提・入力!$B$13*C21*前提・入力!$B$29/前提・入力!$B$30,0) -> 36677 | E21: =前提・入力!D20 -> 0.5 | F21: =ROUND(前提・入力!$B$13*E21*前提・入力!$B$29/前提・入力!$B$30,0) -> 36677 | G21: =前提・入力!E20 -> 0.5 | H21: =ROUND(前提・入力!$B$13*G21*前提・入力!$B$29/前提・入力!$B$30,0) -> 36677 | I21: =前提・入力!F20 -> 0.5 | J21: =ROUND(前提・入力!$B$13*I21*前提・入力!$B$29/前提・入力!$B$30,0) -> 36677
A22: 5会場 合計 | C22: =SUM(C18:C21) -> 0.84 | D22: =SUM(D18:D21) -> 61617 | E22: =SUM(E18:E21) -> 0.866 | F22: =SUM(F18:F21) -> 63524 | G22: =SUM(G18:G21) -> 0.70600547 | H22: =SUM(H18:H21) -> 51789 | I22: =SUM(I18:I21) -> 0.84 | J22: =SUM(J18:J21) -> 61617
A24: ■ 商品別 シナリオ別 必要数と追加生産必要数（供給可能在庫はシナリオ共通）
A25: No. | B25: JAN | C25: 商品名 | D25: 按分 構成比 | E25: 仙台以降 供給可能在庫 | F25: ①ユーザー指定 必要数 | G25: ①ユーザー指定 追加生産 | H25: ②企画概要書ベース 必要数 | I25: ②企画概要書ベース 追加生産 | J25: ③石川実績連動(保守) 必要数 | K25: ③石川実績連動(保守) 追加生産 | L25: ④手動入力 必要数 | M25: ④手動入力 追加生産
A26: 1 | B26: 4515142545082 | C26: 呪術廻戦 メタリックポストカード 展示会キービジュアル | D26: =③仙台以降予測!H31 -> 0.054914619 | E26: =③仙台以降予測!V31 -> 2489 | F26: =ROUND($D26*D$22,0) -> 3384 | G26: =MAX(0,F26-$E26) -> 895 | H26: =ROUND($D26*F$22,0) -> 3488 | I26: =MAX(0,H26-$E26) -> 999 | J26: =ROUND($D26*H$22,0) -> 2844 | K26: =MAX(0,J26-$E26) -> 355 | L26: =ROUND($D26*J$22,0) -> 3384 | M26: =MAX(0,L26-$E26) -> 895
A27: 2 | B27: 4515142545099 | C27: 呪術廻戦 クリアファイル 展示会キービジュアル | D27: =③仙台以降予測!H32 -> 0.061971297 | E27: =③仙台以降予測!V32 -> 4170 | F27: =ROUND($D27*D$22,0) -> 3818 | G27: =MAX(0,F27-$E27) -> 0 | H27: =ROUND($D27*F$22,0) -> 3937 | I27: =MAX(0,H27-$E27) -> 0 | J27: =ROUND($D27*H$22,0) -> 3209 | K27: =MAX(0,J27-$E27) -> 0 | L27: =ROUND($D27*J$22,0) -> 3818 | M27: =MAX(0,L27-$E27) -> 0
A28: 3 | B28: 4515142545105 | C28: 呪術廻戦 懐玉・玉折 ポストカードセット（5枚入） | D28: =③仙台以降予測!H33 -> 0.020958079 | E28: =③仙台以降予測!V33 -> 1857 | F28: =ROUND($D28*D$22,0) -> 1291 | G28: =MAX(0,F28-$E28) -> 0 | H28: =ROUND($D28*F$22,0) -> 1331 | I28: =MAX(0,H28-$E28) -> 0 | J28: =ROUND($D28*H$22,0) -> 1085 | K28: =MAX(0,J28-$E28) -> 0 | L28: =ROUND($D28*J$22,0) -> 1291 | M28: =MAX(0,L28-$E28) -> 0
A29: 4 | B29: 4515142545112 | C29: 呪術廻戦 渋谷事変 ポストカードセット（9枚入） | D29: =③仙台以降予測!H34 -> 0.025829138 | E29: =③仙台以降予測!V34 -> 3153 | F29: =ROUND($D29*D$22,0) -> 1592 | G29: =MAX(0,F29-$E29) -> 0 | H29: =ROUND($D29*F$22,0) -> 1641 | I29: =MAX(0,H29-$E29) -> 0 | J29: =ROUND($D29*H$22,0) -> 1338 | K29: =MAX(0,J29-$E29) -> 0 | L29: =ROUND($D29*J$22,0) -> 1592 | M29: =MAX(0,L29-$E29) -> 0
A30: 5 | B30: 4515142545129 | C30: 呪術廻戦 懐玉・玉折 ブラインド缶バッジ（全5種） | D30: =③仙台以降予測!H35 -> 0.051498103 | E30: =③仙台以降予測!V35 -> 39392 | F30: =ROUND($D30*D$22,0) -> 3173 | G30: =MAX(0,F30-$E30) -> 0 | H30: =ROUND($D30*F$22,0) -> 3271 | I30: =MAX(0,H30-$E30) -> 0 | J30: =ROUND($D30*H$22,0) -> 2667 | K30: =MAX(0,J30-$E30) -> 0 | L30: =ROUND($D30*J$22,0) -> 3173 | M30: =MAX(0,L30-$E30) -> 0
A31: 6 | B31: 4515142545136 | C31: 呪術廻戦 渋谷事変 ブラインド缶バッジ（全9種） | D31: =③仙台以降予測!H36 -> 0.1134423 | E31: =③仙台以降予測!V36 -> 50228 | F31: =ROUND($D31*D$22,0) -> 6990 | G31: =MAX(0,F31-$E31) -> 0 | H31: =ROUND($D31*F$22,0) -> 7206 | I31: =MAX(0,H31-$E31) -> 0 | J31: =ROUND($D31*H$22,0) -> 5875 | K31: =MAX(0,J31-$E31) -> 0 | L31: =ROUND($D31*J$22,0) -> 6990 | M31: =MAX(0,L31-$E31) -> 0
A32: 7 | B32: 4515142545143 | C32: 呪術廻戦 懐玉・玉折 ブラインドダイカットステッカー（全5種） | D32: =③仙台以降予測!H37 -> 0.02653256 | E32: =③仙台以降予測!V37 -> 4249 | F32: =ROUND($D32*D$22,0) -> 1635 | G32: =MAX(0,F32-$E32) -> 0 | H32: =ROUND($D32*F$22,0) -> 1685 | I32: =MAX(0,H32-$E32) -> 0 | J32: =ROUND($D32*H$22,0) -> 1374 | K32: =MAX(0,J32-$E32) -> 0 | L32: =ROUND($D32*J$22,0) -> 1635 | M32: =MAX(0,L32-$E32) -> 0
A33: 8 | B33: 4515142545150 | C33: 呪術廻戦 渋谷事変 ブラインドダイカットステッカー（全9種） | D33: =③仙台以降予測!H38 -> 0.043928428 | E33: =③仙台以降予測!V38 -> 8034 | F33: =ROUND($D33*D$22,0) -> 2707 | G33: =MAX(0,F33-$E33) -> 0 | H33: =ROUND($D33*F$22,0) -> 2791 | I33: =MAX(0,H33-$E33) -> 0 | J33: =ROUND($D33*H$22,0) -> 2275 | K33: =MAX(0,J33-$E33) -> 0 | L33: =ROUND($D33*J$22,0) -> 2707 | M33: =MAX(0,L33-$E33) -> 0
A34: 9 | B34: 4515142545372 | C34: 呪術廻戦 懐玉・玉折 クリアファイル（五条 悟） | D34: =③仙台以降予測!H39 -> 0.013948358 | E34: =③仙台以降予測!V39 -> 8547 | F34: =ROUND($D34*D$22,0) -> 859 | G34: =MAX(0,F34-$E34) -> 0 | H34: =ROUND($D34*F$22,0) -> 886 | I34: =MAX(0,H34-$E34) -> 0 | J34: =ROUND($D34*H$22,0) -> 722 | K34: =MAX(0,J34-$E34) -> 0 | L34: =ROUND($D34*J$22,0) -> 859 | M34: =MAX(0,L34-$E34) -> 0
A35: 10 | B35: 4515142545389 | C35: 呪術廻戦 懐玉・玉折 クリアファイル（夏油 傑） | D35: =③仙台以降予測!H40 -> 0.0052593326 | E35: =③仙台以降予測!V40 -> 4856 | F35: =ROUND($D35*D$22,0) -> 324 | G35: =MAX(0,F35-$E35) -> 0 | H35: =ROUND($D35*F$22,0) -> 334 | I35: =MAX(0,H35-$E35) -> 0 | J35: =ROUND($D35*H$22,0) -> 272 | K35: =MAX(0,J35-$E35) -> 0 | L35: =ROUND($D35*J$22,0) -> 324 | M35: =MAX(0,L35-$E35) -> 0
A36: 11 | B36: 4515142545396 | C36: 呪術廻戦 懐玉・玉折 クリアファイル（家入 硝子） | D36: =③仙台以降予測!H41 -> 0.0019575178 | E36: =③仙台以降予測!V41 -> 609 | F36: =ROUND($D36*D$22,0) -> 121 | G36: =MAX(0,F36-$E36) -> 0 | H36: =ROUND($D36*F$22,0) -> 124 | I36: =MAX(0,H36-$E36) -> 0 | J36: =ROUND($D36*H$22,0) -> 101 | K36: =MAX(0,J36-$E36) -> 0 | L36: =ROUND($D36*J$22,0) -> 121 | M36: =MAX(0,L36-$E36) -> 0
A37: 12 | B37: 4515142545402 | C37: 呪術廻戦 懐玉・玉折 クリアファイル（七海 建人） | D37: =③仙台以降予測!H42 -> 0.0040683407 | E37: =③仙台以降予測!V42 -> 891 | F37: =ROUND($D37*D$22,0) -> 251 | G37: =MAX(0,F37-$E37) -> 0 | H37: =ROUND($D37*F$22,0) -> 258 | I37: =MAX(0,H37-$E37) -> 0 | J37: =ROUND($D37*H$22,0) -> 211 | K37: =MAX(0,J37-$E37) -> 0 | L37: =ROUND($D37*J$22,0) -> 251 | M37: =MAX(0,L37-$E37) -> 0
... A67: 42 | B67: 4515142545365 | C67: 伏黒 恵 イメージフラグメントケース | D67: =③仙台以降予測!H72 -> 5.6236644e-05 | E67: =③仙台以降予測!V72 -> 48 | F67: =ROUND($D67*D$22,0) -> 3 | G67: =MAX(0,F67-$E67) -> 0 | H67: =ROUND($D67*F$22,0) -> 4 | I67: =MAX(0,H67-$E67) -> 0 | J67: =ROUND($D67*H$22,0) -> 3 | K67: =MAX(0,J67-$E67) -> 0 | L67: =ROUND($D67*J$22,0) -> 3 | M67: =MAX(0,L67-$E67) -> 0
C68: 合計（LEGS 42SKU） | D68: =SUM(D26:D67) -> 1 | E68: =SUM(E26:E67) -> 234426 | F68: =SUM(F26:F67) -> 61618 | G68: =SUM(G26:G67) -> 4583 | H68: =SUM(H26:H67) -> 63524 | I68: =SUM(I26:I67) -> 4822 | J68: =SUM(J26:J67) -> 51786 | K68: =SUM(K26:K67) -> 3340 | ... M68: =SUM(M26:M67) -> 4583
A70: ■ シナリオ別 結論
A71: 項目 | B71: ①ユーザー指定 | C71: ②企画概要書ベース | D71: ③石川実績連動(保守) | E71: ④手動入力
A72: 仙台以降 LEGS必要数 | B72: =F68 -> 61618 | C72: =H68 -> 63524 | D72: =J68 -> 51786 | E72: =L68 -> 61618
A73: 仙台以降 供給可能在庫 | B73: =$E$68 -> 234426 | C73: =$E$68 -> 234426 | D73: =$E$68 -> 234426 | E73: =$E$68 -> 234426
A74: 全体過不足 | B74: =B73-B72 -> 172808 | C74: =C73-C72 -> 170902 | D74: =D73-D72 -> 182640 | E74: =E73-E72 -> 172808
A75: 追加生産 必要数 | B75: =G68 -> 4583 | C75: =I68 -> 4822 | D75: =K68 -> 3340 | E75: =M68 -> 4583
A76: 不足品目数 | B76: =COUNTIF(G26:G67,">0")&"品目" -> 13品目 | C76: =COUNTIF(I26:I67,">0")&"品目" -> 13品目 | D76: =COUNTIF(K26:K67,">0")&"品目" -> 12品目 | E76: =COUNTIF(M26:M67,">0")&"品目" -> 13品目
A77: 推奨発注数(安全率込) | B77: =ROUNDUP(G68*(1+前提・入力!$B$34),0) -> 5042 | C77: =ROUNDUP(I68*(1+前提・入力!$B$34),0) -> 5305 | D77: =ROUNDUP(K68*(1+前提・入力!$B$34),0) -> 3674 | E77: =ROUNDUP(M68*(1+前提・入力!$B$34),0) -> 5042
A79: 推奨 | B79: ②企画概要書ベースは①より強気。直近会場が計画を下回っている実態を踏まえると、
B80: 発注量の意思決定は③石川実績連動（保守）を下限、②企画概要書ベースを上限としたレンジで持つのが妥当。
A81: 留意 | B81: 名古屋・博多・大阪の3会場はいずれも計画を大きく超過した一方、直近会場は下振れしている。
B82: これが会場規模・立地に起因する個別要因か、地方会場全体の傾向かで判断が分かれる。
B83: 仙台以降の前売/予約状況が判明した時点でシナリオを確定させることを推奨する。

Sheet ⑪会場別引当・発注期限
A1: ⑪ 仙台以降 会場別 在庫引当シミュレーションと 最終追加発注期限
A2: 石川の欠品分は倉庫在庫から追納する前提。仙台以降の供給可能在庫（＝倉庫残 ＋ 札幌会期末残 − 石川会期18日予測販売数）を会場順に引き当て、在庫が尽きる会場＝「欠品発生会場」を特定する
A3: 発注期限 ＝ 欠品発生会場の会期初日 − 生産日数 − 発注〜納品バッファ（既定14日）。生産日数は2026/7/28時点の提示値で、物価高騰・素材/材料の入手困難等により変動の可能性あり
A5: ■ 既に手配済みの追加発注（参考）
A6: 商品 | B6: 発注／納品日 | C6: 充当先 | D6: 備考
A7: 呪術廻戦 渋谷事変／懐玉・玉折 ブラインド缶バッジ | B7: 2026/4/24(金) | C7: 一部 大阪＆北海道(札幌)以降用
A8: 呪術廻戦 渋谷事変 ブラインドミニ色紙（全5種） | B8: 2026/5/8(金) | C8: 北海道(札幌)会場以降用
A9: 宿儺の指風お菓子 | B9: 2026/5/15(金) | C9: 仙台会場以降 | D9: ★賞味期限4か月以内のものは販売不可
A10: ― 開催中会場への追納 ― | D10: 2026/8 石川(金沢)会場への札幌転送分＋8/22追納
A11: 札幌会場からの転送（LEGS 42SKU 計） | B11: 2026/8/13 | C11: 石川会場（41,612個） | D11: 札幌の会期末残41,615個のうち41,612個を金沢へ横持ち
A12: 宿儺の指風お菓子 | B12: 2026/8/22 | C12: 石川会場（20個） | D12: 倉庫残100個のうち20個を追納。金沢は8/25時点で80個完売
A14: ■ 商品別 会場別 在庫引当と発注期限
A15: No. | B15: JAN | C15: 商品名 | D15: 生産日数 (か月) | E15: 生産日数 (日換算) | F15: 仙台以降 供給可能在庫 | G15: 仙台 必要数 | H15: 仙台 引当後残 | I15: 神戸阪急 必要数 | J15: 神戸阪急 引当後残 | K15: 鳥取島根 必要数 | L15: 鳥取島根 引当後残 | M15: 東京凱旋 必要数 | N15: 東京凱旋 引当後残 | O15: 欠品発生会場 | P15: 欠品会場 会期初日 | Q15: 不足数 (会期末まで) | R15: 推奨発注数 (安全率込) | S15: 最終発注期限 | T15: 基準日からの 残日数 | U15: 緊急度 | V15: 備考
A16: 1 | B16: 4515142545082 | C16: 呪術廻戦 メタリックポストカード 展示会キービジュアル | D16: 1 | E16: =IF(ISNUMBER(D16),ROUND(D16*30,0),"－") -> 30 | F16: =③仙台以降予測!V31 -> 2489 | G16: =③仙台以降予測!I31 -> 524 | H16: =F16-G16 -> 1965 | I16: =③仙台以降予測!J31 -> 483 | J16: =H16-I16 -> 1482 | K16: =③仙台以降予測!K31 -> 363 | L16: =J16-K16 -> 1119 | M16: =③仙台以降予測!L31 -> 2014 | N16: =L16-M16 -> -895 | O16: =_xlfn.IFS(H16<0,"仙台 Ebeans",J16<0,"神戸阪急",L16<0,"鳥取島根 夢みなとタワー",N16<0,"東京凱旋 東京建物ぴあホール",TRUE(),"—") -> 東京凱旋 東京建物ぴあホール | P16: =IF(O16="—","",_xlfn.IFS(H16<0,DATE(2026,9,5),J16<0,DATE(2026,12,16),L16<0,DATE(2027,3,15),N16<0,DATE(2027,4,1))) -> 46478 | Q16: =MAX(0,-N16) -> 895 | R16: =IF(Q16>0,ROUNDUP(Q16*(1+前提・入力!$B$34),0),0) -> 985 | S16: =IF(P16="","",IF(NOT(ISNUMBER(D16)),"再生産不可",P16-E16-前提・入力!$B$37)) -> 46434 | T16: =IF(OR(S16="",S16="再生産不可"),"",S16-前提・入力!$B$38) -> 174 | U16: =IF(O16="","—",IF(S16="再生産不可","×再生産不可",_xlfn.IFS(T16<0,"★期限超過",T16<=30,"★至急(30日以内)",T16<=90,"要着手(90日以内)",TRUE(),"余裕あり"))) -> 余裕あり
A17: 2 | B17: 4515142545099 | C17: 呪術廻戦 クリアファイル 展示会キービジュアル | D17: 1 | E17: =IF(ISNUMBER(D17),ROUND(D17*30,0),"－") -> 30 | F17: =③仙台以降予測!V32 -> 4170 | G17: =③仙台以降予測!I32 -> 591 | H17: =F17-G17 -> 3579 | I17: =③仙台以降予測!J32 -> 545 | J17: =H17-I17 -> 3034 | K17: =③仙台以降予測!K32 -> 409 | L17: =J17-K17 -> 2625 | M17: =③仙台以降予測!L32 -> 2273 | N17: =L17-M17 -> 352 | O17: =_xlfn.IFS(H17<0,"仙台 Ebeans",J17<0,"神戸阪急",L17<0,"鳥取島根 夢みなとタワー",N17<0,"東京凱旋 東京建物ぴあホール",TRUE(),"—") -> — | P17: =IF(O17="—","",_xlfn.IFS(H17<0,DATE(2026,9,5),J17<0,DATE(2026,12,16),L17<0,DATE(2027,3,15),N17<0,DATE(2027,4,1))) | Q17: =MAX(0,-N17) -> 0 | R17: =IF(Q17>0,ROUNDUP(Q17*(1+前提・入力!$B$34),0),0) -> 0 | S17: =IF(P17="","",IF(NOT(ISNUMBER(D17)),"再生産不可",P17-E17-前提・入力!$B$37)) | T17: =IF(OR(S17="",S17="再生産不可"),"",S17-前提・入力!$B$38) | U17: =IF(O17="","—",IF(S17="再生産不可","×再生産不可",_xlfn.IFS(T17<0,"★期限超過",T17<=30,"★至急(30日以内)",T17<=90,"要着手(90日以内)",TRUE(),"余裕あり"))) -> 余裕あり
A18: 3 | B18: 4515142545105 | C18: 呪術廻戦 懐玉・玉折 ポストカードセット（5枚入） | D18: 1 | E18: =IF(ISNUMBER(D18),ROUND(D18*30,0),"－") -> 30 | F18: =③仙台以降予測!V33 -> 1857 | G18: =③仙台以降予測!I33 -> 200 | H18: =F18-G18 -> 1657 | I18: =③仙台以降予測!J33 -> 184 | J18: =H18-I18 -> 1473 | K18: =③仙台以降予測!K33 -> 138 | L18: =J18-K18 -> 1335 | M18: =③仙台以降予測!L33 -> 769 | N18: =L18-M18 -> 566 | O18: =_xlfn.IFS(H18<0,"仙台 Ebeans",J18<0,"神戸阪急",L18<0,"鳥取島根 夢みなとタワー",N18<0,"東京凱旋 東京建物ぴあホール",TRUE(),"—") -> — | P18: =IF(O18="—","",_xlfn.IFS(H18<0,DATE(2026,9,5),J18<0,DATE(2026,12,16),L18<0,DATE(2027,3,15),N18<0,DATE(2027,4,1))) | Q18: =MAX(0,-N18) -> 0 | R18: =IF(Q18>0,ROUNDUP(Q18*(1+前提・入力!$B$34),0),0) -> 0 | S18: =IF(P18="","",IF(NOT(ISNUMBER(D18)),"再生産不可",P18-E18-前提・入力!$B$37)) | T18: =IF(OR(S18="",S18="再生産不可"),"",S18-前提・入力!$B$38) | U18: =IF(O18="","—",IF(S18="再生産不可","×再生産不可",_xlfn.IFS(T18<0,"★期限超過",T18<=30,"★至急(30日以内)",T18<=90,"要着手(90日以内)",TRUE(),"余裕あり"))) -> 余裕あり
